Workbook

Sheet 🏠 PORTADA
E2: 🌎 CALCULADORA PROFESIONAL DE COSTOS DE IMPORTACIÓN
E3: P E R Ú — S I S T E M A D E G E S T I Ó N A D U A N E R A
E6: La herramienta definitiva para calcular costos, tributos y precios de importación en el Perú
E8: ✦ ¿QUÉ INCLUYE ESTA HERRAMIENTA? ✦
E9: 📋 DATOS GENERALES | G9: Registro completo del DUA, importador, Incoterm y parámetros tributarios configurables
E10: 🧾 FACTURA COMERCIAL | G10: Ingreso de hasta 30+ productos con cálculo automático de FOB total y prorrateo unitario
E11: 📦 GASTOS DE IMPORTACIÓN | G11: 21 conceptos pre-cargados: handling, tracción, almacenaje, agente, transporte y más
E12: ⚖️ TRIBUTOS ADUANEROS | G12: Cálculo automático: CIF, ADV, IPM, IGV, Deuda Aduanera y Percepción según SUNAT
E13: 🧮 COSTOS POR PRODUCTO | G13: Factor de prorrateo (6 dígitos) y costo unitario en USD y S/. para cada producto
E14: 💰 PRECIO DE VENTA | G14: Margen global o por producto. VV = CT/(1-Margen%). Punto de equilibrio automático
E15: 🏦 CRÉDITO FISCAL | G15: Detalle completo: IGV, IPM, Percepción y gastos afectos. Valor total recuperable en S/.
E16: 📊 DASHBOARD EJECUTIVO | G16: 8+ gráficos dinámicos: costos, tributos, márgenes, rentabilidad por producto y más
E18: ✦ FLUJO DE TRABAJO — 8 PASOS SIMPLES ✦
E19: PASO 1 Configura | F19: PASO 2 Carga | G19: PASO 3 Registra | H19: PASO 4 Automático | I19: PASO 5 Analiza | J19: PASO 6 Define | K19: PASO 7 Recupera | L19: PASO 8 Decide
E20: Datos generales, tipo de cambio y parámetros tributarios | F20: Productos de la factura comercial con FOB unitario | G20: Gastos de importación pagados a operadores y agentes | H20: El sistema calcula CIF, tributos y deuda aduanera | I20: Revisa el costo unitario y factor de prorrateo | J20: Establece tu margen y obtén precios de venta sugeridos | K20: Visualiza tu crédito fiscal total a recuperar | L20: Revisa el dashboard con todos los KPIs y gráficos
E22: ✦ LEYENDA DE COLORES ✦
E23: 🟡 AMARILLO Campo editable — ingresa tus datos aquí | G23: 🟢 VERDE Calculado automáticamente — no editar | I23: 🔵 AZUL Total o resumen principal de la sección | K23: 🟠 NARANJA Precio de venta o margen de ganancia
E25: ⚠️ IMPORTANTE: Actualice el Tipo de Cambio antes de cada operación | Verifique el Ad Valorem con su Agente de Aduanas
E26: 📧 Herramienta desarrollada para uso profesional en comercio exterior peruano Elaborado por : Rosalinda Jiménez Espinoza By Sally Control Tower Con Derechos de Autoria | J26: Versión 2.0 | 2026

Sheet 📖 Instrucciones
A1: 📖 GUÍA COMPLETA DE USO — CALCULADORA DE COSTOS DE IMPORTACIÓN PERÚ
D3: PASO 1 — 📋 DATOS GENERALES
D4: → Complete todos los datos en color AMARILLO: DUA, razón social, RUC, fecha, país, proveedor, incoterm, canal. | F4: "📌 NOTA IMPORTANTE — USO DE LA PLANTILLA Esta calculadora está diseñada para ser usada por operación de importación. Si realizas varias importaciones, te recomendamos seguir este flujo de trabajo: 1️⃣ Completa esta plantilla con los datos de tu importación actual. 2️⃣ Guarda el archivo con un nombre que identifique la operación — por ejemplo: Importación_Enero2026_China o DAM-2026-000001. 3️⃣ Para tu próxima importación, abre el archivo original, haz una copia y renómbrala. De esta forma tendrás un historial ordenado de cada importación, con todos sus costos, tributos y márgenes guardados por separado. ✅ Así podrás comparar operaciones, identificar en cuál ganaste más y tomar mejores decisiones en cada nueva importación."
D5: → IMPORTANTE: Actualice el Tipo de Cambio USD→PEN antes de cada operación (fuente: SUNAT / BCR).
D6: → Configure los parámetros tributarios: Ad Valorem según partida arancelaria (0%, 6% u 11%), percepción según tipo de importador.
D7: → Tasas de percepción: 10% = primera importación / empresa nueva | 3.5% = producto nuevo importador frecuente | 5% = producto de segundo uso.
D9: PASO 2 — 🧾 FACTURA COMERCIAL
D10: → Ingrese cada producto: descripción, unidad de medida, cantidad total y precio FOB unitario en USD.
D11: → El sistema calcula automáticamente el FOB Total, el Factor de Prorrateo y el Costo Unitario.
D12: → Puede manejar hasta 30 productos diferentes en una misma importación.
D14: PASO 3 — 📦 GASTOS DE IMPORTACIÓN
D15: → Ingrese el monto de cada gasto pagado a los operadores: handling, descarga, tracción, almacenaje, transporte, etc.
D16: → Los gastos marcados ⭐ son afectos a IGV (18%) y generan crédito fiscal.
D17: → El Derecho de Emisión del Seguro y la Comisión del Agente se calculan automáticamente.
D18: → Complete también los gastos administrativos y financieros (transferencias, intereses de letras, carta de crédito).
... D49: ⚠️ Esta plantilla es una herramienta de estimación profesional — consulte siempre a un agente de aduanas certificado.

Sheet Doc. Necesarios
B2: DOCUMENTOS QUE DEBES DE TENER A LA MANO PARA LLENAR LA PLANTILLA
B4: 1 | C4: Proforma Comercial y/o Factura Invoice
B5: 2 | C5: Proforma o Liquidación del Agente de Aduana
C6: 2.1 | D6: Derechos de Aduana
C7: 2.2 | D7: Flete Internacional
C8: 2.3 | D8: Comisión del Agente
C9: 2.4 | D9: Gastos de Nacionalizacion
C10: 2.5 | D10: Transporte Interno

Sheet 📋 Datos Generales
D1: 📋 CALCULADORA DE COSTOS DE IMPORTACIÓN — PERÚ
D2: Complete los datos en AMARILLO 🟡. Los campos en VERDE 🟢 se calculan automáticamente.
D4: 📄 DATOS DE LA OPERACIÓN DE IMPORTACIÓN
D5: Número de DUA / DAM | E5: DAM-2025-000001
D6: Razón Social del Importador | E6: EMPRESA IMPORTADORA S.A.C.
D7: RUC del Importador | E7: 20XXXXXXXXX
D8: Fecha de Numeración DAM | E8: 24/02/2026
D9: País de Origen | E9: China
D10: Proveedor / Exportador | E10: HWPI Co. Ltd.
D11: Incoterm | E11: FOB
D12: Vía de Transporte | E12: Marítima
D13: Puerto de Embarque | E13: Shekou, China
D14: Puerto de Destino | E14: Callao, Perú
D15: Agente de Aduanas | E15: Agencia SAC
D16: Canal de Control | E16: Naranja
D18: ⚖️ PARÁMETROS TRIBUTARIOS (Configuración)
D19: Tipo de Cambio USD → PEN | E19: 3.72 | F19: Actualizar según SUNAT / BCR
D20: Ad Valorem — Arancel (%) | E20: 0.06 | F20: 0%, 6% u 11% según partida arancelaria
D21: IGV (%) | E21: 0.16 | F21: Fijo 16%
D22: IPM (%) | E22: 0.02 | F22: Fijo 2%
D23: Percepción IGV (%) | E23: 0.035 | F23: 10% nueva empresa / 3.5% producto nuevo / 5% segundo uso
D24: Prima Neta Seguro (%) | E24: 0 | F24: % sobre la Suma Asegurada
D25: Derecho de Emisión Seguro (%) | E25: 0 | F25: 3% sobre Prima Neta — negociable
D26: Deducible Seguro (%) | E26: 0 | F26: % del que somos responsables en siniestro
D27: Comisión Agente Aduanas (%) | E27: 0.01 | F27: % sobre CIF (mín. S/. 100)
D28: IGV Servicios (%) | E28: 0.18 | F28: 18% (IGV 16% + IPM 2%)
D30: 🟡 Amarillo = Dato editable 🟢 Verde = Calculado automáticamente 🔵 Azul = Total general

Sheet 🧾 Factura Comercial
D2: 🧾 FACTURA COMERCIAL — DETALLE DE PRODUCTOS
D3: Ingrese cada producto: descripción, unidad, cantidad y precio FOB unitario (USD).
D4: # | E4: DESCRIPCIÓN DEL PRODUCTO | F4: UNIDAD MEDIDA | G4: CANTIDAD (unid.) | H4: FOB UNIT. (USD) | I4: FOB TOTAL (USD) | J4: PARTICIPACIÓN | K4: COSTO UNIT. (PEN) | L4: PRECIO VENTA (PEN)
D5: 1 | E5: Case Transparente TPU iPhone 15 | F5: Unid. | G5: 480 | H5: 1.21 | I5: =IF(G5=0,0,G5*H5) -> 580.8 | J5: =IF(I5=0,0,I5/$I$35) -> 0.040861813 | K5: ='🧮 Costos x Producto'!K7 -> 5.886674 | L5: ='💰 Precio de Venta'!H8 -> 9.8111233
D6: 2 | E6: Cable USB-C Trenzado 1m | F6: Unid. | G6: 2880 | H6: 0.68 | I6: =IF(G6=0,0,G6*H6) -> 1958.4 | J6: =IF(I6=0,0,I6/$I$35) -> 0.13778198 | K6: ='🧮 Costos x Producto'!K8 -> 3.3082135 | L6: ='💰 Precio de Venta'!H9 -> 5.5136892
D7: 3 | E7: Protector Pantalla Vidrio Templado | F7: Unid. | G7: 2880 | H7: 0.4 | I7: =IF(G7=0,0,G7*H7) -> 1152 | J7: =IF(I7=0,0,I7/$I$35) -> 0.081048224 | K7: ='🧮 Costos x Producto'!K9 -> 1.9460079 | L7: ='💰 Precio de Venta'!H10 -> 3.2433466
D8: 4 | E8: Audífonos In-Ear con Micrófono | F8: Unid. | G8: 10224 | H8: 0.34 | I8: =IF(G8=0,0,G8*H8) -> 3476.16 | J8: =IF(I8=0,0,I8/$I$35) -> 0.24456301 | K8: ='🧮 Costos x Producto'!K10 -> 1.6541067 | L8: ='💰 Precio de Venta'!H11 -> 2.7568446
D9: 5 | E9: Cable Micro USB 2m Nylon | F9: Unid. | G9: 8640 | H9: 0.26 | I9: =IF(G9=0,0,G9*H9) -> 2246.4 | J9: =IF(I9=0,0,I9/$I$35) -> 0.15804404 | K9: ='🧮 Costos x Producto'!K11 -> 1.2649052 | L9: ='💰 Precio de Venta'!H12 -> 2.1081753
D10: 6 | E10: Soporte Anillo Pop Socket Metálico | F10: Unid. | G10: 2160 | H10: 0.29 | I10: =IF(G10=0,0,G10*H10) -> 626.4 | J10: =IF(I10=0,0,I10/$I$35) -> 0.044069972 | K10: ='🧮 Costos x Producto'!K12 -> 1.4108558 | L10: ='💰 Precio de Venta'!H13 -> 2.3514263
D11: 7 | E11: Cargador Inalámbrico 15W Qi | F11: Unid. | G11: 240 | H11: 5.71 | I11: =IF(G11=0,0,G11*H11) -> 1370.4 | J11: =IF(I11=0,0,I11/$I$35) -> 0.096413616 | K11: ='🧮 Costos x Producto'!K13 -> 27.779263 | L11: ='💰 Precio de Venta'!H14 -> 46.298772
D12: 8 | E12: Case Wallet Cuero PU Samsung S24 | F12: Unid. | G12: 1920 | H12: 0.76 | I12: =IF(G12=0,0,G12*H12) -> 1459.2 | J12: =IF(I12=0,0,I12/$I$35) -> 0.10266108 | K12: ='🧮 Costos x Producto'!K14 -> 3.6974151 | L12: ='💰 Precio de Venta'!H15 -> 6.1623585
D13: 9 | E13: Adaptador USB-C a Jack 3.5mm | F13: Unid. | G13: 4800 | H13: 0.28 | I13: =IF(G13=0,0,G13*H13) -> 1344 | J13: =IF(I13=0,0,I13/$I$35) -> 0.094556261 | K13: ='🧮 Costos x Producto'!K15 -> 1.3622056 | L13: ='💰 Precio de Venta'!H16 -> 2.2703426
D14: 10 | F14: Unid. | G14: 0 | H14: 0 | I14: =IF(G14=0,0,G14*H14) -> 0 | J14: =IF(I14=0,0,I14/$I$35) -> 0 | K14: ='🧮 Costos x Producto'!K16 -> 0 | L14: ='💰 Precio de Venta'!H17 -> 0
D15: 11 | F15: Unid. | G15: 0 | H15: 0 | I15: =IF(G15=0,0,G15*H15) -> 0 | J15: =IF(I15=0,0,I15/$I$35) -> 0 | K15: ='🧮 Costos x Producto'!K17 -> 0 | L15: ='💰 Precio de Venta'!H18 -> 0
D16: 12 | F16: Unid. | G16: 0 | H16: 0 | I16: =IF(G16=0,0,G16*H16) -> 0 | J16: =IF(I16=0,0,I16/$I$35) -> 0 | K16: ='🧮 Costos x Producto'!K18 -> 0 | L16: ='💰 Precio de Venta'!H19 -> 0
D17: 13 | F17: Unid. | G17: 0 | H17: 0 | I17: =IF(G17=0,0,G17*H17) -> 0 | J17: =IF(I17=0,0,I17/$I$35) -> 0 | K17: ='🧮 Costos x Producto'!K19 -> 0 | L17: ='💰 Precio de Venta'!H20 -> 0
D18: 14 | F18: Unid. | G18: 0 | H18: 0 | I18: =IF(G18=0,0,G18*H18) -> 0 | J18: =IF(I18=0,0,I18/$I$35) -> 0 | K18: ='🧮 Costos x Producto'!K20 -> 0 | L18: ='💰 Precio de Venta'!H21 -> 0
D19: 15 | F19: Unid. | G19: 0 | H19: 0 | I19: =IF(G19=0,0,G19*H19) -> 0 | J19: =IF(I19=0,0,I19/$I$35) -> 0 | K19: ='🧮 Costos x Producto'!K21 -> 0 | L19: ='💰 Precio de Venta'!H22 -> 0
D20: 16 | F20: Unid. | G20: 0 | H20: 0 | I20: =IF(G20=0,0,G20*H20) -> 0 | J20: =IF(I20=0,0,I20/$I$35) -> 0 | K20: ='🧮 Costos x Producto'!K22 -> 0 | L20: ='💰 Precio de Venta'!H23 -> 0
D21: 17 | F21: Unid. | G21: 0 | H21: 0 | I21: =IF(G21=0,0,G21*H21) -> 0 | J21: =IF(I21=0,0,I21/$I$35) -> 0 | K21: ='🧮 Costos x Producto'!K23 -> 0 | L21: ='💰 Precio de Venta'!H24 -> 0
D22: 18 | F22: Unid. | G22: 0 | H22: 0 | I22: =IF(G22=0,0,G22*H22) -> 0 | J22: =IF(I22=0,0,I22/$I$35) -> 0 | K22: ='🧮 Costos x Producto'!K24 -> 0 | L22: ='💰 Precio de Venta'!H25 -> 0
D23: 19 | F23: Unid. | G23: 0 | H23: 0 | I23: =IF(G23=0,0,G23*H23) -> 0 | J23: =IF(I23=0,0,I23/$I$35) -> 0 | K23: ='🧮 Costos x Producto'!K25 -> 0 | L23: ='💰 Precio de Venta'!H26 -> 0
D24: 20 | F24: Unid. | G24: 0 | H24: 0 | I24: =IF(G24=0,0,G24*H24) -> 0 | J24: =IF(I24=0,0,I24/$I$35) -> 0 | K24: ='🧮 Costos x Producto'!K26 -> 0 | L24: ='💰 Precio de Venta'!H27 -> 0
D25: 21 | F25: Unid. | G25: 0 | H25: 0 | I25: =IF(G25=0,0,G25*H25) -> 0 | J25: =IF(I25=0,0,I25/$I$35) -> 0 | K25: ='🧮 Costos x Producto'!K27 -> 0 | L25: ='💰 Precio de Venta'!H28 -> 0
... D34: 30 | F34: Unid. | G34: 0 | H34: 0 | I34: =IF(G34=0,0,G34*H34) -> 0 | J34: =IF(I34=0,0,I34/$I$35) -> 0 | K34: ='🧮 Costos x Producto'!K36 -> 0 | L34: ='💰 Precio de Venta'!H37 -> 0
D35: TOTAL FOB (USD) | I35: =SUM(I5:I34) -> 14213.76

Sheet 📦 Gastos Importación
D2: 📦 GASTOS DE IMPORTACIÓN (Tercer Elemento)
D3: Ingrese el monto de cada gasto. Los gastos marcados con ⭐ están sujetos a IGV del 18%.
D4: CONCEPTO / GASTO | E4: MONTO (USD) | F4: AFECTO IGV | G4: NOTAS
D5: ⭐ Derecho de Emisión (Seguro) | E5: ='🧾 Tributos Aduana'!F9 -> - | F5: SÍ | G5: Auto-calculado desde Tributos Aduana
D6: ⭐ Handling | E6: 34.03 | F6: SÍ | G6: Manipuleo de la carga
D7: ⭐ Servicio de Descarga | E7: 100.69 | F7: SÍ | G7: Descarga del contenedor
D8: ⭐ Movilización de Carga | E8: 36.46 | F8: SÍ | G8: Traslado interno del terminal
D9: ⭐ Tracción | E9: 48.61 | F9: SÍ | G9: Transporte del contenedor
D10: ⭐ Servicio al Cliente (V°B°) | E10: 12.15 | F10: SÍ | G10: Verificación de pago del flete
D11: ⭐ Gastos Operativos Agente | E11: 70 | F11: SÍ | G11: Gestión del despacho
D12: ⭐ Almacenaje | E12: 121.53 | F12: SÍ | G12: Días de almacén temporal
D13: ⭐ Cargadores / Cuadrilla | E13: 62.5 | F13: SÍ | G13: Personal de carga
D14: ⭐ Serv. Administrativos | E14: 13.89 | F14: SÍ | G14: Documentación
D15: ⭐ Seguro de Contenedor | E15: 41.67 | F15: SÍ | G15: Seguro de la carga en tránsito local
D16: ⭐ Posicionamiento de Carga | E16: 62.5 | F16: SÍ | G16: Reconocimiento físico si aplica
D17: ⭐ Transporte Interno / Última Milla | E17: 104.17 | F17: SÍ | G17: Traslado a almacenes del importador
... D25: Comisiones C/C | E25: 0 | F25: NO | G25: 1.2% CFR si aplica carta de crédito
D26: SUB-TOTAL AFECTOS A IGV (US$) | E26: =E6+E7+E8+E9+E10+E11+E12+E13+E14+E15+E16+E17+E18+E19+E20 -> 997.24 | F26: =SUM(E6:E20)*'📋 Datos Generales'!E28 -> 179.5032
D27: SUB-TOTAL NO AFECTOS A IGV (US$) | E27: =E21+E22+E23+E24+E25 -> 167.5 | F27: No genera IGV
D28: ⭐ TOTAL COSTOS IMPORTACIÓN (US$) | E28: ='🧾 Tributos Aduana'!$F$14+'🧾 Tributos Aduana'!$F$17+E26+E27 -> 18588.77
H30: Tipo | I30: US$
H31: Afectos IGV | I31: =E26 -> 997.24
H32: No Afectos | I32: =E27 -> 167.5

Sheet 🧾 Tributos Aduana
E2: 🧾 TRIBUTOS ADUANEROS — CÁLCULO AUTOMÁTICO
E3: Todos los valores se calculan automáticamente. Solo configure los parámetros en '📋 Datos Generales'.
E5: 🛡️ CÁLCULO DEL SEGURO (Prima Neta → Suma Asegurada)
E6: FOB Total (USD) | F6: ='🧾 Factura Comercial'!I35 -> 14213.76 | G6: Valor FOB total de la factura comercial
E7: Flete Internacional (USD) | F7: 2090 | G7: Monto del flete — copiar del BL/AWB
E8: CFR = FOB + Flete (USD) | F8: =F6+F7 -> 16303.76 | G8: Valor CFR = base para calcular SA
E9: Suma Asegurada (USD) | F9: - | G9: SA = CFR / (1 - deducible%) — Fórmula del libro
E10: Prima Neta (USD) | F10: 134.27 | G10: Prima Neta = SA × 24%
E11: D. Emisión Seguro (USD) | F11: =F10*'📋 Datos Generales'!E25 -> 0 | G11: Derecho de Emisión = 3% × Prima Neta → va a Gastos
E12: IGV Seguro (USD) | F12: =SUM(F10:F11)*'📋 Datos Generales'!E28 -> 24.1686 | G12: IGV sobre Prima Neta → va a Crédito Fiscal
E13: Seguro (Prima Neta) → CIF | F13: =F10 -> 134.27 | G13: Prima Neta forma parte del CIF
E14: CIF = CFR + Prima Neta | F14: =F8+F10 -> 16438.03 | G14: CIF = Valor en Aduanas
E16: ⚖️ DEUDA ADUANERA (ADEUDO) — Pago a SUNAT-ADUANAS
E17: Ad Valorem — ADV (USD) | F17: =ROUND(F14*'📋 Datos Generales'!E20,0) -> 986 | G17: ADV = CIF × Ad Valorem% — redondeado entero
E18: IPM (USD) | F18: =ROUND((F14+F17)*'📋 Datos Generales'!E22,0) -> 348 | G18: IPM = (CIF + ADV) × 2% — redondeado
E19: IGV (USD) | F19: =ROUND((F14+F17)*'📋 Datos Generales'!E21,0) -> 2788 | G19: IGV = (CIF + ADV) × 16% — redondeado
E20: DEUDA ADUANERA = DA (USD) | F20: =F17+F18+F19 -> 4122 | G20: DA = ADV + IPM + IGV
E22: 💸 PERCEPCIÓN IGV Y DERECHOS (costo real)
E23: Percepción IGV (USD) | F23: =ROUND((F14+F20)*'📋 Datos Generales'!E23,2) -> 719.6 | G23: Base = CIF + DA — tasa según tipo importador
E24: DERECHOS = ADV (USD) | F24: =F17 -> 986 | G24: Solo el ADV es costo (IPM e IGV = crédito fiscal)
E25: Comisión Agente (USD) | F25: =MAX(F14*'📋 Datos Generales'!E27,100/'📋 Datos Generales'!E19) -> 164.3803 | G25: Máx entre 1% CIF y mín USD 100
F35: Componente | G35: Monto US$
F36: Ad Valorem | G36: =F17 -> 986
F37: IPM | G37: =F18 -> 348
F38: IGV Aduanas | G38: =F19 -> 2788
F39: Percepción | G39: =F23 -> 719.6
F42: Componente | G42: Monto US$
F43: FOB | G43: =F6 -> 14213.76
F44: Flete | G44: =F7 -> 2090
F45: Seguro | G45: =F10 -> 134.27

Sheet 🧮 Costos x Producto
D2: 🧮 COSTO DE IMPORTACIÓN POR PRODUCTO (Factor de Prorrateo)
D3: El Costo Unitario se calcula multiplicando el Factor de Prorrateo × FOB Unitario. Factor = C/M Total / FOB Total
D4: COSTO TOTAL DE IMPORTACIÓN (US$) | G4: ='📦 Gastos Importación'!E28 -> 18588.77 | I4: =G4*'📋 Datos Generales'!E19 -> 69150.224
D5: FACTOR DE PRORRATEO = C/M Total (US$) / FOB Total (US$) | G5: =IF('🧾 Factura Comercial'!I35=0,0,G4/'🧾 Factura Comercial'!I35) -> 1.307801
D6: # | E6: PRODUCTO | F6: CANTIDAD | G6: FOB UNIT. (USD) | H6: FOB TOTAL (USD) | I6: % PARTICIPACÓN | J6: C/M UNIT. (USD) | K6: C/M UNIT. (PEN)
D7: 1 | E7: ='🧾 Factura Comercial'!E5 -> Case Transparente TPU iPhone 15 | F7: ='🧾 Factura Comercial'!G5 -> 480 | G7: ='🧾 Factura Comercial'!H5 -> 1.21 | H7: ='🧾 Factura Comercial'!I5 -> 580.8 | I7: ='🧾 Factura Comercial'!J5 -> 0.040861813 | J7: =IF(G5=0,0,G5*G7) -> 1.5824392 | K7: =J7*'📋 Datos Generales'!E19 -> 5.886674
D8: 2 | E8: ='🧾 Factura Comercial'!E6 -> Cable USB-C Trenzado 1m | F8: ='🧾 Factura Comercial'!G6 -> 2880 | G8: ='🧾 Factura Comercial'!H6 -> 0.68 | H8: ='🧾 Factura Comercial'!I6 -> 1958.4 | I8: ='🧾 Factura Comercial'!J6 -> 0.13778198 | J8: =IF(G5=0,0,G5*G8) -> 0.8893047 | K8: =J8*'📋 Datos Generales'!E19 -> 3.3082135
D9: 3 | E9: ='🧾 Factura Comercial'!E7 -> Protector Pantalla Vidrio Templado | F9: ='🧾 Factura Comercial'!G7 -> 2880 | G9: ='🧾 Factura Comercial'!H7 -> 0.4 | H9: ='🧾 Factura Comercial'!I7 -> 1152 | I9: ='🧾 Factura Comercial'!J7 -> 0.081048224 | J9: =IF(G5=0,0,G5*G9) -> 0.52312041 | K9: =J9*'📋 Datos Generales'!E19 -> 1.9460079
D10: 4 | E10: ='🧾 Factura Comercial'!E8 -> Audífonos In-Ear con Micrófono | F10: ='🧾 Factura Comercial'!G8 -> 10224 | G10: ='🧾 Factura Comercial'!H8 -> 0.34 | H10: ='🧾 Factura Comercial'!I8 -> 3476.16 | I10: ='🧾 Factura Comercial'!J8 -> 0.24456301 | J10: =IF(G5=0,0,G5*G10) -> 0.44465235 | K10: =J10*'📋 Datos Generales'!E19 -> 1.6541067
D11: 5 | E11: ='🧾 Factura Comercial'!E9 -> Cable Micro USB 2m Nylon | F11: ='🧾 Factura Comercial'!G9 -> 8640 | G11: ='🧾 Factura Comercial'!H9 -> 0.26 | H11: ='🧾 Factura Comercial'!I9 -> 2246.4 | I11: ='🧾 Factura Comercial'!J9 -> 0.15804404 | J11: =IF(G5=0,0,G5*G11) -> 0.34002827 | K11: =J11*'📋 Datos Generales'!E19 -> 1.2649052
D12: 6 | E12: ='🧾 Factura Comercial'!E10 -> Soporte Anillo Pop Socket Metálico | F12: ='🧾 Factura Comercial'!G10 -> 2160 | G12: ='🧾 Factura Comercial'!H10 -> 0.29 | H12: ='🧾 Factura Comercial'!I10 -> 626.4 | I12: ='🧾 Factura Comercial'!J10 -> 0.044069972 | J12: =IF(G5=0,0,G5*G12) -> 0.3792623 | K12: =J12*'📋 Datos Generales'!E19 -> 1.4108558
D13: 7 | E13: ='🧾 Factura Comercial'!E11 -> Cargador Inalámbrico 15W Qi | F13: ='🧾 Factura Comercial'!G11 -> 240 | G13: ='🧾 Factura Comercial'!H11 -> 5.71 | H13: ='🧾 Factura Comercial'!I11 -> 1370.4 | I13: ='🧾 Factura Comercial'!J11 -> 0.096413616 | J13: =IF(G5=0,0,G5*G13) -> 7.4675439 | K13: =J13*'📋 Datos Generales'!E19 -> 27.779263
D14: 8 | E14: ='🧾 Factura Comercial'!E12 -> Case Wallet Cuero PU Samsung S24 | F14: ='🧾 Factura Comercial'!G12 -> 1920 | G14: ='🧾 Factura Comercial'!H12 -> 0.76 | H14: ='🧾 Factura Comercial'!I12 -> 1459.2 | I14: ='🧾 Factura Comercial'!J12 -> 0.10266108 | J14: =IF(G5=0,0,G5*G14) -> 0.99392878 | K14: =J14*'📋 Datos Generales'!E19 -> 3.6974151
D15: 9 | E15: ='🧾 Factura Comercial'!E13 -> Adaptador USB-C a Jack 3.5mm | F15: ='🧾 Factura Comercial'!G13 -> 4800 | G15: ='🧾 Factura Comercial'!H13 -> 0.28 | H15: ='🧾 Factura Comercial'!I13 -> 1344 | I15: ='🧾 Factura Comercial'!J13 -> 0.094556261 | J15: =IF(G5=0,0,G5*G15) -> 0.36618429 | K15: =J15*'📋 Datos Generales'!E19 -> 1.3622056
D16: 10 | E16: ='🧾 Factura Comercial'!E14 -> 0 | F16: ='🧾 Factura Comercial'!G14 -> 0 | G16: ='🧾 Factura Comercial'!H14 -> 0 | H16: ='🧾 Factura Comercial'!I14 -> 0 | I16: ='🧾 Factura Comercial'!J14 -> 0 | J16: =IF(G5=0,0,G5*G16) -> 0 | K16: =J16*'📋 Datos Generales'!E19 -> 0
D17: 11 | E17: ='🧾 Factura Comercial'!E15 -> 0 | F17: ='🧾 Factura Comercial'!G15 -> 0 | G17: ='🧾 Factura Comercial'!H15 -> 0 | H17: ='🧾 Factura Comercial'!I15 -> 0 | I17: ='🧾 Factura Comercial'!J15 -> 0 | J17: =IF(G5=0,0,G5*G17) -> 0 | K17: =J17*'📋 Datos Generales'!E19 -> 0
D18: 12 | E18: ='🧾 Factura Comercial'!E16 -> 0 | F18: ='🧾 Factura Comercial'!G16 -> 0 | G18: ='🧾 Factura Comercial'!H16 -> 0 | H18: ='🧾 Factura Comercial'!I16 -> 0 | I18: ='🧾 Factura Comercial'!J16 -> 0 | J18: =IF(G5=0,0,G5*G18) -> 0 | K18: =J18*'📋 Datos Generales'!E19 -> 0
D19: 13 | E19: ='🧾 Factura Comercial'!E17 -> 0 | F19: ='🧾 Factura Comercial'!G17 -> 0 | G19: ='🧾 Factura Comercial'!H17 -> 0 | H19: ='🧾 Factura Comercial'!I17 -> 0 | I19: ='🧾 Factura Comercial'!J17 -> 0 | J19: =IF(G5=0,0,G5*G19) -> 0 | K19: =J19*'📋 Datos Generales'!E19 -> 0
D20: 14 | E20: ='🧾 Factura Comercial'!E18 -> 0 | F20: ='🧾 Factura Comercial'!G18 -> 0 | G20: ='🧾 Factura Comercial'!H18 -> 0 | H20: ='🧾 Factura Comercial'!I18 -> 0 | I20: ='🧾 Factura Comercial'!J18 -> 0 | J20: =IF(G5=0,0,G5*G20) -> 0 | K20: =J20*'📋 Datos Generales'!E19 -> 0
D21: 15 | E21: ='🧾 Factura Comercial'!E19 -> 0 | F21: ='🧾 Factura Comercial'!G19 -> 0 | G21: ='🧾 Factura Comercial'!H19 -> 0 | H21: ='🧾 Factura Comercial'!I19 -> 0 | I21: ='🧾 Factura Comercial'!J19 -> 0 | J21: =IF(G5=0,0,G5*G21) -> 0 | K21: =J21*'📋 Datos Generales'!E19 -> 0
D22: 16 | E22: ='🧾 Factura Comercial'!E20 -> 0 | F22: ='🧾 Factura Comercial'!G20 -> 0 | G22: ='🧾 Factura Comercial'!H20 -> 0 | H22: ='🧾 Factura Comercial'!I20 -> 0 | I22: ='🧾 Factura Comercial'!J20 -> 0 | J22: =IF(G5=0,0,G5*G22) -> 0 | K22: =J22*'📋 Datos Generales'!E19 -> 0
D23: 17 | E23: ='🧾 Factura Comercial'!E21 -> 0 | F23: ='🧾 Factura Comercial'!G21 -> 0 | G23: ='🧾 Factura Comercial'!H21 -> 0 | H23: ='🧾 Factura Comercial'!I21 -> 0 | I23: ='🧾 Factura Comercial'!J21 -> 0 | J23: =IF(G5=0,0,G5*G23) -> 0 | K23: =J23*'📋 Datos Generales'!E19 -> 0
D24: 18 | E24: ='🧾 Factura Comercial'!E22 -> 0 | F24: ='🧾 Factura Comercial'!G22 -> 0 | G24: ='🧾 Factura Comercial'!H22 -> 0 | H24: ='🧾 Factura Comercial'!I22 -> 0 | I24: ='🧾 Factura Comercial'!J22 -> 0 | J24: =IF(G5=0,0,G5*G24) -> 0 | K24: =J24*'📋 Datos Generales'!E19 -> 0
D25: 19 | E25: ='🧾 Factura Comercial'!E23 -> 0 | F25: ='🧾 Factura Comercial'!G23 -> 0 | G25: ='🧾 Factura Comercial'!H23 -> 0 | H25: ='🧾 Factura Comercial'!I23 -> 0 | I25: ='🧾 Factura Comercial'!J23 -> 0 | J25: =IF(G5=0,0,G5*G25) -> 0 | K25: =J25*'📋 Datos Generales'!E19 -> 0
D26: 20 | E26: ='🧾 Factura Comercial'!E24 -> 0 | F26: ='🧾 Factura Comercial'!G24 -> 0 | G26: ='🧾 Factura Comercial'!H24 -> 0 | H26: ='🧾 Factura Comercial'!I24 -> 0 | I26: ='🧾 Factura Comercial'!J24 -> 0 | J26: =IF(G5=0,0,G5*G26) -> 0 | K26: =J26*'📋 Datos Generales'!E19 -> 0
D27: 21 | E27: ='🧾 Factura Comercial'!E25 -> 0 | F27: ='🧾 Factura Comercial'!G25 -> 0 | G27: ='🧾 Factura Comercial'!H25 -> 0 | H27: ='🧾 Factura Comercial'!I25 -> 0 | I27: ='🧾 Factura Comercial'!J25 -> 0 | J27: =IF(G5=0,0,G5*G27) -> 0 | K27: =J27*'📋 Datos Generales'!E19 -> 0
D28: 22 | E28: ='🧾 Factura Comercial'!E26 -> 0 | F28: ='🧾 Factura Comercial'!G26 -> 0 | G28: ='🧾 Factura Comercial'!H26 -> 0 | H28: ='🧾 Factura Comercial'!I26 -> 0 | I28: ='🧾 Factura Comercial'!J26 -> 0 | J28: =IF(G5=0,0,G5*G28) -> 0 | K28: =J28*'📋 Datos Generales'!E19 -> 0
D29: 23 | E29: ='🧾 Factura Comercial'!E27 -> 0 | F29: ='🧾 Factura Comercial'!G27 -> 0 | G29: ='🧾 Factura Comercial'!H27 -> 0 | H29: ='🧾 Factura Comercial'!I27 -> 0 | I29: ='🧾 Factura Comercial'!J27 -> 0 | J29: =IF(G5=0,0,G5*G29) -> 0 | K29: =J29*'📋 Datos Generales'!E19 -> 0
D30: 24 | E30: ='🧾 Factura Comercial'!E28 -> 0 | F30: ='🧾 Factura Comercial'!G28 -> 0 | G30: ='🧾 Factura Comercial'!H28 -> 0 | H30: ='🧾 Factura Comercial'!I28 -> 0 | I30: ='🧾 Factura Comercial'!J28 -> 0 | J30: =IF(G5=0,0,G5*G30) -> 0 | K30: =J30*'📋 Datos Generales'!E19 -> 0
D31: 25 | E31: ='🧾 Factura Comercial'!E29 -> 0 | F31: ='🧾 Factura Comercial'!G29 -> 0 | G31: ='🧾 Factura Comercial'!H29 -> 0 | H31: ='🧾 Factura Comercial'!I29 -> 0 | I31: ='🧾 Factura Comercial'!J29 -> 0 | J31: =IF(G5=0,0,G5*G31) -> 0 | K31: =J31*'📋 Datos Generales'!E19 -> 0
D32: 26 | E32: ='🧾 Factura Comercial'!E30 -> 0 | F32: ='🧾 Factura Comercial'!G30 -> 0 | G32: ='🧾 Factura Comercial'!H30 -> 0 | H32: ='🧾 Factura Comercial'!I30 -> 0 | I32: ='🧾 Factura Comercial'!J30 -> 0 | J32: =IF(G5=0,0,G5*G32) -> 0 | K32: =J32*'📋 Datos Generales'!E19 -> 0
D33: 27 | E33: ='🧾 Factura Comercial'!E31 -> 0 | F33: ='🧾 Factura Comercial'!G31 -> 0 | G33: ='🧾 Factura Comercial'!H31 -> 0 | H33: ='🧾 Factura Comercial'!I31 -> 0 | I33: ='🧾 Factura Comercial'!J31 -> 0 | J33: =IF(G5=0,0,G5*G33) -> 0 | K33: =J33*'📋 Datos Generales'!E19 -> 0
D34: 28 | E34: ='🧾 Factura Comercial'!E32 -> 0 | F34: ='🧾 Factura Comercial'!G32 -> 0 | G34: ='🧾 Factura Comercial'!H32 -> 0 | H34: ='🧾 Factura Comercial'!I32 -> 0 | I34: ='🧾 Factura Comercial'!J32 -> 0 | J34: =IF(G5=0,0,G5*G34) -> 0 | K34: =J34*'📋 Datos Generales'!E19 -> 0
D35: 29 | E35: ='🧾 Factura Comercial'!E33 -> 0 | F35: ='🧾 Factura Comercial'!G33 -> 0 | G35: ='🧾 Factura Comercial'!H33 -> 0 | H35: ='🧾 Factura Comercial'!I33 -> 0 | I35: ='🧾 Factura Comercial'!J33 -> 0 | J35: =IF(G5=0,0,G5*G35) -> 0 | K35: =J35*'📋 Datos Generales'!E19 -> 0
D36: 30 | E36: ='🧾 Factura Comercial'!E34 -> 0 | F36: ='🧾 Factura Comercial'!G34 -> 0 | G36: ='🧾 Factura Comercial'!H34 -> 0 | H36: ='🧾 Factura Comercial'!I34 -> 0 | I36: ='🧾 Factura Comercial'!J34 -> 0 | J36: =IF(G5=0,0,G5*G36) -> 0 | K36: =J36*'📋 Datos Generales'!E19 -> 0

Sheet 💰 Precio de Venta
D2: 💰 PRECIO DE VENTA — POLÍTICA DE UTILIDADES
D3: Ingrese su margen de ganancia deseado. VV = Costo Total / (1 - Margen%) — Precio de Venta incluye IGV (18%).
D4: MARGEN DE UTILIDAD GLOBAL (aplica a todos — puedes personalizar por producto ↓) | H4: 0.4
D5: VALOR DE VENTA TOTAL SIN IGV USD | H5: ='📦 Gastos Importación'!E28*H4 -> 7435.508
D6: FACTOR DE PRORRATEO = PV TOTAL / FOB TOTAL | H6: =('📦 Gastos Importación'!E28+H5)/'🧾 Factura Comercial'!I35 -> 1.8309214
D7: # | E7: PRODUCTO | F7: C/M UNIT. (PEN) | G7: MARGEN % | H7: VALOR VENTA UNIT. (S/.) | I7: PRECIO VENTA UNIT. c/IGV (S/.) | J7: GANANCIA UNIT. (S/.) | K7: PUNTO EQUILIBRIO
D8: 1 | E8: ='🧾 Factura Comercial'!E5 -> Case Transparente TPU iPhone 15 | F8: ='🧮 Costos x Producto'!K7 -> 5.886674 | G8: =$H$4 -> 0.4 | H8: =IF(F8=0,0,F8/(1-G8)) -> 9.8111233 | I8: =IF(H8=0,0,H8*(1+'📋 Datos Generales'!$E$28)) -> 11.577126 | J8: =IF(H8=0,0,H8-F8) -> 3.9244493 | K8: =IF(OR(I8=0,'🧾 Factura Comercial'!G5=0),0,CEILING('🧮 Costos x Producto'!J7*'🧾 Factura Comercial'!G5/I8,1)) -> 66
D9: 2 | E9: ='🧾 Factura Comercial'!E6 -> Cable USB-C Trenzado 1m | F9: ='🧮 Costos x Producto'!K8 -> 3.3082135 | G9: =$H$4 -> 0.4 | H9: =IF(F9=0,0,F9/(1-G9)) -> 5.5136892 | I9: =IF(H9=0,0,H9*(1+'📋 Datos Generales'!$E$28)) -> 6.5061532 | J9: =IF(H9=0,0,H9-F9) -> 2.2054757 | K9: =IF(OR(I9=0,'🧾 Factura Comercial'!G6=0),0,CEILING('🧮 Costos x Producto'!J8*'🧾 Factura Comercial'!G6/I9,1)) -> 394
D10: 3 | E10: ='🧾 Factura Comercial'!E7 -> Protector Pantalla Vidrio Templado | F10: ='🧮 Costos x Producto'!K9 -> 1.9460079 | G10: 0.4 | H10: =IF(F10=0,0,F10/(1-G10)) -> 3.2433466 | I10: =IF(H10=0,0,H10*(1+'📋 Datos Generales'!$E$28)) -> 3.8271489 | J10: =IF(H10=0,0,H10-F10) -> 1.2973386 | K10: =IF(OR(I10=0,'🧾 Factura Comercial'!G7=0),0,CEILING('🧮 Costos x Producto'!J9*'🧾 Factura Comercial'!G7/I10,1)) -> 394
D11: 4 | E11: ='🧾 Factura Comercial'!E8 -> Audífonos In-Ear con Micrófono | F11: ='🧮 Costos x Producto'!K10 -> 1.6541067 | G11: =$H$4 -> 0.4 | H11: =IF(F11=0,0,F11/(1-G11)) -> 2.7568446 | I11: =IF(H11=0,0,H11*(1+'📋 Datos Generales'!$E$28)) -> 3.2530766 | J11: =IF(H11=0,0,H11-F11) -> 1.1027378 | K11: =IF(OR(I11=0,'🧾 Factura Comercial'!G8=0),0,CEILING('🧮 Costos x Producto'!J10*'🧾 Factura Comercial'!G8/I11,1)) -> 1398
D12: 5 | E12: ='🧾 Factura Comercial'!E9 -> Cable Micro USB 2m Nylon | F12: ='🧮 Costos x Producto'!K11 -> 1.2649052 | G12: =$H$4 -> 0.4 | H12: =IF(F12=0,0,F12/(1-G12)) -> 2.1081753 | I12: =IF(H12=0,0,H12*(1+'📋 Datos Generales'!$E$28)) -> 2.4876468 | J12: =IF(H12=0,0,H12-F12) -> 0.84327011 | K12: =IF(OR(I12=0,'🧾 Factura Comercial'!G9=0),0,CEILING('🧮 Costos x Producto'!J11*'🧾 Factura Comercial'!G9/I12,1)) -> 1181
D13: 6 | E13: ='🧾 Factura Comercial'!E10 -> Soporte Anillo Pop Socket Metálico | F13: ='🧮 Costos x Producto'!K12 -> 1.4108558 | G13: =$H$4 -> 0.4 | H13: =IF(F13=0,0,F13/(1-G13)) -> 2.3514263 | I13: =IF(H13=0,0,H13*(1+'📋 Datos Generales'!$E$28)) -> 2.774683 | J13: =IF(H13=0,0,H13-F13) -> 0.9405705 | K13: =IF(OR(I13=0,'🧾 Factura Comercial'!G10=0),0,CEILING('🧮 Costos x Producto'!J12*'🧾 Factura Comercial'!G10/I13,1)) -> 296
D14: 7 | E14: ='🧾 Factura Comercial'!E11 -> Cargador Inalámbrico 15W Qi | F14: ='🧮 Costos x Producto'!K13 -> 27.779263 | G14: =$H$4 -> 0.4 | H14: =IF(F14=0,0,F14/(1-G14)) -> 46.298772 | I14: =IF(H14=0,0,H14*(1+'📋 Datos Generales'!$E$28)) -> 54.632551 | J14: =IF(H14=0,0,H14-F14) -> 18.519509 | K14: =IF(OR(I14=0,'🧾 Factura Comercial'!G11=0),0,CEILING('🧮 Costos x Producto'!J13*'🧾 Factura Comercial'!G11/I14,1)) -> 33
D15: 8 | E15: ='🧾 Factura Comercial'!E12 -> Case Wallet Cuero PU Samsung S24 | F15: ='🧮 Costos x Producto'!K14 -> 3.6974151 | G15: =$H$4 -> 0.4 | H15: =IF(F15=0,0,F15/(1-G15)) -> 6.1623585 | I15: =IF(H15=0,0,H15*(1+'📋 Datos Generales'!$E$28)) -> 7.271583 | J15: =IF(H15=0,0,H15-F15) -> 2.4649434 | K15: =IF(OR(I15=0,'🧾 Factura Comercial'!G12=0),0,CEILING('🧮 Costos x Producto'!J14*'🧾 Factura Comercial'!G12/I15,1)) -> 263
D16: 9 | E16: ='🧾 Factura Comercial'!E13 -> Adaptador USB-C a Jack 3.5mm | F16: ='🧮 Costos x Producto'!K15 -> 1.3622056 | G16: =$H$4 -> 0.4 | H16: =IF(F16=0,0,F16/(1-G16)) -> 2.2703426 | I16: =IF(H16=0,0,H16*(1+'📋 Datos Generales'!$E$28)) -> 2.6790043 | J16: =IF(H16=0,0,H16-F16) -> 0.90813704 | K16: =IF(OR(I16=0,'🧾 Factura Comercial'!G13=0),0,CEILING('🧮 Costos x Producto'!J15*'🧾 Factura Comercial'!G13/I16,1)) -> 657
D17: 10 | E17: ='🧾 Factura Comercial'!E14 -> 0 | F17: ='🧮 Costos x Producto'!K16 -> 0 | G17: =$H$4 -> 0.4 | H17: =IF(F17=0,0,F17/(1-G17)) -> 0 | I17: =IF(H17=0,0,H17*(1+'📋 Datos Generales'!$E$28)) -> 0 | J17: =IF(H17=0,0,H17-F17) -> 0 | K17: =IF(OR(I17=0,'🧾 Factura Comercial'!G14=0),0,CEILING('🧮 Costos x Producto'!J16*'🧾 Factura Comercial'!G14/I17,1)) -> 0
D18: 11 | E18: ='🧾 Factura Comercial'!E15 -> 0 | F18: ='🧮 Costos x Producto'!K17 -> 0 | G18: =$H$4 -> 0.4 | H18: =IF(F18=0,0,F18/(1-G18)) -> 0 | I18: =IF(H18=0,0,H18*(1+'📋 Datos Generales'!$E$28)) -> 0 | J18: =IF(H18=0,0,H18-F18) -> 0 | K18: =IF(OR(I18=0,'🧾 Factura Comercial'!G15=0),0,CEILING('🧮 Costos x Producto'!J17*'🧾 Factura Comercial'!G15/I18,1)) -> 0
D19: 12 | E19: ='🧾 Factura Comercial'!E16 -> 0 | F19: ='🧮 Costos x Producto'!K18 -> 0 | G19: =$H$4 -> 0.4 | H19: =IF(F19=0,0,F19/(1-G19)) -> 0 | I19: =IF(H19=0,0,H19*(1+'📋 Datos Generales'!$E$28)) -> 0 | J19: =IF(H19=0,0,H19-F19) -> 0 | K19: =IF(OR(I19=0,'🧾 Factura Comercial'!G16=0),0,CEILING('🧮 Costos x Producto'!J18*'🧾 Factura Comercial'!G16/I19,1)) -> 0
D20: 13 | E20: ='🧾 Factura Comercial'!E17 -> 0 | F20: ='🧮 Costos x Producto'!K19 -> 0 | G20: =$H$4 -> 0.4 | H20: =IF(F20=0,0,F20/(1-G20)) -> 0 | I20: =IF(H20=0,0,H20*(1+'📋 Datos Generales'!$E$28)) -> 0 | J20: =IF(H20=0,0,H20-F20) -> 0 | K20: =IF(OR(I20=0,'🧾 Factura Comercial'!G17=0),0,CEILING('🧮 Costos x Producto'!J19*'🧾 Factura Comercial'!G17/I20,1)) -> 0
D21: 14 | E21: ='🧾 Factura Comercial'!E18 -> 0 | F21: ='🧮 Costos x Producto'!K20 -> 0 | G21: =$H$4 -> 0.4 | H21: =IF(F21=0,0,F21/(1-G21)) -> 0 | I21: =IF(H21=0,0,H21*(1+'📋 Datos Generales'!$E$28)) -> 0 | J21: =IF(H21=0,0,H21-F21) -> 0 | K21: =IF(OR(I21=0,'🧾 Factura Comercial'!G18=0),0,CEILING('🧮 Costos x Producto'!J20*'🧾 Factura Comercial'!G18/I21,1)) -> 0
D22: 15 | E22: ='🧾 Factura Comercial'!E19 -> 0 | F22: ='🧮 Costos x Producto'!K21 -> 0 | G22: =$H$4 -> 0.4 | H22: =IF(F22=0,0,F22/(1-G22)) -> 0 | I22: =IF(H22=0,0,H22*(1+'📋 Datos Generales'!$E$28)) -> 0 | J22: =IF(H22=0,0,H22-F22) -> 0 | K22: =IF(OR(I22=0,'🧾 Factura Comercial'!G19=0),0,CEILING('🧮 Costos x Producto'!J21*'🧾 Factura Comercial'!G19/I22,1)) -> 0
... D37: 30 | E37: ='🧾 Factura Comercial'!E34 -> 0 | F37: ='🧮 Costos x Producto'!K36 -> 0 | G37: =$H$4 -> 0.4 | H37: =IF(F37=0,0,F37/(1-G37)) -> 0 | I37: =IF(H37=0,0,H37*(1+'📋 Datos Generales'!$E$28)) -> 0 | J37: =IF(H37=0,0,H37-F37) -> 0 | K37: =IF(OR(I37=0,'🧾 Factura Comercial'!G34=0),0,CEILING('🧮 Costos x Producto'!J36*'🧾 Factura Comercial'!G34/I37,1)) -> 0

Sheet 🏦 Crédito Fiscal
B7: 🏦 CRÉDITO FISCAL DEL IMPORTADOR
B8: El Crédito Fiscal se recupera al vender los productos. IPM, IGV y Percepción NO son costo — se recuperan.
B10: 🏦 DETALLE DEL CRÉDITO FISCAL (en US$ — convertir a S/. con TC)
B11: IGV del Seguro (Crédito Fiscal) | C11: ='🧾 Tributos Aduana'!F12 -> 24.1686 | D11: IGV pagado a Cía. de Seguros
B12: IPM — Derechos (Crédito Fiscal) | C12: ='🧾 Tributos Aduana'!F18 -> 348 | D12: IPM pagado a SUNAT-Aduanas
B13: IGV — Derechos (Crédito Fiscal) | C13: ='🧾 Tributos Aduana'!F19 -> 2788 | D13: IGV pagado a SUNAT-Aduanas
B14: Percepción IGV (Crédito Fiscal) | C14: ='🧾 Tributos Aduana'!F23 -> 719.6 | D14: Percepción pagada — se recupera
B15: IGV Gastos Afectos (Crédito Fiscal) | C15: ='📦 Gastos Importación'!F26 -> 179.5032 | D15: 18% de gastos afectos
B16: ✅ TOTAL CRÉDITO FISCAL (US$) | C16: =C11+C12+C13+C14+C15 -> 4059.2718
B17: ✅ TOTAL CRÉDITO FISCAL (S/. PEN) | C17: =C16*'📋 Datos Generales'!E19 -> 15100.491
B19: 📌 ¿QUÉ ES EL CRÉDITO FISCAL? El IGV, IPM y la Percepción que pagas al importar NO son un costo definitivo. Los recuperas cuando vendes tus productos y cobras IGV a tus clientes. El importador declara ante SUNAT: IGV cobrado en ventas - Crédito Fiscal = IGV a pagar. ⚠️ SOLO el Ad Valorem (ADV) es un costo real de importación.

Sheet Detallado por producto
B1: 📦 SECCIÓN 1: IDENTIFICACIÓN DEL PRODUCTO Y VALOR FOB | AE1: 🧮 SECCIÓN 3: COSTO DE IMPORTACIÓN · CRÉDITO FISCAL · PRECIO DE VENTA · MARGENARGEN
A2: DESCRIPCIÓN DEL PRODUCTO | B2: UNIDAD | C2: CANTIDAD (unid.) | D2: FOB UNIT. (US$) | E2: FOB TOTAL (US$) | F2: % PART. FOB | G2: FOB UNIT. (S/.) | H2: FOB TOTAL (S/.) | I2: ADV UNIT. (US$) ⚠️COSTO | J2: ADV TOTAL (US$) ⚠️COSTO | K2: IPM UNIT. (US$) ✅CF | L2: IPM TOTAL (US$) ✅CF | M2: IGV UNIT. (US$) ✅CF | N2: IGV TOTAL (US$) ✅CF | O2: PERCEP. UNIT.(US$) ✅CF | P2: PERCEP. TOTAL.(US$) ✅CF | Q2: DEUDA ADUANERA UNIT. | R2: DEUDA ADUANERA TOTAL | S2: ADV UNIT. (S/.) | T2: ADV TOTAL. (S/.) | U2: IPM UNIT. (S/.) | V2: IPM TOTAL (S/.)2 | W2: IGV UNIT. (S/.) | X2: IGV TOTAL (S/.)2 | Y2: PERCEP. UNIT.(S/.) | Z2: PERCEP. TOTAL.(S/.)2 | AA2: TOTAL PAGO SUNAT UNIT.(US$) | AB2: TOTAL PAGO SUNAT TOTAL(US$) | AC2: TOTAL TRIB. UNIT.(S/.) | AD2: TOTAL TRIB. TOTAL .(S/.) | AE2: GASTOS IMP. UNIT.(US$) | AF2: GASTOS IMP. TOTAL.(US$)2 | AG2: GASTOS IMP. UNIT.(S/.) | AH2: GASTOS IMP. TOTAL.(S/.)2 | AI2: C/M UNIT. (US$) | AJ2: C/M UNIT. (S/.) | AK2: ADV UNIT. ⚠️COSTO (US$) | AL2: CF UNIT. ✅RECUP. (US$) | AM2: CF UNIT. ✅RECUP.(S/.) | AN2: CREDITO FISCAL POR PRODUCTO | AO2: MARGEN % | AP2: VALOR VTA. UNIT.(S/.) | AQ2: PRECIO VTA. c/IGV(S/.) | AR2: GANANCIA UNIT.(S/.) | AS2: PUNTO EQUILIBRIO | AT2: GANANCIA TOTAL(S/.) | AU2: % UTILIDAD S/PRECIO | AV2: ROI UNIT. | AW2: CLASIF. MARGEN
A3: ='🧾 Factura Comercial'!E5 -> Case Transparente TPU iPhone 15 | B3: ='🧾 Factura Comercial'!F5 -> Unid. | C3: ='🧾 Factura Comercial'!G5 -> 480 | D3: ='🧾 Factura Comercial'!H5 -> 1.21 | E3: ='🧾 Factura Comercial'!I5 -> 580.8 | F3: =IF('🧾 Tributos Aduana'!$F$6=0,0,'🧾 Factura Comercial'!I5/'🧾 Tributos Aduana'!$F$6) -> 0.040861813 | G3: ='🧾 Factura Comercial'!H5*'📋 Datos Generales'!$E$19 -> 4.5012 | H3: =TABLA_BASE[[#This Row],[FOB UNIT. (S/.)]]*TABLA_BASE[[#This Row],[CANTIDAD (unid.)]] -> 2160.576 | I3: =IF('🧾 Tributos Aduana'!$F$6=0,0,'🧾 Tributos Aduana'!$F$17*('🧾 Factura Comercial'!H5/'🧾 Tributos Aduana'!$F$6)) -> 0.083936974 | J3: =TABLA_BASE[[#This Row],[ADV UNIT. (US$) ⚠️COSTO]]*TABLA_BASE[[#This Row],[CANTIDAD (unid.)]] -> 40.289747 | K3: =IF('🧾 Tributos Aduana'!$F$6=0,0,'🧾 Tributos Aduana'!$F$18*('🧾 Factura Comercial'!H5/'🧾 Tributos Aduana'!$F$6)) -> 0.029624814 | L3: =TABLA_BASE[[#This Row],[IPM UNIT. (US$) ✅CF]]*TABLA_BASE[[#This Row],[CANTIDAD (unid.)]] -> 14.219911 | M3: =IF('🧾 Tributos Aduana'!$F$6=0,0,'🧾 Tributos Aduana'!$F$19*('🧾 Factura Comercial'!H5/'🧾 Tributos Aduana'!$F$6)) -> 0.23733903 | N3: =TABLA_BASE[[#This Row],[IGV UNIT. (US$) ✅CF]]*TABLA_BASE[[#This Row],[CANTIDAD (unid.)]] -> 113.92273 | O3: =IF('🧾 Tributos Aduana'!$F$6=0,0,'🧾 Tributos Aduana'!$F$23*('🧾 Factura Comercial'!H5/'🧾 Tributos Aduana'!$F$6)) -> 0.061258668 | P3: =TABLA_BASE[[#This Row],[PERCEP. UNIT.(US$) ✅CF]]*TABLA_BASE[[#This Row],[CANTIDAD (unid.)]] -> 29.40416 | Q3: =TABLA_BASE[[#This Row],[ADV UNIT. (US$) ⚠️COSTO]]+TABLA_BASE[[#This Row],[IPM UNIT. (US$) ✅CF]]+TABLA_BASE[[#This Row],[IGV UNIT. (US$) ✅CF]] -> 0.35090082 | R3: =TABLA_BASE[[#This Row],[DEUDA ADUANERA UNIT.]]*TABLA_BASE[[#This Row],[CANTIDAD (unid.)]] -> 168.43239 | S3: =TABLA_BASE[[#This Row],[ADV UNIT. (US$) ⚠️COSTO]]*'📋 Datos Generales'!$E$19 -> 0.31224554 | T3: =TABLA_BASE[[#This Row],[ADV UNIT. (S/.)]]*TABLA_BASE[[#This Row],[CANTIDAD (unid.)]] -> 149.87786 | U3: =TABLA_BASE[[#This Row],[IPM UNIT. (US$) ✅CF]]*'📋 Datos Generales'!$E$19 -> 0.11020431 | V3: =TABLA_BASE[[#This Row],[IPM UNIT. (S/.)]]*TABLA_BASE[[#This Row],[CANTIDAD (unid.)]] -> 52.898068 | W3: =TABLA_BASE[[#This Row],[IGV UNIT. (US$) ✅CF]]*'📋 Datos Generales'!$E$19 -> 0.88290119 | X3: =TABLA_BASE[[#This Row],[IGV UNIT. (S/.)]]*TABLA_BASE[[#This Row],[CANTIDAD (unid.)]] -> 423.79257 | Y3: =TABLA_BASE[[#This Row],[PERCEP. UNIT.(US$) ✅CF]]*'📋 Datos Generales'!$E$19 -> 0.22788224 | Z3: =TABLA_BASE[[#This Row],[PERCEP. UNIT.(S/.)]]*TABLA_BASE[[#This Row],[CANTIDAD (unid.)]] -> 109.38348 | AA3: =TABLA_BASE[[#This Row],[ADV UNIT. (US$) ⚠️COSTO]]+TABLA_BASE[[#This Row],[IPM UNIT. (US$) ✅CF]]+TABLA_BASE[[#This Row],[IGV UNIT. (US$) ✅CF]]+TABLA_BASE[[#This Row],[PERCEP. UNIT.(US$) ✅CF]] -> 0.41215948 | AB3: =TABLA_BASE[[#This Row],[TOTAL PAGO SUNAT UNIT.(US$)]]*TABLA_BASE[[#This Row],[CANTIDAD (unid.)]] -> 197.83655 | AC3: =TABLA_BASE[[#This Row],[TOTAL PAGO SUNAT UNIT.(US$)]]*'📋 Datos Generales'!$E$19 -> 1.5332333 | AD3: =TABLA_BASE[[#This Row],[TOTAL TRIB. UNIT.(S/.)]]*TABLA_BASE[[#This Row],[CANTIDAD (unid.)]] -> 735.95198 | AE3: =IF('🧾 Factura Comercial'!G5=0,0,'📦 Gastos Importación'!$E$28*(IF('🧾 Tributos Aduana'!$F$6=0,0,'🧾 Factura Comercial'!I5/'🧾 Tributos Aduana'!$F$6))/'🧾 Factura Comercial'!G5) -> 1.5824392 | AF3: =TABLA_BASE[[#This Row],[GASTOS IMP. UNIT.(US$)]]*TABLA_BASE[[#This Row],[CANTIDAD (unid.)]] -> 759.57084 | AG3: =TABLA_BASE[[#This Row],[GASTOS IMP. UNIT.(US$)]]*'📋 Datos Generales'!$E$19 -> 5.886674 | AH3: =TABLA_BASE[[#This Row],[GASTOS IMP. UNIT.(S/.)]]*TABLA_BASE[[#This Row],[CANTIDAD (unid.)]] -> 2825.6035 | AI3: ='🧮 Costos x Producto'!J7 -> 1.5824392 | AJ3: ='🧮 Costos x Producto'!K7 -> 5.886674 | AK3: =IF('🧾 Factura Comercial'!G5=0,0,'🧾 Tributos Aduana'!$F$17*(IF('🧾 Tributos Aduana'!$F$6=0,0,'🧾 Factura Comercial'!I5/'🧾 Tributos Aduana'!$F$6))/'🧾 Factura Comercial'!G5) -> 0.083936974 | AL3: =IF('🧾 Factura Comercial'!G5=0,0,'🏦 Crédito Fiscal'!$C$16*(IF('🧾 Tributos Aduana'!$F$6=0,0,'🧾 Factura Comercial'!I5/'🧾 Tributos Aduana'!$F$6))/'🧾 Factura Comercial'!G5) -> 0.34556084 | AM3: =TABLA_BASE[[#This Row],[CF UNIT. ✅RECUP. (US$)]]*'📋 Datos Generales'!$E$19 -> 1.2854863 | AN3: =TABLA_BASE[[#This Row],[CF UNIT. ✅RECUP.(S/.)]]*TABLA_BASE[[#This Row],[CANTIDAD (unid.)]] -> 617.03344 | AO3: ='💰 Precio de Venta'!G8 -> 0.4 | AP3: ='💰 Precio de Venta'!H8 -> 9.8111233 | AQ3: ='💰 Precio de Venta'!I8 -> 11.577126 | AR3: ='💰 Precio de Venta'!J8 -> 3.9244493 | AS3: ='💰 Precio de Venta'!K8 -> 66 | AT3: =TABLA_BASE[[#This Row],[GANANCIA UNIT.(S/.)]]*'🧾 Factura Comercial'!G5 -> 1883.7357 | AU3: =IF(TABLA_BASE[[#This Row],[PRECIO VTA. c/IGV(S/.)]]=0,0,TABLA_BASE[[#This Row],[GANANCIA UNIT.(S/.)]]/TABLA_BASE[[#This Row],[PRECIO VTA. c/IGV(S/.)]]) -> 0.33898305 | AV3: =IF(TABLA_BASE[[#This Row],[C/M UNIT. (S/.)]]=0,0,TABLA_BASE[[#This Row],[GANANCIA UNIT.(S/.)]]/TABLA_BASE[[#This Row],[C/M UNIT. (S/.)]]) -> 0.66666667 | AW3: =IF(TABLA_BASE[[#This Row],[MARGEN %]]>=0.5,"🟢 ALTO",IF(TABLA_BASE[[#This Row],[MARGEN %]]>=0.3,"🟡 MEDIO","🔴 BAJO")) -> 🟡 MEDIO
A4: ='🧾 Factura Comercial'!E6 -> Cable USB-C Trenzado 1m | B4: ='🧾 Factura Comercial'!F6 -> Unid. | C4: ='🧾 Factura Comercial'!G6 -> 2880 | D4: ='🧾 Factura Comercial'!H6 -> 0.68 | E4: ='🧾 Factura Comercial'!I6 -> 1958.4 | F4: =IF('🧾 Tributos Aduana'!$F$6=0,0,'🧾 Factura Comercial'!I6/'🧾 Tributos Aduana'!$F$6) -> 0.13778198 | G4: ='🧾 Factura Comercial'!H6*'📋 Datos Generales'!$E$19 -> 2.5296 | H4: =TABLA_BASE[[#This Row],[FOB UNIT. (S/.)]]*TABLA_BASE[[#This Row],[CANTIDAD (unid.)]] -> 7285.248 | I4: =IF('🧾 Tributos Aduana'!$F$6=0,0,'🧾 Tributos Aduana'!$F$17*('🧾 Factura Comercial'!H6/'🧾 Tributos Aduana'!$F$6)) -> 0.047171192 | J4: =TABLA_BASE[[#This Row],[ADV UNIT. (US$) ⚠️COSTO]]*TABLA_BASE[[#This Row],[CANTIDAD (unid.)]] -> 135.85303 | K4: =IF('🧾 Tributos Aduana'!$F$6=0,0,'🧾 Tributos Aduana'!$F$18*('🧾 Factura Comercial'!H6/'🧾 Tributos Aduana'!$F$6)) -> 0.016648656 | L4: =TABLA_BASE[[#This Row],[IPM UNIT. (US$) ✅CF]]*TABLA_BASE[[#This Row],[CANTIDAD (unid.)]] -> 47.948129 | M4: =IF('🧾 Tributos Aduana'!$F$6=0,0,'🧾 Tributos Aduana'!$F$19*('🧾 Factura Comercial'!H6/'🧾 Tributos Aduana'!$F$6)) -> 0.13338061 | N4: =TABLA_BASE[[#This Row],[IGV UNIT. (US$) ✅CF]]*TABLA_BASE[[#This Row],[CANTIDAD (unid.)]] -> 384.13616 | O4: =IF('🧾 Tributos Aduana'!$F$6=0,0,'🧾 Tributos Aduana'!$F$23*('🧾 Factura Comercial'!H6/'🧾 Tributos Aduana'!$F$6)) -> 0.034426359 | P4: =TABLA_BASE[[#This Row],[PERCEP. UNIT.(US$) ✅CF]]*TABLA_BASE[[#This Row],[CANTIDAD (unid.)]] -> 99.147913 | Q4: =TABLA_BASE[[#This Row],[ADV UNIT. (US$) ⚠️COSTO]]+TABLA_BASE[[#This Row],[IPM UNIT. (US$) ✅CF]]+TABLA_BASE[[#This Row],[IGV UNIT. (US$) ✅CF]] -> 0.19720046 | R4: =TABLA_BASE[[#This Row],[DEUDA ADUANERA UNIT.]]*TABLA_BASE[[#This Row],[CANTIDAD (unid.)]] -> 567.93732 | S4: =TABLA_BASE[[#This Row],[ADV UNIT. (US$) ⚠️COSTO]]*'📋 Datos Generales'!$E$19 -> 0.17547683 | T4: =TABLA_BASE[[#This Row],[ADV UNIT. (S/.)]]*TABLA_BASE[[#This Row],[CANTIDAD (unid.)]] -> 505.37328 | U4: =TABLA_BASE[[#This Row],[IPM UNIT. (US$) ✅CF]]*'📋 Datos Generales'!$E$19 -> 0.061933 | V4: =TABLA_BASE[[#This Row],[IPM UNIT. (S/.)]]*TABLA_BASE[[#This Row],[CANTIDAD (unid.)]] -> 178.36704 | W4: =TABLA_BASE[[#This Row],[IGV UNIT. (US$) ✅CF]]*'📋 Datos Generales'!$E$19 -> 0.49617587 | X4: =TABLA_BASE[[#This Row],[IGV UNIT. (S/.)]]*TABLA_BASE[[#This Row],[CANTIDAD (unid.)]] -> 1428.9865 | Y4: =TABLA_BASE[[#This Row],[PERCEP. UNIT.(US$) ✅CF]]*'📋 Datos Generales'!$E$19 -> 0.12806605 | Z4: =TABLA_BASE[[#This Row],[PERCEP. UNIT.(S/.)]]*TABLA_BASE[[#This Row],[CANTIDAD (unid.)]] -> 368.83024 | AA4: =TABLA_BASE[[#This Row],[ADV UNIT. (US$) ⚠️COSTO]]+TABLA_BASE[[#This Row],[IPM UNIT. (US$) ✅CF]]+TABLA_BASE[[#This Row],[IGV UNIT. (US$) ✅CF]]+TABLA_BASE[[#This Row],[PERCEP. UNIT.(US$) ✅CF]] -> 0.23162682 | AB4: =TABLA_BASE[[#This Row],[TOTAL PAGO SUNAT UNIT.(US$)]]*TABLA_BASE[[#This Row],[CANTIDAD (unid.)]] -> 667.08524 | AC4: =TABLA_BASE[[#This Row],[TOTAL PAGO SUNAT UNIT.(US$)]]*'📋 Datos Generales'!$E$19 -> 0.86165176 | AD4: =TABLA_BASE[[#This Row],[TOTAL TRIB. UNIT.(S/.)]]*TABLA_BASE[[#This Row],[CANTIDAD (unid.)]] -> 2481.5571 | AE4: =IF('🧾 Factura Comercial'!G6=0,0,'📦 Gastos Importación'!$E$28*(IF('🧾 Tributos Aduana'!$F$6=0,0,'🧾 Factura Comercial'!I6/'🧾 Tributos Aduana'!$F$6))/'🧾 Factura Comercial'!G6) -> 0.8893047 | AF4: =TABLA_BASE[[#This Row],[GASTOS IMP. UNIT.(US$)]]*TABLA_BASE[[#This Row],[CANTIDAD (unid.)]] -> 2561.1975 | AG4: =TABLA_BASE[[#This Row],[GASTOS IMP. UNIT.(US$)]]*'📋 Datos Generales'!$E$19 -> 3.3082135 | AH4: =TABLA_BASE[[#This Row],[GASTOS IMP. UNIT.(S/.)]]*TABLA_BASE[[#This Row],[CANTIDAD (unid.)]] -> 9527.6549 | AI4: ='🧮 Costos x Producto'!J8 -> 0.8893047 | AJ4: ='🧮 Costos x Producto'!K8 -> 3.3082135 | AK4: =IF('🧾 Factura Comercial'!G6=0,0,'🧾 Tributos Aduana'!$F$17*(IF('🧾 Tributos Aduana'!$F$6=0,0,'🧾 Factura Comercial'!I6/'🧾 Tributos Aduana'!$F$6))/'🧾 Factura Comercial'!G6) -> 0.047171192 | AL4: =IF('🧾 Factura Comercial'!G6=0,0,'🏦 Crédito Fiscal'!$C$16*(IF('🧾 Tributos Aduana'!$F$6=0,0,'🧾 Factura Comercial'!I6/'🧾 Tributos Aduana'!$F$6))/'🧾 Factura Comercial'!G6) -> 0.19419948 | AM4: =TABLA_BASE[[#This Row],[CF UNIT. ✅RECUP. (US$)]]*'📋 Datos Generales'!$E$19 -> 0.72242207 | AN4: =TABLA_BASE[[#This Row],[CF UNIT. ✅RECUP.(S/.)]]*TABLA_BASE[[#This Row],[CANTIDAD (unid.)]] -> 2080.5756 | AO4: ='💰 Precio de Venta'!G9 -> 0.4 | AP4: ='💰 Precio de Venta'!H9 -> 5.5136892 | AQ4: ='💰 Precio de Venta'!I9 -> 6.5061532 | AR4: ='💰 Precio de Venta'!J9 -> 2.2054757 | AS4: ='💰 Precio de Venta'!K9 -> 394 | AT4: =TABLA_BASE[[#This Row],[GANANCIA UNIT.(S/.)]]*'🧾 Factura Comercial'!G6 -> 6351.7699 | AU4: =IF(TABLA_BASE[[#This Row],[PRECIO VTA. c/IGV(S/.)]]=0,0,TABLA_BASE[[#This Row],[GANANCIA UNIT.(S/.)]]/TABLA_BASE[[#This Row],[PRECIO VTA. c/IGV(S/.)]]) -> 0.33898305 | AV4: =IF(TABLA_BASE[[#This Row],[C/M UNIT. (S/.)]]=0,0,TABLA_BASE[[#This Row],[GANANCIA UNIT.(S/.)]]/TABLA_BASE[[#This Row],[C/M UNIT. (S/.)]]) -> 0.66666667 | AW4: =IF(TABLA_BASE[[#This Row],[MARGEN %]]>=0.5,"🟢 ALTO",IF(TABLA_BASE[[#This Row],[MARGEN %]]>=0.3,"🟡 MEDIO","🔴 BAJO")) -> 🟡 MEDIO
A5: ='🧾 Factura Comercial'!E7 -> Protector Pantalla Vidrio Templado | B5: ='🧾 Factura Comercial'!F7 -> Unid. | C5: ='🧾 Factura Comercial'!G7 -> 2880 | D5: ='🧾 Factura Comercial'!H7 -> 0.4 | E5: ='🧾 Factura Comercial'!I7 -> 1152 | F5: =IF('🧾 Tributos Aduana'!$F$6=0,0,'🧾 Factura Comercial'!I7/'🧾 Tributos Aduana'!$F$6) -> 0.081048224 | G5: ='🧾 Factura Comercial'!H7*'📋 Datos Generales'!$E$19 -> 1.488 | H5: =TABLA_BASE[[#This Row],[FOB UNIT. (S/.)]]*TABLA_BASE[[#This Row],[CANTIDAD (unid.)]] -> 4285.44 | I5: =IF('🧾 Tributos Aduana'!$F$6=0,0,'🧾 Tributos Aduana'!$F$17*('🧾 Factura Comercial'!H7/'🧾 Tributos Aduana'!$F$6)) -> 0.02774776 | J5: =TABLA_BASE[[#This Row],[ADV UNIT. (US$) ⚠️COSTO]]*TABLA_BASE[[#This Row],[CANTIDAD (unid.)]] -> 79.913549 | K5: =IF('🧾 Tributos Aduana'!$F$6=0,0,'🧾 Tributos Aduana'!$F$18*('🧾 Factura Comercial'!H7/'🧾 Tributos Aduana'!$F$6)) -> 0.009793327 | L5: =TABLA_BASE[[#This Row],[IPM UNIT. (US$) ✅CF]]*TABLA_BASE[[#This Row],[CANTIDAD (unid.)]] -> 28.204782 | M5: =IF('🧾 Tributos Aduana'!$F$6=0,0,'🧾 Tributos Aduana'!$F$19*('🧾 Factura Comercial'!H7/'🧾 Tributos Aduana'!$F$6)) -> 0.078459183 | N5: =TABLA_BASE[[#This Row],[IGV UNIT. (US$) ✅CF]]*TABLA_BASE[[#This Row],[CANTIDAD (unid.)]] -> 225.96245 | O5: =IF('🧾 Tributos Aduana'!$F$6=0,0,'🧾 Tributos Aduana'!$F$23*('🧾 Factura Comercial'!H7/'🧾 Tributos Aduana'!$F$6)) -> 0.020250799 | P5: =TABLA_BASE[[#This Row],[PERCEP. UNIT.(US$) ✅CF]]*TABLA_BASE[[#This Row],[CANTIDAD (unid.)]] -> 58.322302 | Q5: =TABLA_BASE[[#This Row],[ADV UNIT. (US$) ⚠️COSTO]]+TABLA_BASE[[#This Row],[IPM UNIT. (US$) ✅CF]]+TABLA_BASE[[#This Row],[IGV UNIT. (US$) ✅CF]] -> 0.11600027 | R5: =TABLA_BASE[[#This Row],[DEUDA ADUANERA UNIT.]]*TABLA_BASE[[#This Row],[CANTIDAD (unid.)]] -> 334.08078 | S5: =TABLA_BASE[[#This Row],[ADV UNIT. (US$) ⚠️COSTO]]*'📋 Datos Generales'!$E$19 -> 0.10322167 | T5: =TABLA_BASE[[#This Row],[ADV UNIT. (S/.)]]*TABLA_BASE[[#This Row],[CANTIDAD (unid.)]] -> 297.2784 | U5: =TABLA_BASE[[#This Row],[IPM UNIT. (US$) ✅CF]]*'📋 Datos Generales'!$E$19 -> 0.036431177 | V5: =TABLA_BASE[[#This Row],[IPM UNIT. (S/.)]]*TABLA_BASE[[#This Row],[CANTIDAD (unid.)]] -> 104.92179 | W5: =TABLA_BASE[[#This Row],[IGV UNIT. (US$) ✅CF]]*'📋 Datos Generales'!$E$19 -> 0.29186816 | X5: =TABLA_BASE[[#This Row],[IGV UNIT. (S/.)]]*TABLA_BASE[[#This Row],[CANTIDAD (unid.)]] -> 840.58031 | Y5: =TABLA_BASE[[#This Row],[PERCEP. UNIT.(US$) ✅CF]]*'📋 Datos Generales'!$E$19 -> 0.075332973 | Z5: =TABLA_BASE[[#This Row],[PERCEP. UNIT.(S/.)]]*TABLA_BASE[[#This Row],[CANTIDAD (unid.)]] -> 216.95896 | AA5: =TABLA_BASE[[#This Row],[ADV UNIT. (US$) ⚠️COSTO]]+TABLA_BASE[[#This Row],[IPM UNIT. (US$) ✅CF]]+TABLA_BASE[[#This Row],[IGV UNIT. (US$) ✅CF]]+TABLA_BASE[[#This Row],[PERCEP. UNIT.(US$) ✅CF]] -> 0.13625107 | AB5: =TABLA_BASE[[#This Row],[TOTAL PAGO SUNAT UNIT.(US$)]]*TABLA_BASE[[#This Row],[CANTIDAD (unid.)]] -> 392.40308 | AC5: =TABLA_BASE[[#This Row],[TOTAL PAGO SUNAT UNIT.(US$)]]*'📋 Datos Generales'!$E$19 -> 0.50685398 | AD5: =TABLA_BASE[[#This Row],[TOTAL TRIB. UNIT.(S/.)]]*TABLA_BASE[[#This Row],[CANTIDAD (unid.)]] -> 1459.7395 | AE5: =IF('🧾 Factura Comercial'!G7=0,0,'📦 Gastos Importación'!$E$28*(IF('🧾 Tributos Aduana'!$F$6=0,0,'🧾 Factura Comercial'!I7/'🧾 Tributos Aduana'!$F$6))/'🧾 Factura Comercial'!G7) -> 0.52312041 | AF5: =TABLA_BASE[[#This Row],[GASTOS IMP. UNIT.(US$)]]*TABLA_BASE[[#This Row],[CANTIDAD (unid.)]] -> 1506.5868 | AG5: =TABLA_BASE[[#This Row],[GASTOS IMP. UNIT.(US$)]]*'📋 Datos Generales'!$E$19 -> 1.9460079 | AH5: =TABLA_BASE[[#This Row],[GASTOS IMP. UNIT.(S/.)]]*TABLA_BASE[[#This Row],[CANTIDAD (unid.)]] -> 5604.5029 | AI5: ='🧮 Costos x Producto'!J9 -> 0.52312041 | AJ5: ='🧮 Costos x Producto'!K9 -> 1.9460079 | AK5: =IF('🧾 Factura Comercial'!G7=0,0,'🧾 Tributos Aduana'!$F$17*(IF('🧾 Tributos Aduana'!$F$6=0,0,'🧾 Factura Comercial'!I7/'🧾 Tributos Aduana'!$F$6))/'🧾 Factura Comercial'!G7) -> 0.02774776 | AL5: =IF('🧾 Factura Comercial'!G7=0,0,'🏦 Crédito Fiscal'!$C$16*(IF('🧾 Tributos Aduana'!$F$6=0,0,'🧾 Factura Comercial'!I7/'🧾 Tributos Aduana'!$F$6))/'🧾 Factura Comercial'!G7) -> 0.11423499 | AM5: =TABLA_BASE[[#This Row],[CF UNIT. ✅RECUP. (US$)]]*'📋 Datos Generales'!$E$19 -> 0.42495416 | AN5: =TABLA_BASE[[#This Row],[CF UNIT. ✅RECUP.(S/.)]]*TABLA_BASE[[#This Row],[CANTIDAD (unid.)]] -> 1223.868 | AO5: ='💰 Precio de Venta'!G10 -> 0.4 | AP5: ='💰 Precio de Venta'!H10 -> 3.2433466 | AQ5: ='💰 Precio de Venta'!I10 -> 3.8271489 | AR5: ='💰 Precio de Venta'!J10 -> 1.2973386 | AS5: ='💰 Precio de Venta'!K10 -> 394 | AT5: =TABLA_BASE[[#This Row],[GANANCIA UNIT.(S/.)]]*'🧾 Factura Comercial'!G7 -> 3736.3352 | AU5: =IF(TABLA_BASE[[#This Row],[PRECIO VTA. c/IGV(S/.)]]=0,0,TABLA_BASE[[#This Row],[GANANCIA UNIT.(S/.)]]/TABLA_BASE[[#This Row],[PRECIO VTA. c/IGV(S/.)]]) -> 0.33898305 | AV5: =IF(TABLA_BASE[[#This Row],[C/M UNIT. (S/.)]]=0,0,TABLA_BASE[[#This Row],[GANANCIA UNIT.(S/.)]]/TABLA_BASE[[#This Row],[C/M UNIT. (S/.)]]) -> 0.66666667 | AW5: =IF(TABLA_BASE[[#This Row],[MARGEN %]]>=0.5,"🟢 ALTO",IF(TABLA_BASE[[#This Row],[MARGEN %]]>=0.3,"🟡 MEDIO","🔴 BAJO")) -> 🟡 MEDIO
A6: ='🧾 Factura Comercial'!E8 -> Audífonos In-Ear con Micrófono | B6: ='🧾 Factura Comercial'!F8 -> Unid. | C6: ='🧾 Factura Comercial'!G8 -> 10224 | D6: ='🧾 Factura Comercial'!H8 -> 0.34 | E6: ='🧾 Factura Comercial'!I8 -> 3476.16 | F6: =IF('🧾 Tributos Aduana'!$F$6=0,0,'🧾 Factura Comercial'!I8/'🧾 Tributos Aduana'!$F$6) -> 0.24456301 | G6: ='🧾 Factura Comercial'!H8*'📋 Datos Generales'!$E$19 -> 1.2648 | H6: =TABLA_BASE[[#This Row],[FOB UNIT. (S/.)]]*TABLA_BASE[[#This Row],[CANTIDAD (unid.)]] -> 12931.315 | I6: =IF('🧾 Tributos Aduana'!$F$6=0,0,'🧾 Tributos Aduana'!$F$17*('🧾 Factura Comercial'!H8/'🧾 Tributos Aduana'!$F$6)) -> 0.023585596 | J6: =TABLA_BASE[[#This Row],[ADV UNIT. (US$) ⚠️COSTO]]*TABLA_BASE[[#This Row],[CANTIDAD (unid.)]] -> 241.13913 | K6: =IF('🧾 Tributos Aduana'!$F$6=0,0,'🧾 Tributos Aduana'!$F$18*('🧾 Factura Comercial'!H8/'🧾 Tributos Aduana'!$F$6)) -> 0.008324328 | L6: =TABLA_BASE[[#This Row],[IPM UNIT. (US$) ✅CF]]*TABLA_BASE[[#This Row],[CANTIDAD (unid.)]] -> 85.107929 | M6: =IF('🧾 Tributos Aduana'!$F$6=0,0,'🧾 Tributos Aduana'!$F$19*('🧾 Factura Comercial'!H8/'🧾 Tributos Aduana'!$F$6)) -> 0.066690306 | N6: =TABLA_BASE[[#This Row],[IGV UNIT. (US$) ✅CF]]*TABLA_BASE[[#This Row],[CANTIDAD (unid.)]] -> 681.84169 | O6: =IF('🧾 Tributos Aduana'!$F$6=0,0,'🧾 Tributos Aduana'!$F$23*('🧾 Factura Comercial'!H8/'🧾 Tributos Aduana'!$F$6)) -> 0.017213179 | P6: =TABLA_BASE[[#This Row],[PERCEP. UNIT.(US$) ✅CF]]*TABLA_BASE[[#This Row],[CANTIDAD (unid.)]] -> 175.98755 | Q6: =TABLA_BASE[[#This Row],[ADV UNIT. (US$) ⚠️COSTO]]+TABLA_BASE[[#This Row],[IPM UNIT. (US$) ✅CF]]+TABLA_BASE[[#This Row],[IGV UNIT. (US$) ✅CF]] -> 0.09860023 | R6: =TABLA_BASE[[#This Row],[DEUDA ADUANERA UNIT.]]*TABLA_BASE[[#This Row],[CANTIDAD (unid.)]] -> 1008.0887 | S6: =TABLA_BASE[[#This Row],[ADV UNIT. (US$) ⚠️COSTO]]*'📋 Datos Generales'!$E$19 -> 0.087738417 | T6: =TABLA_BASE[[#This Row],[ADV UNIT. (S/.)]]*TABLA_BASE[[#This Row],[CANTIDAD (unid.)]] -> 897.03757 | U6: =TABLA_BASE[[#This Row],[IPM UNIT. (US$) ✅CF]]*'📋 Datos Generales'!$E$19 -> 0.0309665 | V6: =TABLA_BASE[[#This Row],[IPM UNIT. (S/.)]]*TABLA_BASE[[#This Row],[CANTIDAD (unid.)]] -> 316.6015 | W6: =TABLA_BASE[[#This Row],[IGV UNIT. (US$) ✅CF]]*'📋 Datos Generales'!$E$19 -> 0.24808794 | X6: =TABLA_BASE[[#This Row],[IGV UNIT. (S/.)]]*TABLA_BASE[[#This Row],[CANTIDAD (unid.)]] -> 2536.4511 | Y6: =TABLA_BASE[[#This Row],[PERCEP. UNIT.(US$) ✅CF]]*'📋 Datos Generales'!$E$19 -> 0.064033027 | Z6: =TABLA_BASE[[#This Row],[PERCEP. UNIT.(S/.)]]*TABLA_BASE[[#This Row],[CANTIDAD (unid.)]] -> 654.67367 | AA6: =TABLA_BASE[[#This Row],[ADV UNIT. (US$) ⚠️COSTO]]+TABLA_BASE[[#This Row],[IPM UNIT. (US$) ✅CF]]+TABLA_BASE[[#This Row],[IGV UNIT. (US$) ✅CF]]+TABLA_BASE[[#This Row],[PERCEP. UNIT.(US$) ✅CF]] -> 0.11581341 | AB6: =TABLA_BASE[[#This Row],[TOTAL PAGO SUNAT UNIT.(US$)]]*TABLA_BASE[[#This Row],[CANTIDAD (unid.)]] -> 1184.0763 | AC6: =TABLA_BASE[[#This Row],[TOTAL PAGO SUNAT UNIT.(US$)]]*'📋 Datos Generales'!$E$19 -> 0.43082588 | AD6: =TABLA_BASE[[#This Row],[TOTAL TRIB. UNIT.(S/.)]]*TABLA_BASE[[#This Row],[CANTIDAD (unid.)]] -> 4404.7638 | AE6: =IF('🧾 Factura Comercial'!G8=0,0,'📦 Gastos Importación'!$E$28*(IF('🧾 Tributos Aduana'!$F$6=0,0,'🧾 Factura Comercial'!I8/'🧾 Tributos Aduana'!$F$6))/'🧾 Factura Comercial'!G8) -> 0.44465235 | AF6: =TABLA_BASE[[#This Row],[GASTOS IMP. UNIT.(US$)]]*TABLA_BASE[[#This Row],[CANTIDAD (unid.)]] -> 4546.1256 | AG6: =TABLA_BASE[[#This Row],[GASTOS IMP. UNIT.(US$)]]*'📋 Datos Generales'!$E$19 -> 1.6541067 | AH6: =TABLA_BASE[[#This Row],[GASTOS IMP. UNIT.(S/.)]]*TABLA_BASE[[#This Row],[CANTIDAD (unid.)]] -> 16911.587 | AI6: ='🧮 Costos x Producto'!J10 -> 0.44465235 | AJ6: ='🧮 Costos x Producto'!K10 -> 1.6541067 | AK6: =IF('🧾 Factura Comercial'!G8=0,0,'🧾 Tributos Aduana'!$F$17*(IF('🧾 Tributos Aduana'!$F$6=0,0,'🧾 Factura Comercial'!I8/'🧾 Tributos Aduana'!$F$6))/'🧾 Factura Comercial'!G8) -> 0.023585596 | AL6: =IF('🧾 Factura Comercial'!G8=0,0,'🏦 Crédito Fiscal'!$C$16*(IF('🧾 Tributos Aduana'!$F$6=0,0,'🧾 Factura Comercial'!I8/'🧾 Tributos Aduana'!$F$6))/'🧾 Factura Comercial'!G8) -> 0.097099741 | AM6: =TABLA_BASE[[#This Row],[CF UNIT. ✅RECUP. (US$)]]*'📋 Datos Generales'!$E$19 -> 0.36121104 | AN6: =TABLA_BASE[[#This Row],[CF UNIT. ✅RECUP.(S/.)]]*TABLA_BASE[[#This Row],[CANTIDAD (unid.)]] -> 3693.0216 | AO6: ='💰 Precio de Venta'!G11 -> 0.4 | AP6: ='💰 Precio de Venta'!H11 -> 2.7568446 | AQ6: ='💰 Precio de Venta'!I11 -> 3.2530766 | AR6: ='💰 Precio de Venta'!J11 -> 1.1027378 | AS6: ='💰 Precio de Venta'!K11 -> 1398 | AT6: =TABLA_BASE[[#This Row],[GANANCIA UNIT.(S/.)]]*'🧾 Factura Comercial'!G8 -> 11274.392 | AU6: =IF(TABLA_BASE[[#This Row],[PRECIO VTA. c/IGV(S/.)]]=0,0,TABLA_BASE[[#This Row],[GANANCIA UNIT.(S/.)]]/TABLA_BASE[[#This Row],[PRECIO VTA. c/IGV(S/.)]]) -> 0.33898305 | AV6: =IF(TABLA_BASE[[#This Row],[C/M UNIT. (S/.)]]=0,0,TABLA_BASE[[#This Row],[GANANCIA UNIT.(S/.)]]/TABLA_BASE[[#This Row],[C/M UNIT. (S/.)]]) -> 0.66666667 | AW6: =IF(TABLA_BASE[[#This Row],[MARGEN %]]>=0.5,"🟢 ALTO",IF(TABLA_BASE[[#This Row],[MARGEN %]]>=0.3,"🟡 MEDIO","🔴 BAJO")) -> 🟡 MEDIO
A7: ='🧾 Factura Comercial'!E9 -> Cable Micro USB 2m Nylon | B7: ='🧾 Factura Comercial'!F9 -> Unid. | C7: ='🧾 Factura Comercial'!G9 -> 8640 | D7: ='🧾 Factura Comercial'!H9 -> 0.26 | E7: ='🧾 Factura Comercial'!I9 -> 2246.4 | F7: =IF('🧾 Tributos Aduana'!$F$6=0,0,'🧾 Factura Comercial'!I9/'🧾 Tributos Aduana'!$F$6) -> 0.15804404 | G7: ='🧾 Factura Comercial'!H9*'📋 Datos Generales'!$E$19 -> 0.9672 | H7: =TABLA_BASE[[#This Row],[FOB UNIT. (S/.)]]*TABLA_BASE[[#This Row],[CANTIDAD (unid.)]] -> 8356.608 | I7: =IF('🧾 Tributos Aduana'!$F$6=0,0,'🧾 Tributos Aduana'!$F$17*('🧾 Factura Comercial'!H9/'🧾 Tributos Aduana'!$F$6)) -> 0.018036044 | J7: =TABLA_BASE[[#This Row],[ADV UNIT. (US$) ⚠️COSTO]]*TABLA_BASE[[#This Row],[CANTIDAD (unid.)]] -> 155.83142 | K7: =IF('🧾 Tributos Aduana'!$F$6=0,0,'🧾 Tributos Aduana'!$F$18*('🧾 Factura Comercial'!H9/'🧾 Tributos Aduana'!$F$6)) -> 0.0063656626 | L7: =TABLA_BASE[[#This Row],[IPM UNIT. (US$) ✅CF]]*TABLA_BASE[[#This Row],[CANTIDAD (unid.)]] -> 54.999325 | M7: =IF('🧾 Tributos Aduana'!$F$6=0,0,'🧾 Tributos Aduana'!$F$19*('🧾 Factura Comercial'!H9/'🧾 Tributos Aduana'!$F$6)) -> 0.050998469 | N7: =TABLA_BASE[[#This Row],[IGV UNIT. (US$) ✅CF]]*TABLA_BASE[[#This Row],[CANTIDAD (unid.)]] -> 440.62677 | O7: =IF('🧾 Tributos Aduana'!$F$6=0,0,'🧾 Tributos Aduana'!$F$23*('🧾 Factura Comercial'!H9/'🧾 Tributos Aduana'!$F$6)) -> 0.013163019 | P7: =TABLA_BASE[[#This Row],[PERCEP. UNIT.(US$) ✅CF]]*TABLA_BASE[[#This Row],[CANTIDAD (unid.)]] -> 113.72849 | Q7: =TABLA_BASE[[#This Row],[ADV UNIT. (US$) ⚠️COSTO]]+TABLA_BASE[[#This Row],[IPM UNIT. (US$) ✅CF]]+TABLA_BASE[[#This Row],[IGV UNIT. (US$) ✅CF]] -> 0.075400176 | R7: =TABLA_BASE[[#This Row],[DEUDA ADUANERA UNIT.]]*TABLA_BASE[[#This Row],[CANTIDAD (unid.)]] -> 651.45752 | S7: =TABLA_BASE[[#This Row],[ADV UNIT. (US$) ⚠️COSTO]]*'📋 Datos Generales'!$E$19 -> 0.067094083 | T7: =TABLA_BASE[[#This Row],[ADV UNIT. (S/.)]]*TABLA_BASE[[#This Row],[CANTIDAD (unid.)]] -> 579.69288 | U7: =TABLA_BASE[[#This Row],[IPM UNIT. (US$) ✅CF]]*'📋 Datos Generales'!$E$19 -> 0.023680265 | V7: =TABLA_BASE[[#This Row],[IPM UNIT. (S/.)]]*TABLA_BASE[[#This Row],[CANTIDAD (unid.)]] -> 204.59749 | W7: =TABLA_BASE[[#This Row],[IGV UNIT. (US$) ✅CF]]*'📋 Datos Generales'!$E$19 -> 0.18971431 | X7: =TABLA_BASE[[#This Row],[IGV UNIT. (S/.)]]*TABLA_BASE[[#This Row],[CANTIDAD (unid.)]] -> 1639.1316 | Y7: =TABLA_BASE[[#This Row],[PERCEP. UNIT.(US$) ✅CF]]*'📋 Datos Generales'!$E$19 -> 0.048966433 | Z7: =TABLA_BASE[[#This Row],[PERCEP. UNIT.(S/.)]]*TABLA_BASE[[#This Row],[CANTIDAD (unid.)]] -> 423.06998 | AA7: =TABLA_BASE[[#This Row],[ADV UNIT. (US$) ⚠️COSTO]]+TABLA_BASE[[#This Row],[IPM UNIT. (US$) ✅CF]]+TABLA_BASE[[#This Row],[IGV UNIT. (US$) ✅CF]]+TABLA_BASE[[#This Row],[PERCEP. UNIT.(US$) ✅CF]] -> 0.088563195 | AB7: =TABLA_BASE[[#This Row],[TOTAL PAGO SUNAT UNIT.(US$)]]*TABLA_BASE[[#This Row],[CANTIDAD (unid.)]] -> 765.18601 | AC7: =TABLA_BASE[[#This Row],[TOTAL PAGO SUNAT UNIT.(US$)]]*'📋 Datos Generales'!$E$19 -> 0.32945509 | AD7: =TABLA_BASE[[#This Row],[TOTAL TRIB. UNIT.(S/.)]]*TABLA_BASE[[#This Row],[CANTIDAD (unid.)]] -> 2846.4919 | AE7: =IF('🧾 Factura Comercial'!G9=0,0,'📦 Gastos Importación'!$E$28*(IF('🧾 Tributos Aduana'!$F$6=0,0,'🧾 Factura Comercial'!I9/'🧾 Tributos Aduana'!$F$6))/'🧾 Factura Comercial'!G9) -> 0.34002827 | AF7: =TABLA_BASE[[#This Row],[GASTOS IMP. UNIT.(US$)]]*TABLA_BASE[[#This Row],[CANTIDAD (unid.)]] -> 2937.8442 | AG7: =TABLA_BASE[[#This Row],[GASTOS IMP. UNIT.(US$)]]*'📋 Datos Generales'!$E$19 -> 1.2649052 | AH7: =TABLA_BASE[[#This Row],[GASTOS IMP. UNIT.(S/.)]]*TABLA_BASE[[#This Row],[CANTIDAD (unid.)]] -> 10928.781 | AI7: ='🧮 Costos x Producto'!J11 -> 0.34002827 | AJ7: ='🧮 Costos x Producto'!K11 -> 1.2649052 | AK7: =IF('🧾 Factura Comercial'!G9=0,0,'🧾 Tributos Aduana'!$F$17*(IF('🧾 Tributos Aduana'!$F$6=0,0,'🧾 Factura Comercial'!I9/'🧾 Tributos Aduana'!$F$6))/'🧾 Factura Comercial'!G9) -> 0.018036044 | AL7: =IF('🧾 Factura Comercial'!G9=0,0,'🏦 Crédito Fiscal'!$C$16*(IF('🧾 Tributos Aduana'!$F$6=0,0,'🧾 Factura Comercial'!I9/'🧾 Tributos Aduana'!$F$6))/'🧾 Factura Comercial'!G9) -> 0.074252743 | AM7: =TABLA_BASE[[#This Row],[CF UNIT. ✅RECUP. (US$)]]*'📋 Datos Generales'!$E$19 -> 0.2762202 | AN7: =TABLA_BASE[[#This Row],[CF UNIT. ✅RECUP.(S/.)]]*TABLA_BASE[[#This Row],[CANTIDAD (unid.)]] -> 2386.5426 | AO7: ='💰 Precio de Venta'!G12 -> 0.4 | AP7: ='💰 Precio de Venta'!H12 -> 2.1081753 | AQ7: ='💰 Precio de Venta'!I12 -> 2.4876468 | AR7: ='💰 Precio de Venta'!J12 -> 0.84327011 | AS7: ='💰 Precio de Venta'!K12 -> 1181 | AT7: =TABLA_BASE[[#This Row],[GANANCIA UNIT.(S/.)]]*'🧾 Factura Comercial'!G9 -> 7285.8537 | AU7: =IF(TABLA_BASE[[#This Row],[PRECIO VTA. c/IGV(S/.)]]=0,0,TABLA_BASE[[#This Row],[GANANCIA UNIT.(S/.)]]/TABLA_BASE[[#This Row],[PRECIO VTA. c/IGV(S/.)]]) -> 0.33898305 | AV7: =IF(TABLA_BASE[[#This Row],[C/M UNIT. (S/.)]]=0,0,TABLA_BASE[[#This Row],[GANANCIA UNIT.(S/.)]]/TABLA_BASE[[#This Row],[C/M UNIT. (S/.)]]) -> 0.66666667 | AW7: =IF(TABLA_BASE[[#This Row],[MARGEN %]]>=0.5,"🟢 ALTO",IF(TABLA_BASE[[#This Row],[MARGEN %]]>=0.3,"🟡 MEDIO","🔴 BAJO")) -> 🟡 MEDIO
A8: ='🧾 Factura Comercial'!E10 -> Soporte Anillo Pop Socket Metálico | B8: ='🧾 Factura Comercial'!F10 -> Unid. | C8: ='🧾 Factura Comercial'!G10 -> 2160 | D8: ='🧾 Factura Comercial'!H10 -> 0.29 | E8: ='🧾 Factura Comercial'!I10 -> 626.4 | F8: =IF('🧾 Tributos Aduana'!$F$6=0,0,'🧾 Factura Comercial'!I10/'🧾 Tributos Aduana'!$F$6) -> 0.044069972 | G8: ='🧾 Factura Comercial'!H10*'📋 Datos Generales'!$E$19 -> 1.0788 | H8: =TABLA_BASE[[#This Row],[FOB UNIT. (S/.)]]*TABLA_BASE[[#This Row],[CANTIDAD (unid.)]] -> 2330.208 | I8: =IF('🧾 Tributos Aduana'!$F$6=0,0,'🧾 Tributos Aduana'!$F$17*('🧾 Factura Comercial'!H10/'🧾 Tributos Aduana'!$F$6)) -> 0.020117126 | J8: =TABLA_BASE[[#This Row],[ADV UNIT. (US$) ⚠️COSTO]]*TABLA_BASE[[#This Row],[CANTIDAD (unid.)]] -> 43.452992 | K8: =IF('🧾 Tributos Aduana'!$F$6=0,0,'🧾 Tributos Aduana'!$F$18*('🧾 Factura Comercial'!H10/'🧾 Tributos Aduana'!$F$6)) -> 0.0071001621 | L8: =TABLA_BASE[[#This Row],[IPM UNIT. (US$) ✅CF]]*TABLA_BASE[[#This Row],[CANTIDAD (unid.)]] -> 15.33635 | M8: =IF('🧾 Tributos Aduana'!$F$6=0,0,'🧾 Tributos Aduana'!$F$19*('🧾 Factura Comercial'!H10/'🧾 Tributos Aduana'!$F$6)) -> 0.056882908 | N8: =TABLA_BASE[[#This Row],[IGV UNIT. (US$) ✅CF]]*TABLA_BASE[[#This Row],[CANTIDAD (unid.)]] -> 122.86708 | O8: =IF('🧾 Tributos Aduana'!$F$6=0,0,'🧾 Tributos Aduana'!$F$23*('🧾 Factura Comercial'!H10/'🧾 Tributos Aduana'!$F$6)) -> 0.014681829 | P8: =TABLA_BASE[[#This Row],[PERCEP. UNIT.(US$) ✅CF]]*TABLA_BASE[[#This Row],[CANTIDAD (unid.)]] -> 31.712752 | Q8: =TABLA_BASE[[#This Row],[ADV UNIT. (US$) ⚠️COSTO]]+TABLA_BASE[[#This Row],[IPM UNIT. (US$) ✅CF]]+TABLA_BASE[[#This Row],[IGV UNIT. (US$) ✅CF]] -> 0.084100196 | R8: =TABLA_BASE[[#This Row],[DEUDA ADUANERA UNIT.]]*TABLA_BASE[[#This Row],[CANTIDAD (unid.)]] -> 181.65642 | S8: =TABLA_BASE[[#This Row],[ADV UNIT. (US$) ⚠️COSTO]]*'📋 Datos Generales'!$E$19 -> 0.074835708 | T8: =TABLA_BASE[[#This Row],[ADV UNIT. (S/.)]]*TABLA_BASE[[#This Row],[CANTIDAD (unid.)]] -> 161.64513 | U8: =TABLA_BASE[[#This Row],[IPM UNIT. (US$) ✅CF]]*'📋 Datos Generales'!$E$19 -> 0.026412603 | V8: =TABLA_BASE[[#This Row],[IPM UNIT. (S/.)]]*TABLA_BASE[[#This Row],[CANTIDAD (unid.)]] -> 57.051222 | W8: =TABLA_BASE[[#This Row],[IGV UNIT. (US$) ✅CF]]*'📋 Datos Generales'!$E$19 -> 0.21160442 | X8: =TABLA_BASE[[#This Row],[IGV UNIT. (S/.)]]*TABLA_BASE[[#This Row],[CANTIDAD (unid.)]] -> 457.06554 | Y8: =TABLA_BASE[[#This Row],[PERCEP. UNIT.(US$) ✅CF]]*'📋 Datos Generales'!$E$19 -> 0.054616406 | Z8: =TABLA_BASE[[#This Row],[PERCEP. UNIT.(S/.)]]*TABLA_BASE[[#This Row],[CANTIDAD (unid.)]] -> 117.97144 | AA8: =TABLA_BASE[[#This Row],[ADV UNIT. (US$) ⚠️COSTO]]+TABLA_BASE[[#This Row],[IPM UNIT. (US$) ✅CF]]+TABLA_BASE[[#This Row],[IGV UNIT. (US$) ✅CF]]+TABLA_BASE[[#This Row],[PERCEP. UNIT.(US$) ✅CF]] -> 0.098782025 | AB8: =TABLA_BASE[[#This Row],[TOTAL PAGO SUNAT UNIT.(US$)]]*TABLA_BASE[[#This Row],[CANTIDAD (unid.)]] -> 213.36917 | AC8: =TABLA_BASE[[#This Row],[TOTAL PAGO SUNAT UNIT.(US$)]]*'📋 Datos Generales'!$E$19 -> 0.36746913 | AD8: =TABLA_BASE[[#This Row],[TOTAL TRIB. UNIT.(S/.)]]*TABLA_BASE[[#This Row],[CANTIDAD (unid.)]] -> 793.73333 | AE8: =IF('🧾 Factura Comercial'!G10=0,0,'📦 Gastos Importación'!$E$28*(IF('🧾 Tributos Aduana'!$F$6=0,0,'🧾 Factura Comercial'!I10/'🧾 Tributos Aduana'!$F$6))/'🧾 Factura Comercial'!G10) -> 0.3792623 | AF8: =TABLA_BASE[[#This Row],[GASTOS IMP. UNIT.(US$)]]*TABLA_BASE[[#This Row],[CANTIDAD (unid.)]] -> 819.20657 | AG8: =TABLA_BASE[[#This Row],[GASTOS IMP. UNIT.(US$)]]*'📋 Datos Generales'!$E$19 -> 1.4108558 | AH8: =TABLA_BASE[[#This Row],[GASTOS IMP. UNIT.(S/.)]]*TABLA_BASE[[#This Row],[CANTIDAD (unid.)]] -> 3047.4484 | AI8: ='🧮 Costos x Producto'!J12 -> 0.3792623 | AJ8: ='🧮 Costos x Producto'!K12 -> 1.4108558 | AK8: =IF('🧾 Factura Comercial'!G10=0,0,'🧾 Tributos Aduana'!$F$17*(IF('🧾 Tributos Aduana'!$F$6=0,0,'🧾 Factura Comercial'!I10/'🧾 Tributos Aduana'!$F$6))/'🧾 Factura Comercial'!G10) -> 0.020117126 | AL8: =IF('🧾 Factura Comercial'!G10=0,0,'🏦 Crédito Fiscal'!$C$16*(IF('🧾 Tributos Aduana'!$F$6=0,0,'🧾 Factura Comercial'!I10/'🧾 Tributos Aduana'!$F$6))/'🧾 Factura Comercial'!G10) -> 0.082820367 | AM8: =TABLA_BASE[[#This Row],[CF UNIT. ✅RECUP. (US$)]]*'📋 Datos Generales'!$E$19 -> 0.30809177 | AN8: =TABLA_BASE[[#This Row],[CF UNIT. ✅RECUP.(S/.)]]*TABLA_BASE[[#This Row],[CANTIDAD (unid.)]] -> 665.47821 | AO8: ='💰 Precio de Venta'!G13 -> 0.4 | AP8: ='💰 Precio de Venta'!H13 -> 2.3514263 | AQ8: ='💰 Precio de Venta'!I13 -> 2.774683 | AR8: ='💰 Precio de Venta'!J13 -> 0.9405705 | AS8: ='💰 Precio de Venta'!K13 -> 296 | AT8: =TABLA_BASE[[#This Row],[GANANCIA UNIT.(S/.)]]*'🧾 Factura Comercial'!G10 -> 2031.6323 | AU8: =IF(TABLA_BASE[[#This Row],[PRECIO VTA. c/IGV(S/.)]]=0,0,TABLA_BASE[[#This Row],[GANANCIA UNIT.(S/.)]]/TABLA_BASE[[#This Row],[PRECIO VTA. c/IGV(S/.)]]) -> 0.33898305 | AV8: =IF(TABLA_BASE[[#This Row],[C/M UNIT. (S/.)]]=0,0,TABLA_BASE[[#This Row],[GANANCIA UNIT.(S/.)]]/TABLA_BASE[[#This Row],[C/M UNIT. (S/.)]]) -> 0.66666667 | AW8: =IF(TABLA_BASE[[#This Row],[MARGEN %]]>=0.5,"🟢 ALTO",IF(TABLA_BASE[[#This Row],[MARGEN %]]>=0.3,"🟡 MEDIO","🔴 BAJO")) -> 🟡 MEDIO
A9: ='🧾 Factura Comercial'!E11 -> Cargador Inalámbrico 15W Qi | B9: ='🧾 Factura Comercial'!F11 -> Unid. | C9: ='🧾 Factura Comercial'!G11 -> 240 | D9: ='🧾 Factura Comercial'!H11 -> 5.71 | E9: ='🧾 Factura Comercial'!I11 -> 1370.4 | F9: =IF('🧾 Tributos Aduana'!$F$6=0,0,'🧾 Factura Comercial'!I11/'🧾 Tributos Aduana'!$F$6) -> 0.096413616 | G9: ='🧾 Factura Comercial'!H11*'📋 Datos Generales'!$E$19 -> 21.2412 | H9: =TABLA_BASE[[#This Row],[FOB UNIT. (S/.)]]*TABLA_BASE[[#This Row],[CANTIDAD (unid.)]] -> 5097.888 | I9: =IF('🧾 Tributos Aduana'!$F$6=0,0,'🧾 Tributos Aduana'!$F$17*('🧾 Factura Comercial'!H11/'🧾 Tributos Aduana'!$F$6)) -> 0.39609927 | J9: =TABLA_BASE[[#This Row],[ADV UNIT. (US$) ⚠️COSTO]]*TABLA_BASE[[#This Row],[CANTIDAD (unid.)]] -> 95.063825 | K9: =IF('🧾 Tributos Aduana'!$F$6=0,0,'🧾 Tributos Aduana'!$F$18*('🧾 Factura Comercial'!H11/'🧾 Tributos Aduana'!$F$6)) -> 0.13979974 | L9: =TABLA_BASE[[#This Row],[IPM UNIT. (US$) ✅CF]]*TABLA_BASE[[#This Row],[CANTIDAD (unid.)]] -> 33.551938 | M9: =IF('🧾 Tributos Aduana'!$F$6=0,0,'🧾 Tributos Aduana'!$F$19*('🧾 Factura Comercial'!H11/'🧾 Tributos Aduana'!$F$6)) -> 1.1200048 | N9: =TABLA_BASE[[#This Row],[IGV UNIT. (US$) ✅CF]]*TABLA_BASE[[#This Row],[CANTIDAD (unid.)]] -> 268.80116 | O9: =IF('🧾 Tributos Aduana'!$F$6=0,0,'🧾 Tributos Aduana'!$F$23*('🧾 Factura Comercial'!H11/'🧾 Tributos Aduana'!$F$6)) -> 0.28908016 | P9: =TABLA_BASE[[#This Row],[PERCEP. UNIT.(US$) ✅CF]]*TABLA_BASE[[#This Row],[CANTIDAD (unid.)]] -> 69.379238 | Q9: =TABLA_BASE[[#This Row],[ADV UNIT. (US$) ⚠️COSTO]]+TABLA_BASE[[#This Row],[IPM UNIT. (US$) ✅CF]]+TABLA_BASE[[#This Row],[IGV UNIT. (US$) ✅CF]] -> 1.6559039 | R9: =TABLA_BASE[[#This Row],[DEUDA ADUANERA UNIT.]]*TABLA_BASE[[#This Row],[CANTIDAD (unid.)]] -> 397.41693 | S9: =TABLA_BASE[[#This Row],[ADV UNIT. (US$) ⚠️COSTO]]*'📋 Datos Generales'!$E$19 -> 1.4734893 | T9: =TABLA_BASE[[#This Row],[ADV UNIT. (S/.)]]*TABLA_BASE[[#This Row],[CANTIDAD (unid.)]] -> 353.63743 | U9: =TABLA_BASE[[#This Row],[IPM UNIT. (US$) ✅CF]]*'📋 Datos Generales'!$E$19 -> 0.52005505 | V9: =TABLA_BASE[[#This Row],[IPM UNIT. (S/.)]]*TABLA_BASE[[#This Row],[CANTIDAD (unid.)]] -> 124.81321 | W9: =TABLA_BASE[[#This Row],[IGV UNIT. (US$) ✅CF]]*'📋 Datos Generales'!$E$19 -> 4.166418 | X9: =TABLA_BASE[[#This Row],[IGV UNIT. (S/.)]]*TABLA_BASE[[#This Row],[CANTIDAD (unid.)]] -> 999.94032 | Y9: =TABLA_BASE[[#This Row],[PERCEP. UNIT.(US$) ✅CF]]*'📋 Datos Generales'!$E$19 -> 1.0753782 | Z9: =TABLA_BASE[[#This Row],[PERCEP. UNIT.(S/.)]]*TABLA_BASE[[#This Row],[CANTIDAD (unid.)]] -> 258.09077 | AA9: =TABLA_BASE[[#This Row],[ADV UNIT. (US$) ⚠️COSTO]]+TABLA_BASE[[#This Row],[IPM UNIT. (US$) ✅CF]]+TABLA_BASE[[#This Row],[IGV UNIT. (US$) ✅CF]]+TABLA_BASE[[#This Row],[PERCEP. UNIT.(US$) ✅CF]] -> 1.944984 | AB9: =TABLA_BASE[[#This Row],[TOTAL PAGO SUNAT UNIT.(US$)]]*TABLA_BASE[[#This Row],[CANTIDAD (unid.)]] -> 466.79616 | AC9: =TABLA_BASE[[#This Row],[TOTAL PAGO SUNAT UNIT.(US$)]]*'📋 Datos Generales'!$E$19 -> 7.2353405 | AD9: =TABLA_BASE[[#This Row],[TOTAL TRIB. UNIT.(S/.)]]*TABLA_BASE[[#This Row],[CANTIDAD (unid.)]] -> 1736.4817 | AE9: =IF('🧾 Factura Comercial'!G11=0,0,'📦 Gastos Importación'!$E$28*(IF('🧾 Tributos Aduana'!$F$6=0,0,'🧾 Factura Comercial'!I11/'🧾 Tributos Aduana'!$F$6))/'🧾 Factura Comercial'!G11) -> 7.4675439 | AF9: =TABLA_BASE[[#This Row],[GASTOS IMP. UNIT.(US$)]]*TABLA_BASE[[#This Row],[CANTIDAD (unid.)]] -> 1792.2105 | AG9: =TABLA_BASE[[#This Row],[GASTOS IMP. UNIT.(US$)]]*'📋 Datos Generales'!$E$19 -> 27.779263 | AH9: =TABLA_BASE[[#This Row],[GASTOS IMP. UNIT.(S/.)]]*TABLA_BASE[[#This Row],[CANTIDAD (unid.)]] -> 6667.0232 | AI9: ='🧮 Costos x Producto'!J13 -> 7.4675439 | AJ9: ='🧮 Costos x Producto'!K13 -> 27.779263 | AK9: =IF('🧾 Factura Comercial'!G11=0,0,'🧾 Tributos Aduana'!$F$17*(IF('🧾 Tributos Aduana'!$F$6=0,0,'🧾 Factura Comercial'!I11/'🧾 Tributos Aduana'!$F$6))/'🧾 Factura Comercial'!G11) -> 0.39609927 | AL9: =IF('🧾 Factura Comercial'!G11=0,0,'🏦 Crédito Fiscal'!$C$16*(IF('🧾 Tributos Aduana'!$F$6=0,0,'🧾 Factura Comercial'!I11/'🧾 Tributos Aduana'!$F$6))/'🧾 Factura Comercial'!G11) -> 1.6307045 | AM9: =TABLA_BASE[[#This Row],[CF UNIT. ✅RECUP. (US$)]]*'📋 Datos Generales'!$E$19 -> 6.0662206 | AN9: =TABLA_BASE[[#This Row],[CF UNIT. ✅RECUP.(S/.)]]*TABLA_BASE[[#This Row],[CANTIDAD (unid.)]] -> 1455.893 | AO9: ='💰 Precio de Venta'!G14 -> 0.4 | AP9: ='💰 Precio de Venta'!H14 -> 46.298772 | AQ9: ='💰 Precio de Venta'!I14 -> 54.632551 | AR9: ='💰 Precio de Venta'!J14 -> 18.519509 | AS9: ='💰 Precio de Venta'!K14 -> 33 | AT9: =TABLA_BASE[[#This Row],[GANANCIA UNIT.(S/.)]]*'🧾 Factura Comercial'!G11 -> 4444.6821 | AU9: =IF(TABLA_BASE[[#This Row],[PRECIO VTA. c/IGV(S/.)]]=0,0,TABLA_BASE[[#This Row],[GANANCIA UNIT.(S/.)]]/TABLA_BASE[[#This Row],[PRECIO VTA. c/IGV(S/.)]]) -> 0.33898305 | AV9: =IF(TABLA_BASE[[#This Row],[C/M UNIT. (S/.)]]=0,0,TABLA_BASE[[#This Row],[GANANCIA UNIT.(S/.)]]/TABLA_BASE[[#This Row],[C/M UNIT. (S/.)]]) -> 0.66666667 | AW9: =IF(TABLA_BASE[[#This Row],[MARGEN %]]>=0.5,"🟢 ALTO",IF(TABLA_BASE[[#This Row],[MARGEN %]]>=0.3,"🟡 MEDIO","🔴 BAJO")) -> 🟡 MEDIO
A10: ='🧾 Factura Comercial'!E12 -> Case Wallet Cuero PU Samsung S24 | B10: ='🧾 Factura Comercial'!F12 -> Unid. | C10: ='🧾 Factura Comercial'!G12 -> 1920 | D10: ='🧾 Factura Comercial'!H12 -> 0.76 | E10: ='🧾 Factura Comercial'!I12 -> 1459.2 | F10: =IF('🧾 Tributos Aduana'!$F$6=0,0,'🧾 Factura Comercial'!I12/'🧾 Tributos Aduana'!$F$6) -> 0.10266108 | G10: ='🧾 Factura Comercial'!H12*'📋 Datos Generales'!$E$19 -> 2.8272 | H10: =TABLA_BASE[[#This Row],[FOB UNIT. (S/.)]]*TABLA_BASE[[#This Row],[CANTIDAD (unid.)]] -> 5428.224 | I10: =IF('🧾 Tributos Aduana'!$F$6=0,0,'🧾 Tributos Aduana'!$F$17*('🧾 Factura Comercial'!H12/'🧾 Tributos Aduana'!$F$6)) -> 0.052720744 | J10: =TABLA_BASE[[#This Row],[ADV UNIT. (US$) ⚠️COSTO]]*TABLA_BASE[[#This Row],[CANTIDAD (unid.)]] -> 101.22383 | K10: =IF('🧾 Tributos Aduana'!$F$6=0,0,'🧾 Tributos Aduana'!$F$18*('🧾 Factura Comercial'!H12/'🧾 Tributos Aduana'!$F$6)) -> 0.018607321 | L10: =TABLA_BASE[[#This Row],[IPM UNIT. (US$) ✅CF]]*TABLA_BASE[[#This Row],[CANTIDAD (unid.)]] -> 35.726057 | M10: =IF('🧾 Tributos Aduana'!$F$6=0,0,'🧾 Tributos Aduana'!$F$19*('🧾 Factura Comercial'!H12/'🧾 Tributos Aduana'!$F$6)) -> 0.14907245 | N10: =TABLA_BASE[[#This Row],[IGV UNIT. (US$) ✅CF]]*TABLA_BASE[[#This Row],[CANTIDAD (unid.)]] -> 286.2191 | O10: =IF('🧾 Tributos Aduana'!$F$6=0,0,'🧾 Tributos Aduana'!$F$23*('🧾 Factura Comercial'!H12/'🧾 Tributos Aduana'!$F$6)) -> 0.038476519 | P10: =TABLA_BASE[[#This Row],[PERCEP. UNIT.(US$) ✅CF]]*TABLA_BASE[[#This Row],[CANTIDAD (unid.)]] -> 73.874916 | Q10: =TABLA_BASE[[#This Row],[ADV UNIT. (US$) ⚠️COSTO]]+TABLA_BASE[[#This Row],[IPM UNIT. (US$) ✅CF]]+TABLA_BASE[[#This Row],[IGV UNIT. (US$) ✅CF]] -> 0.22040051 | R10: =TABLA_BASE[[#This Row],[DEUDA ADUANERA UNIT.]]*TABLA_BASE[[#This Row],[CANTIDAD (unid.)]] -> 423.16899 | S10: =TABLA_BASE[[#This Row],[ADV UNIT. (US$) ⚠️COSTO]]*'📋 Datos Generales'!$E$19 -> 0.19612117 | T10: =TABLA_BASE[[#This Row],[ADV UNIT. (S/.)]]*TABLA_BASE[[#This Row],[CANTIDAD (unid.)]] -> 376.55264 | U10: =TABLA_BASE[[#This Row],[IPM UNIT. (US$) ✅CF]]*'📋 Datos Generales'!$E$19 -> 0.069219235 | V10: =TABLA_BASE[[#This Row],[IPM UNIT. (S/.)]]*TABLA_BASE[[#This Row],[CANTIDAD (unid.)]] -> 132.90093 | W10: =TABLA_BASE[[#This Row],[IGV UNIT. (US$) ✅CF]]*'📋 Datos Generales'!$E$19 -> 0.55454951 | X10: =TABLA_BASE[[#This Row],[IGV UNIT. (S/.)]]*TABLA_BASE[[#This Row],[CANTIDAD (unid.)]] -> 1064.7351 | Y10: =TABLA_BASE[[#This Row],[PERCEP. UNIT.(US$) ✅CF]]*'📋 Datos Generales'!$E$19 -> 0.14313265 | Z10: =TABLA_BASE[[#This Row],[PERCEP. UNIT.(S/.)]]*TABLA_BASE[[#This Row],[CANTIDAD (unid.)]] -> 274.81469 | AA10: =TABLA_BASE[[#This Row],[ADV UNIT. (US$) ⚠️COSTO]]+TABLA_BASE[[#This Row],[IPM UNIT. (US$) ✅CF]]+TABLA_BASE[[#This Row],[IGV UNIT. (US$) ✅CF]]+TABLA_BASE[[#This Row],[PERCEP. UNIT.(US$) ✅CF]] -> 0.25887703 | AB10: =TABLA_BASE[[#This Row],[TOTAL PAGO SUNAT UNIT.(US$)]]*TABLA_BASE[[#This Row],[CANTIDAD (unid.)]] -> 497.0439 | AC10: =TABLA_BASE[[#This Row],[TOTAL PAGO SUNAT UNIT.(US$)]]*'📋 Datos Generales'!$E$19 -> 0.96302256 | AD10: =TABLA_BASE[[#This Row],[TOTAL TRIB. UNIT.(S/.)]]*TABLA_BASE[[#This Row],[CANTIDAD (unid.)]] -> 1849.0033 | AE10: =IF('🧾 Factura Comercial'!G12=0,0,'📦 Gastos Importación'!$E$28*(IF('🧾 Tributos Aduana'!$F$6=0,0,'🧾 Factura Comercial'!I12/'🧾 Tributos Aduana'!$F$6))/'🧾 Factura Comercial'!G12) -> 0.99392878 | AF10: =TABLA_BASE[[#This Row],[GASTOS IMP. UNIT.(US$)]]*TABLA_BASE[[#This Row],[CANTIDAD (unid.)]] -> 1908.3433 | AG10: =TABLA_BASE[[#This Row],[GASTOS IMP. UNIT.(US$)]]*'📋 Datos Generales'!$E$19 -> 3.6974151 | AH10: =TABLA_BASE[[#This Row],[GASTOS IMP. UNIT.(S/.)]]*TABLA_BASE[[#This Row],[CANTIDAD (unid.)]] -> 7099.037 | AI10: ='🧮 Costos x Producto'!J14 -> 0.99392878 | AJ10: ='🧮 Costos x Producto'!K14 -> 3.6974151 | AK10: =IF('🧾 Factura Comercial'!G12=0,0,'🧾 Tributos Aduana'!$F$17*(IF('🧾 Tributos Aduana'!$F$6=0,0,'🧾 Factura Comercial'!I12/'🧾 Tributos Aduana'!$F$6))/'🧾 Factura Comercial'!G12) -> 0.052720744 | AL10: =IF('🧾 Factura Comercial'!G12=0,0,'🏦 Crédito Fiscal'!$C$16*(IF('🧾 Tributos Aduana'!$F$6=0,0,'🧾 Factura Comercial'!I12/'🧾 Tributos Aduana'!$F$6))/'🧾 Factura Comercial'!G12) -> 0.21704648 | AM10: =TABLA_BASE[[#This Row],[CF UNIT. ✅RECUP. (US$)]]*'📋 Datos Generales'!$E$19 -> 0.8074129 | AN10: =TABLA_BASE[[#This Row],[CF UNIT. ✅RECUP.(S/.)]]*TABLA_BASE[[#This Row],[CANTIDAD (unid.)]] -> 1550.2328 | AO10: ='💰 Precio de Venta'!G15 -> 0.4 | AP10: ='💰 Precio de Venta'!H15 -> 6.1623585 | AQ10: ='💰 Precio de Venta'!I15 -> 7.271583 | AR10: ='💰 Precio de Venta'!J15 -> 2.4649434 | AS10: ='💰 Precio de Venta'!K15 -> 263 | AT10: =TABLA_BASE[[#This Row],[GANANCIA UNIT.(S/.)]]*'🧾 Factura Comercial'!G12 -> 4732.6913 | AU10: =IF(TABLA_BASE[[#This Row],[PRECIO VTA. c/IGV(S/.)]]=0,0,TABLA_BASE[[#This Row],[GANANCIA UNIT.(S/.)]]/TABLA_BASE[[#This Row],[PRECIO VTA. c/IGV(S/.)]]) -> 0.33898305 | AV10: =IF(TABLA_BASE[[#This Row],[C/M UNIT. (S/.)]]=0,0,TABLA_BASE[[#This Row],[GANANCIA UNIT.(S/.)]]/TABLA_BASE[[#This Row],[C/M UNIT. (S/.)]]) -> 0.66666667 | AW10: =IF(TABLA_BASE[[#This Row],[MARGEN %]]>=0.5,"🟢 ALTO",IF(TABLA_BASE[[#This Row],[MARGEN %]]>=0.3,"🟡 MEDIO","🔴 BAJO")) -> 🟡 MEDIO
A11: ='🧾 Factura Comercial'!E13 -> Adaptador USB-C a Jack 3.5mm | B11: ='🧾 Factura Comercial'!F13 -> Unid. | C11: ='🧾 Factura Comercial'!G13 -> 4800 | D11: ='🧾 Factura Comercial'!H13 -> 0.28 | E11: ='🧾 Factura Comercial'!I13 -> 1344 | F11: =IF('🧾 Tributos Aduana'!$F$6=0,0,'🧾 Factura Comercial'!I13/'🧾 Tributos Aduana'!$F$6) -> 0.094556261 | G11: ='🧾 Factura Comercial'!H13*'📋 Datos Generales'!$E$19 -> 1.0416 | H11: =TABLA_BASE[[#This Row],[FOB UNIT. (S/.)]]*TABLA_BASE[[#This Row],[CANTIDAD (unid.)]] -> 4999.68 | I11: =IF('🧾 Tributos Aduana'!$F$6=0,0,'🧾 Tributos Aduana'!$F$17*('🧾 Factura Comercial'!H13/'🧾 Tributos Aduana'!$F$6)) -> 0.019423432 | J11: =TABLA_BASE[[#This Row],[ADV UNIT. (US$) ⚠️COSTO]]*TABLA_BASE[[#This Row],[CANTIDAD (unid.)]] -> 93.232473 | K11: =IF('🧾 Tributos Aduana'!$F$6=0,0,'🧾 Tributos Aduana'!$F$18*('🧾 Factura Comercial'!H13/'🧾 Tributos Aduana'!$F$6)) -> 0.0068553289 | L11: =TABLA_BASE[[#This Row],[IPM UNIT. (US$) ✅CF]]*TABLA_BASE[[#This Row],[CANTIDAD (unid.)]] -> 32.905579 | M11: =IF('🧾 Tributos Aduana'!$F$6=0,0,'🧾 Tributos Aduana'!$F$19*('🧾 Factura Comercial'!H13/'🧾 Tributos Aduana'!$F$6)) -> 0.054921428 | N11: =TABLA_BASE[[#This Row],[IGV UNIT. (US$) ✅CF]]*TABLA_BASE[[#This Row],[CANTIDAD (unid.)]] -> 263.62286 | O11: =IF('🧾 Tributos Aduana'!$F$6=0,0,'🧾 Tributos Aduana'!$F$23*('🧾 Factura Comercial'!H13/'🧾 Tributos Aduana'!$F$6)) -> 0.014175559 | P11: =TABLA_BASE[[#This Row],[PERCEP. UNIT.(US$) ✅CF]]*TABLA_BASE[[#This Row],[CANTIDAD (unid.)]] -> 68.042685 | Q11: =TABLA_BASE[[#This Row],[ADV UNIT. (US$) ⚠️COSTO]]+TABLA_BASE[[#This Row],[IPM UNIT. (US$) ✅CF]]+TABLA_BASE[[#This Row],[IGV UNIT. (US$) ✅CF]] -> 0.081200189 | R11: =TABLA_BASE[[#This Row],[DEUDA ADUANERA UNIT.]]*TABLA_BASE[[#This Row],[CANTIDAD (unid.)]] -> 389.76091 | S11: =TABLA_BASE[[#This Row],[ADV UNIT. (US$) ⚠️COSTO]]*'📋 Datos Generales'!$E$19 -> 0.072255167 | T11: =TABLA_BASE[[#This Row],[ADV UNIT. (S/.)]]*TABLA_BASE[[#This Row],[CANTIDAD (unid.)]] -> 346.8248 | U11: =TABLA_BASE[[#This Row],[IPM UNIT. (US$) ✅CF]]*'📋 Datos Generales'!$E$19 -> 0.025501824 | V11: =TABLA_BASE[[#This Row],[IPM UNIT. (S/.)]]*TABLA_BASE[[#This Row],[CANTIDAD (unid.)]] -> 122.40875 | W11: =TABLA_BASE[[#This Row],[IGV UNIT. (US$) ✅CF]]*'📋 Datos Generales'!$E$19 -> 0.20430771 | X11: =TABLA_BASE[[#This Row],[IGV UNIT. (S/.)]]*TABLA_BASE[[#This Row],[CANTIDAD (unid.)]] -> 980.67702 | Y11: =TABLA_BASE[[#This Row],[PERCEP. UNIT.(US$) ✅CF]]*'📋 Datos Generales'!$E$19 -> 0.052733081 | Z11: =TABLA_BASE[[#This Row],[PERCEP. UNIT.(S/.)]]*TABLA_BASE[[#This Row],[CANTIDAD (unid.)]] -> 253.11879 | AA11: =TABLA_BASE[[#This Row],[ADV UNIT. (US$) ⚠️COSTO]]+TABLA_BASE[[#This Row],[IPM UNIT. (US$) ✅CF]]+TABLA_BASE[[#This Row],[IGV UNIT. (US$) ✅CF]]+TABLA_BASE[[#This Row],[PERCEP. UNIT.(US$) ✅CF]] -> 0.095375749 | AB11: =TABLA_BASE[[#This Row],[TOTAL PAGO SUNAT UNIT.(US$)]]*TABLA_BASE[[#This Row],[CANTIDAD (unid.)]] -> 457.80359 | AC11: =TABLA_BASE[[#This Row],[TOTAL PAGO SUNAT UNIT.(US$)]]*'📋 Datos Generales'!$E$19 -> 0.35479778 | AD11: =TABLA_BASE[[#This Row],[TOTAL TRIB. UNIT.(S/.)]]*TABLA_BASE[[#This Row],[CANTIDAD (unid.)]] -> 1703.0294 | AE11: =IF('🧾 Factura Comercial'!G13=0,0,'📦 Gastos Importación'!$E$28*(IF('🧾 Tributos Aduana'!$F$6=0,0,'🧾 Factura Comercial'!I13/'🧾 Tributos Aduana'!$F$6))/'🧾 Factura Comercial'!G13) -> 0.36618429 | AF11: =TABLA_BASE[[#This Row],[GASTOS IMP. UNIT.(US$)]]*TABLA_BASE[[#This Row],[CANTIDAD (unid.)]] -> 1757.6846 | AG11: =TABLA_BASE[[#This Row],[GASTOS IMP. UNIT.(US$)]]*'📋 Datos Generales'!$E$19 -> 1.3622056 | AH11: =TABLA_BASE[[#This Row],[GASTOS IMP. UNIT.(S/.)]]*TABLA_BASE[[#This Row],[CANTIDAD (unid.)]] -> 6538.5867 | AI11: ='🧮 Costos x Producto'!J15 -> 0.36618429 | AJ11: ='🧮 Costos x Producto'!K15 -> 1.3622056 | AK11: =IF('🧾 Factura Comercial'!G13=0,0,'🧾 Tributos Aduana'!$F$17*(IF('🧾 Tributos Aduana'!$F$6=0,0,'🧾 Factura Comercial'!I13/'🧾 Tributos Aduana'!$F$6))/'🧾 Factura Comercial'!G13) -> 0.019423432 | AL11: =IF('🧾 Factura Comercial'!G13=0,0,'🏦 Crédito Fiscal'!$C$16*(IF('🧾 Tributos Aduana'!$F$6=0,0,'🧾 Factura Comercial'!I13/'🧾 Tributos Aduana'!$F$6))/'🧾 Factura Comercial'!G13) -> 0.079964492 | AM11: =TABLA_BASE[[#This Row],[CF UNIT. ✅RECUP. (US$)]]*'📋 Datos Generales'!$E$19 -> 0.29746791 | AN11: =TABLA_BASE[[#This Row],[CF UNIT. ✅RECUP.(S/.)]]*TABLA_BASE[[#This Row],[CANTIDAD (unid.)]] -> 1427.846 | AO11: ='💰 Precio de Venta'!G16 -> 0.4 | AP11: ='💰 Precio de Venta'!H16 -> 2.2703426 | AQ11: ='💰 Precio de Venta'!I16 -> 2.6790043 | AR11: ='💰 Precio de Venta'!J16 -> 0.90813704 | AS11: ='💰 Precio de Venta'!K16 -> 657 | AT11: =TABLA_BASE[[#This Row],[GANANCIA UNIT.(S/.)]]*'🧾 Factura Comercial'!G13 -> 4359.0578 | AU11: =IF(TABLA_BASE[[#This Row],[PRECIO VTA. c/IGV(S/.)]]=0,0,TABLA_BASE[[#This Row],[GANANCIA UNIT.(S/.)]]/TABLA_BASE[[#This Row],[PRECIO VTA. c/IGV(S/.)]]) -> 0.33898305 | AV11: =IF(TABLA_BASE[[#This Row],[C/M UNIT. (S/.)]]=0,0,TABLA_BASE[[#This Row],[GANANCIA UNIT.(S/.)]]/TABLA_BASE[[#This Row],[C/M UNIT. (S/.)]]) -> 0.66666667 | AW11: =IF(TABLA_BASE[[#This Row],[MARGEN %]]>=0.5,"🟢 ALTO",IF(TABLA_BASE[[#This Row],[MARGEN %]]>=0.3,"🟡 MEDIO","🔴 BAJO")) -> 🟡 MEDIO
A12: ='🧾 Factura Comercial'!E14 -> 0 | B12: ='🧾 Factura Comercial'!F14 -> Unid. | C12: ='🧾 Factura Comercial'!G14 -> 0 | D12: ='🧾 Factura Comercial'!H14 -> 0 | E12: ='🧾 Factura Comercial'!I14 -> 0 | F12: =IF('🧾 Tributos Aduana'!$F$6=0,0,'🧾 Factura Comercial'!I14/'🧾 Tributos Aduana'!$F$6) -> 0 | G12: ='🧾 Factura Comercial'!H14*'📋 Datos Generales'!$E$19 -> 0 | H12: =TABLA_BASE[[#This Row],[FOB UNIT. (S/.)]]*TABLA_BASE[[#This Row],[CANTIDAD (unid.)]] -> 0 | I12: =IF('🧾 Tributos Aduana'!$F$6=0,0,'🧾 Tributos Aduana'!$F$17*('🧾 Factura Comercial'!H14/'🧾 Tributos Aduana'!$F$6)) -> 0 | J12: =TABLA_BASE[[#This Row],[ADV UNIT. (US$) ⚠️COSTO]]*TABLA_BASE[[#This Row],[CANTIDAD (unid.)]] -> 0 | K12: =IF('🧾 Tributos Aduana'!$F$6=0,0,'🧾 Tributos Aduana'!$F$18*('🧾 Factura Comercial'!H14/'🧾 Tributos Aduana'!$F$6)) -> 0 | L12: =TABLA_BASE[[#This Row],[IPM UNIT. (US$) ✅CF]]*TABLA_BASE[[#This Row],[CANTIDAD (unid.)]] -> 0 | M12: =IF('🧾 Tributos Aduana'!$F$6=0,0,'🧾 Tributos Aduana'!$F$19*('🧾 Factura Comercial'!H14/'🧾 Tributos Aduana'!$F$6)) -> 0 | N12: =TABLA_BASE[[#This Row],[IGV UNIT. (US$) ✅CF]]*TABLA_BASE[[#This Row],[CANTIDAD (unid.)]] -> 0 | O12: =IF('🧾 Tributos Aduana'!$F$6=0,0,'🧾 Tributos Aduana'!$F$23*('🧾 Factura Comercial'!H14/'🧾 Tributos Aduana'!$F$6)) -> 0 | P12: =TABLA_BASE[[#This Row],[PERCEP. UNIT.(US$) ✅CF]]*TABLA_BASE[[#This Row],[CANTIDAD (unid.)]] -> 0 | Q12: =TABLA_BASE[[#This Row],[ADV UNIT. (US$) ⚠️COSTO]]+TABLA_BASE[[#This Row],[IPM UNIT. (US$) ✅CF]]+TABLA_BASE[[#This Row],[IGV UNIT. (US$) ✅CF]] -> 0 | R12: =TABLA_BASE[[#This Row],[DEUDA ADUANERA UNIT.]]*TABLA_BASE[[#This Row],[CANTIDAD (unid.)]] -> 0 | S12: =TABLA_BASE[[#This Row],[ADV UNIT. (US$) ⚠️COSTO]]*'📋 Datos Generales'!$E$19 -> 0 | T12: =TABLA_BASE[[#This Row],[ADV UNIT. (S/.)]]*TABLA_BASE[[#This Row],[CANTIDAD (unid.)]] -> 0 | U12: =TABLA_BASE[[#This Row],[IPM UNIT. (US$) ✅CF]]*'📋 Datos Generales'!$E$19 -> 0 | V12: =TABLA_BASE[[#This Row],[IPM UNIT. (S/.)]]*TABLA_BASE[[#This Row],[CANTIDAD (unid.)]] -> 0 | W12: =TABLA_BASE[[#This Row],[IGV UNIT. (US$) ✅CF]]*'📋 Datos Generales'!$E$19 -> 0 | X12: =TABLA_BASE[[#This Row],[IGV UNIT. (S/.)]]*TABLA_BASE[[#This Row],[CANTIDAD (unid.)]] -> 0 | Y12: =TABLA_BASE[[#This Row],[PERCEP. UNIT.(US$) ✅CF]]*'📋 Datos Generales'!$E$19 -> 0 | Z12: =TABLA_BASE[[#This Row],[PERCEP. UNIT.(S/.)]]*TABLA_BASE[[#This Row],[CANTIDAD (unid.)]] -> 0 | AA12: =TABLA_BASE[[#This Row],[ADV UNIT. (US$) ⚠️COSTO]]+TABLA_BASE[[#This Row],[IPM UNIT. (US$) ✅CF]]+TABLA_BASE[[#This Row],[IGV UNIT. (US$) ✅CF]]+TABLA_BASE[[#This Row],[PERCEP. UNIT.(US$) ✅CF]] -> 0 | AB12: =TABLA_BASE[[#This Row],[TOTAL PAGO SUNAT UNIT.(US$)]]*TABLA_BASE[[#This Row],[CANTIDAD (unid.)]] -> 0 | AC12: =TABLA_BASE[[#This Row],[TOTAL PAGO SUNAT UNIT.(US$)]]*'📋 Datos Generales'!$E$19 -> 0 | AD12: =TABLA_BASE[[#This Row],[TOTAL TRIB. UNIT.(S/.)]]*TABLA_BASE[[#This Row],[CANTIDAD (unid.)]] -> 0 | AE12: =IF('🧾 Factura Comercial'!G14=0,0,'📦 Gastos Importación'!$E$28*(IF('🧾 Tributos Aduana'!$F$6=0,0,'🧾 Factura Comercial'!I14/'🧾 Tributos Aduana'!$F$6))/'🧾 Factura Comercial'!G14) -> 0 | AF12: =TABLA_BASE[[#This Row],[GASTOS IMP. UNIT.(US$)]]*TABLA_BASE[[#This Row],[CANTIDAD (unid.)]] -> 0 | AG12: =TABLA_BASE[[#This Row],[GASTOS IMP. UNIT.(US$)]]*'📋 Datos Generales'!$E$19 -> 0 | AH12: =TABLA_BASE[[#This Row],[GASTOS IMP. UNIT.(S/.)]]*TABLA_BASE[[#This Row],[CANTIDAD (unid.)]] -> 0 | AI12: ='🧮 Costos x Producto'!J16 -> 0 | AJ12: ='🧮 Costos x Producto'!K16 -> 0 | AK12: =IF('🧾 Factura Comercial'!G14=0,0,'🧾 Tributos Aduana'!$F$17*(IF('🧾 Tributos Aduana'!$F$6=0,0,'🧾 Factura Comercial'!I14/'🧾 Tributos Aduana'!$F$6))/'🧾 Factura Comercial'!G14) -> 0 | AL12: =IF('🧾 Factura Comercial'!G14=0,0,'🏦 Crédito Fiscal'!$C$16*(IF('🧾 Tributos Aduana'!$F$6=0,0,'🧾 Factura Comercial'!I14/'🧾 Tributos Aduana'!$F$6))/'🧾 Factura Comercial'!G14) -> 0 | AM12: =TABLA_BASE[[#This Row],[CF UNIT. ✅RECUP. (US$)]]*'📋 Datos Generales'!$E$19 -> 0 | AN12: =TABLA_BASE[[#This Row],[CF UNIT. ✅RECUP.(S/.)]]*TABLA_BASE[[#This Row],[CANTIDAD (unid.)]] -> 0 | AO12: ='💰 Precio de Venta'!G17 -> 0.4 | AP12: ='💰 Precio de Venta'!H17 -> 0 | AQ12: ='💰 Precio de Venta'!I17 -> 0 | AR12: ='💰 Precio de Venta'!J17 -> 0 | AS12: ='💰 Precio de Venta'!K17 -> 0 | AT12: =TABLA_BASE[[#This Row],[GANANCIA UNIT.(S/.)]]*'🧾 Factura Comercial'!G14 -> 0 | AU12: =IF(TABLA_BASE[[#This Row],[PRECIO VTA. c/IGV(S/.)]]=0,0,TABLA_BASE[[#This Row],[GANANCIA UNIT.(S/.)]]/TABLA_BASE[[#This Row],[PRECIO VTA. c/IGV(S/.)]]) -> 0 | AV12: =IF(TABLA_BASE[[#This Row],[C/M UNIT. (S/.)]]=0,0,TABLA_BASE[[#This Row],[GANANCIA UNIT.(S/.)]]/TABLA_BASE[[#This Row],[C/M UNIT. (S/.)]]) -> 0 | AW12: =IF(TABLA_BASE[[#This Row],[MARGEN %]]>=0.5,"🟢 ALTO",IF(TABLA_BASE[[#This Row],[MARGEN %]]>=0.3,"🟡 MEDIO","🔴 BAJO")) -> 🟡 MEDIO
A13: ='🧾 Factura Comercial'!E15 -> 0 | B13: ='🧾 Factura Comercial'!F15 -> Unid. | C13: ='🧾 Factura Comercial'!G15 -> 0 | D13: ='🧾 Factura Comercial'!H15 -> 0 | E13: ='🧾 Factura Comercial'!I15 -> 0 | F13: =IF('🧾 Tributos Aduana'!$F$6=0,0,'🧾 Factura Comercial'!I15/'🧾 Tributos Aduana'!$F$6) -> 0 | G13: ='🧾 Factura Comercial'!H15*'📋 Datos Generales'!$E$19 -> 0 | H13: =TABLA_BASE[[#This Row],[FOB UNIT. (S/.)]]*TABLA_BASE[[#This Row],[CANTIDAD (unid.)]] -> 0 | I13: =IF('🧾 Tributos Aduana'!$F$6=0,0,'🧾 Tributos Aduana'!$F$17*('🧾 Factura Comercial'!H15/'🧾 Tributos Aduana'!$F$6)) -> 0 | J13: =TABLA_BASE[[#This Row],[ADV UNIT. (US$) ⚠️COSTO]]*TABLA_BASE[[#This Row],[CANTIDAD (unid.)]] -> 0 | K13: =IF('🧾 Tributos Aduana'!$F$6=0,0,'🧾 Tributos Aduana'!$F$18*('🧾 Factura Comercial'!H15/'🧾 Tributos Aduana'!$F$6)) -> 0 | L13: =TABLA_BASE[[#This Row],[IPM UNIT. (US$) ✅CF]]*TABLA_BASE[[#This Row],[CANTIDAD (unid.)]] -> 0 | M13: =IF('🧾 Tributos Aduana'!$F$6=0,0,'🧾 Tributos Aduana'!$F$19*('🧾 Factura Comercial'!H15/'🧾 Tributos Aduana'!$F$6)) -> 0 | N13: =TABLA_BASE[[#This Row],[IGV UNIT. (US$) ✅CF]]*TABLA_BASE[[#This Row],[CANTIDAD (unid.)]] -> 0 | O13: =IF('🧾 Tributos Aduana'!$F$6=0,0,'🧾 Tributos Aduana'!$F$23*('🧾 Factura Comercial'!H15/'🧾 Tributos Aduana'!$F$6)) -> 0 | P13: =TABLA_BASE[[#This Row],[PERCEP. UNIT.(US$) ✅CF]]*TABLA_BASE[[#This Row],[CANTIDAD (unid.)]] -> 0 | Q13: =TABLA_BASE[[#This Row],[ADV UNIT. (US$) ⚠️COSTO]]+TABLA_BASE[[#This Row],[IPM UNIT. (US$) ✅CF]]+TABLA_BASE[[#This Row],[IGV UNIT. (US$) ✅CF]] -> 0 | R13: =TABLA_BASE[[#This Row],[DEUDA ADUANERA UNIT.]]*TABLA_BASE[[#This Row],[CANTIDAD (unid.)]] -> 0 | S13: =TABLA_BASE[[#This Row],[ADV UNIT. (US$) ⚠️COSTO]]*'📋 Datos Generales'!$E$19 -> 0 | T13: =TABLA_BASE[[#This Row],[ADV UNIT. (S/.)]]*TABLA_BASE[[#This Row],[CANTIDAD (unid.)]] -> 0 | U13: =TABLA_BASE[[#This Row],[IPM UNIT. (US$) ✅CF]]*'📋 Datos Generales'!$E$19 -> 0 | V13: =TABLA_BASE[[#This Row],[IPM UNIT. (S/.)]]*TABLA_BASE[[#This Row],[CANTIDAD (unid.)]] -> 0 | W13: =TABLA_BASE[[#This Row],[IGV UNIT. (US$) ✅CF]]*'📋 Datos Generales'!$E$19 -> 0 | X13: =TABLA_BASE[[#This Row],[IGV UNIT. (S/.)]]*TABLA_BASE[[#This Row],[CANTIDAD (unid.)]] -> 0 | Y13: =TABLA_BASE[[#This Row],[PERCEP. UNIT.(US$) ✅CF]]*'📋 Datos Generales'!$E$19 -> 0 | Z13: =TABLA_BASE[[#This Row],[PERCEP. UNIT.(S/.)]]*TABLA_BASE[[#This Row],[CANTIDAD (unid.)]] -> 0 | AA13: =TABLA_BASE[[#This Row],[ADV UNIT. (US$) ⚠️COSTO]]+TABLA_BASE[[#This Row],[IPM UNIT. (US$) ✅CF]]+TABLA_BASE[[#This Row],[IGV UNIT. (US$) ✅CF]]+TABLA_BASE[[#This Row],[PERCEP. UNIT.(US$) ✅CF]] -> 0 | AB13: =TABLA_BASE[[#This Row],[TOTAL PAGO SUNAT UNIT.(US$)]]*TABLA_BASE[[#This Row],[CANTIDAD (unid.)]] -> 0 | AC13: =TABLA_BASE[[#This Row],[TOTAL PAGO SUNAT UNIT.(US$)]]*'📋 Datos Generales'!$E$19 -> 0 | AD13: =TABLA_BASE[[#This Row],[TOTAL TRIB. UNIT.(S/.)]]*TABLA_BASE[[#This Row],[CANTIDAD (unid.)]] -> 0 | AE13: =IF('🧾 Factura Comercial'!G15=0,0,'📦 Gastos Importación'!$E$28*(IF('🧾 Tributos Aduana'!$F$6=0,0,'🧾 Factura Comercial'!I15/'🧾 Tributos Aduana'!$F$6))/'🧾 Factura Comercial'!G15) -> 0 | AF13: =TABLA_BASE[[#This Row],[GASTOS IMP. UNIT.(US$)]]*TABLA_BASE[[#This Row],[CANTIDAD (unid.)]] -> 0 | AG13: =TABLA_BASE[[#This Row],[GASTOS IMP. UNIT.(US$)]]*'📋 Datos Generales'!$E$19 -> 0 | AH13: =TABLA_BASE[[#This Row],[GASTOS IMP. UNIT.(S/.)]]*TABLA_BASE[[#This Row],[CANTIDAD (unid.)]] -> 0 | AI13: ='🧮 Costos x Producto'!J17 -> 0 | AJ13: ='🧮 Costos x Producto'!K17 -> 0 | AK13: =IF('🧾 Factura Comercial'!G15=0,0,'🧾 Tributos Aduana'!$F$17*(IF('🧾 Tributos Aduana'!$F$6=0,0,'🧾 Factura Comercial'!I15/'🧾 Tributos Aduana'!$F$6))/'🧾 Factura Comercial'!G15) -> 0 | AL13: =IF('🧾 Factura Comercial'!G15=0,0,'🏦 Crédito Fiscal'!$C$16*(IF('🧾 Tributos Aduana'!$F$6=0,0,'🧾 Factura Comercial'!I15/'🧾 Tributos Aduana'!$F$6))/'🧾 Factura Comercial'!G15) -> 0 | AM13: =TABLA_BASE[[#This Row],[CF UNIT. ✅RECUP. (US$)]]*'📋 Datos Generales'!$E$19 -> 0 | AN13: =TABLA_BASE[[#This Row],[CF UNIT. ✅RECUP.(S/.)]]*TABLA_BASE[[#This Row],[CANTIDAD (unid.)]] -> 0 | AO13: ='💰 Precio de Venta'!G18 -> 0.4 | AP13: ='💰 Precio de Venta'!H18 -> 0 | AQ13: ='💰 Precio de Venta'!I18 -> 0 | AR13: ='💰 Precio de Venta'!J18 -> 0 | AS13: ='💰 Precio de Venta'!K18 -> 0 | AT13: =TABLA_BASE[[#This Row],[GANANCIA UNIT.(S/.)]]*'🧾 Factura Comercial'!G15 -> 0 | AU13: =IF(TABLA_BASE[[#This Row],[PRECIO VTA. c/IGV(S/.)]]=0,0,TABLA_BASE[[#This Row],[GANANCIA UNIT.(S/.)]]/TABLA_BASE[[#This Row],[PRECIO VTA. c/IGV(S/.)]]) -> 0 | AV13: =IF(TABLA_BASE[[#This Row],[C/M UNIT. (S/.)]]=0,0,TABLA_BASE[[#This Row],[GANANCIA UNIT.(S/.)]]/TABLA_BASE[[#This Row],[C/M UNIT. (S/.)]]) -> 0 | AW13: =IF(TABLA_BASE[[#This Row],[MARGEN %]]>=0.5,"🟢 ALTO",IF(TABLA_BASE[[#This Row],[MARGEN %]]>=0.3,"🟡 MEDIO","🔴 BAJO")) -> 🟡 MEDIO
A14: ='🧾 Factura Comercial'!E16 -> 0 | B14: ='🧾 Factura Comercial'!F16 -> Unid. | C14: ='🧾 Factura Comercial'!G16 -> 0 | D14: ='🧾 Factura Comercial'!H16 -> 0 | E14: ='🧾 Factura Comercial'!I16 -> 0 | F14: =IF('🧾 Tributos Aduana'!$F$6=0,0,'🧾 Factura Comercial'!I16/'🧾 Tributos Aduana'!$F$6) -> 0 | G14: ='🧾 Factura Comercial'!H16*'📋 Datos Generales'!$E$19 -> 0 | H14: =TABLA_BASE[[#This Row],[FOB UNIT. (S/.)]]*TABLA_BASE[[#This Row],[CANTIDAD (unid.)]] -> 0 | I14: =IF('🧾 Tributos Aduana'!$F$6=0,0,'🧾 Tributos Aduana'!$F$17*('🧾 Factura Comercial'!H16/'🧾 Tributos Aduana'!$F$6)) -> 0 | J14: =TABLA_BASE[[#This Row],[ADV UNIT. (US$) ⚠️COSTO]]*TABLA_BASE[[#This Row],[CANTIDAD (unid.)]] -> 0 | K14: =IF('🧾 Tributos Aduana'!$F$6=0,0,'🧾 Tributos Aduana'!$F$18*('🧾 Factura Comercial'!H16/'🧾 Tributos Aduana'!$F$6)) -> 0 | L14: =TABLA_BASE[[#This Row],[IPM UNIT. (US$) ✅CF]]*TABLA_BASE[[#This Row],[CANTIDAD (unid.)]] -> 0 | M14: =IF('🧾 Tributos Aduana'!$F$6=0,0,'🧾 Tributos Aduana'!$F$19*('🧾 Factura Comercial'!H16/'🧾 Tributos Aduana'!$F$6)) -> 0 | N14: =TABLA_BASE[[#This Row],[IGV UNIT. (US$) ✅CF]]*TABLA_BASE[[#This Row],[CANTIDAD (unid.)]] -> 0 | O14: =IF('🧾 Tributos Aduana'!$F$6=0,0,'🧾 Tributos Aduana'!$F$23*('🧾 Factura Comercial'!H16/'🧾 Tributos Aduana'!$F$6)) -> 0 | P14: =TABLA_BASE[[#This Row],[PERCEP. UNIT.(US$) ✅CF]]*TABLA_BASE[[#This Row],[CANTIDAD (unid.)]] -> 0 | Q14: =TABLA_BASE[[#This Row],[ADV UNIT. (US$) ⚠️COSTO]]+TABLA_BASE[[#This Row],[IPM UNIT. (US$) ✅CF]]+TABLA_BASE[[#This Row],[IGV UNIT. (US$) ✅CF]] -> 0 | R14: =TABLA_BASE[[#This Row],[DEUDA ADUANERA UNIT.]]*TABLA_BASE[[#This Row],[CANTIDAD (unid.)]] -> 0 | S14: =TABLA_BASE[[#This Row],[ADV UNIT. (US$) ⚠️COSTO]]*'📋 Datos Generales'!$E$19 -> 0 | T14: =TABLA_BASE[[#This Row],[ADV UNIT. (S/.)]]*TABLA_BASE[[#This Row],[CANTIDAD (unid.)]] -> 0 | U14: =TABLA_BASE[[#This Row],[IPM UNIT. (US$) ✅CF]]*'📋 Datos Generales'!$E$19 -> 0 | V14: =TABLA_BASE[[#This Row],[IPM UNIT. (S/.)]]*TABLA_BASE[[#This Row],[CANTIDAD (unid.)]] -> 0 | W14: =TABLA_BASE[[#This Row],[IGV UNIT. (US$) ✅CF]]*'📋 Datos Generales'!$E$19 -> 0 | X14: =TABLA_BASE[[#This Row],[IGV UNIT. (S/.)]]*TABLA_BASE[[#This Row],[CANTIDAD (unid.)]] -> 0 | Y14: =TABLA_BASE[[#This Row],[PERCEP. UNIT.(US$) ✅CF]]*'📋 Datos Generales'!$E$19 -> 0 | Z14: =TABLA_BASE[[#This Row],[PERCEP. UNIT.(S/.)]]*TABLA_BASE[[#This Row],[CANTIDAD (unid.)]] -> 0 | AA14: =TABLA_BASE[[#This Row],[ADV UNIT. (US$) ⚠️COSTO]]+TABLA_BASE[[#This Row],[IPM UNIT. (US$) ✅CF]]+TABLA_BASE[[#This Row],[IGV UNIT. (US$) ✅CF]]+TABLA_BASE[[#This Row],[PERCEP. UNIT.(US$) ✅CF]] -> 0 | AB14: =TABLA_BASE[[#This Row],[TOTAL PAGO SUNAT UNIT.(US$)]]*TABLA_BASE[[#This Row],[CANTIDAD (unid.)]] -> 0 | AC14: =TABLA_BASE[[#This Row],[TOTAL PAGO SUNAT UNIT.(US$)]]*'📋 Datos Generales'!$E$19 -> 0 | AD14: =TABLA_BASE[[#This Row],[TOTAL TRIB. UNIT.(S/.)]]*TABLA_BASE[[#This Row],[CANTIDAD (unid.)]] -> 0 | AE14: =IF('🧾 Factura Comercial'!G16=0,0,'📦 Gastos Importación'!$E$28*(IF('🧾 Tributos Aduana'!$F$6=0,0,'🧾 Factura Comercial'!I16/'🧾 Tributos Aduana'!$F$6))/'🧾 Factura Comercial'!G16) -> 0 | AF14: =TABLA_BASE[[#This Row],[GASTOS IMP. UNIT.(US$)]]*TABLA_BASE[[#This Row],[CANTIDAD (unid.)]] -> 0 | AG14: =TABLA_BASE[[#This Row],[GASTOS IMP. UNIT.(US$)]]*'📋 Datos Generales'!$E$19 -> 0 | AH14: =TABLA_BASE[[#This Row],[GASTOS IMP. UNIT.(S/.)]]*TABLA_BASE[[#This Row],[CANTIDAD (unid.)]] -> 0 | AI14: ='🧮 Costos x Producto'!J18 -> 0 | AJ14: ='🧮 Costos x Producto'!K18 -> 0 | AK14: =IF('🧾 Factura Comercial'!G16=0,0,'🧾 Tributos Aduana'!$F$17*(IF('🧾 Tributos Aduana'!$F$6=0,0,'🧾 Factura Comercial'!I16/'🧾 Tributos Aduana'!$F$6))/'🧾 Factura Comercial'!G16) -> 0 | AL14: =IF('🧾 Factura Comercial'!G16=0,0,'🏦 Crédito Fiscal'!$C$16*(IF('🧾 Tributos Aduana'!$F$6=0,0,'🧾 Factura Comercial'!I16/'🧾 Tributos Aduana'!$F$6))/'🧾 Factura Comercial'!G16) -> 0 | AM14: =TABLA_BASE[[#This Row],[CF UNIT. ✅RECUP. (US$)]]*'📋 Datos Generales'!$E$19 -> 0 | AN14: =TABLA_BASE[[#This Row],[CF UNIT. ✅RECUP.(S/.)]]*TABLA_BASE[[#This Row],[CANTIDAD (unid.)]] -> 0 | AO14: ='💰 Precio de Venta'!G19 -> 0.4 | AP14: ='💰 Precio de Venta'!H19 -> 0 | AQ14: ='💰 Precio de Venta'!I19 -> 0 | AR14: ='💰 Precio de Venta'!J19 -> 0 | AS14: ='💰 Precio de Venta'!K19 -> 0 | AT14: =TABLA_BASE[[#This Row],[GANANCIA UNIT.(S/.)]]*'🧾 Factura Comercial'!G16 -> 0 | AU14: =IF(TABLA_BASE[[#This Row],[PRECIO VTA. c/IGV(S/.)]]=0,0,TABLA_BASE[[#This Row],[GANANCIA UNIT.(S/.)]]/TABLA_BASE[[#This Row],[PRECIO VTA. c/IGV(S/.)]]) -> 0 | AV14: =IF(TABLA_BASE[[#This Row],[C/M UNIT. (S/.)]]=0,0,TABLA_BASE[[#This Row],[GANANCIA UNIT.(S/.)]]/TABLA_BASE[[#This Row],[C/M UNIT. (S/.)]]) -> 0 | AW14: =IF(TABLA_BASE[[#This Row],[MARGEN %]]>=0.5,"🟢 ALTO",IF(TABLA_BASE[[#This Row],[MARGEN %]]>=0.3,"🟡 MEDIO","🔴 BAJO")) -> 🟡 MEDIO
... A89: ='🧾 Factura Comercial'!E91 -> 0 | B89: ='🧾 Factura Comercial'!F91 -> 0 | C89: ='🧾 Factura Comercial'!G91 -> 0 | D89: ='🧾 Factura Comercial'!H91 -> 0 | E89: ='🧾 Factura Comercial'!I91 -> 0 | F89: =IF('🧾 Tributos Aduana'!$F$6=0,0,'🧾 Factura Comercial'!I91/'🧾 Tributos Aduana'!$F$6) -> 0 | G89: ='🧾 Factura Comercial'!H91*'📋 Datos Generales'!$E$19 -> 0 | H89: =TABLA_BASE[[#This Row],[FOB UNIT. (S/.)]]*TABLA_BASE[[#This Row],[CANTIDAD (unid.)]] -> 0 | I89: =IF('🧾 Tributos Aduana'!$F$6=0,0,'🧾 Tributos Aduana'!$F$17*('🧾 Factura Comercial'!H91/'🧾 Tributos Aduana'!$F$6)) -> 0 | J89: =TABLA_BASE[[#This Row],[ADV UNIT. (US$) ⚠️COSTO]]*TABLA_BASE[[#This Row],[CANTIDAD (unid.)]] -> 0 | K89: =IF('🧾 Tributos Aduana'!$F$6=0,0,'🧾 Tributos Aduana'!$F$18*('🧾 Factura Comercial'!H91/'🧾 Tributos Aduana'!$F$6)) -> 0 | L89: =TABLA_BASE[[#This Row],[IPM UNIT. (US$) ✅CF]]*TABLA_BASE[[#This Row],[CANTIDAD (unid.)]] -> 0 | M89: =IF('🧾 Tributos Aduana'!$F$6=0,0,'🧾 Tributos Aduana'!$F$19*('🧾 Factura Comercial'!H91/'🧾 Tributos Aduana'!$F$6)) -> 0 | N89: =TABLA_BASE[[#This Row],[IGV UNIT. (US$) ✅CF]]*TABLA_BASE[[#This Row],[CANTIDAD (unid.)]] -> 0 | O89: =IF('🧾 Tributos Aduana'!$F$6=0,0,'🧾 Tributos Aduana'!$F$23*('🧾 Factura Comercial'!H91/'🧾 Tributos Aduana'!$F$6)) -> 0 | P89: =TABLA_BASE[[#This Row],[PERCEP. UNIT.(US$) ✅CF]]*TABLA_BASE[[#This Row],[CANTIDAD (unid.)]] -> 0 | Q89: =TABLA_BASE[[#This Row],[ADV UNIT. (US$) ⚠️COSTO]]+TABLA_BASE[[#This Row],[IPM UNIT. (US$) ✅CF]]+TABLA_BASE[[#This Row],[IGV UNIT. (US$) ✅CF]] -> 0 | R89: =TABLA_BASE[[#This Row],[DEUDA ADUANERA UNIT.]]*TABLA_BASE[[#This Row],[CANTIDAD (unid.)]] -> 0 | S89: =TABLA_BASE[[#This Row],[ADV UNIT. (US$) ⚠️COSTO]]*'📋 Datos Generales'!$E$19 -> 0 | T89: =TABLA_BASE[[#This Row],[ADV UNIT. (S/.)]]*TABLA_BASE[[#This Row],[CANTIDAD (unid.)]] -> 0 | U89: =TABLA_BASE[[#This Row],[IPM UNIT. (US$) ✅CF]]*'📋 Datos Generales'!$E$19 -> 0 | V89: =TABLA_BASE[[#This Row],[IPM UNIT. (S/.)]]*TABLA_BASE[[#This Row],[CANTIDAD (unid.)]] -> 0 | W89: =TABLA_BASE[[#This Row],[IGV UNIT. (US$) ✅CF]]*'📋 Datos Generales'!$E$19 -> 0 | X89: =TABLA_BASE[[#This Row],[IGV UNIT. (S/.)]]*TABLA_BASE[[#This Row],[CANTIDAD (unid.)]] -> 0 | Y89: =TABLA_BASE[[#This Row],[PERCEP. UNIT.(US$) ✅CF]]*'📋 Datos Generales'!$E$19 -> 0 | Z89: =TABLA_BASE[[#This Row],[PERCEP. UNIT.(S/.)]]*TABLA_BASE[[#This Row],[CANTIDAD (unid.)]] -> 0 | AA89: =TABLA_BASE[[#This Row],[ADV UNIT. (US$) ⚠️COSTO]]+TABLA_BASE[[#This Row],[IPM UNIT. (US$) ✅CF]]+TABLA_BASE[[#This Row],[IGV UNIT. (US$) ✅CF]]+TABLA_BASE[[#This Row],[PERCEP. UNIT.(US$) ✅CF]] -> 0 | AB89: =TABLA_BASE[[#This Row],[TOTAL PAGO SUNAT UNIT.(US$)]]*TABLA_BASE[[#This Row],[CANTIDAD (unid.)]] -> 0 | AC89: =TABLA_BASE[[#This Row],[TOTAL PAGO SUNAT UNIT.(US$)]]*'📋 Datos Generales'!$E$19 -> 0 | AD89: =TABLA_BASE[[#This Row],[TOTAL TRIB. UNIT.(S/.)]]*TABLA_BASE[[#This Row],[CANTIDAD (unid.)]] -> 0 | AE89: =IF('🧾 Factura Comercial'!G91=0,0,'📦 Gastos Importación'!$E$28*(IF('🧾 Tributos Aduana'!$F$6=0,0,'🧾 Factura Comercial'!I91/'🧾 Tributos Aduana'!$F$6))/'🧾 Factura Comercial'!G91) -> 0 | AF89: =TABLA_BASE[[#This Row],[GASTOS IMP. UNIT.(US$)]]*TABLA_BASE[[#This Row],[CANTIDAD (unid.)]] -> 0 | AG89: =TABLA_BASE[[#This Row],[GASTOS IMP. UNIT.(US$)]]*'📋 Datos Generales'!$E$19 -> 0 | AH89: =TABLA_BASE[[#This Row],[GASTOS IMP. UNIT.(S/.)]]*TABLA_BASE[[#This Row],[CANTIDAD (unid.)]] -> 0 | AI89: ='🧮 Costos x Producto'!J93 -> 0 | AJ89: ='🧮 Costos x Producto'!K93 -> 0 | AK89: =IF('🧾 Factura Comercial'!G91=0,0,'🧾 Tributos Aduana'!$F$17*(IF('🧾 Tributos Aduana'!$F$6=0,0,'🧾 Factura Comercial'!I91/'🧾 Tributos Aduana'!$F$6))/'🧾 Factura Comercial'!G91) -> 0 | AL89: =IF('🧾 Factura Comercial'!G91=0,0,'🏦 Crédito Fiscal'!$C$16*(IF('🧾 Tributos Aduana'!$F$6=0,0,'🧾 Factura Comercial'!I91/'🧾 Tributos Aduana'!$F$6))/'🧾 Factura Comercial'!G91) -> 0 | AM89: =TABLA_BASE[[#This Row],[CF UNIT. ✅RECUP. (US$)]]*'📋 Datos Generales'!$E$19 -> 0 | AN89: =TABLA_BASE[[#This Row],[CF UNIT. ✅RECUP.(S/.)]]*TABLA_BASE[[#This Row],[CANTIDAD (unid.)]] -> 0 | AO89: ='💰 Precio de Venta'!G94 -> 0 | AP89: ='💰 Precio de Venta'!H94 -> 0 | AQ89: ='💰 Precio de Venta'!I94 -> 0 | AR89: ='💰 Precio de Venta'!J94 -> 0 | AS89: ='💰 Precio de Venta'!K94 -> 0 | AT89: =TABLA_BASE[[#This Row],[GANANCIA UNIT.(S/.)]]*'🧾 Factura Comercial'!G91 -> 0 | AU89: =IF(TABLA_BASE[[#This Row],[PRECIO VTA. c/IGV(S/.)]]=0,0,TABLA_BASE[[#This Row],[GANANCIA UNIT.(S/.)]]/TABLA_BASE[[#This Row],[PRECIO VTA. c/IGV(S/.)]]) -> 0 | AV89: =IF(TABLA_BASE[[#This Row],[C/M UNIT. (S/.)]]=0,0,TABLA_BASE[[#This Row],[GANANCIA UNIT.(S/.)]]/TABLA_BASE[[#This Row],[C/M UNIT. (S/.)]]) -> 0 | AW89: =IF(TABLA_BASE[[#This Row],[MARGEN %]]>=0.5,"🟢 ALTO",IF(TABLA_BASE[[#This Row],[MARGEN %]]>=0.3,"🟡 MEDIO","🔴 BAJO")) -> 🔴 BAJO
C90: =SUM(TABLA_BASE[CANTIDAD (unid.)]) -> 34224 | D90: =SUM(TABLA_BASE[FOB UNIT. (US$)]) -> 9.93 | E90: =SUM(TABLA_BASE[FOB TOTAL (US$)]) -> 28427.52 | G90: =SUM(TABLA_BASE[FOB UNIT. (S/.)]) -> 36.9396 | H90: =SUM(TABLA_BASE[FOB TOTAL (S/.)]) -> 52875.187 | I90: =SUM(TABLA_BASE[ADV UNIT. (US$) ⚠️COSTO]) -> 0.68883814 | J90: =SUM(TABLA_BASE[ADV TOTAL (US$) ⚠️COSTO]) -> 986 | K90: =SUM(TABLA_BASE[IPM UNIT. (US$) ✅CF]) -> 0.24311934 | L90: =SUM(TABLA_BASE[IPM TOTAL (US$) ✅CF]) -> 348 | M90: =SUM(TABLA_BASE[IGV UNIT. (US$) ✅CF]) -> 1.9477492 | N90: =SUM(TABLA_BASE[IGV TOTAL (US$) ✅CF]) -> 2788 | O90: =SUM(TABLA_BASE[PERCEP. UNIT.(US$) ✅CF]) -> 0.50272609 | P90: =SUM(TABLA_BASE[PERCEP. TOTAL.(US$) ✅CF]) -> 719.6 | Q90: =SUM(TABLA_BASE[DEUDA ADUANERA UNIT.]) -> 2.8797067 | R90: =SUM(TABLA_BASE[DEUDA ADUANERA TOTAL]) -> 4122 | S90: =SUM(TABLA_BASE[ADV UNIT. (S/.)]) -> 2.5624779 | T90: =SUM(TABLA_BASE[ADV TOTAL. (S/.)]) -> 3667.92 | U90: =SUM(TABLA_BASE[IPM UNIT. (S/.)]) -> 0.90440396 | V90: =SUM(TABLA_BASE[IPM TOTAL (S/.)2]) -> 1294.56 | W90: =SUM(TABLA_BASE[IGV UNIT. (S/.)]) -> 7.2456271 | X90: =SUM(TABLA_BASE[IGV TOTAL (S/.)2]) -> 10371.36 | Y90: =SUM(TABLA_BASE[PERCEP. UNIT.(S/.)]) -> 1.8701411 | Z90: =SUM(TABLA_BASE[PERCEP. TOTAL.(S/.)2]) -> 2676.912 | AA90: =SUM(TABLA_BASE[TOTAL PAGO SUNAT UNIT.(US$)]) -> 3.3824328 | AB90: =SUM(TABLA_BASE[TOTAL PAGO SUNAT TOTAL(US$)]) -> 4841.6 | AC90: =SUM(TABLA_BASE[TOTAL TRIB. UNIT.(S/.)]) -> 12.58265 | AD90: =SUM(TABLA_BASE[TOTAL TRIB. TOTAL .(S/.)]) -> 18010.752 | AE90: =SUM(TABLA_BASE[GASTOS IMP. UNIT.(US$)]) -> 12.986464 | AF90: =SUM(TABLA_BASE[GASTOS IMP. TOTAL.(US$)2]) -> 18588.77 | AG90: =SUM(TABLA_BASE[GASTOS IMP. UNIT.(S/.)]) -> 48.309647 | AH90: =SUM(TABLA_BASE[GASTOS IMP. TOTAL.(S/.)2]) -> 69150.224 | AI90: =SUM(TABLA_BASE[C/M UNIT. (US$)]) -> 12.986464 | AJ90: =SUM(TABLA_BASE[C/M UNIT. (S/.)]) -> 48.309647 | AK90: =SUM(TABLA_BASE[ADV UNIT. ⚠️COSTO (US$)]) -> 0.68883814 | AL90: =SUM(TABLA_BASE[CF UNIT. ✅RECUP. (US$)]) -> 2.8358836 | AM90: =SUM(TABLA_BASE[CF UNIT. ✅RECUP.(S/.)]) -> 10.549487 | AN90: =SUM(AN3:AN11) -> 15100.491 | AO90: =SUM(TABLA_BASE[MARGEN %]) -> 12 | AT90: =SUM(TABLA_BASE[GANANCIA TOTAL(S/.)]) -> 46100.15 | AV90: =SUM(TABLA_BASE[ROI UNIT.]) -> 6 | AW90: =SUM(TABLA_BASE[CLASIF. MARGEN]) -> 0

Sheet 📊 Dashboard
E1: 📊 CALCULADORA DE COSTOS DE IMPORTACIÓN — DASHBOARD EJECUTIVO
E2: ='📋 Datos Generales'!E6&" | DUA: "&'📋 Datos Generales'!E5&" | País: "&'📋 Datos Generales'!E9&" | Proveedor: "&'📋 Datos Generales'!E10&" | Incoterm: "&'📋 Datos Generales'!E11&" | TC: S/."&TEXT('📋 Datos Generales'!E19,"0.000") -> EMPRESA IMPORTADORA S.A.C. | DUA: DAM-2025-000001 | País: China | Proveedor: HWPI Co. Ltd. | Incoterm: FOB | TC: S/.3.720
E4: 💰 COSTO TOTAL IMPORTACIÓN (S/.) | F4: 📦 VALOR CIF (US$) | G4: ⚖️ ADV ARANCEL (US$) | H4: 📋 DEUDA ADUANERA (US$) | I4: 💹 INGRESOS EST. TOTALES (S/.) | J4: 🏦 CRÉDITO FISCAL (US$) | K4: 📈 MARGEN GLOBAL (%) | L4: 🎯 PERCEPCIÓN IGV (US$)
E5: ='🧮 Costos x Producto'!I4 -> 69150.224 | F5: ='🧾 Tributos Aduana'!F14 -> 16438.03 | G5: ='🧾 Tributos Aduana'!F17 -> 986 | H5: ='🧾 Tributos Aduana'!F20 -> 4122 | I5: =SUMPRODUCT('🧾 Factura Comercial'!G5:G34,'💰 Precio de Venta'!H8:H37) -> 115250.37 | J5: ='🏦 Crédito Fiscal'!C16 -> 4059.2718 | K5: =IF(SUMPRODUCT('🧾 Factura Comercial'!G5:G34,'💰 Precio de Venta'!H8:H37)=0,0,(SUMPRODUCT('🧾 Factura Comercial'!G5:G34,'💰 Precio de Venta'!H8:H37)-'🧮 Costos x Producto'!I4)/SUMPRODUCT('🧾 Factura Comercial'!G5:G34,'💰 Precio de Venta'!H8:H37)) -> 0.4 | L5: ='🧾 Tributos Aduana'!F23 -> 719.6
E8: PERCEPCIÓN IGV (US$) | F8: TIPO DE CAMBIO (PEN) | G8: AD VALOREM (%) | H8: PERCEPCIÓN (%) | I8: CIF = VALOR EN ADUANAS (US$)
E9: ='🧾 Tributos Aduana'!F23 -> 719.6 | F9: ='📋 Datos Generales'!E19 -> 3.72 | G9: ='📋 Datos Generales'!E20 -> 0.06 | H9: ='📋 Datos Generales'!E23 -> 0.035 | I9: ='🧾 Tributos Aduana'!F14 -> 16438.03
E12: 📊 DESGLOSE DE COSTOS DE IMPORTACIÓN
E13: CONCEPTO | F13: MONTO (US$) | G13: MONTO (S/.) | H13: % DEL TOTAL
E14: Valor FOB Total | F14: ='🧾 Tributos Aduana'!F6 -> 14213.76 | G14: =F14*'📋 Datos Generales'!E19 -> 52875.187 | H14: =IF('🧮 Costos x Producto'!G4=0,0,F14/'🧮 Costos x Producto'!G4) -> 0.76464231
E15: Flete Internacional | F15: ='🧾 Tributos Aduana'!F7 -> 2090 | G15: =F15*'📋 Datos Generales'!E19 -> 7774.8 | H15: =IF('🧮 Costos x Producto'!G4=0,0,F15/'🧮 Costos x Producto'!G4) -> 0.11243347
E16: Seguro (Prima Neta) | F16: ='🧾 Tributos Aduana'!F10 -> 134.27 | G16: =F16*'📋 Datos Generales'!E19 -> 499.4844 | H16: =IF('🧮 Costos x Producto'!G4=0,0,F16/'🧮 Costos x Producto'!G4) -> 0.0072231783
E17: Aranceles (ADV) | F17: ='🧾 Tributos Aduana'!F17 -> 986 | G17: =F17*'📋 Datos Generales'!E19 -> 3667.92 | H17: =IF('🧮 Costos x Producto'!G4=0,0,F17/'🧮 Costos x Producto'!G4) -> 0.053042778
E18: IGV + IPM Aduanas | F18: ='🧾 Tributos Aduana'!F19+'🧾 Tributos Aduana'!F18 -> 3136 | G18: =F18*'📋 Datos Generales'!E19 -> 11665.92 | H18: =IF('🧮 Costos x Producto'!G4=0,0,F18/'🧮 Costos x Producto'!G4) -> 0.16870401
E19: Percepción IGV | F19: ='🧾 Tributos Aduana'!F23 -> 719.6 | G19: =F19*'📋 Datos Generales'!E19 -> 2676.912 | H19: =IF('🧮 Costos x Producto'!G4=0,0,F19/'🧮 Costos x Producto'!G4) -> 0.038711545
E20: Gastos de Importación | F20: ='📦 Gastos Importación'!E28 -> 18588.77 | G20: =F20*'📋 Datos Generales'!E19 -> 69150.224 | H20: =IF('🧮 Costos x Producto'!G4=0,0,F20/'🧮 Costos x Producto'!G4) -> 1
E22: 💹 RESUMEN DE RENTABILIDAD
E23: Costo Total Importación (S/.) | F23: ='🧮 Costos x Producto'!I4 -> 69150.224 | G23: Ingresos Totales si se vende todo (S/.) | H23: =SUMPRODUCT('🧾 Factura Comercial'!G5:G34,'💰 Precio de Venta'!H8:H37) -> 115250.37
E24: Utilidad Bruta Total (S/.) | F24: =H23-F23 -> 46100.15 | G24: Margen Global Real (%) | H24: =IF(H23=0,0,(H23-F23)/H23) -> 0.4 | I24: =IF(H23=0,0,(H23-F23)/H23) -> 0.4
E25: Crédito Fiscal a Favor (US$) | F25: ='🏦 Crédito Fiscal'!C16 -> 4059.2718 | G25: Crédito Fiscal a Favor (S/.) | H25: ='🏦 Crédito Fiscal'!C17 -> 15100.491
E26: 💹 ANÁLISIS DE RENTABILIDAD Y PRECIOS POR PRODUCTO
E27: 🏷️ TOTAL INGRESOS (S/.) | F27: 📦 COSTO TOTAL (S/.) | G27: 💵 UTILIDAD BRUTA (S/.) | H27: 📊 MARGEN NETO (%) | I27: 🏦 CF a FAVOR (US$) | J27: 🏦 CF a FAVOR (S/.) | K27: 📦 PRODS. IMPORTADOS | L27: 💲 FOB PROMEDIO (US$)
E28: =SUMPRODUCT('🧾 Factura Comercial'!G5:G34,'💰 Precio de Venta'!H8:H37) -> 115250.37 | F28: ='🧮 Costos x Producto'!I4 -> 69150.224 | G28: =E28-F28 -> 46100.15 | H28: =IF(E28=0,0,G28/E28) -> 0.4 | I28: ='🏦 Crédito Fiscal'!C16 -> 4059.2718 | J28: ='🏦 Crédito Fiscal'!C17 -> 15100.491 | K28: =COUNTIF('🧾 Factura Comercial'!E5:E34,"?*") -> 9 | L28: =IF(K28=0,0,'🧾 Factura Comercial'!I35/K28) -> 1579.3067
E48: 🏦 DETALLE CRÉDITO FISCAL vs COSTOS REALES
E49: CONCEPTO | F49: MONTO (US$) | G49: MONTO (S/.) | H49: TIPO
E50: Ad Valorem (COSTO REAL) | F50: ='🧾 Tributos Aduana'!F17 -> 986 | G50: =F50*'📋 Datos Generales'!E19 -> 3667.92 | H50: 💸 COSTO
E51: IPM (Crédito Fiscal) | F51: ='🧾 Tributos Aduana'!F18 -> 348 | G51: =F51*'📋 Datos Generales'!E19 -> 1294.56 | H51: ✅ CF
E52: IGV Aduanas (Crédito Fiscal) | F52: ='🧾 Tributos Aduana'!F19 -> 2788 | G52: =F52*'📋 Datos Generales'!E19 -> 10371.36 | H52: ✅ CF
E53: Percepción (Crédito Fiscal) | F53: ='🧾 Tributos Aduana'!F23 -> 719.6 | G53: =F53*'📋 Datos Generales'!E19 -> 2676.912 | H53: ✅ CF
E54: IGV Seguro (Crédito Fiscal) | F54: ='🧾 Tributos Aduana'!F12 -> 24.1686 | G54: =F54*'📋 Datos Generales'!E19 -> 89.907192 | H54: ✅ CF
E55: IGV Gastos Afectos (CF) | F55: ='📦 Gastos Importación'!F26 -> 179.5032 | G55: =F55*'📋 Datos Generales'!E19 -> 667.7519 | H55: ✅ CF
E56: TOTAL CRÉDITO FISCAL (US$) | F56: ='🏦 Crédito Fiscal'!C16 -> 4059.2718 | G56: ='🏦 Crédito Fiscal'!C17 -> 15100.491 | H56: COSTO REAL: ='🧾 Tributos Aduana'!C16&" US$"
N60: Componente | O60: US$ | P60: S/.
N61: FOB Mercadería | O61: ='🧾 Tributos Aduana'!F6 -> 14213.76 | P61: =O61*'📋 Datos Generales'!E19 -> 52875.187
N62: Flete | O62: ='🧾 Tributos Aduana'!F7 -> 2090 | P62: =O62*'📋 Datos Generales'!E19 -> 7774.8
N63: Seguro | O63: ='🧾 Tributos Aduana'!F10 -> 134.27 | P63: =O63*'📋 Datos Generales'!E19 -> 499.4844
N64: Aranceles (ADV) | O64: ='🧾 Tributos Aduana'!F17 -> 986 | P64: =O64*'📋 Datos Generales'!E19 -> 3667.92
N65: Gastos Operativos | O65: ='📦 Gastos Importación'!E26 -> 997.24 | P65: =O65*'📋 Datos Generales'!E19 -> 3709.7328
N66: Gastos Admin/Fin. | O66: ='📦 Gastos Importación'!E27 -> 167.5 | P66: =O66*'📋 Datos Generales'!E19 -> 623.1
N70: Tributo | O70: Monto US$
N71: Ad Valorem | O71: ='🧾 Tributos Aduana'!F17 -> 986
N72: IPM | O72: ='🧾 Tributos Aduana'!F18 -> 348
N73: IGV Aduanas | O73: ='🧾 Tributos Aduana'!F19 -> 2788
N74: Percepción | O74: ='🧾 Tributos Aduana'!F23 -> 719.6
N75: IGV Seguro | O75: ='🧾 Tributos Aduana'!F12 -> 24.1686
N80: Producto | O80: FOB Total US$ | P80: C/M Unit PEN | Q80: PV Unit PEN | R80: Ganancia Unit PEN
N81: ='🧾 Factura Comercial'!E5 -> Case Transparente TPU iPhone 15 | O81: ='🧾 Factura Comercial'!I5 -> 580.8 | P81: ='🧮 Costos x Producto'!K7 -> 5.886674 | Q81: ='💰 Precio de Venta'!H8 -> 9.8111233 | R81: ='💰 Precio de Venta'!J8 -> 3.9244493
N82: ='🧾 Factura Comercial'!E6 -> Cable USB-C Trenzado 1m | O82: ='🧾 Factura Comercial'!I6 -> 1958.4 | P82: ='🧮 Costos x Producto'!K8 -> 3.3082135 | Q82: ='💰 Precio de Venta'!H9 -> 5.5136892 | R82: ='💰 Precio de Venta'!J9 -> 2.2054757
N83: ='🧾 Factura Comercial'!E7 -> Protector Pantalla Vidrio Templado | O83: ='🧾 Factura Comercial'!I7 -> 1152 | P83: ='🧮 Costos x Producto'!K9 -> 1.9460079 | Q83: ='💰 Precio de Venta'!H10 -> 3.2433466 | R83: ='💰 Precio de Venta'!J10 -> 1.2973386
N84: ='🧾 Factura Comercial'!E8 -> Audífonos In-Ear con Micrófono | O84: ='🧾 Factura Comercial'!I8 -> 3476.16 | P84: ='🧮 Costos x Producto'!K10 -> 1.6541067 | Q84: ='💰 Precio de Venta'!H11 -> 2.7568446 | R84: ='💰 Precio de Venta'!J11 -> 1.1027378
N85: ='🧾 Factura Comercial'!E9 -> Cable Micro USB 2m Nylon | O85: ='🧾 Factura Comercial'!I9 -> 2246.4 | P85: ='🧮 Costos x Producto'!K11 -> 1.2649052 | Q85: ='💰 Precio de Venta'!H12 -> 2.1081753 | R85: ='💰 Precio de Venta'!J12 -> 0.84327011
N86: ='🧾 Factura Comercial'!E10 -> Soporte Anillo Pop Socket Metálico | O86: ='🧾 Factura Comercial'!I10 -> 626.4 | P86: ='🧮 Costos x Producto'!K12 -> 1.4108558 | Q86: ='💰 Precio de Venta'!H13 -> 2.3514263 | R86: ='💰 Precio de Venta'!J13 -> 0.9405705
N87: ='🧾 Factura Comercial'!E11 -> Cargador Inalámbrico 15W Qi | O87: ='🧾 Factura Comercial'!I11 -> 1370.4 | P87: ='🧮 Costos x Producto'!K13 -> 27.779263 | Q87: ='💰 Precio de Venta'!H14 -> 46.298772 | R87: ='💰 Precio de Venta'!J14 -> 18.519509
N88: ='🧾 Factura Comercial'!E12 -> Case Wallet Cuero PU Samsung S24 | O88: ='🧾 Factura Comercial'!I12 -> 1459.2 | P88: ='🧮 Costos x Producto'!K14 -> 3.6974151 | Q88: ='💰 Precio de Venta'!H15 -> 6.1623585 | R88: ='💰 Precio de Venta'!J15 -> 2.4649434
N89: ='🧾 Factura Comercial'!E13 -> Adaptador USB-C a Jack 3.5mm | O89: ='🧾 Factura Comercial'!I13 -> 1344 | P89: ='🧮 Costos x Producto'!K15 -> 1.3622056 | Q89: ='💰 Precio de Venta'!H16 -> 2.2703426 | R89: ='💰 Precio de Venta'!J16 -> 0.90813704
N90: Concepto | O90: Monto US$ | P90: Tipo
N91: Ad Valorem | O91: ='🧾 Tributos Aduana'!F17 -> 986
N92: IPM | O92: ='🧾 Tributos Aduana'!F18 -> 348
N93: IGV Aduanas | O93: ='🧾 Tributos Aduana'!F19 -> 2788
N94: Percepción | O94: ='🧾 Tributos Aduana'!F23 -> 719.6
N95: IGV Seguro | O95: ='🧾 Tributos Aduana'!F12 -> 24.1686
N96: IGV Gastos | O96: ='📦 Gastos Importación'!F26 -> 179.5032
N100: Concepto | O100: US$
N101: Costo Real (ADV) | O101: ='🧾 Tributos Aduana'!F17 -> 986
N102: Crédito Fiscal | O102: ='🏦 Crédito Fiscal'!C16 -> 4059.2718

Sheet 📊 Dashboard General
C13: ='📋 Datos Generales'!E6&" | DUA: "&'📋 Datos Generales'!E5&" | País: "&'📋 Datos Generales'!E9&" | Proveedor: "&'📋 Datos Generales'!E10&" | Incoterm: "&'📋 Datos Generales'!E11&" | TC: S/."&TEXT('📋 Datos Generales'!E19,"0.000") -> EMPRESA IMPORTADORA S.A.C. | DUA: DAM-2025-000001 | País: China | Proveedor: HWPI Co. Ltd. | Incoterm: FOB | TC: S/.3.720
AK20: ¿

Sheet 🏦Detallado por Producto
B2: 🔍 ANÁLISIS DETALLADO POR PRODUCTO — TODOS LOS COSTOS, TRIBUTOS Y MÁRGENES
B4: 📦 FOB TOTAL (US$): | C4: ='[1]🧾 Tributos Aduana'!C5 -> 14213.76 | E4: 🚢 CIF (US$): | F4: ='[1]🧾 Tributos Aduana'!C13 -> 14687.558 | H4: ⚖️ FACTOR PRORRATEO: | I4: ='[1]🧮 Costos x Producto'!D4 -> 0 | K4: 💱 TIPO DE CAMBIO: | L4: ='[1]📋 Datos Generales'!C19 -> 3.72 | N4: 📊 COSTO TOTAL (US$): | O4: ='[1]🧮 Costos x Producto'!D3 -> 0 | Q4: 🏦 CRÉDITO FISCAL (US$): | R4: ='[1]🏦 Crédito Fiscal'!C10 -> 6341.0973
B6: 📦 SECCIÓN 1: IDENTIFICACIÓN DEL PRODUCTO Y VALOR FOB
B7: # | C7: DESCRIPCIÓN DEL PRODUCTO | D7: UNIDAD | E7: CANTIDAD (unid.) | F7: FOB UNIT. (US$) | G7: FOB TOTAL (US$) | H7: % PART. FOB | I7: FOB UNIT. (S/.) | J7: FOB TOTAL (S/.)
B8: =1 -> 1 | C8: ='🧾 Factura Comercial'!E5:E34 | D8: ='[1]🧾 Factura Comercial'!D4 -> Unid. | E8: ='[1]🧾 Factura Comercial'!E4 -> 480 | F8: ='[1]🧾 Factura Comercial'!F4 -> 1.21 | G8: ='[1]🧾 Factura Comercial'!G4 -> 580.8 | H8: =IF('[1]🧾 Tributos Aduana'!C5=0,0,'[1]🧾 Factura Comercial'!G4/'[1]🧾 Tributos Aduana'!C5) -> 0.040861813 | I8: ='[1]🧾 Factura Comercial'!F4*'[1]📋 Datos Generales'!C19 -> 4.5012 | J8: ='[1]🧾 Factura Comercial'!G4*'[1]📋 Datos Generales'!C19 -> 2160.576
B9: =2 -> 2 | C9: ='[1]🧾 Factura Comercial'!C5 -> Friction Cars OPP Bag 23cm | D9: ='[1]🧾 Factura Comercial'!D5 -> Unid. | E9: ='[1]🧾 Factura Comercial'!E5 -> 2880 | F9: ='[1]🧾 Factura Comercial'!F5 -> 0.68 | G9: ='[1]🧾 Factura Comercial'!G5 -> 1958.4 | H9: =IF('[1]🧾 Tributos Aduana'!C5=0,0,'[1]🧾 Factura Comercial'!G5/'[1]🧾 Tributos Aduana'!C5) -> 0.13778198 | I9: ='[1]🧾 Factura Comercial'!F5*'[1]📋 Datos Generales'!C19 -> 2.5296 | J9: ='[1]🧾 Factura Comercial'!G5*'[1]📋 Datos Generales'!C19 -> 7285.248 | L9: Free Wheel Motor OPP Bag 21cm
B10: =3 -> 3 | C10: ='[1]🧾 Factura Comercial'!C6 -> Free Wheel Motor OPP Bag 21cm | D10: ='[1]🧾 Factura Comercial'!D6 -> Unid. | E10: ='[1]🧾 Factura Comercial'!E6 -> 2880 | F10: ='[1]🧾 Factura Comercial'!F6 -> 0.4 | G10: ='[1]🧾 Factura Comercial'!G6 -> 1152 | H10: =IF('[1]🧾 Tributos Aduana'!C5=0,0,'[1]🧾 Factura Comercial'!G6/'[1]🧾 Tributos Aduana'!C5) -> 0.081048224 | I10: ='[1]🧾 Factura Comercial'!F6*'[1]📋 Datos Generales'!C19 -> 1.488 | J10: ='[1]🧾 Factura Comercial'!G6*'[1]📋 Datos Generales'!C19 -> 4285.44
B11: =4 -> 4 | C11: ='[1]🧾 Factura Comercial'!C7 -> Friction Cars OPP Bag 22cm | D11: ='[1]🧾 Factura Comercial'!D7 -> Unid. | E11: ='[1]🧾 Factura Comercial'!E7 -> 10224 | F11: ='[1]🧾 Factura Comercial'!F7 -> 0.34 | G11: ='[1]🧾 Factura Comercial'!G7 -> 3476.16 | H11: =IF('[1]🧾 Tributos Aduana'!C5=0,0,'[1]🧾 Factura Comercial'!G7/'[1]🧾 Tributos Aduana'!C5) -> 0.24456301 | I11: ='[1]🧾 Factura Comercial'!F7*'[1]📋 Datos Generales'!C19 -> 1.2648 | J11: ='[1]🧾 Factura Comercial'!G7*'[1]📋 Datos Generales'!C19 -> 12931.315
B12: =5 -> 5 | C12: ='[1]🧾 Factura Comercial'!C8 -> Pull Line Friction Car OPP Bag | D12: ='[1]🧾 Factura Comercial'!D8 -> Unid. | E12: ='[1]🧾 Factura Comercial'!E8 -> 8640 | F12: ='[1]🧾 Factura Comercial'!F8 -> 0.26 | G12: ='[1]🧾 Factura Comercial'!G8 -> 2246.4 | H12: =IF('[1]🧾 Tributos Aduana'!C5=0,0,'[1]🧾 Factura Comercial'!G8/'[1]🧾 Tributos Aduana'!C5) -> 0.15804404 | I12: ='[1]🧾 Factura Comercial'!F8*'[1]📋 Datos Generales'!C19 -> 0.9672 | J12: ='[1]🧾 Factura Comercial'!G8*'[1]📋 Datos Generales'!C19 -> 8356.608
B13: =6 -> 6 | C13: ='[1]🧾 Factura Comercial'!C9 -> Friction Car OPP Bag | D13: ='[1]🧾 Factura Comercial'!D9 -> Unid. | E13: ='[1]🧾 Factura Comercial'!E9 -> 2160 | F13: ='[1]🧾 Factura Comercial'!F9 -> 0.29 | G13: ='[1]🧾 Factura Comercial'!G9 -> 626.4 | H13: =IF('[1]🧾 Tributos Aduana'!C5=0,0,'[1]🧾 Factura Comercial'!G9/'[1]🧾 Tributos Aduana'!C5) -> 0.044069972 | I13: ='[1]🧾 Factura Comercial'!F9*'[1]📋 Datos Generales'!C19 -> 1.0788 | J13: ='[1]🧾 Factura Comercial'!G9*'[1]📋 Datos Generales'!C19 -> 2330.208
B14: =7 -> 7 | C14: ='[1]🧾 Factura Comercial'!C10 -> Free Wheel Ride on Digger Handle | D14: ='[1]🧾 Factura Comercial'!D10 -> Unid. | E14: ='[1]🧾 Factura Comercial'!E10 -> 240 | F14: ='[1]🧾 Factura Comercial'!F10 -> 5.71 | G14: ='[1]🧾 Factura Comercial'!G10 -> 1370.4 | H14: =IF('[1]🧾 Tributos Aduana'!C5=0,0,'[1]🧾 Factura Comercial'!G10/'[1]🧾 Tributos Aduana'!C5) -> 0.096413616 | I14: ='[1]🧾 Factura Comercial'!F10*'[1]📋 Datos Generales'!C19 -> 21.2412 | J14: ='[1]🧾 Factura Comercial'!G10*'[1]📋 Datos Generales'!C19 -> 5097.888
B15: =8 -> 8 | C15: ='[1]🧾 Factura Comercial'!C11 -> Friction Car with Music and Light | D15: ='[1]🧾 Factura Comercial'!D11 -> Unid. | E15: ='[1]🧾 Factura Comercial'!E11 -> 1920 | F15: ='[1]🧾 Factura Comercial'!F11 -> 0.76 | G15: ='[1]🧾 Factura Comercial'!G11 -> 1459.2 | H15: =IF('[1]🧾 Tributos Aduana'!C5=0,0,'[1]🧾 Factura Comercial'!G11/'[1]🧾 Tributos Aduana'!C5) -> 0.10266108 | I15: ='[1]🧾 Factura Comercial'!F11*'[1]📋 Datos Generales'!C19 -> 2.8272 | J15: ='[1]🧾 Factura Comercial'!G11*'[1]📋 Datos Generales'!C19 -> 5428.224
B16: =9 -> 9 | C16: ='[1]🧾 Factura Comercial'!C12 -> Pull Line Function Car OPP Bag | D16: ='[1]🧾 Factura Comercial'!D12 -> Unid. | E16: ='[1]🧾 Factura Comercial'!E12 -> 4800 | F16: ='[1]🧾 Factura Comercial'!F12 -> 0.28 | G16: ='[1]🧾 Factura Comercial'!G12 -> 1344 | H16: =IF('[1]🧾 Tributos Aduana'!C5=0,0,'[1]🧾 Factura Comercial'!G12/'[1]🧾 Tributos Aduana'!C5) -> 0.094556261 | I16: ='[1]🧾 Factura Comercial'!F12*'[1]📋 Datos Generales'!C19 -> 1.0416 | J16: ='[1]🧾 Factura Comercial'!G12*'[1]📋 Datos Generales'!C19 -> 4999.68
C17: ✦ TOTALES | E17: =SUM('[1]🧾 Factura Comercial'!E4:E12) -> 34224 | G17: ='[1]🧾 Tributos Aduana'!C5 -> 14213.76 | H17: =1 -> 1 | J17: ='[1]🧾 Tributos Aduana'!C5*'[1]📋 Datos Generales'!C19 -> 52875.187
B19: ⚖️ SECCIÓN 2: TRIBUTOS ADUANEROS POR PRODUCTO (prorrateo por FOB)
B20: # | C20: PRODUCTO | D20: FACTOR PRORRATEO | E20: ADV UNIT. (US$) ⚠️COSTO | F20: IPM UNIT. (US$) ✅CF | G20: IGV UNIT. (US$) ✅CF | H20: PERCEP. UNIT.(US$) ✅CF | I20: DEUDA ADUANERA UNIT. | J20: ADV UNIT. (S/.) | K20: IPM UNIT. (S/.) | L20: IGV UNIT. (S/.) | M20: PERCEP. UNIT.(S/.) | N20: TOTAL TRIB. UNIT.(US$) | O20: TOTAL TRIB. UNIT.(S/.)
B21: =1 -> 1 | C21: ='[1]🧾 Factura Comercial'!C4 -> Friction Car Platform Cover | D21: ='[1]🧮 Costos x Producto'!F6 -> 580.8 | E21: =IF('[1]🧾 Tributos Aduana'!C5=0,0,'[1]🧾 Tributos Aduana'!C16*('[1]🧾 Factura Comercial'!F4/'[1]🧾 Tributos Aduana'!C5)) -> 0.074998452 | F21: =IF('[1]🧾 Tributos Aduana'!C5=0,0,'[1]🧾 Tributos Aduana'!C17*('[1]🧾 Factura Comercial'!F4/'[1]🧾 Tributos Aduana'!C5)) -> 0.02647505 | G21: =IF('[1]🧾 Tributos Aduana'!C5=0,0,'[1]🧾 Tributos Aduana'!C18*('[1]🧾 Factura Comercial'!F4/'[1]🧾 Tributos Aduana'!C5)) -> 0.21205578 | H21: =IF('[1]🧾 Tributos Aduana'!C5=0,0,'[1]🧾 Tributos Aduana'!C22*('[1]🧾 Factura Comercial'!F4/'[1]🧾 Tributos Aduana'!C5)) -> 0.05473525 | I21: =D21+E21+F21+G21 -> 581.11353 | J21: =D21*'[1]📋 Datos Generales'!C19 -> 2160.576 | K21: =E21*'[1]📋 Datos Generales'!C19 -> 0.27899424 | L21: =F21*'[1]📋 Datos Generales'!C19 -> 0.098487184 | M21: =G21*'[1]📋 Datos Generales'!C19 -> 0.78884751 | N21: =D21+E21+F21+G21 -> 581.11353 | O21: =N21*'[1]📋 Datos Generales'!C19 -> 2161.7423
B22: =2 -> 2 | C22: ='[1]🧾 Factura Comercial'!C5 -> Friction Cars OPP Bag 23cm | D22: ='[1]🧮 Costos x Producto'!F7 -> 1958.4 | E22: =IF('[1]🧾 Tributos Aduana'!C5=0,0,'[1]🧾 Tributos Aduana'!C16*('[1]🧾 Factura Comercial'!F5/'[1]🧾 Tributos Aduana'!C5)) -> 0.04214789 | F22: =IF('[1]🧾 Tributos Aduana'!C5=0,0,'[1]🧾 Tributos Aduana'!C17*('[1]🧾 Factura Comercial'!F5/'[1]🧾 Tributos Aduana'!C5)) -> 0.01487854 | G22: =IF('[1]🧾 Tributos Aduana'!C5=0,0,'[1]🧾 Tributos Aduana'!C18*('[1]🧾 Factura Comercial'!F5/'[1]🧾 Tributos Aduana'!C5)) -> 0.11917184 | H22: =IF('[1]🧾 Tributos Aduana'!C5=0,0,'[1]🧾 Tributos Aduana'!C22*('[1]🧾 Factura Comercial'!F5/'[1]🧾 Tributos Aduana'!C5)) -> 0.030760306 | I22: =D22+E22+F22+G22 -> 1958.5762 | J22: =D22*'[1]📋 Datos Generales'!C19 -> 7285.248 | K22: =E22*'[1]📋 Datos Generales'!C19 -> 0.15679015 | L22: =F22*'[1]📋 Datos Generales'!C19 -> 0.05534817 | M22: =G22*'[1]📋 Datos Generales'!C19 -> 0.44331926 | N22: =D22+E22+F22+G22 -> 1958.5762 | O22: =N22*'[1]📋 Datos Generales'!C19 -> 7285.9035
B23: =3 -> 3 | C23: ='[1]🧾 Factura Comercial'!C6 -> Free Wheel Motor OPP Bag 21cm | D23: ='[1]🧮 Costos x Producto'!F8 -> 1152 | E23: =IF('[1]🧾 Tributos Aduana'!C5=0,0,'[1]🧾 Tributos Aduana'!C16*('[1]🧾 Factura Comercial'!F6/'[1]🧾 Tributos Aduana'!C5)) -> 0.024792877 | F23: =IF('[1]🧾 Tributos Aduana'!C5=0,0,'[1]🧾 Tributos Aduana'!C17*('[1]🧾 Factura Comercial'!F6/'[1]🧾 Tributos Aduana'!C5)) -> 0.0087520825 | G23: =IF('[1]🧾 Tributos Aduana'!C5=0,0,'[1]🧾 Tributos Aduana'!C18*('[1]🧾 Factura Comercial'!F6/'[1]🧾 Tributos Aduana'!C5)) -> 0.070101085 | H23: =IF('[1]🧾 Tributos Aduana'!C5=0,0,'[1]🧾 Tributos Aduana'!C22*('[1]🧾 Factura Comercial'!F6/'[1]🧾 Tributos Aduana'!C5)) -> 0.018094297 | I23: =D23+E23+F23+G23 -> 1152.1036 | J23: =D23*'[1]📋 Datos Generales'!C19 -> 4285.44 | K23: =E23*'[1]📋 Datos Generales'!C19 -> 0.092229502 | L23: =F23*'[1]📋 Datos Generales'!C19 -> 0.032557747 | M23: =G23*'[1]📋 Datos Generales'!C19 -> 0.26077604 | N23: =D23+E23+F23+G23 -> 1152.1036 | O23: =N23*'[1]📋 Datos Generales'!C19 -> 4285.8256
B24: =4 -> 4 | C24: ='[1]🧾 Factura Comercial'!C7 -> Friction Cars OPP Bag 22cm | D24: ='[1]🧮 Costos x Producto'!F9 -> 3476.16 | E24: =IF('[1]🧾 Tributos Aduana'!C5=0,0,'[1]🧾 Tributos Aduana'!C16*('[1]🧾 Factura Comercial'!F7/'[1]🧾 Tributos Aduana'!C5)) -> 0.021073945 | F24: =IF('[1]🧾 Tributos Aduana'!C5=0,0,'[1]🧾 Tributos Aduana'!C17*('[1]🧾 Factura Comercial'!F7/'[1]🧾 Tributos Aduana'!C5)) -> 0.0074392701 | G24: =IF('[1]🧾 Tributos Aduana'!C5=0,0,'[1]🧾 Tributos Aduana'!C18*('[1]🧾 Factura Comercial'!F7/'[1]🧾 Tributos Aduana'!C5)) -> 0.059585922 | H24: =IF('[1]🧾 Tributos Aduana'!C5=0,0,'[1]🧾 Tributos Aduana'!C22*('[1]🧾 Factura Comercial'!F7/'[1]🧾 Tributos Aduana'!C5)) -> 0.015380153 | I24: =D24+E24+F24+G24 -> 3476.2481 | J24: =D24*'[1]📋 Datos Generales'!C19 -> 12931.315 | K24: =E24*'[1]📋 Datos Generales'!C19 -> 0.078395076 | L24: =F24*'[1]📋 Datos Generales'!C19 -> 0.027674085 | M24: =G24*'[1]📋 Datos Generales'!C19 -> 0.22165963 | N24: =D24+E24+F24+G24 -> 3476.2481 | O24: =N24*'[1]📋 Datos Generales'!C19 -> 12931.643
B25: =5 -> 5 | C25: ='[1]🧾 Factura Comercial'!C8 -> Pull Line Friction Car OPP Bag | D25: ='[1]🧮 Costos x Producto'!F10 -> 2246.4 | E25: =IF('[1]🧾 Tributos Aduana'!C5=0,0,'[1]🧾 Tributos Aduana'!C16*('[1]🧾 Factura Comercial'!F8/'[1]🧾 Tributos Aduana'!C5)) -> 0.01611537 | F25: =IF('[1]🧾 Tributos Aduana'!C5=0,0,'[1]🧾 Tributos Aduana'!C17*('[1]🧾 Factura Comercial'!F8/'[1]🧾 Tributos Aduana'!C5)) -> 0.0056888536 | G25: =IF('[1]🧾 Tributos Aduana'!C5=0,0,'[1]🧾 Tributos Aduana'!C18*('[1]🧾 Factura Comercial'!F8/'[1]🧾 Tributos Aduana'!C5)) -> 0.045565705 | H25: =IF('[1]🧾 Tributos Aduana'!C5=0,0,'[1]🧾 Tributos Aduana'!C22*('[1]🧾 Factura Comercial'!F8/'[1]🧾 Tributos Aduana'!C5)) -> 0.011761293 | I25: =D25+E25+F25+G25 -> 2246.4674 | J25: =D25*'[1]📋 Datos Generales'!C19 -> 8356.608 | K25: =E25*'[1]📋 Datos Generales'!C19 -> 0.059949176 | L25: =F25*'[1]📋 Datos Generales'!C19 -> 0.021162535 | M25: =G25*'[1]📋 Datos Generales'!C19 -> 0.16950442 | N25: =D25+E25+F25+G25 -> 2246.4674 | O25: =N25*'[1]📋 Datos Generales'!C19 -> 8356.8586
B26: =6 -> 6 | C26: ='[1]🧾 Factura Comercial'!C9 -> Friction Car OPP Bag | D26: ='[1]🧮 Costos x Producto'!F11 -> 626.4 | E26: =IF('[1]🧾 Tributos Aduana'!C5=0,0,'[1]🧾 Tributos Aduana'!C16*('[1]🧾 Factura Comercial'!F9/'[1]🧾 Tributos Aduana'!C5)) -> 0.017974836 | F26: =IF('[1]🧾 Tributos Aduana'!C5=0,0,'[1]🧾 Tributos Aduana'!C17*('[1]🧾 Factura Comercial'!F9/'[1]🧾 Tributos Aduana'!C5)) -> 0.0063452598 | G26: =IF('[1]🧾 Tributos Aduana'!C5=0,0,'[1]🧾 Tributos Aduana'!C18*('[1]🧾 Factura Comercial'!F9/'[1]🧾 Tributos Aduana'!C5)) -> 0.050823287 | H26: =IF('[1]🧾 Tributos Aduana'!C5=0,0,'[1]🧾 Tributos Aduana'!C22*('[1]🧾 Factura Comercial'!F9/'[1]🧾 Tributos Aduana'!C5)) -> 0.013118366 | I26: =D26+E26+F26+G26 -> 626.47514 | J26: =D26*'[1]📋 Datos Generales'!C19 -> 2330.208 | K26: =E26*'[1]📋 Datos Generales'!C19 -> 0.066866389 | L26: =F26*'[1]📋 Datos Generales'!C19 -> 0.023604366 | M26: =G26*'[1]📋 Datos Generales'!C19 -> 0.18906263 | N26: =D26+E26+F26+G26 -> 626.47514 | O26: =N26*'[1]📋 Datos Generales'!C19 -> 2330.4875
B27: =7 -> 7 | C27: ='[1]🧾 Factura Comercial'!C10 -> Free Wheel Ride on Digger Handle | D27: ='[1]🧮 Costos x Producto'!F12 -> 1370.4 | E27: =IF('[1]🧾 Tributos Aduana'!C5=0,0,'[1]🧾 Tributos Aduana'!C16*('[1]🧾 Factura Comercial'!F10/'[1]🧾 Tributos Aduana'!C5)) -> 0.35391832 | F27: =IF('[1]🧾 Tributos Aduana'!C5=0,0,'[1]🧾 Tributos Aduana'!C17*('[1]🧾 Factura Comercial'!F10/'[1]🧾 Tributos Aduana'!C5)) -> 0.12493598 | G27: =IF('[1]🧾 Tributos Aduana'!C5=0,0,'[1]🧾 Tributos Aduana'!C18*('[1]🧾 Factura Comercial'!F10/'[1]🧾 Tributos Aduana'!C5)) -> 1.000693 | H27: =IF('[1]🧾 Tributos Aduana'!C5=0,0,'[1]🧾 Tributos Aduana'!C22*('[1]🧾 Factura Comercial'!F10/'[1]🧾 Tributos Aduana'!C5)) -> 0.25829609 | I27: =D27+E27+F27+G27 -> 1371.8795 | J27: =D27*'[1]📋 Datos Generales'!C19 -> 5097.888 | K27: =E27*'[1]📋 Datos Generales'!C19 -> 1.3165761 | L27: =F27*'[1]📋 Datos Generales'!C19 -> 0.46476184 | M27: =G27*'[1]📋 Datos Generales'!C19 -> 3.7225779 | N27: =D27+E27+F27+G27 -> 1371.8795 | O27: =N27*'[1]📋 Datos Generales'!C19 -> 5103.3919
B28: =8 -> 8 | C28: ='[1]🧾 Factura Comercial'!C11 -> Friction Car with Music and Light | D28: ='[1]🧮 Costos x Producto'!F13 -> 1459.2 | E28: =IF('[1]🧾 Tributos Aduana'!C5=0,0,'[1]🧾 Tributos Aduana'!C16*('[1]🧾 Factura Comercial'!F11/'[1]🧾 Tributos Aduana'!C5)) -> 0.047106466 | F28: =IF('[1]🧾 Tributos Aduana'!C5=0,0,'[1]🧾 Tributos Aduana'!C17*('[1]🧾 Factura Comercial'!F11/'[1]🧾 Tributos Aduana'!C5)) -> 0.016628957 | G28: =IF('[1]🧾 Tributos Aduana'!C5=0,0,'[1]🧾 Tributos Aduana'!C18*('[1]🧾 Factura Comercial'!F11/'[1]🧾 Tributos Aduana'!C5)) -> 0.13319206 | H28: =IF('[1]🧾 Tributos Aduana'!C5=0,0,'[1]🧾 Tributos Aduana'!C22*('[1]🧾 Factura Comercial'!F11/'[1]🧾 Tributos Aduana'!C5)) -> 0.034379165 | I28: =D28+E28+F28+G28 -> 1459.3969 | J28: =D28*'[1]📋 Datos Generales'!C19 -> 5428.224 | K28: =E28*'[1]📋 Datos Generales'!C19 -> 0.17523605 | L28: =F28*'[1]📋 Datos Generales'!C19 -> 0.061859719 | M28: =G28*'[1]📋 Datos Generales'!C19 -> 0.49547447 | N28: =D28+E28+F28+G28 -> 1459.3969 | O28: =N28*'[1]📋 Datos Generales'!C19 -> 5428.9566
B29: =9 -> 9 | C29: ='[1]🧾 Factura Comercial'!C12 -> Pull Line Function Car OPP Bag | D29: ='[1]🧮 Costos x Producto'!F14 -> 1344 | E29: =IF('[1]🧾 Tributos Aduana'!C5=0,0,'[1]🧾 Tributos Aduana'!C16*('[1]🧾 Factura Comercial'!F12/'[1]🧾 Tributos Aduana'!C5)) -> 0.017355014 | F29: =IF('[1]🧾 Tributos Aduana'!C5=0,0,'[1]🧾 Tributos Aduana'!C17*('[1]🧾 Factura Comercial'!F12/'[1]🧾 Tributos Aduana'!C5)) -> 0.0061264577 | G29: =IF('[1]🧾 Tributos Aduana'!C5=0,0,'[1]🧾 Tributos Aduana'!C18*('[1]🧾 Factura Comercial'!F12/'[1]🧾 Tributos Aduana'!C5)) -> 0.04907076 | H29: =IF('[1]🧾 Tributos Aduana'!C5=0,0,'[1]🧾 Tributos Aduana'!C22*('[1]🧾 Factura Comercial'!F12/'[1]🧾 Tributos Aduana'!C5)) -> 0.012666008 | I29: =D29+E29+F29+G29 -> 1344.0726 | J29: =D29*'[1]📋 Datos Generales'!C19 -> 4999.68 | K29: =E29*'[1]📋 Datos Generales'!C19 -> 0.064560651 | L29: =F29*'[1]📋 Datos Generales'!C19 -> 0.022790423 | M29: =G29*'[1]📋 Datos Generales'!C19 -> 0.18254323 | N29: =D29+E29+F29+G29 -> 1344.0726 | O29: =N29*'[1]📋 Datos Generales'!C19 -> 4999.9499
C30: ✦ TOTALES | E30: ='[1]🧾 Tributos Aduana'!C16 -> 881 | F30: ='[1]🧾 Tributos Aduana'!C17 -> 311 | G30: ='[1]🧾 Tributos Aduana'!C18 -> 2491 | H30: ='[1]🧾 Tributos Aduana'!C22 -> 642.97 | I30: ='[1]🧾 Tributos Aduana'!C19+'[1]🧾 Tributos Aduana'!C22 -> 4325.97 | N30: ='[1]🧾 Tributos Aduana'!C19 -> 3683 | O30: ='[1]🧾 Tributos Aduana'!C19*'[1]📋 Datos Generales'!C19 -> 13700.76
B32: 🧮 SECCIÓN 3: COSTO DE IMPORTACIÓN · CRÉDITO FISCAL · PRECIO DE VENTA · MARGEN
B33: # | C33: PRODUCTO | D33: GASTOS IMP. UNIT.(US$) | E33: GASTOS IMP. UNIT.(S/.) | F33: C/M UNIT. (US$) | G33: C/M UNIT. (S/.) | H33: ADV UNIT. ⚠️COSTO(US$) | I33: CF UNIT. ✅RECUP.(US$) | J33: CF UNIT. ✅RECUP.(S/.) | K33: MARGEN % | L33: VALOR VTA. UNIT.(S/.) | M33: PRECIO VTA. c/IGV(S/.) | N33: GANANCIA UNIT.(S/.) | O33: PUNTO EQUILIBRIO | P33: GANANCIA TOTAL(S/.) | Q33: % UTILIDAD S/PRECIO | R33: ROI UNIT. | S33: CLASIF. MARGEN
B34: =1 -> 1 | C34: ='[1]🧾 Factura Comercial'!C4 -> Friction Car Platform Cover | D34: =IF('[1]🧾 Factura Comercial'!E4=0,0,'[1]📦 Gastos Importación'!C27*(IF('[1]🧾 Tributos Aduana'!C5=0,0,'[1]🧾 Factura Comercial'!F4/'[1]🧾 Tributos Aduana'!C5))/'[1]🧾 Factura Comercial'!E4) -> 0.0028601925 | E34: =D34*'[1]📋 Datos Generales'!C19 -> 0.010639916 | F34: ='[1]🧮 Costos x Producto'!H6 -> 2.6982247 | G34: ='[1]🧮 Costos x Producto'!I6 -> 10.037396 | H34: =IF('[1]🧾 Factura Comercial'!E4=0,0,'[1]🧾 Tributos Aduana'!C16*(IF('[1]🧾 Tributos Aduana'!C5=0,0,'[1]🧾 Factura Comercial'!F4/'[1]🧾 Tributos Aduana'!C5))/'[1]🧾 Factura Comercial'!E4) -> 0.00015624678 | I34: =IF('[1]🧾 Factura Comercial'!E4=0,0,'[1]🏦 Crédito Fiscal'!C10*(IF('[1]🧾 Tributos Aduana'!C5=0,0,'[1]🧾 Factura Comercial'!F4/'[1]🧾 Tributos Aduana'!C5))/'[1]🧾 Factura Comercial'!E4) -> 0.0011246039 | J34: =I34*'[1]📋 Datos Generales'!C19 -> 0.0041835264 | K34: ='[1]💰 Precio de Venta'!E5 -> 0.4 | L34: ='[1]💰 Precio de Venta'!F5 -> 16.728993 | M34: ='[1]💰 Precio de Venta'!G5 -> 19.740212 | N34: ='[1]💰 Precio de Venta'!H5 -> 6.6915973 | O34: ='[1]💰 Precio de Venta'!I5 -> 66 | P34: =N34*'[1]🧾 Factura Comercial'!E4 -> 3211.9667 | Q34: =IF(M34=0,0,N34/M34) -> 0.33898305 | R34: =IF(G34=0,0,N34/G34) -> 0.66666667 | S34: =IF(K34>=0.5,"🟢 ALTO",IF(K34>=0.3,"🟡 MEDIO","🔴 BAJO")) -> 🟡 MEDIO
B35: =2 -> 2 | C35: ='[1]🧾 Factura Comercial'!C5 -> Friction Cars OPP Bag 23cm | D35: =IF('[1]🧾 Factura Comercial'!E5=0,0,'[1]📦 Gastos Importación'!C27*(IF('[1]🧾 Tributos Aduana'!C5=0,0,'[1]🧾 Factura Comercial'!F5/'[1]🧾 Tributos Aduana'!C5))/'[1]🧾 Factura Comercial'!E5) -> 0.00026789682 | E35: =D35*'[1]📋 Datos Generales'!C19 -> 0.00099657616 | F35: ='[1]🧮 Costos x Producto'!H7 -> 1.5163577 | G35: ='[1]🧮 Costos x Producto'!I7 -> 5.6408506 | H35: =IF('[1]🧾 Factura Comercial'!E5=0,0,'[1]🧾 Tributos Aduana'!C16*(IF('[1]🧾 Tributos Aduana'!C5=0,0,'[1]🧾 Factura Comercial'!F5/'[1]🧾 Tributos Aduana'!C5))/'[1]🧾 Factura Comercial'!E5) -> 1.4634684e-05 | I35: =IF('[1]🧾 Factura Comercial'!E5=0,0,'[1]🏦 Crédito Fiscal'!C10*(IF('[1]🧾 Tributos Aduana'!C5=0,0,'[1]🧾 Factura Comercial'!F5/'[1]🧾 Tributos Aduana'!C5))/'[1]🧾 Factura Comercial'!E5) -> 0.0001053348 | J35: =I35*'[1]📋 Datos Generales'!C19 -> 0.00039184545 | K35: ='[1]💰 Precio de Venta'!E6 -> 0.4 | L35: ='[1]💰 Precio de Venta'!F6 -> 9.4014176 | M35: ='[1]💰 Precio de Venta'!G6 -> 11.093673 | N35: ='[1]💰 Precio de Venta'!H6 -> 3.7605671 | O35: ='[1]💰 Precio de Venta'!I6 -> 394 | P35: =N35*'[1]🧾 Factura Comercial'!E5 -> 10830.433 | Q35: =IF(M35=0,0,N35/M35) -> 0.33898305 | R35: =IF(G35=0,0,N35/G35) -> 0.66666667 | S35: =IF(K35>=0.5,"🟢 ALTO",IF(K35>=0.3,"🟡 MEDIO","🔴 BAJO")) -> 🟡 MEDIO
B36: =3 -> 3 | C36: ='[1]🧾 Factura Comercial'!C6 -> Free Wheel Motor OPP Bag 21cm | D36: =IF('[1]🧾 Factura Comercial'!E6=0,0,'[1]📦 Gastos Importación'!C27*(IF('[1]🧾 Tributos Aduana'!C5=0,0,'[1]🧾 Factura Comercial'!F6/'[1]🧾 Tributos Aduana'!C5))/'[1]🧾 Factura Comercial'!E6) -> 0.00015758636 | E36: =D36*'[1]📋 Datos Generales'!C19 -> 0.00058622127 | F36: ='[1]🧮 Costos x Producto'!H8 -> 0.89197511 | G36: ='[1]🧮 Costos x Producto'!I8 -> 3.3181474 | H36: =IF('[1]🧾 Factura Comercial'!E6=0,0,'[1]🧾 Tributos Aduana'!C16*(IF('[1]🧾 Tributos Aduana'!C5=0,0,'[1]🧾 Factura Comercial'!F6/'[1]🧾 Tributos Aduana'!C5))/'[1]🧾 Factura Comercial'!E6) -> 8.6086378e-06 | I36: =IF('[1]🧾 Factura Comercial'!E6=0,0,'[1]🏦 Crédito Fiscal'!C10*(IF('[1]🧾 Tributos Aduana'!C5=0,0,'[1]🧾 Factura Comercial'!F6/'[1]🧾 Tributos Aduana'!C5))/'[1]🧾 Factura Comercial'!E6) -> 6.1961645e-05 | J36: =I36*'[1]📋 Datos Generales'!C19 -> 0.00023049732 | K36: ='[1]💰 Precio de Venta'!E7 -> 0.4 | L36: ='[1]💰 Precio de Venta'!F7 -> 5.5302457 | M36: ='[1]💰 Precio de Venta'!G7 -> 6.5256899 | N36: ='[1]💰 Precio de Venta'!H7 -> 2.2120983 | O36: ='[1]💰 Precio de Venta'!I7 -> 394 | P36: =N36*'[1]🧾 Factura Comercial'!E6 -> 6370.843 | Q36: =IF(M36=0,0,N36/M36) -> 0.33898305 | R36: =IF(G36=0,0,N36/G36) -> 0.66666667 | S36: =IF(K36>=0.5,"🟢 ALTO",IF(K36>=0.3,"🟡 MEDIO","🔴 BAJO")) -> 🟡 MEDIO
B37: =4 -> 4 | C37: ='[1]🧾 Factura Comercial'!C7 -> Friction Cars OPP Bag 22cm | D37: =IF('[1]🧾 Factura Comercial'!E7=0,0,'[1]📦 Gastos Importación'!C27*(IF('[1]🧾 Tributos Aduana'!C5=0,0,'[1]🧾 Factura Comercial'!F7/'[1]🧾 Tributos Aduana'!C5))/'[1]🧾 Factura Comercial'!E7) -> 3.7731946e-05 | E37: =D37*'[1]📋 Datos Generales'!C19 -> 0.00014036284 | F37: ='[1]🧮 Costos x Producto'!H9 -> 0.75817884 | G37: ='[1]🧮 Costos x Producto'!I9 -> 2.8204253 | H37: =IF('[1]🧾 Factura Comercial'!E7=0,0,'[1]🧾 Tributos Aduana'!C16*(IF('[1]🧾 Tributos Aduana'!C5=0,0,'[1]🧾 Factura Comercial'!F7/'[1]🧾 Tributos Aduana'!C5))/'[1]🧾 Factura Comercial'!E7) -> 2.0612231e-06 | I37: =IF('[1]🧾 Factura Comercial'!E7=0,0,'[1]🏦 Crédito Fiscal'!C10*(IF('[1]🧾 Tributos Aduana'!C5=0,0,'[1]🧾 Factura Comercial'!F7/'[1]🧾 Tributos Aduana'!C5))/'[1]🧾 Factura Comercial'!E7) -> 1.4835887e-05 | J37: =I37*'[1]📋 Datos Generales'!C19 -> 5.5189499e-05 | K37: ='[1]💰 Precio de Venta'!E8 -> 0.4 | L37: ='[1]💰 Precio de Venta'!F8 -> 4.7007088 | M37: ='[1]💰 Precio de Venta'!G8 -> 5.5468364 | N37: ='[1]💰 Precio de Venta'!H8 -> 1.8802835 | O37: ='[1]💰 Precio de Venta'!I8 -> 1398 | P37: =N37*'[1]🧾 Factura Comercial'!E7 -> 19224.019 | Q37: =IF(M37=0,0,N37/M37) -> 0.33898305 | R37: =IF(G37=0,0,N37/G37) -> 0.66666667 | S37: =IF(K37>=0.5,"🟢 ALTO",IF(K37>=0.3,"🟡 MEDIO","🔴 BAJO")) -> 🟡 MEDIO
B38: =5 -> 5 | C38: ='[1]🧾 Factura Comercial'!C8 -> Pull Line Friction Car OPP Bag | D38: =IF('[1]🧾 Factura Comercial'!E8=0,0,'[1]📦 Gastos Importación'!C27*(IF('[1]🧾 Tributos Aduana'!C5=0,0,'[1]🧾 Factura Comercial'!F8/'[1]🧾 Tributos Aduana'!C5))/'[1]🧾 Factura Comercial'!E8) -> 3.4143712e-05 | E38: =D38*'[1]📋 Datos Generales'!C19 -> 0.00012701461 | F38: ='[1]🧮 Costos x Producto'!H10 -> 0.57978382 | G38: ='[1]🧮 Costos x Producto'!I10 -> 2.1567958 | H38: =IF('[1]🧾 Factura Comercial'!E8=0,0,'[1]🧾 Tributos Aduana'!C16*(IF('[1]🧾 Tributos Aduana'!C5=0,0,'[1]🧾 Factura Comercial'!F8/'[1]🧾 Tributos Aduana'!C5))/'[1]🧾 Factura Comercial'!E8) -> 1.8652048e-06 | I38: =IF('[1]🧾 Factura Comercial'!E8=0,0,'[1]🏦 Crédito Fiscal'!C10*(IF('[1]🧾 Tributos Aduana'!C5=0,0,'[1]🧾 Factura Comercial'!F8/'[1]🧾 Tributos Aduana'!C5))/'[1]🧾 Factura Comercial'!E8) -> 1.3425023e-05 | J38: =I38*'[1]📋 Datos Generales'!C19 -> 4.9941086e-05 | K38: ='[1]💰 Precio de Venta'!E9 -> 0.4 | L38: ='[1]💰 Precio de Venta'!F9 -> 3.5946597 | M38: ='[1]💰 Precio de Venta'!G9 -> 4.2416984 | N38: ='[1]💰 Precio de Venta'!H9 -> 1.4378639 | O38: ='[1]💰 Precio de Venta'!I9 -> 1181 | P38: =N38*'[1]🧾 Factura Comercial'!E8 -> 12423.144 | Q38: =IF(M38=0,0,N38/M38) -> 0.33898305 | R38: =IF(G38=0,0,N38/G38) -> 0.66666667 | S38: =IF(K38>=0.5,"🟢 ALTO",IF(K38>=0.3,"🟡 MEDIO","🔴 BAJO")) -> 🟡 MEDIO
B39: =6 -> 6 | C39: ='[1]🧾 Factura Comercial'!C9 -> Friction Car OPP Bag | D39: =IF('[1]🧾 Factura Comercial'!E9=0,0,'[1]📦 Gastos Importación'!C27*(IF('[1]🧾 Tributos Aduana'!C5=0,0,'[1]🧾 Factura Comercial'!F9/'[1]🧾 Tributos Aduana'!C5))/'[1]🧾 Factura Comercial'!E9) -> 0.00015233348 | E39: =D39*'[1]📋 Datos Generales'!C19 -> 0.00056668056 | F39: ='[1]🧮 Costos x Producto'!H11 -> 0.64668195 | G39: ='[1]🧮 Costos x Producto'!I11 -> 2.4056569 | H39: =IF('[1]🧾 Factura Comercial'!E9=0,0,'[1]🧾 Tributos Aduana'!C16*(IF('[1]🧾 Tributos Aduana'!C5=0,0,'[1]🧾 Factura Comercial'!F9/'[1]🧾 Tributos Aduana'!C5))/'[1]🧾 Factura Comercial'!E9) -> 8.3216832e-06 | I39: =IF('[1]🧾 Factura Comercial'!E9=0,0,'[1]🏦 Crédito Fiscal'!C10*(IF('[1]🧾 Tributos Aduana'!C5=0,0,'[1]🧾 Factura Comercial'!F9/'[1]🧾 Tributos Aduana'!C5))/'[1]🧾 Factura Comercial'!E9) -> 5.9896257e-05 | J39: =I39*'[1]📋 Datos Generales'!C19 -> 0.00022281408 | K39: ='[1]💰 Precio de Venta'!E10 -> 0.4 | L39: ='[1]💰 Precio de Venta'!F10 -> 4.0094281 | M39: ='[1]💰 Precio de Venta'!G10 -> 4.7311252 | N39: ='[1]💰 Precio de Venta'!H10 -> 1.6037712 | O39: ='[1]💰 Precio de Venta'!I10 -> 296 | P39: =N39*'[1]🧾 Factura Comercial'!E9 -> 3464.1459 | Q39: =IF(M39=0,0,N39/M39) -> 0.33898305 | R39: =IF(G39=0,0,N39/G39) -> 0.66666667 | S39: =IF(K39>=0.5,"🟢 ALTO",IF(K39>=0.3,"🟡 MEDIO","🔴 BAJO")) -> 🟡 MEDIO
B40: =7 -> 7 | C40: ='[1]🧾 Factura Comercial'!C10 -> Free Wheel Ride on Digger Handle | D40: =IF('[1]🧾 Factura Comercial'!E10=0,0,'[1]📦 Gastos Importación'!C27*(IF('[1]🧾 Tributos Aduana'!C5=0,0,'[1]🧾 Factura Comercial'!F10/'[1]🧾 Tributos Aduana'!C5))/'[1]🧾 Factura Comercial'!E10) -> 0.026994544 | E40: =D40*'[1]📋 Datos Generales'!C19 -> 0.1004197 | F40: ='[1]🧮 Costos x Producto'!H12 -> 12.732945 | G40: ='[1]🧮 Costos x Producto'!I12 -> 47.366554 | H40: =IF('[1]🧾 Factura Comercial'!E10=0,0,'[1]🧾 Tributos Aduana'!C16*(IF('[1]🧾 Tributos Aduana'!C5=0,0,'[1]🧾 Factura Comercial'!F10/'[1]🧾 Tributos Aduana'!C5))/'[1]🧾 Factura Comercial'!E10) -> 0.0014746596 | I40: =IF('[1]🧾 Factura Comercial'!E10=0,0,'[1]🏦 Crédito Fiscal'!C10*(IF('[1]🧾 Tributos Aduana'!C5=0,0,'[1]🧾 Factura Comercial'!F10/'[1]🧾 Tributos Aduana'!C5))/'[1]🧾 Factura Comercial'!E10) -> 0.01061403 | J40: =I40*'[1]📋 Datos Generales'!C19 -> 0.039484191 | K40: ='[1]💰 Precio de Venta'!E11 -> 0.4 | L40: ='[1]💰 Precio de Venta'!F11 -> 78.944257 | M40: ='[1]💰 Precio de Venta'!G11 -> 93.154223 | N40: ='[1]💰 Precio de Venta'!H11 -> 31.577703 | O40: ='[1]💰 Precio de Venta'!I11 -> 33 | P40: =N40*'[1]🧾 Factura Comercial'!E10 -> 7578.6487 | Q40: =IF(M40=0,0,N40/M40) -> 0.33898305 | R40: =IF(G40=0,0,N40/G40) -> 0.66666667 | S40: =IF(K40>=0.5,"🟢 ALTO",IF(K40>=0.3,"🟡 MEDIO","🔴 BAJO")) -> 🟡 MEDIO
B41: =8 -> 8 | C41: ='[1]🧾 Factura Comercial'!C11 -> Friction Car with Music and Light | D41: =IF('[1]🧾 Factura Comercial'!E11=0,0,'[1]📦 Gastos Importación'!C27*(IF('[1]🧾 Tributos Aduana'!C5=0,0,'[1]🧾 Factura Comercial'!F11/'[1]🧾 Tributos Aduana'!C5))/'[1]🧾 Factura Comercial'!E11) -> 0.00044912113 | E41: =D41*'[1]📋 Datos Generales'!C19 -> 0.0016707306 | F41: ='[1]🧮 Costos x Producto'!H13 -> 1.6947527 | G41: ='[1]🧮 Costos x Producto'!I13 -> 6.3044801 | H41: =IF('[1]🧾 Factura Comercial'!E11=0,0,'[1]🧾 Tributos Aduana'!C16*(IF('[1]🧾 Tributos Aduana'!C5=0,0,'[1]🧾 Factura Comercial'!F11/'[1]🧾 Tributos Aduana'!C5))/'[1]🧾 Factura Comercial'!E11) -> 2.4534618e-05 | I41: =IF('[1]🧾 Factura Comercial'!E11=0,0,'[1]🏦 Crédito Fiscal'!C10*(IF('[1]🧾 Tributos Aduana'!C5=0,0,'[1]🧾 Factura Comercial'!F11/'[1]🧾 Tributos Aduana'!C5))/'[1]🧾 Factura Comercial'!E11) -> 0.00017659069 | J41: =I41*'[1]📋 Datos Generales'!C19 -> 0.00065691736 | K41: ='[1]💰 Precio de Venta'!E12 -> 0.4 | L41: ='[1]💰 Precio de Venta'!F12 -> 10.507467 | M41: ='[1]💰 Precio de Venta'!G12 -> 12.398811 | N41: ='[1]💰 Precio de Venta'!H12 -> 4.2029867 | O41: ='[1]💰 Precio de Venta'!I12 -> 263 | P41: =N41*'[1]🧾 Factura Comercial'!E11 -> 8069.7345 | Q41: =IF(M41=0,0,N41/M41) -> 0.33898305 | R41: =IF(G41=0,0,N41/G41) -> 0.66666667 | S41: =IF(K41>=0.5,"🟢 ALTO",IF(K41>=0.3,"🟡 MEDIO","🔴 BAJO")) -> 🟡 MEDIO
B42: =9 -> 9 | C42: ='[1]🧾 Factura Comercial'!C12 -> Pull Line Function Car OPP Bag | D42: =IF('[1]🧾 Factura Comercial'!E12=0,0,'[1]📦 Gastos Importación'!C27*(IF('[1]🧾 Tributos Aduana'!C5=0,0,'[1]🧾 Factura Comercial'!F12/'[1]🧾 Tributos Aduana'!C5))/'[1]🧾 Factura Comercial'!E12) -> 6.6186272e-05 | E42: =D42*'[1]📋 Datos Generales'!C19 -> 0.00024621293 | F42: ='[1]🧮 Costos x Producto'!H14 -> 0.62438258 | G42: ='[1]🧮 Costos x Producto'!I14 -> 2.3227032 | H42: =IF('[1]🧾 Factura Comercial'!E12=0,0,'[1]🧾 Tributos Aduana'!C16*(IF('[1]🧾 Tributos Aduana'!C5=0,0,'[1]🧾 Factura Comercial'!F12/'[1]🧾 Tributos Aduana'!C5))/'[1]🧾 Factura Comercial'!E12) -> 3.6156279e-06 | I42: =IF('[1]🧾 Factura Comercial'!E12=0,0,'[1]🏦 Crédito Fiscal'!C10*(IF('[1]🧾 Tributos Aduana'!C5=0,0,'[1]🧾 Factura Comercial'!F12/'[1]🧾 Tributos Aduana'!C5))/'[1]🧾 Factura Comercial'!E12) -> 2.6023891e-05 | J42: =I42*'[1]📋 Datos Generales'!C19 -> 9.6808875e-05 | K42: ='[1]💰 Precio de Venta'!E13 -> 0.4 | L42: ='[1]💰 Precio de Venta'!F13 -> 3.871172 | M42: ='[1]💰 Precio de Venta'!G13 -> 4.5679829 | N42: ='[1]💰 Precio de Venta'!H13 -> 1.5484688 | O42: ='[1]💰 Precio de Venta'!I13 -> 657 | P42: =N42*'[1]🧾 Factura Comercial'!E12 -> 7432.6502 | Q42: =IF(M42=0,0,N42/M42) -> 0.33898305 | R42: =IF(G42=0,0,N42/G42) -> 0.66666667 | S42: =IF(K42>=0.5,"🟢 ALTO",IF(K42>=0.3,"🟡 MEDIO","🔴 BAJO")) -> 🟡 MEDIO
C43: ✦ TOTALES Y PROMEDIOS | F43: ='[1]🧮 Costos x Producto'!D3 -> 0 | G43: ='[1]🧮 Costos x Producto'!F3 -> 0 | H43: ='[1]🧾 Tributos Aduana'!C16 -> 881 | I43: ='[1]🏦 Crédito Fiscal'!C10 -> 6341.0973 | J43: ='[1]🏦 Crédito Fiscal'!C11 -> 23588.882 | K43: =AVERAGE('[1]💰 Precio de Venta'!E5:E13) -> 0.4 | N43: =SUM(N34:N42) -> 54.91534 | P43: =SUM(P34:P42) -> 78605.585 | Q43: =AVERAGE(Q34:Q42) -> 0.33898305 | R43: =AVERAGE(R34:R42) -> 0.66666667
B45: 📊 SECCIÓN 4: RESUMEN VISUAL — TOP PRODUCTOS
B46: P1 | D46: P2 | F46: P3 | H46: P4 | J46: P5 | L46: P6 | N46: P7 | P46: P8 | R46: P9
B47: ='[1]🧾 Factura Comercial'!C4 -> Friction Car Platform Cover | D47: ='[1]🧾 Factura Comercial'!C5 -> Friction Cars OPP Bag 23cm | F47: ='[1]🧾 Factura Comercial'!C6 -> Free Wheel Motor OPP Bag 21cm | H47: ='[1]🧾 Factura Comercial'!C7 -> Friction Cars OPP Bag 22cm | J47: ='[1]🧾 Factura Comercial'!C8 -> Pull Line Friction Car OPP Bag | L47: ='[1]🧾 Factura Comercial'!C9 -> Friction Car OPP Bag | N47: ='[1]🧾 Factura Comercial'!C10 -> Free Wheel Ride on Digger Handle | P47: ='[1]🧾 Factura Comercial'!C11 -> Friction Car with Music and Light | R47: ='[1]🧾 Factura Comercial'!C12 -> Pull Line Function Car OPP Bag
B48: C/M | C48: ='[1]🧮 Costos x Producto'!I6 -> 10.037396 | D48: C/M | E48: ='[1]🧮 Costos x Producto'!I7 -> 5.6408506 | F48: C/M | G48: ='[1]🧮 Costos x Producto'!I8 -> 3.3181474 | H48: C/M | I48: ='[1]🧮 Costos x Producto'!I9 -> 2.8204253 | J48: C/M | K48: ='[1]🧮 Costos x Producto'!I10 -> 2.1567958 | L48: C/M | M48: ='[1]🧮 Costos x Producto'!I11 -> 2.4056569 | N48: C/M | O48: ='[1]🧮 Costos x Producto'!I12 -> 47.366554 | P48: C/M | Q48: ='[1]🧮 Costos x Producto'!I13 -> 6.3044801 | R48: C/M | S48: ='[1]🧮 Costos x Producto'!I14 -> 2.3227032
B49: PV | C49: ='[1]💰 Precio de Venta'!G5 -> 19.740212 | D49: PV | E49: ='[1]💰 Precio de Venta'!G6 -> 11.093673 | F49: PV | G49: ='[1]💰 Precio de Venta'!G7 -> 6.5256899 | H49: PV | I49: ='[1]💰 Precio de Venta'!G8 -> 5.5468364 | J49: PV | K49: ='[1]💰 Precio de Venta'!G9 -> 4.2416984 | L49: PV | M49: ='[1]💰 Precio de Venta'!G10 -> 4.7311252 | N49: PV | O49: ='[1]💰 Precio de Venta'!G11 -> 93.154223 | P49: PV | Q49: ='[1]💰 Precio de Venta'!G12 -> 12.398811 | R49: PV | S49: ='[1]💰 Precio de Venta'!G13 -> 4.5679829
B50: GAN. | C50: ='[1]💰 Precio de Venta'!H5 -> 6.6915973 | D50: GAN. | E50: ='[1]💰 Precio de Venta'!H6 -> 3.7605671 | F50: GAN. | G50: ='[1]💰 Precio de Venta'!H7 -> 2.2120983 | H50: GAN. | I50: ='[1]💰 Precio de Venta'!H8 -> 1.8802835 | J50: GAN. | K50: ='[1]💰 Precio de Venta'!H9 -> 1.4378639 | L50: GAN. | M50: ='[1]💰 Precio de Venta'!H10 -> 1.6037712 | N50: GAN. | O50: ='[1]💰 Precio de Venta'!H11 -> 31.577703 | P50: GAN. | Q50: ='[1]💰 Precio de Venta'!H12 -> 4.2029867 | R50: GAN. | S50: ='[1]💰 Precio de Venta'!H13 -> 1.5484688
B51: MARG. | C51: ='[1]💰 Precio de Venta'!E5 -> 0.4 | D51: MARG. | E51: ='[1]💰 Precio de Venta'!E6 -> 0.4 | F51: MARG. | G51: ='[1]💰 Precio de Venta'!E7 -> 0.4 | H51: MARG. | I51: ='[1]💰 Precio de Venta'!E8 -> 0.4 | J51: MARG. | K51: ='[1]💰 Precio de Venta'!E9 -> 0.4 | L51: MARG. | M51: ='[1]💰 Precio de Venta'!E10 -> 0.4 | N51: MARG. | O51: ='[1]💰 Precio de Venta'!E11 -> 0.4 | P51: MARG. | Q51: ='[1]💰 Precio de Venta'!E12 -> 0.4 | R51: MARG. | S51: ='[1]💰 Precio de Venta'!E13 -> 0.4
B52: ROI | C52: =IF('[1]🧮 Costos x Producto'!I6=0,0,'[1]💰 Precio de Venta'!H5/'[1]🧮 Costos x Producto'!I6) -> 0.66666667 | D52: ROI | E52: =IF('[1]🧮 Costos x Producto'!I7=0,0,'[1]💰 Precio de Venta'!H6/'[1]🧮 Costos x Producto'!I7) -> 0.66666667 | F52: ROI | G52: =IF('[1]🧮 Costos x Producto'!I8=0,0,'[1]💰 Precio de Venta'!H7/'[1]🧮 Costos x Producto'!I8) -> 0.66666667 | H52: ROI | I52: =IF('[1]🧮 Costos x Producto'!I9=0,0,'[1]💰 Precio de Venta'!H8/'[1]🧮 Costos x Producto'!I9) -> 0.66666667 | J52: ROI | K52: =IF('[1]🧮 Costos x Producto'!I10=0,0,'[1]💰 Precio de Venta'!H9/'[1]🧮 Costos x Producto'!I10) -> 0.66666667 | L52: ROI | M52: =IF('[1]🧮 Costos x Producto'!I11=0,0,'[1]💰 Precio de Venta'!H10/'[1]🧮 Costos x Producto'!I11) -> 0.66666667 | N52: ROI | O52: =IF('[1]🧮 Costos x Producto'!I12=0,0,'[1]💰 Precio de Venta'!H11/'[1]🧮 Costos x Producto'!I12) -> 0.66666667 | P52: ROI | Q52: =IF('[1]🧮 Costos x Producto'!I13=0,0,'[1]💰 Precio de Venta'!H12/'[1]🧮 Costos x Producto'!I13) -> 0.66666667 | R52: ROI | S52: =IF('[1]🧮 Costos x Producto'!I14=0,0,'[1]💰 Precio de Venta'!H13/'[1]🧮 Costos x Producto'!I14) -> 0.66666667
B72: 🔍 DETALLE POR PRODUCTO — Todos los valores se calculan automáticamente desde las hojas fuente · © 2026
B200: Producto | C200: Ganancia Total S/. | D200: C/M Unit S/. | E200: PV Unit S/.
B201: ='[1]🧾 Factura Comercial'!C4 -> Friction Car Platform Cover | C201: =P34 -> 3211.9667 | D201: ='[1]🧮 Costos x Producto'!I6 -> 10.037396 | E201: ='[1]💰 Precio de Venta'!G5 -> 19.740212
B202: ='[1]🧾 Factura Comercial'!C5 -> Friction Cars OPP Bag 23cm | C202: =P35 -> 10830.433 | D202: ='[1]🧮 Costos x Producto'!I7 -> 5.6408506 | E202: ='[1]💰 Precio de Venta'!G6 -> 11.093673
B203: ='[1]🧾 Factura Comercial'!C6 -> Free Wheel Motor OPP Bag 21cm | C203: =P36 -> 6370.843 | D203: ='[1]🧮 Costos x Producto'!I8 -> 3.3181474 | E203: ='[1]💰 Precio de Venta'!G7 -> 6.5256899
B204: ='[1]🧾 Factura Comercial'!C7 -> Friction Cars OPP Bag 22cm | C204: =P37 -> 19224.019 | D204: ='[1]🧮 Costos x Producto'!I9 -> 2.8204253 | E204: ='[1]💰 Precio de Venta'!G8 -> 5.5468364
B205: ='[1]🧾 Factura Comercial'!C8 -> Pull Line Friction Car OPP Bag | C205: =P38 -> 12423.144 | D205: ='[1]🧮 Costos x Producto'!I10 -> 2.1567958 | E205: ='[1]💰 Precio de Venta'!G9 -> 4.2416984
B206: ='[1]🧾 Factura Comercial'!C9 -> Friction Car OPP Bag | C206: =P39 -> 3464.1459 | D206: ='[1]🧮 Costos x Producto'!I11 -> 2.4056569 | E206: ='[1]💰 Precio de Venta'!G10 -> 4.7311252
B207: ='[1]🧾 Factura Comercial'!C10 -> Free Wheel Ride on Digger Handle | C207: =P40 -> 7578.6487 | D207: ='[1]🧮 Costos x Producto'!I12 -> 47.366554 | E207: ='[1]💰 Precio de Venta'!G11 -> 93.154223
B208: ='[1]🧾 Factura Comercial'!C11 -> Friction Car with Music and Light | C208: =P41 -> 8069.7345 | D208: ='[1]🧮 Costos x Producto'!I13 -> 6.3044801 | E208: ='[1]💰 Precio de Venta'!G12 -> 12.398811
B209: ='[1]🧾 Factura Comercial'!C12 -> Pull Line Function Car OPP Bag | C209: =P42 -> 7432.6502 | D209: ='[1]🧮 Costos x Producto'!I14 -> 2.3227032 | E209: ='[1]💰 Precio de Venta'!G13 -> 4.5679829

Sheet 📊 KPI x Producto
B13: ='📋 Datos Generales'!E6&" | DUA: "&'📋 Datos Generales'!E5&" | País: "&'📋 Datos Generales'!E9&" | Proveedor: "&'📋 Datos Generales'!E10&" | Incoterm: "&'📋 Datos Generales'!E11&" | TC: S/."&TEXT('📋 Datos Generales'!E19,"0.000") -> EMPRESA IMPORTADORA S.A.C. | DUA: DAM-2025-000001 | País: China | Proveedor: HWPI Co. Ltd. | Incoterm: FOB | TC: S/.3.720 | AH13: LISTA DE PRODUCTOS
AH14: Cable USB-C Trenzado 1m
H22: =VLOOKUP($AH$14,TABLA_BASE[],3,FALSE) -> 2880 | K22: =VLOOKUP($AH$14,TABLA_BASE[],4,FALSE) -> 0.68 | M22: =VLOOKUP($AH$14,TABLA_BASE[],5,FALSE) -> 1958.4 | O22: =VLOOKUP($AH$14,TABLA_BASE[],6,FALSE) -> 0.13778198 | Q22: =VLOOKUP($AH$14,TABLA_BASE[],7,FALSE) -> 2.5296 | T22: =VLOOKUP($AH$14,TABLA_BASE[],8,FALSE) -> 7285.248
K33: =VLOOKUP($AH$14,TABLA_BASE[],22,FALSE) -> 178.36704 | M33: =VLOOKUP($AH$14,TABLA_BASE[],24,FALSE) -> 1428.9865 | O33: =VLOOKUP($AH$14,TABLA_BASE[],26,FALSE) -> 368.83024 | Q33: =VLOOKUP($AH$14,TABLA_BASE[],30,FALSE) -> 2481.5571 | T33: ='Detallado por producto'!AO3 -> 0.4
H34: =VLOOKUP($AH$14,TABLA_BASE[],20,FALSE) -> 505.37328
H40: ='Detallado por producto'!AP3 -> 9.8111233 | K40: =VLOOKUP($AH$14,TABLA_BASE[],43,FALSE) -> 6.5061532 | M40: =VLOOKUP($AH$14,TABLA_BASE[],44,FALSE) -> 2.2054757 | O40: ='Detallado por producto'!AS3 -> 66 | Q40: ='Detallado por producto'!AT3 -> 1883.7357
M48: =VLOOKUP($AH$14,TABLA_BASE[],46,FALSE) -> 6351.7699
J51: =VLOOKUP($AH$14,TABLA_BASE[],45,FALSE) -> 394
H52: =VLOOKUP($AH$14,TABLA_BASE[],33,FALSE) -> 3.3082135
O54: =VLOOKUP($AH$14,TABLA_BASE[],40,FALSE) -> 2080.5756
H59: =VLOOKUP($AH$14,TABLA_BASE[],42,FALSE) -> 5.5136892
