Workbook

Sheet 🏠 PORTADA
E2: 🌎 CALCULADORA PROFESIONAL DE COSTOS DE IMPORTACIÓN
E3: P E R Ú — S I S T E M A D E G E S T I Ó N A D U A N E R A
E6: La herramienta definitiva para calcular costos, tributos y precios de importación en el Perú
E8: ✦ ¿QUÉ INCLUYE ESTA HERRAMIENTA? ✦
E9: 📋 DATOS GENERALES | G9: Registro completo del DUA, importador, Incoterm y parámetros tributarios configurables
E10: 🧾 FACTURA COMERCIAL | G10: Ingreso de hasta 30+ productos con cálculo automático de FOB total y prorrateo unitario
E11: 📦 GASTOS DE IMPORTACIÓN | G11: 21 conceptos pre-cargados: handling, tracción, almacenaje, agente, transporte y más
E12: ⚖️ TRIBUTOS ADUANEROS | G12: Cálculo automático: CIF, ADV, IPM, IGV, Deuda Aduanera y Percepción según SUNAT
E13: 🧮 COSTOS POR PRODUCTO | G13: Factor de prorrateo (6 dígitos) y costo unitario en USD y S/. para cada producto
E14: 💰 PRECIO DE VENTA | G14: Margen global o por producto. VV = CT/(1-Margen%). Punto de equilibrio automático
E15: 🏦 CRÉDITO FISCAL | G15: Detalle completo: IGV, IPM, Percepción y gastos afectos. Valor total recuperable en S/.
E16: 📊 DASHBOARD EJECUTIVO | G16: 8+ gráficos dinámicos: costos, tributos, márgenes, rentabilidad por producto y más
E18: ✦ FLUJO DE TRABAJO — 8 PASOS SIMPLES ✦
E19: PASO 1 Configura | F19: PASO 2 Carga | G19: PASO 3 Registra | H19: PASO 4 Automático | I19: PASO 5 Analiza | J19: PASO 6 Define | K19: PASO 7 Recupera | L19: PASO 8 Decide
E20: Datos generales, tipo de cambio y parámetros tributarios | F20: Productos de la factura comercial con FOB unitario | G20: Gastos de importación pagados a operadores y agentes | H20: El sistema calcula CIF, tributos y deuda aduanera | I20: Revisa el costo unitario y factor de prorrateo | J20: Establece tu margen y obtén precios de venta sugeridos | K20: Visualiza tu crédito fiscal total a recuperar | L20: Revisa el dashboard con todos los KPIs y gráficos
E22: ✦ LEYENDA DE COLORES ✦
E23: 🟡 AMARILLO Campo editable — ingresa tus datos aquí | G23: 🟢 VERDE Calculado automáticamente — no editar | I23: 🔵 AZUL Total o resumen principal de la sección | K23: 🟠 NARANJA Precio de venta o margen de ganancia
E25: ⚠️ IMPORTANTE: Actualice el Tipo de Cambio antes de cada operación | Verifique el Ad Valorem con su Agente de Aduanas
E26: 📧 Herramienta desarrollada para uso profesional en comercio exterior peruano Elaborado por : Rosalinda Jiménez Espinoza By Sally Control Tower Con Derechos de Autoria | J26: Versión 2.0 | 2026

Sheet 📖 Instrucciones
A1: 📖 GUÍA COMPLETA DE USO — CALCULADORA DE COSTOS DE IMPORTACIÓN PERÚ
D3: PASO 1 — 📋 DATOS GENERALES
D4: → Complete todos los datos en color AMARILLO: DUA, razón social, RUC, fecha, país, proveedor, incoterm, canal. | F4: "📌 NOTA IMPORTANTE — USO DE LA PLANTILLA Esta calculadora está diseñada para ser usada por operación de importación. Si realizas varias importaciones, te recomendamos seguir este flujo de trabajo: 1️⃣ Completa esta plantilla con los datos de tu importación actual. 2️⃣ Guarda el archivo con un nombre que identifique la operación — por ejemplo: Importación_Enero2026_China o DAM-2026-000001. 3️⃣ Para tu próxima importación, abre el archivo original, haz una copia y renómbrala. De esta forma tendrás un historial ordenado de cada importación, con todos sus costos, tributos y márgenes guardados por separado. ✅ Así podrás comparar operaciones, identificar en cuál ganaste más y tomar mejores decisiones en cada nueva importación."
D5: → IMPORTANTE: Actualice el Tipo de Cambio USD→PEN antes de cada operación (fuente: SUNAT / BCR).
D6: → Configure los parámetros tributarios: Ad Valorem según partida arancelaria (0%, 6% u 11%), percepción según tipo de importador.
D7: → Tasas de percepción: 10% = primera importación / empresa nueva | 3.5% = producto nuevo importador frecuente | 5% = producto de segundo uso.
D9: PASO 2 — 🧾 FACTURA COMERCIAL
D10: → Ingrese cada producto: descripción, unidad de medida, cantidad total y precio FOB unitario en USD.
D11: → El sistema calcula automáticamente el FOB Total, el Factor de Prorrateo y el Costo Unitario.
D12: → Puede manejar hasta 30 productos diferentes en una misma importación.
D14: PASO 3 — 📦 GASTOS DE IMPORTACIÓN
D15: → Ingrese el monto de cada gasto pagado a los operadores: handling, descarga, tracción, almacenaje, transporte, etc.
D16: → Los gastos marcados ⭐ son afectos a IGV (18%) y generan crédito fiscal.
D17: → El Derecho de Emisión del Seguro y la Comisión del Agente se calculan automáticamente.
D18: → Complete también los gastos administrativos y financieros (transferencias, intereses de letras, carta de crédito).
... D49: ⚠️ Esta plantilla es una herramienta de estimación profesional — consulte siempre a un agente de aduanas certificado.

Sheet Doc. Necesarios
B2: DOCUMENTOS QUE DEBES DE TENER A LA MANO PARA LLENAR LA PLANTILLA
B4: 1 | C4: Proforma Comercial y/o Factura Invoice
B5: 2 | C5: Proforma o Liquidación del Agente de Aduana
C6: 2.1 | D6: Derechos de Aduana
C7: 2.2 | D7: Flete Internacional
C8: 2.3 | D8: Comisión del Agente
C9: 2.4 | D9: Gastos de Nacionalizacion
C10: 2.5 | D10: Transporte Interno

Sheet 📋 Datos Generales
D1: 📋 CALCULADORA DE COSTOS DE IMPORTACIÓN — PERÚ
D2: Complete los datos en AMARILLO 🟡. Los campos en VERDE 🟢 se calculan automáticamente.
D4: 📄 DATOS DE LA OPERACIÓN DE IMPORTACIÓN
D5: Número de DUA / DAM | E5: DAM-2025-000001
D6: Razón Social del Importador | E6: EMPRESA IMPORTADORA S.A.C.
D7: RUC del Importador | E7: 20XXXXXXXXX
D8: Fecha de Numeración DAM | E8: 24/02/2026
D9: País de Origen | E9: China
D10: Proveedor / Exportador | E10: HWPI Co. Ltd.
D11: Incoterm | E11: FOB
D12: Vía de Transporte | E12: Marítima
D13: Puerto de Embarque | E13: Shekou, China
D14: Puerto de Destino | E14: Callao, Perú
D15: Agente de Aduanas | E15: Agencia SAC
D16: Canal de Control | E16: Naranja
D18: ⚖️ PARÁMETROS TRIBUTARIOS (Configuración)
D19: Tipo de Cambio USD → PEN | E19: 3.72 | F19: Actualizar según SUNAT / BCR
D20: Ad Valorem — Arancel (%) | E20: 0.06 | F20: 0%, 6% u 11% según partida arancelaria
D21: IGV (%) | E21: 0.16 | F21: Fijo 16%
D22: IPM (%) | E22: 0.02 | F22: Fijo 2%
D23: Percepción IGV (%) | E23: 0.035 | F23: 10% nueva empresa / 3.5% producto nuevo / 5% segundo uso
D24: Prima Neta Seguro (%) | E24: 0 | F24: % sobre la Suma Asegurada
D25: Derecho de Emisión Seguro (%) | E25: 0 | F25: 3% sobre Prima Neta — negociable
D26: Deducible Seguro (%) | E26: 0 | F26: % del que somos responsables en siniestro
D27: Comisión Agente Aduanas (%) | E27: 0.01 | F27: % sobre CIF (mín. S/. 100)
D28: IGV Servicios (%) | E28: 0.18 | F28: 18% (IGV 16% + IPM 2%)
D30: 🟡 Amarillo = Dato editable 🟢 Verde = Calculado automáticamente 🔵 Azul = Total general

Sheet 🧾 Factura Comercial
E2: MONTO TOTAL FOB USD | F2: =I507 -> 43641.28
D4: 🧾 FACTURA COMERCIAL — DETALLE DE PRODUCTOS
D5: Ingrese cada producto: descripción, unidad, cantidad y precio FOB unitario (USD).
D6: # | E6: DESCRIPCIÓN DEL PRODUCTO | F6: UNIDAD MEDIDA | G6: CANTIDAD (unid.) | H6: FOB UNIT. (USD) | I6: FOB TOTAL (USD) | J6: PARTICIPACIÓN | K6: COSTO UNIT. (PEN) | L6: PRECIO VENTA (PEN)
D7: 1 | E7: Case Transparente TPU iPhone 15 | F7: Unid. | G7: 480 | H7: 1.21 | I7: =IF(G7=0,0,G7*H7) -> 580.8 | J7: =IF(I7=0,0,I7/$I$507) -> 0.013308501 | K7: ='🧮 Costos x Producto'!K7 -> 5.1345892 | L7: ='💰 Precio de Venta'!H8 -> 8.5576486
D8: 2 | E8: Cable USB-C Trenzado 1m | F8: Unid. | G8: 2880 | H8: 0.68 | I8: =IF(G8=0,0,G8*H8) -> 1958.4 | J8: =IF(I8=0,0,I8/$I$507) -> 0.044874944 | K8: ='🧮 Costos x Producto'!K8 -> 2.8855542 | L8: ='💰 Precio de Venta'!H9 -> 4.8092571
D9: 3 | E9: Protector Pantalla Vidrio Templado | F9: Unid. | G9: 2880 | H9: 0.4 | I9: =IF(G9=0,0,G9*H9) -> 1152 | J9: =IF(I9=0,0,I9/$I$507) -> 0.026397026 | K9: ='🧮 Costos x Producto'!K9 -> 1.6973849 | L9: ='💰 Precio de Venta'!H10 -> 2.8289748
D10: 4 | E10: Audífonos In-Ear con Micrófono | F10: Unid. | G10: 10224 | H10: 0.34 | I10: =IF(G10=0,0,G10*H10) -> 3476.16 | J10: =IF(I10=0,0,I10/$I$507) -> 0.079653026 | K10: ='🧮 Costos x Producto'!K10 -> 1.4427771 | L10: ='💰 Precio de Venta'!H11 -> 2.4046285
D11: 5 | E11: Cable Micro USB 2m Nylon | F11: Unid. | G11: 8640 | H11: 0.26 | I11: =IF(G11=0,0,G11*H11) -> 2246.4 | J11: =IF(I11=0,0,I11/$I$507) -> 0.051474201 | K11: ='🧮 Costos x Producto'!K11 -> 1.1033002 | L11: ='💰 Precio de Venta'!H12 -> 1.8388336
D12: 6 | E12: Soporte Anillo Pop Socket Metálico | F12: Unid. | G12: 2160 | H12: 0.29 | I12: =IF(G12=0,0,G12*H12) -> 626.4 | J12: =IF(I12=0,0,I12/$I$507) -> 0.014353383 | K12: ='🧮 Costos x Producto'!K12 -> 1.230604 | L12: ='💰 Precio de Venta'!H13 -> 2.0510067
D13: 7 | E13: Cargador Inalámbrico 15W Qi | F13: Unid. | G13: 240 | H13: 5.71 | I13: =IF(G13=0,0,G13*H13) -> 1370.4 | J13: =IF(I13=0,0,I13/$I$507) -> 0.031401462 | K13: ='🧮 Costos x Producto'!K13 -> 24.230169 | L13: ='💰 Precio de Venta'!H14 -> 40.383615
D14: 8 | E14: Case Wallet Cuero PU Samsung S24 | F14: Unid. | G14: 1920 | H14: 0.76 | I14: =IF(G14=0,0,G14*H14) -> 1459.2 | J14: =IF(I14=0,0,I14/$I$507) -> 0.033436233 | K14: ='🧮 Costos x Producto'!K14 -> 3.2250312 | L14: ='💰 Precio de Venta'!H15 -> 5.375052
D15: 9 | E15: Adaptador USB-C a Jack 3.5mm | F15: Unid. | G15: 4800 | H15: 0.28 | I15: =IF(G15=0,0,G15*H15) -> 1344 | J15: =IF(I15=0,0,I15/$I$507) -> 0.03079653 | K15: ='🧮 Costos x Producto'!K15 -> 1.1881694 | L15: ='💰 Precio de Venta'!H16 -> 1.9802823
D16: 10 | E16: Adaptador YYY 67 | F16: Unid. | G16: 2000 | H16: 0.5 | I16: =IF(G16=0,0,G16*H16) -> 1000 | J16: =IF(I16=0,0,I16/$I$507) -> 0.022914085 | K16: ='🧮 Costos x Producto'!K16 -> 2.1217311 | L16: ='💰 Precio de Venta'!H17 -> 3.5362184
D17: 11 | E17: Case Transparente TPU iPhone 15 | F17: Unid. | G17: 480 | H17: 1.21 | I17: =IF(G17=0,0,G17*H17) -> 580.8 | J17: =IF(I17=0,0,I17/$I$507) -> 0.013308501 | K17: ='🧮 Costos x Producto'!K17 -> 5.1345892 | L17: ='💰 Precio de Venta'!H18 -> 8.5576486
D18: 12 | E18: Cable USB-C Trenzado 1m | F18: Unid. | G18: 2880 | H18: 0.68 | I18: =IF(G18=0,0,G18*H18) -> 1958.4 | J18: =IF(I18=0,0,I18/$I$507) -> 0.044874944 | K18: ='🧮 Costos x Producto'!K18 -> 2.8855542 | L18: ='💰 Precio de Venta'!H19 -> 4.8092571
... D34: 28 | E34: Adaptador USB-C a Jack 3.5mm | F34: Unid. | G34: 4800 | H34: 0.28 | I34: =IF(G34=0,0,G34*H34) -> 1344 | J34: =IF(I34=0,0,I34/$I$507) -> 0.03079653 | K34: ='🧮 Costos x Producto'!K34 -> 1.1881694 | L34: ='💰 Precio de Venta'!H35 -> 1.9802823
D35: 29 | F35: Unid. | G35: 0 | H35: 0 | I35: =IF(G35=0,0,G35*H35) -> 0 | J35: =IF(I35=0,0,I35/$I$507) -> 0 | K35: ='🧮 Costos x Producto'!K35 -> 0 | L35: ='💰 Precio de Venta'!H36 -> 0
D36: 30 | F36: Unid. | G36: 0 | H36: 0 | I36: =IF(G36=0,0,G36*H36) -> 0 | J36: =IF(I36=0,0,I36/$I$507) -> 0 | K36: ='🧮 Costos x Producto'!K36 -> 0 | L36: ='💰 Precio de Venta'!H37 -> 0
D37: 31 | F37: Unid. | G37: 0 | H37: 0 | I37: =IF(G37=0,0,G37*H37) -> 0 | J37: =IF(I37=0,0,I37/$I$507) -> 0 | K37: ='🧮 Costos x Producto'!K37 -> 0 | L37: ='💰 Precio de Venta'!H38 -> 0
D38: 32 | F38: Unid. | G38: 0 | H38: 0 | I38: =IF(G38=0,0,G38*H38) -> 0 | J38: =IF(I38=0,0,I38/$I$507) -> 0 | K38: ='🧮 Costos x Producto'!K38 -> 0 | L38: ='💰 Precio de Venta'!H39 -> 0
D39: 33 | F39: Unid. | G39: 0 | H39: 0 | I39: =IF(G39=0,0,G39*H39) -> 0 | J39: =IF(I39=0,0,I39/$I$507) -> 0 | K39: ='🧮 Costos x Producto'!K39 -> 0 | L39: ='💰 Precio de Venta'!H40 -> 0
D40: 34 | F40: Unid. | G40: 0 | H40: 0 | I40: =IF(G40=0,0,G40*H40) -> 0 | J40: =IF(I40=0,0,I40/$I$507) -> 0 | K40: ='🧮 Costos x Producto'!K40 -> 0 | L40: ='💰 Precio de Venta'!H41 -> 0
D41: 35 | F41: Unid. | G41: 0 | H41: 0 | I41: =IF(G41=0,0,G41*H41) -> 0 | J41: =IF(I41=0,0,I41/$I$507) -> 0 | K41: ='🧮 Costos x Producto'!K41 -> 0 | L41: ='💰 Precio de Venta'!H42 -> 0
D42: 36 | F42: Unid. | G42: 0 | H42: 0 | I42: =IF(G42=0,0,G42*H42) -> 0 | J42: =IF(I42=0,0,I42/$I$507) -> 0 | K42: ='🧮 Costos x Producto'!K42 -> 0 | L42: ='💰 Precio de Venta'!H43 -> 0
D43: 37 | F43: Unid. | G43: 0 | H43: 0 | I43: =IF(G43=0,0,G43*H43) -> 0 | J43: =IF(I43=0,0,I43/$I$507) -> 0 | K43: ='🧮 Costos x Producto'!K43 -> 0 | L43: ='💰 Precio de Venta'!H44 -> 0
D44: 38 | F44: Unid. | G44: 0 | H44: 0 | I44: =IF(G44=0,0,G44*H44) -> 0 | J44: =IF(I44=0,0,I44/$I$507) -> 0 | K44: ='🧮 Costos x Producto'!K44 -> 0 | L44: ='💰 Precio de Venta'!H45 -> 0
D45: 39 | F45: Unid. | G45: 0 | H45: 0 | I45: =IF(G45=0,0,G45*H45) -> 0 | J45: =IF(I45=0,0,I45/$I$507) -> 0 | K45: ='🧮 Costos x Producto'!K45 -> 0 | L45: ='💰 Precio de Venta'!H46 -> 0
D46: 40 | F46: Unid. | G46: 0 | H46: 0 | I46: =IF(G46=0,0,G46*H46) -> 0 | J46: =IF(I46=0,0,I46/$I$507) -> 0 | K46: ='🧮 Costos x Producto'!K46 -> 0 | L46: ='💰 Precio de Venta'!H47 -> 0
... D506: 500 | F506: Unid. | G506: 0 | H506: 0 | I506: =IF(G506=0,0,G506*H506) -> 0 | J506: =IF(I506=0,0,I506/$I$507) -> 0 | K506: ='🧮 Costos x Producto'!K506 -> 0 | L506: ='💰 Precio de Venta'!H507 -> 0
D507: TOTAL FOB (USD) | I507: =SUM(I7:I506) -> 43641.28

Sheet 📦 Gastos Importación
D2: 📦 GASTOS DE IMPORTACIÓN (Tercer Elemento)
D3: Ingrese el monto de cada gasto. Los gastos marcados con ⭐ están sujetos a IGV del 18%.
D4: CONCEPTO / GASTO | E4: MONTO (USD) | F4: AFECTO IGV | G4: NOTAS
D5: ⭐ Derecho de Emisión (Seguro) | E5: ='🧾 Tributos Aduana'!F9 -> - | F5: SÍ | G5: Auto-calculado desde Tributos Aduana
D6: ⭐ Handling | E6: 34.03 | F6: SÍ | G6: Manipuleo de la carga
D7: ⭐ Servicio de Descarga | E7: 100.69 | F7: SÍ | G7: Descarga del contenedor
D8: ⭐ Movilización de Carga | E8: 36.46 | F8: SÍ | G8: Traslado interno del terminal
D9: ⭐ Tracción | E9: 48.61 | F9: SÍ | G9: Transporte del contenedor
D10: ⭐ Servicio al Cliente (V°B°) | E10: 12.15 | F10: SÍ | G10: Verificación de pago del flete
D11: ⭐ Gastos Operativos Agente | E11: 70 | F11: SÍ | G11: Gestión del despacho
D12: ⭐ Almacenaje | E12: 121.53 | F12: SÍ | G12: Días de almacén temporal
D13: ⭐ Cargadores / Cuadrilla | E13: 62.5 | F13: SÍ | G13: Personal de carga
D14: ⭐ Serv. Administrativos | E14: 13.89 | F14: SÍ | G14: Documentación
D15: ⭐ Seguro de Contenedor | E15: 41.67 | F15: SÍ | G15: Seguro de la carga en tránsito local
D16: ⭐ Posicionamiento de Carga | E16: 62.5 | F16: SÍ | G16: Reconocimiento físico si aplica
D17: ⭐ Transporte Interno / Última Milla | E17: 104.17 | F17: SÍ | G17: Traslado a almacenes del importador
... D25: Comisiones C/C | E25: 0 | F25: NO | G25: 1.2% CFR si aplica carta de crédito
D26: SUB-TOTAL AFECTOS A IGV (US$) | E26: =E6+E7+E8+E9+E10+E11+E12+E13+E14+E15+E16+E17+E18+E19+E20 -> 997.24 | F26: =SUM(E6:E20)*'📋 Datos Generales'!E28 -> 179.5032
D27: SUB-TOTAL NO AFECTOS A IGV (US$) | E27: =E21+E22+E23+E24+E25 -> 167.5 | F27: No genera IGV
D28: ⭐ TOTAL COSTOS IMPORTACIÓN (US$) | E28: ='🧾 Tributos Aduana'!$F$14+'🧾 Tributos Aduana'!$F$17+E26+E27 -> 49782.29
H30: Tipo | I30: US$
H31: Afectos IGV | I31: =E26 -> 997.24
H32: No Afectos | I32: =E27 -> 167.5

Sheet 🧾 Tributos Aduana
E2: 🧾 TRIBUTOS ADUANEROS — CÁLCULO AUTOMÁTICO
E3: Todos los valores se calculan automáticamente. Solo configure los parámetros en '📋 Datos Generales'.
E5: 🛡️ CÁLCULO DEL SEGURO (Prima Neta → Suma Asegurada)
E6: FOB Total (USD) | F6: ='🧾 Factura Comercial'!I507 -> 43641.28 | G6: Valor FOB total de la factura comercial
E7: Flete Internacional (USD) | F7: 2090 | G7: Monto del flete — copiar del BL/AWB
E8: CFR = FOB + Flete (USD) | F8: =F6+F7 -> 45731.28 | G8: Valor CFR = base para calcular SA
E9: Suma Asegurada (USD) | F9: - | G9: SA = CFR / (1 - deducible%) — Fórmula del libro
E10: Prima Neta (USD) | F10: 134.27 | G10: Prima Neta = SA × 24%
E11: D. Emisión Seguro (USD) | F11: =F10*'📋 Datos Generales'!E25 -> 0 | G11: Derecho de Emisión = 3% × Prima Neta → va a Gastos
E12: IGV Seguro (USD) | F12: =SUM(F10:F11)*'📋 Datos Generales'!E28 -> 24.1686 | G12: IGV sobre Prima Neta → va a Crédito Fiscal
E13: Seguro (Prima Neta) → CIF | F13: =F10 -> 134.27 | G13: Prima Neta forma parte del CIF
E14: CIF = CFR + Prima Neta | F14: =F8+F10 -> 45865.55 | G14: CIF = Valor en Aduanas
E16: ⚖️ DEUDA ADUANERA (ADEUDO) — Pago a SUNAT-ADUANAS
E17: Ad Valorem — ADV (USD) | F17: =ROUND(F14*'📋 Datos Generales'!E20,0) -> 2752 | G17: ADV = CIF × Ad Valorem% — redondeado entero
E18: IPM (USD) | F18: =ROUND((F14+F17)*'📋 Datos Generales'!E22,0) -> 972 | G18: IPM = (CIF + ADV) × 2% — redondeado
E19: IGV (USD) | F19: =ROUND((F14+F17)*'📋 Datos Generales'!E21,0) -> 7779 | G19: IGV = (CIF + ADV) × 16% — redondeado
E20: DEUDA ADUANERA = DA (USD) | F20: =F17+F18+F19 -> 11503 | G20: DA = ADV + IPM + IGV
E22: 💸 PERCEPCIÓN IGV Y DERECHOS (costo real)
E23: Percepción IGV (USD) | F23: =ROUND((F14+F20)*'📋 Datos Generales'!E23,2) -> 2007.9 | G23: Base = CIF + DA — tasa según tipo importador
E24: DERECHOS = ADV (USD) | F24: =F17 -> 2752 | G24: Solo el ADV es costo (IPM e IGV = crédito fiscal)
E25: Comisión Agente (USD) | F25: =MAX(F14*'📋 Datos Generales'!E27,100/'📋 Datos Generales'!E19) -> 458.6555 | G25: Máx entre 1% CIF y mín USD 100
F35: Componente | G35: Monto US$
F36: Ad Valorem | G36: =F17 -> 2752
F37: IPM | G37: =F18 -> 972
F38: IGV Aduanas | G38: =F19 -> 7779
F39: Percepción | G39: =F23 -> 2007.9
F42: Componente | G42: Monto US$
F43: FOB | G43: =F6 -> 43641.28
F44: Flete | G44: =F7 -> 2090
F45: Seguro | G45: =F10 -> 134.27

Sheet 🧮 Costos x Producto
D2: 🧮 COSTO DE IMPORTACIÓN POR PRODUCTO (Factor de Prorrateo)
D3: El Costo Unitario se calcula multiplicando el Factor de Prorrateo × FOB Unitario. Factor = C/M Total / FOB Total
D4: COSTO TOTAL DE IMPORTACIÓN (US$) | G4: ='📦 Gastos Importación'!E28 -> 49782.29 | I4: =G4*'📋 Datos Generales'!E19 -> 185190.12
D5: FACTOR DE PRORRATEO = C/M Total (US$) / FOB Total (US$) | G5: =IF('🧾 Factura Comercial'!I507=0,0,G4/'🧾 Factura Comercial'!I507) -> 1.1407156
D6: # | E6: PRODUCTO | F6: CANTIDAD | G6: FOB UNIT. (USD) | H6: FOB TOTAL (USD) | I6: % PARTICIPACÓN | J6: C/M UNIT. (USD) | K6: C/M UNIT. (PEN)
D7: 1 | E7: ='🧾 Factura Comercial'!E7 -> Case Transparente TPU iPhone 15 | F7: ='🧾 Factura Comercial'!G7 -> 480 | G7: ='🧾 Factura Comercial'!H7 -> 1.21 | H7: ='🧾 Factura Comercial'!I7 -> 580.8 | I7: ='🧾 Factura Comercial'!J7 -> 0.013308501 | J7: =IF($G$5=0,0,$G$5*G7) -> 1.3802659 | K7: =J7*'📋 Datos Generales'!$E$19 -> 5.1345892
D8: 2 | E8: ='🧾 Factura Comercial'!E8 -> Cable USB-C Trenzado 1m | F8: ='🧾 Factura Comercial'!G8 -> 2880 | G8: ='🧾 Factura Comercial'!H8 -> 0.68 | H8: ='🧾 Factura Comercial'!I8 -> 1958.4 | I8: ='🧾 Factura Comercial'!J8 -> 0.044874944 | J8: =IF($G$5=0,0,$G$5*G8) -> 0.77568663 | K8: =J8*'📋 Datos Generales'!$E$19 -> 2.8855542
D9: 3 | E9: ='🧾 Factura Comercial'!E9 -> Protector Pantalla Vidrio Templado | F9: ='🧾 Factura Comercial'!G9 -> 2880 | G9: ='🧾 Factura Comercial'!H9 -> 0.4 | H9: ='🧾 Factura Comercial'!I9 -> 1152 | I9: ='🧾 Factura Comercial'!J9 -> 0.026397026 | J9: =IF($G$5=0,0,$G$5*G9) -> 0.45628625 | K9: =J9*'📋 Datos Generales'!$E$19 -> 1.6973849
D10: 4 | E10: ='🧾 Factura Comercial'!E10 -> Audífonos In-Ear con Micrófono | F10: ='🧾 Factura Comercial'!G10 -> 10224 | G10: ='🧾 Factura Comercial'!H10 -> 0.34 | H10: ='🧾 Factura Comercial'!I10 -> 3476.16 | I10: ='🧾 Factura Comercial'!J10 -> 0.079653026 | J10: =IF($G$5=0,0,$G$5*G10) -> 0.38784331 | K10: =J10*'📋 Datos Generales'!$E$19 -> 1.4427771
D11: 5 | E11: ='🧾 Factura Comercial'!E11 -> Cable Micro USB 2m Nylon | F11: ='🧾 Factura Comercial'!G11 -> 8640 | G11: ='🧾 Factura Comercial'!H11 -> 0.26 | H11: ='🧾 Factura Comercial'!I11 -> 2246.4 | I11: ='🧾 Factura Comercial'!J11 -> 0.051474201 | J11: =IF($G$5=0,0,$G$5*G11) -> 0.29658606 | K11: =J11*'📋 Datos Generales'!$E$19 -> 1.1033002
D12: 6 | E12: ='🧾 Factura Comercial'!E12 -> Soporte Anillo Pop Socket Metálico | F12: ='🧾 Factura Comercial'!G12 -> 2160 | G12: ='🧾 Factura Comercial'!H12 -> 0.29 | H12: ='🧾 Factura Comercial'!I12 -> 626.4 | I12: ='🧾 Factura Comercial'!J12 -> 0.014353383 | J12: =IF($G$5=0,0,$G$5*G12) -> 0.33080753 | K12: =J12*'📋 Datos Generales'!$E$19 -> 1.230604
D13: 7 | E13: ='🧾 Factura Comercial'!E13 -> Cargador Inalámbrico 15W Qi | F13: ='🧾 Factura Comercial'!G13 -> 240 | G13: ='🧾 Factura Comercial'!H13 -> 5.71 | H13: ='🧾 Factura Comercial'!I13 -> 1370.4 | I13: ='🧾 Factura Comercial'!J13 -> 0.031401462 | J13: =IF($G$5=0,0,$G$5*G13) -> 6.5134862 | K13: =J13*'📋 Datos Generales'!$E$19 -> 24.230169
D14: 8 | E14: ='🧾 Factura Comercial'!E14 -> Case Wallet Cuero PU Samsung S24 | F14: ='🧾 Factura Comercial'!G14 -> 1920 | G14: ='🧾 Factura Comercial'!H14 -> 0.76 | H14: ='🧾 Factura Comercial'!I14 -> 1459.2 | I14: ='🧾 Factura Comercial'!J14 -> 0.033436233 | J14: =IF($G$5=0,0,$G$5*G14) -> 0.86694388 | K14: =J14*'📋 Datos Generales'!$E$19 -> 3.2250312
D15: 9 | E15: ='🧾 Factura Comercial'!E15 -> Adaptador USB-C a Jack 3.5mm | F15: ='🧾 Factura Comercial'!G15 -> 4800 | G15: ='🧾 Factura Comercial'!H15 -> 0.28 | H15: ='🧾 Factura Comercial'!I15 -> 1344 | I15: ='🧾 Factura Comercial'!J15 -> 0.03079653 | J15: =IF($G$5=0,0,$G$5*G15) -> 0.31940038 | K15: =J15*'📋 Datos Generales'!$E$19 -> 1.1881694
D16: 10 | E16: ='🧾 Factura Comercial'!E16 -> Adaptador YYY 67 | F16: ='🧾 Factura Comercial'!G16 -> 2000 | G16: ='🧾 Factura Comercial'!H16 -> 0.5 | H16: ='🧾 Factura Comercial'!I16 -> 1000 | I16: ='🧾 Factura Comercial'!J16 -> 0.022914085 | J16: =IF($G$5=0,0,$G$5*G16) -> 0.57035781 | K16: =J16*'📋 Datos Generales'!$E$19 -> 2.1217311
D17: 11 | E17: ='🧾 Factura Comercial'!E17 -> Case Transparente TPU iPhone 15 | F17: ='🧾 Factura Comercial'!G17 -> 480 | G17: ='🧾 Factura Comercial'!H17 -> 1.21 | H17: ='🧾 Factura Comercial'!I17 -> 580.8 | I17: ='🧾 Factura Comercial'!J17 -> 0.013308501 | J17: =IF($G$5=0,0,$G$5*G17) -> 1.3802659 | K17: =J17*'📋 Datos Generales'!$E$19 -> 5.1345892
D18: 12 | E18: ='🧾 Factura Comercial'!E18 -> Cable USB-C Trenzado 1m | F18: ='🧾 Factura Comercial'!G18 -> 2880 | G18: ='🧾 Factura Comercial'!H18 -> 0.68 | H18: ='🧾 Factura Comercial'!I18 -> 1958.4 | I18: ='🧾 Factura Comercial'!J18 -> 0.044874944 | J18: =IF($G$5=0,0,$G$5*G18) -> 0.77568663 | K18: =J18*'📋 Datos Generales'!$E$19 -> 2.8855542
... D505: 499 | E505: ='🧾 Factura Comercial'!E505 -> 0 | F505: ='🧾 Factura Comercial'!G505 -> 0 | G505: ='🧾 Factura Comercial'!H505 -> 0 | H505: ='🧾 Factura Comercial'!I505 -> 0 | I505: ='🧾 Factura Comercial'!J505 -> 0 | J505: =IF($G$5=0,0,$G$5*G505) -> 0 | K505: =J505*'📋 Datos Generales'!$E$19 -> 0

Sheet 💰 Precio de Venta
D2: 💰 PRECIO DE VENTA — POLÍTICA DE UTILIDADES
D3: Ingrese su margen de ganancia deseado. VV = Costo Total / (1 - Margen%) — Precio de Venta incluye IGV (18%).
D4: MARGEN DE UTILIDAD GLOBAL (aplica a todos — puedes personalizar por producto ↓) | H4: 0.4
D5: VALOR DE VENTA TOTAL SIN IGV USD | H5: ='📦 Gastos Importación'!E28*H4 -> 19912.916
D6: FACTOR DE PRORRATEO = PV TOTAL / FOB TOTAL | H6: =('📦 Gastos Importación'!E28+H5)/'🧾 Factura Comercial'!I507 -> 1.5970019
D7: # | E7: PRODUCTO | F7: C/M UNIT. (PEN) | G7: MARGEN % | H7: VALOR VENTA UNIT. (S/.) | I7: PRECIO VENTA UNIT. c/IGV (S/.) | J7: GANANCIA UNIT. (S/.) | K7: PUNTO EQUILIBRIO
D8: 1 | E8: ='🧾 Factura Comercial'!E7 -> Case Transparente TPU iPhone 15 | F8: ='🧮 Costos x Producto'!K7 -> 5.1345892 | G8: =$H$4 -> 0.4 | H8: =IF(F8=0,0,F8/(1-G8)) -> 8.5576486 | I8: =IF(H8=0,0,H8*(1+'📋 Datos Generales'!$E$28)) -> 10.098025 | J8: =IF(H8=0,0,H8-F8) -> 3.4230594 | K8: =IF(OR(I8=0,'🧾 Factura Comercial'!G7=0),0,CEILING('🧮 Costos x Producto'!J7*'🧾 Factura Comercial'!G7/I8,1)) -> 66
D9: 2 | E9: ='🧾 Factura Comercial'!E8 -> Cable USB-C Trenzado 1m | F9: ='🧮 Costos x Producto'!K8 -> 2.8855542 | G9: =$H$4 -> 0.4 | H9: =IF(F9=0,0,F9/(1-G9)) -> 4.8092571 | I9: =IF(H9=0,0,H9*(1+'📋 Datos Generales'!$E$28)) -> 5.6749233 | J9: =IF(H9=0,0,H9-F9) -> 1.9237028 | K9: =IF(OR(I9=0,'🧾 Factura Comercial'!G8=0),0,CEILING('🧮 Costos x Producto'!J8*'🧾 Factura Comercial'!G8/I9,1)) -> 394
D10: 3 | E10: ='🧾 Factura Comercial'!E9 -> Protector Pantalla Vidrio Templado | F10: ='🧮 Costos x Producto'!K9 -> 1.6973849 | G10: 0.4 | H10: =IF(F10=0,0,F10/(1-G10)) -> 2.8289748 | I10: =IF(H10=0,0,H10*(1+'📋 Datos Generales'!$E$28)) -> 3.3381902 | J10: =IF(H10=0,0,H10-F10) -> 1.1315899 | K10: =IF(OR(I10=0,'🧾 Factura Comercial'!G9=0),0,CEILING('🧮 Costos x Producto'!J9*'🧾 Factura Comercial'!G9/I10,1)) -> 394
D11: 4 | E11: ='🧾 Factura Comercial'!E10 -> Audífonos In-Ear con Micrófono | F11: ='🧮 Costos x Producto'!K10 -> 1.4427771 | G11: =$H$4 -> 0.4 | H11: =IF(F11=0,0,F11/(1-G11)) -> 2.4046285 | I11: =IF(H11=0,0,H11*(1+'📋 Datos Generales'!$E$28)) -> 2.8374617 | J11: =IF(H11=0,0,H11-F11) -> 0.96185142 | K11: =IF(OR(I11=0,'🧾 Factura Comercial'!G10=0),0,CEILING('🧮 Costos x Producto'!J10*'🧾 Factura Comercial'!G10/I11,1)) -> 1398
D12: 5 | E12: ='🧾 Factura Comercial'!E11 -> Cable Micro USB 2m Nylon | F12: ='🧮 Costos x Producto'!K11 -> 1.1033002 | G12: =$H$4 -> 0.4 | H12: =IF(F12=0,0,F12/(1-G12)) -> 1.8388336 | I12: =IF(H12=0,0,H12*(1+'📋 Datos Generales'!$E$28)) -> 2.1698236 | J12: =IF(H12=0,0,H12-F12) -> 0.73553344 | K12: =IF(OR(I12=0,'🧾 Factura Comercial'!G11=0),0,CEILING('🧮 Costos x Producto'!J11*'🧾 Factura Comercial'!G11/I12,1)) -> 1181
D13: 6 | E13: ='🧾 Factura Comercial'!E12 -> Soporte Anillo Pop Socket Metálico | F13: ='🧮 Costos x Producto'!K12 -> 1.230604 | G13: =$H$4 -> 0.4 | H13: =IF(F13=0,0,F13/(1-G13)) -> 2.0510067 | I13: =IF(H13=0,0,H13*(1+'📋 Datos Generales'!$E$28)) -> 2.4201879 | J13: =IF(H13=0,0,H13-F13) -> 0.82040268 | K13: =IF(OR(I13=0,'🧾 Factura Comercial'!G12=0),0,CEILING('🧮 Costos x Producto'!J12*'🧾 Factura Comercial'!G12/I13,1)) -> 296
D14: 7 | E14: ='🧾 Factura Comercial'!E13 -> Cargador Inalámbrico 15W Qi | F14: ='🧮 Costos x Producto'!K13 -> 24.230169 | G14: =$H$4 -> 0.4 | H14: =IF(F14=0,0,F14/(1-G14)) -> 40.383615 | I14: =IF(H14=0,0,H14*(1+'📋 Datos Generales'!$E$28)) -> 47.652665 | J14: =IF(H14=0,0,H14-F14) -> 16.153446 | K14: =IF(OR(I14=0,'🧾 Factura Comercial'!G13=0),0,CEILING('🧮 Costos x Producto'!J13*'🧾 Factura Comercial'!G13/I14,1)) -> 33
D15: 8 | E15: ='🧾 Factura Comercial'!E14 -> Case Wallet Cuero PU Samsung S24 | F15: ='🧮 Costos x Producto'!K14 -> 3.2250312 | G15: =$H$4 -> 0.4 | H15: =IF(F15=0,0,F15/(1-G15)) -> 5.375052 | I15: =IF(H15=0,0,H15*(1+'📋 Datos Generales'!$E$28)) -> 6.3425614 | J15: =IF(H15=0,0,H15-F15) -> 2.1500208 | K15: =IF(OR(I15=0,'🧾 Factura Comercial'!G14=0),0,CEILING('🧮 Costos x Producto'!J14*'🧾 Factura Comercial'!G14/I15,1)) -> 263
D16: 9 | E16: ='🧾 Factura Comercial'!E15 -> Adaptador USB-C a Jack 3.5mm | F16: ='🧮 Costos x Producto'!K15 -> 1.1881694 | G16: =$H$4 -> 0.4 | H16: =IF(F16=0,0,F16/(1-G16)) -> 1.9802823 | I16: =IF(H16=0,0,H16*(1+'📋 Datos Generales'!$E$28)) -> 2.3367331 | J16: =IF(H16=0,0,H16-F16) -> 0.79211293 | K16: =IF(OR(I16=0,'🧾 Factura Comercial'!G15=0),0,CEILING('🧮 Costos x Producto'!J15*'🧾 Factura Comercial'!G15/I16,1)) -> 657
D17: 10 | E17: ='🧾 Factura Comercial'!E16 -> Adaptador YYY 67 | F17: ='🧮 Costos x Producto'!K16 -> 2.1217311 | G17: =$H$4 -> 0.4 | H17: =IF(F17=0,0,F17/(1-G17)) -> 3.5362184 | I17: =IF(H17=0,0,H17*(1+'📋 Datos Generales'!$E$28)) -> 4.1727378 | J17: =IF(H17=0,0,H17-F17) -> 1.4144874 | K17: =IF(OR(I17=0,'🧾 Factura Comercial'!G16=0),0,CEILING('🧮 Costos x Producto'!J16*'🧾 Factura Comercial'!G16/I17,1)) -> 274
D18: 11 | E18: ='🧾 Factura Comercial'!E17 -> Case Transparente TPU iPhone 15 | F18: ='🧮 Costos x Producto'!K17 -> 5.1345892 | G18: =$H$4 -> 0.4 | H18: =IF(F18=0,0,F18/(1-G18)) -> 8.5576486 | I18: =IF(H18=0,0,H18*(1+'📋 Datos Generales'!$E$28)) -> 10.098025 | J18: =IF(H18=0,0,H18-F18) -> 3.4230594 | K18: =IF(OR(I18=0,'🧾 Factura Comercial'!G17=0),0,CEILING('🧮 Costos x Producto'!J17*'🧾 Factura Comercial'!G17/I18,1)) -> 66
D19: 12 | E19: ='🧾 Factura Comercial'!E18 -> Cable USB-C Trenzado 1m | F19: ='🧮 Costos x Producto'!K18 -> 2.8855542 | G19: =$H$4 -> 0.4 | H19: =IF(F19=0,0,F19/(1-G19)) -> 4.8092571 | I19: =IF(H19=0,0,H19*(1+'📋 Datos Generales'!$E$28)) -> 5.6749233 | J19: =IF(H19=0,0,H19-F19) -> 1.9237028 | K19: =IF(OR(I19=0,'🧾 Factura Comercial'!G18=0),0,CEILING('🧮 Costos x Producto'!J18*'🧾 Factura Comercial'!G18/I19,1)) -> 394
D20: 13 | E20: ='🧾 Factura Comercial'!E19 -> Protector Pantalla Vidrio Templado | F20: ='🧮 Costos x Producto'!K19 -> 1.6973849 | G20: =$H$4 -> 0.4 | H20: =IF(F20=0,0,F20/(1-G20)) -> 2.8289748 | I20: =IF(H20=0,0,H20*(1+'📋 Datos Generales'!$E$28)) -> 3.3381902 | J20: =IF(H20=0,0,H20-F20) -> 1.1315899 | K20: =IF(OR(I20=0,'🧾 Factura Comercial'!G19=0),0,CEILING('🧮 Costos x Producto'!J19*'🧾 Factura Comercial'!G19/I20,1)) -> 394
D21: 14 | E21: ='🧾 Factura Comercial'!E20 -> Audífonos In-Ear con Micrófono | F21: ='🧮 Costos x Producto'!K20 -> 1.4427771 | G21: =$H$4 -> 0.4 | H21: =IF(F21=0,0,F21/(1-G21)) -> 2.4046285 | I21: =IF(H21=0,0,H21*(1+'📋 Datos Generales'!$E$28)) -> 2.8374617 | J21: =IF(H21=0,0,H21-F21) -> 0.96185142 | K21: =IF(OR(I21=0,'🧾 Factura Comercial'!G20=0),0,CEILING('🧮 Costos x Producto'!J20*'🧾 Factura Comercial'!G20/I21,1)) -> 1398
D22: 15 | E22: ='🧾 Factura Comercial'!E21 -> Cable Micro USB 2m Nylon | F22: ='🧮 Costos x Producto'!K21 -> 1.1033002 | G22: =$H$4 -> 0.4 | H22: =IF(F22=0,0,F22/(1-G22)) -> 1.8388336 | I22: =IF(H22=0,0,H22*(1+'📋 Datos Generales'!$E$28)) -> 2.1698236 | J22: =IF(H22=0,0,H22-F22) -> 0.73553344 | K22: =IF(OR(I22=0,'🧾 Factura Comercial'!G21=0),0,CEILING('🧮 Costos x Producto'!J21*'🧾 Factura Comercial'!G21/I22,1)) -> 1181
... D520: 513 | E520: ='🧾 Factura Comercial'!E519 -> 0 | F520: ='🧮 Costos x Producto'!K519 -> 0 | G520: =$H$4 -> 0.4 | H520: =IF(F520=0,0,F520/(1-G520)) -> 0 | I520: =IF(H520=0,0,H520*(1+'📋 Datos Generales'!$E$28)) -> 0 | J520: =IF(H520=0,0,H520-F520) -> 0 | K520: =IF(OR(I520=0,'🧾 Factura Comercial'!G519=0),0,CEILING('🧮 Costos x Producto'!J519*'🧾 Factura Comercial'!G519/I520,1)) -> 0

Sheet 🏦 Crédito Fiscal
B7: 🏦 CRÉDITO FISCAL DEL IMPORTADOR
B8: El Crédito Fiscal se recupera al vender los productos. IPM, IGV y Percepción NO son costo — se recuperan.
B10: 🏦 DETALLE DEL CRÉDITO FISCAL (en US$ — convertir a S/. con TC)
B11: IGV del Seguro (Crédito Fiscal) | C11: ='🧾 Tributos Aduana'!F12 -> 24.1686 | D11: IGV pagado a Cía. de Seguros
B12: IPM — Derechos (Crédito Fiscal) | C12: ='🧾 Tributos Aduana'!F18 -> 972 | D12: IPM pagado a SUNAT-Aduanas
B13: IGV — Derechos (Crédito Fiscal) | C13: ='🧾 Tributos Aduana'!F19 -> 7779 | D13: IGV pagado a SUNAT-Aduanas
B14: Percepción IGV (Crédito Fiscal) | C14: ='🧾 Tributos Aduana'!F23 -> 2007.9 | D14: Percepción pagada — se recupera
B15: IGV Gastos Afectos (Crédito Fiscal) | C15: ='📦 Gastos Importación'!F26 -> 179.5032 | D15: 18% de gastos afectos
B16: ✅ TOTAL CRÉDITO FISCAL (US$) | C16: =C11+C12+C13+C14+C15 -> 10962.572
B17: ✅ TOTAL CRÉDITO FISCAL (S/. PEN) | C17: =C16*'📋 Datos Generales'!E19 -> 40780.767
B19: 📌 ¿QUÉ ES EL CRÉDITO FISCAL? El IGV, IPM y la Percepción que pagas al importar NO son un costo definitivo. Los recuperas cuando vendes tus productos y cobras IGV a tus clientes. El importador declara ante SUNAT: IGV cobrado en ventas - Crédito Fiscal = IGV a pagar. ⚠️ SOLO el Ad Valorem (ADV) es un costo real de importación.

Sheet Detallado por producto
B1: 📦 SECCIÓN 1: IDENTIFICACIÓN DEL PRODUCTO Y VALOR FOB | AG1: 🧮 SECCIÓN 3: COSTO DE IMPORTACIÓN · CRÉDITO FISCAL · PRECIO DE VENTA · MARGENARGEN
A2: DESCRIPCIÓN DEL PRODUCTO | B2: UNIDAD | C2: CANTIDAD (unid.) | D2: FOB UNIT. (US$) | E2: FOB TOTAL (US$) | F2: % PART. FOB | G2: FOB UNIT. (S/.) | H2: FOB TOTAL (S/.) | I2: ADV UNIT. (US$) ⚠️COSTO | J2: ADV TOTAL (US$) ⚠️COSTO | K2: IPM UNIT. (US$) ✅CF | L2: IPM TOTAL (US$) ✅CF | M2: IGV UNIT. (US$) ✅CF | N2: IGV TOTAL (US$) ✅CF | O2: PERCEP. UNIT.(US$) ✅CF | P2: PERCEP. TOTAL.(US$) ✅CF | Q2: DEUDA ADUANERA UNIT. | R2: DEUDA ADUANERA TOTAL | S2: DEUDA ADUANERA UNIT. /S/.) | T2: DEUDA ADUANERA TOTAL (s/.)2 | U2: ADV UNIT. (S/.) | V2: ADV TOTAL. (S/.) | W2: IPM UNIT. (S/.) | X2: IPM TOTAL (S/.)2 | Y2: IGV UNIT. (S/.) | Z2: IGV TOTAL (S/.)2 | AA2: PERCEP. UNIT.(S/.) | AB2: PERCEP. TOTAL.(S/.)2 | AC2: TOTAL PAGO SUNAT UNIT.(US$) | AD2: TOTAL PAGO SUNAT TOTAL(US$) | AE2: TOTAL TRIB. UNIT.(S/.) | AF2: TOTAL TRIB. TOTAL .(S/.) | AG2: GASTOS IMP. UNIT.(US$) | AH2: GASTOS IMP. TOTAL.(US$)2 | AI2: GASTOS IMP. UNIT.(S/.) | AJ2: GASTOS IMP. TOTAL.(S/.)2 | AK2: C/M UNIT. (US$) | AL2: C/M UNIT. (S/.) | AM2: C/M TOTAL (S/.)2 | AN2: ADV UNIT. ⚠️COSTO (US$) | AO2: CF UNIT. ✅RECUP. (US$) | AP2: CF UNIT. ✅RECUP.(S/.) | AQ2: TOTAL CREDITO FISCAL POR PRODUCTO | AR2: MARGEN % | AS2: VALOR VTA. UNIT.(S/.) | AT2: VALOR VTA. TOTAL (S/.) | AU2: PRECIO VTA. c/IGV(S/.) | AV2: GANANCIA UNIT.(S/.) | AW2: GANANCIA TOTAL.(S/.) | AX2: PUNTO EQUILIBRIO | AY2: GANANCIA TOTAL(S/.) | AZ2: % UTILIDAD S/PRECIO | BA2: ROI UNIT. | BB2: CLASIF. MARGEN
A3: ='🧾 Factura Comercial'!E7 -> Case Transparente TPU iPhone 15 | B3: ='🧾 Factura Comercial'!F7 -> Unid. | C3: ='🧾 Factura Comercial'!G7 -> 480 | D3: ='🧾 Factura Comercial'!H7 -> 1.21 | E3: ='🧾 Factura Comercial'!I7 -> 580.8 | F3: =IF('🧾 Tributos Aduana'!$F$6=0,0,'🧾 Factura Comercial'!I7/'🧾 Tributos Aduana'!$F$6) -> 0.013308501 | G3: ='🧾 Factura Comercial'!H7*'📋 Datos Generales'!$E$19 -> 4.5012 | H3: =TABLA_BASE[[#This Row],[FOB UNIT. (S/.)]]*TABLA_BASE[[#This Row],[CANTIDAD (unid.)]] -> 2160.576 | I3: =IF('🧾 Tributos Aduana'!$F$6=0,0,'🧾 Tributos Aduana'!$F$17*('🧾 Factura Comercial'!H7/'🧾 Tributos Aduana'!$F$6)) -> 0.07630207 | J3: =TABLA_BASE[[#This Row],[ADV UNIT. (US$) ⚠️COSTO]]*TABLA_BASE[[#This Row],[CANTIDAD (unid.)]] -> 36.624994 | K3: =IF('🧾 Tributos Aduana'!$F$6=0,0,'🧾 Tributos Aduana'!$F$18*('🧾 Factura Comercial'!H7/'🧾 Tributos Aduana'!$F$6)) -> 0.026949714 | L3: =TABLA_BASE[[#This Row],[IPM UNIT. (US$) ✅CF]]*TABLA_BASE[[#This Row],[CANTIDAD (unid.)]] -> 12.935863 | M3: =IF('🧾 Tributos Aduana'!$F$6=0,0,'🧾 Tributos Aduana'!$F$19*('🧾 Factura Comercial'!H7/'🧾 Tributos Aduana'!$F$6)) -> 0.21568089 | N3: =TABLA_BASE[[#This Row],[IGV UNIT. (US$) ✅CF]]*TABLA_BASE[[#This Row],[CANTIDAD (unid.)]] -> 103.52683 | O3: =IF('🧾 Tributos Aduana'!$F$6=0,0,'🧾 Tributos Aduana'!$F$23*('🧾 Factura Comercial'!H7/'🧾 Tributos Aduana'!$F$6)) -> 0.055671121 | P3: =TABLA_BASE[[#This Row],[PERCEP. UNIT.(US$) ✅CF]]*TABLA_BASE[[#This Row],[CANTIDAD (unid.)]] -> 26.722138 | Q3: =TABLA_BASE[[#This Row],[ADV UNIT. (US$) ⚠️COSTO]]+TABLA_BASE[[#This Row],[IPM UNIT. (US$) ✅CF]]+TABLA_BASE[[#This Row],[IGV UNIT. (US$) ✅CF]] -> 0.31893267 | R3: =TABLA_BASE[[#This Row],[DEUDA ADUANERA UNIT.]]*TABLA_BASE[[#This Row],[CANTIDAD (unid.)]] -> 153.08768 | S3: =TABLA_BASE[[#This Row],[DEUDA ADUANERA UNIT.]]*'📋 Datos Generales'!$E$19 -> 1.1864295 | T3: =TABLA_BASE[[#This Row],[DEUDA ADUANERA TOTAL]]*'📋 Datos Generales'!$E$19 -> 569.48618 | U3: =TABLA_BASE[[#This Row],[ADV UNIT. (US$) ⚠️COSTO]]*'📋 Datos Generales'!$E$19 -> 0.2838437 | V3: =TABLA_BASE[[#This Row],[ADV UNIT. (S/.)]]*TABLA_BASE[[#This Row],[CANTIDAD (unid.)]] -> 136.24498 | W3: =TABLA_BASE[[#This Row],[IPM UNIT. (US$) ✅CF]]*'📋 Datos Generales'!$E$19 -> 0.10025293 | X3: =TABLA_BASE[[#This Row],[IPM UNIT. (S/.)]]*TABLA_BASE[[#This Row],[CANTIDAD (unid.)]] -> 48.121409 | Y3: =TABLA_BASE[[#This Row],[IGV UNIT. (US$) ✅CF]]*'📋 Datos Generales'!$E$19 -> 0.8023329 | Z3: =TABLA_BASE[[#This Row],[IGV UNIT. (S/.)]]*TABLA_BASE[[#This Row],[CANTIDAD (unid.)]] -> 385.11979 | AA3: =TABLA_BASE[[#This Row],[PERCEP. UNIT.(US$) ✅CF]]*'📋 Datos Generales'!$E$19 -> 0.20709657 | AB3: =TABLA_BASE[[#This Row],[PERCEP. UNIT.(S/.)]]*TABLA_BASE[[#This Row],[CANTIDAD (unid.)]] -> 99.406354 | AC3: =TABLA_BASE[[#This Row],[ADV UNIT. (US$) ⚠️COSTO]]+TABLA_BASE[[#This Row],[IPM UNIT. (US$) ✅CF]]+TABLA_BASE[[#This Row],[IGV UNIT. (US$) ✅CF]]+TABLA_BASE[[#This Row],[PERCEP. UNIT.(US$) ✅CF]] -> 0.37460379 | AD3: =TABLA_BASE[[#This Row],[TOTAL PAGO SUNAT UNIT.(US$)]]*TABLA_BASE[[#This Row],[CANTIDAD (unid.)]] -> 179.80982 | AE3: =TABLA_BASE[[#This Row],[TOTAL PAGO SUNAT UNIT.(US$)]]*'📋 Datos Generales'!$E$19 -> 1.3935261 | AF3: =TABLA_BASE[[#This Row],[TOTAL TRIB. UNIT.(S/.)]]*TABLA_BASE[[#This Row],[CANTIDAD (unid.)]] -> 668.89253 | AG3: =IF('🧾 Factura Comercial'!G7=0,0,'📦 Gastos Importación'!$E$28*(IF('🧾 Tributos Aduana'!$F$6=0,0,'🧾 Factura Comercial'!I7/'🧾 Tributos Aduana'!$F$6))/'🧾 Factura Comercial'!G7) -> 1.3802659 | AH3: =TABLA_BASE[[#This Row],[GASTOS IMP. UNIT.(US$)]]*TABLA_BASE[[#This Row],[CANTIDAD (unid.)]] -> 662.52764 | AI3: =TABLA_BASE[[#This Row],[GASTOS IMP. UNIT.(US$)]]*'📋 Datos Generales'!$E$19 -> 5.1345892 | AJ3: =TABLA_BASE[[#This Row],[GASTOS IMP. UNIT.(S/.)]]*TABLA_BASE[[#This Row],[CANTIDAD (unid.)]] -> 2464.6028 | AK3: ='🧮 Costos x Producto'!J7 -> 1.3802659 | AL3: ='🧮 Costos x Producto'!K7 -> 5.1345892 | AM3: =TABLA_BASE[[#This Row],[C/M UNIT. (S/.)]]*TABLA_BASE[[#This Row],[CANTIDAD (unid.)]] -> 2464.6028 | AN3: =IF('🧾 Factura Comercial'!G7=0,0,'🧾 Tributos Aduana'!$F$17*(IF('🧾 Tributos Aduana'!$F$6=0,0,'🧾 Factura Comercial'!I7/'🧾 Tributos Aduana'!$F$6))/'🧾 Factura Comercial'!G7) -> 0.07630207 | AO3: =IF('🧾 Factura Comercial'!G7=0,0,'🏦 Crédito Fiscal'!$C$16*(IF('🧾 Tributos Aduana'!$F$6=0,0,'🧾 Factura Comercial'!I7/'🧾 Tributos Aduana'!$F$6))/'🧾 Factura Comercial'!G7) -> 0.30394874 | AP3: =TABLA_BASE[[#This Row],[CF UNIT. ✅RECUP. (US$)]]*'📋 Datos Generales'!$E$19 -> 1.1306893 | AQ3: =TABLA_BASE[[#This Row],[CF UNIT. ✅RECUP.(S/.)]]*TABLA_BASE[[#This Row],[CANTIDAD (unid.)]] -> 542.73086 | AR3: ='💰 Precio de Venta'!G8 -> 0.4 | AS3: ='💰 Precio de Venta'!H8 -> 8.5576486 | AT3: =TABLA_BASE[[#This Row],[VALOR VTA. UNIT.(S/.)]]*TABLA_BASE[[#This Row],[CANTIDAD (unid.)]] -> 4107.6713 | AU3: ='💰 Precio de Venta'!I8 -> 10.098025 | AV3: ='💰 Precio de Venta'!J8 -> 3.4230594 | AW3: =TABLA_BASE[[#This Row],[GANANCIA UNIT.(S/.)]]*TABLA_BASE[[#This Row],[CANTIDAD (unid.)]] -> 1643.0685 | AX3: ='💰 Precio de Venta'!K8 -> 66 | AY3: =TABLA_BASE[[#This Row],[GANANCIA UNIT.(S/.)]]*'🧾 Factura Comercial'!G7 -> 1643.0685 | AZ3: =IF(TABLA_BASE[[#This Row],[PRECIO VTA. c/IGV(S/.)]]=0,0,TABLA_BASE[[#This Row],[GANANCIA UNIT.(S/.)]]/TABLA_BASE[[#This Row],[PRECIO VTA. c/IGV(S/.)]]) -> 0.33898305 | BA3: =IF(TABLA_BASE[[#This Row],[C/M UNIT. (S/.)]]=0,0,TABLA_BASE[[#This Row],[GANANCIA UNIT.(S/.)]]/TABLA_BASE[[#This Row],[C/M UNIT. (S/.)]]) -> 0.66666667 | BB3: =IF(TABLA_BASE[[#This Row],[MARGEN %]]>=0.5,"🟢 ALTO",IF(TABLA_BASE[[#This Row],[MARGEN %]]>=0.3,"🟡 MEDIO","🔴 BAJO")) -> 🟡 MEDIO
A4: ='🧾 Factura Comercial'!E8 -> Cable USB-C Trenzado 1m | B4: ='🧾 Factura Comercial'!F8 -> Unid. | C4: ='🧾 Factura Comercial'!G8 -> 2880 | D4: ='🧾 Factura Comercial'!H8 -> 0.68 | E4: ='🧾 Factura Comercial'!I8 -> 1958.4 | F4: =IF('🧾 Tributos Aduana'!$F$6=0,0,'🧾 Factura Comercial'!I8/'🧾 Tributos Aduana'!$F$6) -> 0.044874944 | G4: ='🧾 Factura Comercial'!H8*'📋 Datos Generales'!$E$19 -> 2.5296 | H4: =TABLA_BASE[[#This Row],[FOB UNIT. (S/.)]]*TABLA_BASE[[#This Row],[CANTIDAD (unid.)]] -> 7285.248 | I4: =IF('🧾 Tributos Aduana'!$F$6=0,0,'🧾 Tributos Aduana'!$F$17*('🧾 Factura Comercial'!H8/'🧾 Tributos Aduana'!$F$6)) -> 0.042880502 | J4: =TABLA_BASE[[#This Row],[ADV UNIT. (US$) ⚠️COSTO]]*TABLA_BASE[[#This Row],[CANTIDAD (unid.)]] -> 123.49585 | K4: =IF('🧾 Tributos Aduana'!$F$6=0,0,'🧾 Tributos Aduana'!$F$18*('🧾 Factura Comercial'!H8/'🧾 Tributos Aduana'!$F$6)) -> 0.015145294 | L4: =TABLA_BASE[[#This Row],[IPM UNIT. (US$) ✅CF]]*TABLA_BASE[[#This Row],[CANTIDAD (unid.)]] -> 43.618446 | M4: =IF('🧾 Tributos Aduana'!$F$6=0,0,'🧾 Tributos Aduana'!$F$19*('🧾 Factura Comercial'!H8/'🧾 Tributos Aduana'!$F$6)) -> 0.12120909 | N4: =TABLA_BASE[[#This Row],[IGV UNIT. (US$) ✅CF]]*TABLA_BASE[[#This Row],[CANTIDAD (unid.)]] -> 349.08219 | O4: =IF('🧾 Tributos Aduana'!$F$6=0,0,'🧾 Tributos Aduana'!$F$23*('🧾 Factura Comercial'!H8/'🧾 Tributos Aduana'!$F$6)) -> 0.03128625 | P4: =TABLA_BASE[[#This Row],[PERCEP. UNIT.(US$) ✅CF]]*TABLA_BASE[[#This Row],[CANTIDAD (unid.)]] -> 90.1044 | Q4: =TABLA_BASE[[#This Row],[ADV UNIT. (US$) ⚠️COSTO]]+TABLA_BASE[[#This Row],[IPM UNIT. (US$) ✅CF]]+TABLA_BASE[[#This Row],[IGV UNIT. (US$) ✅CF]] -> 0.17923489 | R4: =TABLA_BASE[[#This Row],[DEUDA ADUANERA UNIT.]]*TABLA_BASE[[#This Row],[CANTIDAD (unid.)]] -> 516.19648 | S4: =TABLA_BASE[[#This Row],[DEUDA ADUANERA UNIT.]]*'📋 Datos Generales'!$E$19 -> 0.66675379 | T4: =TABLA_BASE[[#This Row],[DEUDA ADUANERA TOTAL]]*'📋 Datos Generales'!$E$19 -> 1920.2509 | U4: =TABLA_BASE[[#This Row],[ADV UNIT. (US$) ⚠️COSTO]]*'📋 Datos Generales'!$E$19 -> 0.15951547 | V4: =TABLA_BASE[[#This Row],[ADV UNIT. (S/.)]]*TABLA_BASE[[#This Row],[CANTIDAD (unid.)]] -> 459.40455 | W4: =TABLA_BASE[[#This Row],[IPM UNIT. (US$) ✅CF]]*'📋 Datos Generales'!$E$19 -> 0.056340492 | X4: =TABLA_BASE[[#This Row],[IPM UNIT. (S/.)]]*TABLA_BASE[[#This Row],[CANTIDAD (unid.)]] -> 162.26062 | Y4: =TABLA_BASE[[#This Row],[IGV UNIT. (US$) ✅CF]]*'📋 Datos Generales'!$E$19 -> 0.45089783 | Z4: =TABLA_BASE[[#This Row],[IGV UNIT. (S/.)]]*TABLA_BASE[[#This Row],[CANTIDAD (unid.)]] -> 1298.5857 | AA4: =TABLA_BASE[[#This Row],[PERCEP. UNIT.(US$) ✅CF]]*'📋 Datos Generales'!$E$19 -> 0.11638485 | AB4: =TABLA_BASE[[#This Row],[PERCEP. UNIT.(S/.)]]*TABLA_BASE[[#This Row],[CANTIDAD (unid.)]] -> 335.18837 | AC4: =TABLA_BASE[[#This Row],[ADV UNIT. (US$) ⚠️COSTO]]+TABLA_BASE[[#This Row],[IPM UNIT. (US$) ✅CF]]+TABLA_BASE[[#This Row],[IGV UNIT. (US$) ✅CF]]+TABLA_BASE[[#This Row],[PERCEP. UNIT.(US$) ✅CF]] -> 0.21052114 | AD4: =TABLA_BASE[[#This Row],[TOTAL PAGO SUNAT UNIT.(US$)]]*TABLA_BASE[[#This Row],[CANTIDAD (unid.)]] -> 606.30088 | AE4: =TABLA_BASE[[#This Row],[TOTAL PAGO SUNAT UNIT.(US$)]]*'📋 Datos Generales'!$E$19 -> 0.78313864 | AF4: =TABLA_BASE[[#This Row],[TOTAL TRIB. UNIT.(S/.)]]*TABLA_BASE[[#This Row],[CANTIDAD (unid.)]] -> 2255.4393 | AG4: =IF('🧾 Factura Comercial'!G8=0,0,'📦 Gastos Importación'!$E$28*(IF('🧾 Tributos Aduana'!$F$6=0,0,'🧾 Factura Comercial'!I8/'🧾 Tributos Aduana'!$F$6))/'🧾 Factura Comercial'!G8) -> 0.77568663 | AH4: =TABLA_BASE[[#This Row],[GASTOS IMP. UNIT.(US$)]]*TABLA_BASE[[#This Row],[CANTIDAD (unid.)]] -> 2233.9775 | AI4: =TABLA_BASE[[#This Row],[GASTOS IMP. UNIT.(US$)]]*'📋 Datos Generales'!$E$19 -> 2.8855542 | AJ4: =TABLA_BASE[[#This Row],[GASTOS IMP. UNIT.(S/.)]]*TABLA_BASE[[#This Row],[CANTIDAD (unid.)]] -> 8310.3962 | AK4: ='🧮 Costos x Producto'!J8 -> 0.77568663 | AL4: ='🧮 Costos x Producto'!K8 -> 2.8855542 | AM4: =TABLA_BASE[[#This Row],[C/M UNIT. (S/.)]]*TABLA_BASE[[#This Row],[CANTIDAD (unid.)]] -> 8310.3962 | AN4: =IF('🧾 Factura Comercial'!G8=0,0,'🧾 Tributos Aduana'!$F$17*(IF('🧾 Tributos Aduana'!$F$6=0,0,'🧾 Factura Comercial'!I8/'🧾 Tributos Aduana'!$F$6))/'🧾 Factura Comercial'!G8) -> 0.042880502 | AO4: =IF('🧾 Factura Comercial'!G8=0,0,'🏦 Crédito Fiscal'!$C$16*(IF('🧾 Tributos Aduana'!$F$6=0,0,'🧾 Factura Comercial'!I8/'🧾 Tributos Aduana'!$F$6))/'🧾 Factura Comercial'!G8) -> 0.17081417 | AP4: =TABLA_BASE[[#This Row],[CF UNIT. ✅RECUP. (US$)]]*'📋 Datos Generales'!$E$19 -> 0.6354287 | AQ4: =TABLA_BASE[[#This Row],[CF UNIT. ✅RECUP.(S/.)]]*TABLA_BASE[[#This Row],[CANTIDAD (unid.)]] -> 1830.0346 | AR4: ='💰 Precio de Venta'!G9 -> 0.4 | AS4: ='💰 Precio de Venta'!H9 -> 4.8092571 | AT4: =TABLA_BASE[[#This Row],[VALOR VTA. UNIT.(S/.)]]*TABLA_BASE[[#This Row],[CANTIDAD (unid.)]] -> 13850.66 | AU4: ='💰 Precio de Venta'!I9 -> 5.6749233 | AV4: ='💰 Precio de Venta'!J9 -> 1.9237028 | AW4: =TABLA_BASE[[#This Row],[GANANCIA UNIT.(S/.)]]*TABLA_BASE[[#This Row],[CANTIDAD (unid.)]] -> 5540.2642 | AX4: ='💰 Precio de Venta'!K9 -> 394 | AY4: =TABLA_BASE[[#This Row],[GANANCIA UNIT.(S/.)]]*'🧾 Factura Comercial'!G8 -> 5540.2642 | AZ4: =IF(TABLA_BASE[[#This Row],[PRECIO VTA. c/IGV(S/.)]]=0,0,TABLA_BASE[[#This Row],[GANANCIA UNIT.(S/.)]]/TABLA_BASE[[#This Row],[PRECIO VTA. c/IGV(S/.)]]) -> 0.33898305 | BA4: =IF(TABLA_BASE[[#This Row],[C/M UNIT. (S/.)]]=0,0,TABLA_BASE[[#This Row],[GANANCIA UNIT.(S/.)]]/TABLA_BASE[[#This Row],[C/M UNIT. (S/.)]]) -> 0.66666667 | BB4: =IF(TABLA_BASE[[#This Row],[MARGEN %]]>=0.5,"🟢 ALTO",IF(TABLA_BASE[[#This Row],[MARGEN %]]>=0.3,"🟡 MEDIO","🔴 BAJO")) -> 🟡 MEDIO
A5: ='🧾 Factura Comercial'!E9 -> Protector Pantalla Vidrio Templado | B5: ='🧾 Factura Comercial'!F9 -> Unid. | C5: ='🧾 Factura Comercial'!G9 -> 2880 | D5: ='🧾 Factura Comercial'!H9 -> 0.4 | E5: ='🧾 Factura Comercial'!I9 -> 1152 | F5: =IF('🧾 Tributos Aduana'!$F$6=0,0,'🧾 Factura Comercial'!I9/'🧾 Tributos Aduana'!$F$6) -> 0.026397026 | G5: ='🧾 Factura Comercial'!H9*'📋 Datos Generales'!$E$19 -> 1.488 | H5: =TABLA_BASE[[#This Row],[FOB UNIT. (S/.)]]*TABLA_BASE[[#This Row],[CANTIDAD (unid.)]] -> 4285.44 | I5: =IF('🧾 Tributos Aduana'!$F$6=0,0,'🧾 Tributos Aduana'!$F$17*('🧾 Factura Comercial'!H9/'🧾 Tributos Aduana'!$F$6)) -> 0.025223825 | J5: =TABLA_BASE[[#This Row],[ADV UNIT. (US$) ⚠️COSTO]]*TABLA_BASE[[#This Row],[CANTIDAD (unid.)]] -> 72.644615 | K5: =IF('🧾 Tributos Aduana'!$F$6=0,0,'🧾 Tributos Aduana'!$F$18*('🧾 Factura Comercial'!H9/'🧾 Tributos Aduana'!$F$6)) -> 0.0089089963 | L5: =TABLA_BASE[[#This Row],[IPM UNIT. (US$) ✅CF]]*TABLA_BASE[[#This Row],[CANTIDAD (unid.)]] -> 25.657909 | M5: =IF('🧾 Tributos Aduana'!$F$6=0,0,'🧾 Tributos Aduana'!$F$19*('🧾 Factura Comercial'!H9/'🧾 Tributos Aduana'!$F$6)) -> 0.071299467 | N5: =TABLA_BASE[[#This Row],[IGV UNIT. (US$) ✅CF]]*TABLA_BASE[[#This Row],[CANTIDAD (unid.)]] -> 205.34246 | O5: =IF('🧾 Tributos Aduana'!$F$6=0,0,'🧾 Tributos Aduana'!$F$23*('🧾 Factura Comercial'!H9/'🧾 Tributos Aduana'!$F$6)) -> 0.018403677 | P5: =TABLA_BASE[[#This Row],[PERCEP. UNIT.(US$) ✅CF]]*TABLA_BASE[[#This Row],[CANTIDAD (unid.)]] -> 53.002588 | Q5: =TABLA_BASE[[#This Row],[ADV UNIT. (US$) ⚠️COSTO]]+TABLA_BASE[[#This Row],[IPM UNIT. (US$) ✅CF]]+TABLA_BASE[[#This Row],[IGV UNIT. (US$) ✅CF]] -> 0.10543229 | R5: =TABLA_BASE[[#This Row],[DEUDA ADUANERA UNIT.]]*TABLA_BASE[[#This Row],[CANTIDAD (unid.)]] -> 303.64499 | S5: =TABLA_BASE[[#This Row],[DEUDA ADUANERA UNIT.]]*'📋 Datos Generales'!$E$19 -> 0.39220811 | T5: =TABLA_BASE[[#This Row],[DEUDA ADUANERA TOTAL]]*'📋 Datos Generales'!$E$19 -> 1129.5594 | U5: =TABLA_BASE[[#This Row],[ADV UNIT. (US$) ⚠️COSTO]]*'📋 Datos Generales'!$E$19 -> 0.093832628 | V5: =TABLA_BASE[[#This Row],[ADV UNIT. (S/.)]]*TABLA_BASE[[#This Row],[CANTIDAD (unid.)]] -> 270.23797 | W5: =TABLA_BASE[[#This Row],[IPM UNIT. (US$) ✅CF]]*'📋 Datos Generales'!$E$19 -> 0.033141466 | X5: =TABLA_BASE[[#This Row],[IPM UNIT. (S/.)]]*TABLA_BASE[[#This Row],[CANTIDAD (unid.)]] -> 95.447422 | Y5: =TABLA_BASE[[#This Row],[IGV UNIT. (US$) ✅CF]]*'📋 Datos Generales'!$E$19 -> 0.26523402 | Z5: =TABLA_BASE[[#This Row],[IGV UNIT. (S/.)]]*TABLA_BASE[[#This Row],[CANTIDAD (unid.)]] -> 763.87397 | AA5: =TABLA_BASE[[#This Row],[PERCEP. UNIT.(US$) ✅CF]]*'📋 Datos Generales'!$E$19 -> 0.068461677 | AB5: =TABLA_BASE[[#This Row],[PERCEP. UNIT.(S/.)]]*TABLA_BASE[[#This Row],[CANTIDAD (unid.)]] -> 197.16963 | AC5: =TABLA_BASE[[#This Row],[ADV UNIT. (US$) ⚠️COSTO]]+TABLA_BASE[[#This Row],[IPM UNIT. (US$) ✅CF]]+TABLA_BASE[[#This Row],[IGV UNIT. (US$) ✅CF]]+TABLA_BASE[[#This Row],[PERCEP. UNIT.(US$) ✅CF]] -> 0.12383596 | AD5: =TABLA_BASE[[#This Row],[TOTAL PAGO SUNAT UNIT.(US$)]]*TABLA_BASE[[#This Row],[CANTIDAD (unid.)]] -> 356.64758 | AE5: =TABLA_BASE[[#This Row],[TOTAL PAGO SUNAT UNIT.(US$)]]*'📋 Datos Generales'!$E$19 -> 0.46066979 | AF5: =TABLA_BASE[[#This Row],[TOTAL TRIB. UNIT.(S/.)]]*TABLA_BASE[[#This Row],[CANTIDAD (unid.)]] -> 1326.729 | AG5: =IF('🧾 Factura Comercial'!G9=0,0,'📦 Gastos Importación'!$E$28*(IF('🧾 Tributos Aduana'!$F$6=0,0,'🧾 Factura Comercial'!I9/'🧾 Tributos Aduana'!$F$6))/'🧾 Factura Comercial'!G9) -> 0.45628625 | AH5: =TABLA_BASE[[#This Row],[GASTOS IMP. UNIT.(US$)]]*TABLA_BASE[[#This Row],[CANTIDAD (unid.)]] -> 1314.1044 | AI5: =TABLA_BASE[[#This Row],[GASTOS IMP. UNIT.(US$)]]*'📋 Datos Generales'!$E$19 -> 1.6973849 | AJ5: =TABLA_BASE[[#This Row],[GASTOS IMP. UNIT.(S/.)]]*TABLA_BASE[[#This Row],[CANTIDAD (unid.)]] -> 4888.4684 | AK5: ='🧮 Costos x Producto'!J9 -> 0.45628625 | AL5: ='🧮 Costos x Producto'!K9 -> 1.6973849 | AM5: =TABLA_BASE[[#This Row],[C/M UNIT. (S/.)]]*TABLA_BASE[[#This Row],[CANTIDAD (unid.)]] -> 4888.4684 | AN5: =IF('🧾 Factura Comercial'!G9=0,0,'🧾 Tributos Aduana'!$F$17*(IF('🧾 Tributos Aduana'!$F$6=0,0,'🧾 Factura Comercial'!I9/'🧾 Tributos Aduana'!$F$6))/'🧾 Factura Comercial'!G9) -> 0.025223825 | AO5: =IF('🧾 Factura Comercial'!G9=0,0,'🏦 Crédito Fiscal'!$C$16*(IF('🧾 Tributos Aduana'!$F$6=0,0,'🧾 Factura Comercial'!I9/'🧾 Tributos Aduana'!$F$6))/'🧾 Factura Comercial'!G9) -> 0.10047892 | AP5: =TABLA_BASE[[#This Row],[CF UNIT. ✅RECUP. (US$)]]*'📋 Datos Generales'!$E$19 -> 0.37378159 | AQ5: =TABLA_BASE[[#This Row],[CF UNIT. ✅RECUP.(S/.)]]*TABLA_BASE[[#This Row],[CANTIDAD (unid.)]] -> 1076.491 | AR5: ='💰 Precio de Venta'!G10 -> 0.4 | AS5: ='💰 Precio de Venta'!H10 -> 2.8289748 | AT5: =TABLA_BASE[[#This Row],[VALOR VTA. UNIT.(S/.)]]*TABLA_BASE[[#This Row],[CANTIDAD (unid.)]] -> 8147.4473 | AU5: ='💰 Precio de Venta'!I10 -> 3.3381902 | AV5: ='💰 Precio de Venta'!J10 -> 1.1315899 | AW5: =TABLA_BASE[[#This Row],[GANANCIA UNIT.(S/.)]]*TABLA_BASE[[#This Row],[CANTIDAD (unid.)]] -> 3258.9789 | AX5: ='💰 Precio de Venta'!K10 -> 394 | AY5: =TABLA_BASE[[#This Row],[GANANCIA UNIT.(S/.)]]*'🧾 Factura Comercial'!G9 -> 3258.9789 | AZ5: =IF(TABLA_BASE[[#This Row],[PRECIO VTA. c/IGV(S/.)]]=0,0,TABLA_BASE[[#This Row],[GANANCIA UNIT.(S/.)]]/TABLA_BASE[[#This Row],[PRECIO VTA. c/IGV(S/.)]]) -> 0.33898305 | BA5: =IF(TABLA_BASE[[#This Row],[C/M UNIT. (S/.)]]=0,0,TABLA_BASE[[#This Row],[GANANCIA UNIT.(S/.)]]/TABLA_BASE[[#This Row],[C/M UNIT. (S/.)]]) -> 0.66666667 | BB5: =IF(TABLA_BASE[[#This Row],[MARGEN %]]>=0.5,"🟢 ALTO",IF(TABLA_BASE[[#This Row],[MARGEN %]]>=0.3,"🟡 MEDIO","🔴 BAJO")) -> 🟡 MEDIO
A6: ='🧾 Factura Comercial'!E10 -> Audífonos In-Ear con Micrófono | B6: ='🧾 Factura Comercial'!F10 -> Unid. | C6: ='🧾 Factura Comercial'!G10 -> 10224 | D6: ='🧾 Factura Comercial'!H10 -> 0.34 | E6: ='🧾 Factura Comercial'!I10 -> 3476.16 | F6: =IF('🧾 Tributos Aduana'!$F$6=0,0,'🧾 Factura Comercial'!I10/'🧾 Tributos Aduana'!$F$6) -> 0.079653026 | G6: ='🧾 Factura Comercial'!H10*'📋 Datos Generales'!$E$19 -> 1.2648 | H6: =TABLA_BASE[[#This Row],[FOB UNIT. (S/.)]]*TABLA_BASE[[#This Row],[CANTIDAD (unid.)]] -> 12931.315 | I6: =IF('🧾 Tributos Aduana'!$F$6=0,0,'🧾 Tributos Aduana'!$F$17*('🧾 Factura Comercial'!H10/'🧾 Tributos Aduana'!$F$6)) -> 0.021440251 | J6: =TABLA_BASE[[#This Row],[ADV UNIT. (US$) ⚠️COSTO]]*TABLA_BASE[[#This Row],[CANTIDAD (unid.)]] -> 219.20513 | K6: =IF('🧾 Tributos Aduana'!$F$6=0,0,'🧾 Tributos Aduana'!$F$18*('🧾 Factura Comercial'!H10/'🧾 Tributos Aduana'!$F$6)) -> 0.0075726468 | L6: =TABLA_BASE[[#This Row],[IPM UNIT. (US$) ✅CF]]*TABLA_BASE[[#This Row],[CANTIDAD (unid.)]] -> 77.422741 | M6: =IF('🧾 Tributos Aduana'!$F$6=0,0,'🧾 Tributos Aduana'!$F$19*('🧾 Factura Comercial'!H10/'🧾 Tributos Aduana'!$F$6)) -> 0.060604547 | N6: =TABLA_BASE[[#This Row],[IGV UNIT. (US$) ✅CF]]*TABLA_BASE[[#This Row],[CANTIDAD (unid.)]] -> 619.62089 | O6: =IF('🧾 Tributos Aduana'!$F$6=0,0,'🧾 Tributos Aduana'!$F$23*('🧾 Factura Comercial'!H10/'🧾 Tributos Aduana'!$F$6)) -> 0.015643125 | P6: =TABLA_BASE[[#This Row],[PERCEP. UNIT.(US$) ✅CF]]*TABLA_BASE[[#This Row],[CANTIDAD (unid.)]] -> 159.93531 | Q6: =TABLA_BASE[[#This Row],[ADV UNIT. (US$) ⚠️COSTO]]+TABLA_BASE[[#This Row],[IPM UNIT. (US$) ✅CF]]+TABLA_BASE[[#This Row],[IGV UNIT. (US$) ✅CF]] -> 0.089617445 | R6: =TABLA_BASE[[#This Row],[DEUDA ADUANERA UNIT.]]*TABLA_BASE[[#This Row],[CANTIDAD (unid.)]] -> 916.24876 | S6: =TABLA_BASE[[#This Row],[DEUDA ADUANERA UNIT.]]*'📋 Datos Generales'!$E$19 -> 0.33337689 | T6: =TABLA_BASE[[#This Row],[DEUDA ADUANERA TOTAL]]*'📋 Datos Generales'!$E$19 -> 3408.4454 | U6: =TABLA_BASE[[#This Row],[ADV UNIT. (US$) ⚠️COSTO]]*'📋 Datos Generales'!$E$19 -> 0.079757734 | V6: =TABLA_BASE[[#This Row],[ADV UNIT. (S/.)]]*TABLA_BASE[[#This Row],[CANTIDAD (unid.)]] -> 815.44307 | W6: =TABLA_BASE[[#This Row],[IPM UNIT. (US$) ✅CF]]*'📋 Datos Generales'!$E$19 -> 0.028170246 | X6: =TABLA_BASE[[#This Row],[IPM UNIT. (S/.)]]*TABLA_BASE[[#This Row],[CANTIDAD (unid.)]] -> 288.0126 | Y6: =TABLA_BASE[[#This Row],[IGV UNIT. (US$) ✅CF]]*'📋 Datos Generales'!$E$19 -> 0.22544891 | Z6: =TABLA_BASE[[#This Row],[IGV UNIT. (S/.)]]*TABLA_BASE[[#This Row],[CANTIDAD (unid.)]] -> 2304.9897 | AA6: =TABLA_BASE[[#This Row],[PERCEP. UNIT.(US$) ✅CF]]*'📋 Datos Generales'!$E$19 -> 0.058192425 | AB6: =TABLA_BASE[[#This Row],[PERCEP. UNIT.(S/.)]]*TABLA_BASE[[#This Row],[CANTIDAD (unid.)]] -> 594.95935 | AC6: =TABLA_BASE[[#This Row],[ADV UNIT. (US$) ⚠️COSTO]]+TABLA_BASE[[#This Row],[IPM UNIT. (US$) ✅CF]]+TABLA_BASE[[#This Row],[IGV UNIT. (US$) ✅CF]]+TABLA_BASE[[#This Row],[PERCEP. UNIT.(US$) ✅CF]] -> 0.10526057 | AD6: =TABLA_BASE[[#This Row],[TOTAL PAGO SUNAT UNIT.(US$)]]*TABLA_BASE[[#This Row],[CANTIDAD (unid.)]] -> 1076.1841 | AE6: =TABLA_BASE[[#This Row],[TOTAL PAGO SUNAT UNIT.(US$)]]*'📋 Datos Generales'!$E$19 -> 0.39156932 | AF6: =TABLA_BASE[[#This Row],[TOTAL TRIB. UNIT.(S/.)]]*TABLA_BASE[[#This Row],[CANTIDAD (unid.)]] -> 4003.4047 | AG6: =IF('🧾 Factura Comercial'!G10=0,0,'📦 Gastos Importación'!$E$28*(IF('🧾 Tributos Aduana'!$F$6=0,0,'🧾 Factura Comercial'!I10/'🧾 Tributos Aduana'!$F$6))/'🧾 Factura Comercial'!G10) -> 0.38784331 | AH6: =TABLA_BASE[[#This Row],[GASTOS IMP. UNIT.(US$)]]*TABLA_BASE[[#This Row],[CANTIDAD (unid.)]] -> 3965.31 | AI6: =TABLA_BASE[[#This Row],[GASTOS IMP. UNIT.(US$)]]*'📋 Datos Generales'!$E$19 -> 1.4427771 | AJ6: =TABLA_BASE[[#This Row],[GASTOS IMP. UNIT.(S/.)]]*TABLA_BASE[[#This Row],[CANTIDAD (unid.)]] -> 14750.953 | AK6: ='🧮 Costos x Producto'!J10 -> 0.38784331 | AL6: ='🧮 Costos x Producto'!K10 -> 1.4427771 | AM6: =TABLA_BASE[[#This Row],[C/M UNIT. (S/.)]]*TABLA_BASE[[#This Row],[CANTIDAD (unid.)]] -> 14750.953 | AN6: =IF('🧾 Factura Comercial'!G10=0,0,'🧾 Tributos Aduana'!$F$17*(IF('🧾 Tributos Aduana'!$F$6=0,0,'🧾 Factura Comercial'!I10/'🧾 Tributos Aduana'!$F$6))/'🧾 Factura Comercial'!G10) -> 0.021440251 | AO6: =IF('🧾 Factura Comercial'!G10=0,0,'🏦 Crédito Fiscal'!$C$16*(IF('🧾 Tributos Aduana'!$F$6=0,0,'🧾 Factura Comercial'!I10/'🧾 Tributos Aduana'!$F$6))/'🧾 Factura Comercial'!G10) -> 0.085407083 | AP6: =TABLA_BASE[[#This Row],[CF UNIT. ✅RECUP. (US$)]]*'📋 Datos Generales'!$E$19 -> 0.31771435 | AQ6: =TABLA_BASE[[#This Row],[CF UNIT. ✅RECUP.(S/.)]]*TABLA_BASE[[#This Row],[CANTIDAD (unid.)]] -> 3248.3115 | AR6: ='💰 Precio de Venta'!G11 -> 0.4 | AS6: ='💰 Precio de Venta'!H11 -> 2.4046285 | AT6: =TABLA_BASE[[#This Row],[VALOR VTA. UNIT.(S/.)]]*TABLA_BASE[[#This Row],[CANTIDAD (unid.)]] -> 24584.922 | AU6: ='💰 Precio de Venta'!I11 -> 2.8374617 | AV6: ='💰 Precio de Venta'!J11 -> 0.96185142 | AW6: =TABLA_BASE[[#This Row],[GANANCIA UNIT.(S/.)]]*TABLA_BASE[[#This Row],[CANTIDAD (unid.)]] -> 9833.9689 | AX6: ='💰 Precio de Venta'!K11 -> 1398 | AY6: =TABLA_BASE[[#This Row],[GANANCIA UNIT.(S/.)]]*'🧾 Factura Comercial'!G10 -> 9833.9689 | AZ6: =IF(TABLA_BASE[[#This Row],[PRECIO VTA. c/IGV(S/.)]]=0,0,TABLA_BASE[[#This Row],[GANANCIA UNIT.(S/.)]]/TABLA_BASE[[#This Row],[PRECIO VTA. c/IGV(S/.)]]) -> 0.33898305 | BA6: =IF(TABLA_BASE[[#This Row],[C/M UNIT. (S/.)]]=0,0,TABLA_BASE[[#This Row],[GANANCIA UNIT.(S/.)]]/TABLA_BASE[[#This Row],[C/M UNIT. (S/.)]]) -> 0.66666667 | BB6: =IF(TABLA_BASE[[#This Row],[MARGEN %]]>=0.5,"🟢 ALTO",IF(TABLA_BASE[[#This Row],[MARGEN %]]>=0.3,"🟡 MEDIO","🔴 BAJO")) -> 🟡 MEDIO
A7: ='🧾 Factura Comercial'!E11 -> Cable Micro USB 2m Nylon | B7: ='🧾 Factura Comercial'!F11 -> Unid. | C7: ='🧾 Factura Comercial'!G11 -> 8640 | D7: ='🧾 Factura Comercial'!H11 -> 0.26 | E7: ='🧾 Factura Comercial'!I11 -> 2246.4 | F7: =IF('🧾 Tributos Aduana'!$F$6=0,0,'🧾 Factura Comercial'!I11/'🧾 Tributos Aduana'!$F$6) -> 0.051474201 | G7: ='🧾 Factura Comercial'!H11*'📋 Datos Generales'!$E$19 -> 0.9672 | H7: =TABLA_BASE[[#This Row],[FOB UNIT. (S/.)]]*TABLA_BASE[[#This Row],[CANTIDAD (unid.)]] -> 8356.608 | I7: =IF('🧾 Tributos Aduana'!$F$6=0,0,'🧾 Tributos Aduana'!$F$17*('🧾 Factura Comercial'!H11/'🧾 Tributos Aduana'!$F$6)) -> 0.016395486 | J7: =TABLA_BASE[[#This Row],[ADV UNIT. (US$) ⚠️COSTO]]*TABLA_BASE[[#This Row],[CANTIDAD (unid.)]] -> 141.657 | K7: =IF('🧾 Tributos Aduana'!$F$6=0,0,'🧾 Tributos Aduana'!$F$18*('🧾 Factura Comercial'!H11/'🧾 Tributos Aduana'!$F$6)) -> 0.0057908476 | L7: =TABLA_BASE[[#This Row],[IPM UNIT. (US$) ✅CF]]*TABLA_BASE[[#This Row],[CANTIDAD (unid.)]] -> 50.032923 | M7: =IF('🧾 Tributos Aduana'!$F$6=0,0,'🧾 Tributos Aduana'!$F$19*('🧾 Factura Comercial'!H11/'🧾 Tributos Aduana'!$F$6)) -> 0.046344654 | N7: =TABLA_BASE[[#This Row],[IGV UNIT. (US$) ✅CF]]*TABLA_BASE[[#This Row],[CANTIDAD (unid.)]] -> 400.41781 | O7: =IF('🧾 Tributos Aduana'!$F$6=0,0,'🧾 Tributos Aduana'!$F$23*('🧾 Factura Comercial'!H11/'🧾 Tributos Aduana'!$F$6)) -> 0.01196239 | P7: =TABLA_BASE[[#This Row],[PERCEP. UNIT.(US$) ✅CF]]*TABLA_BASE[[#This Row],[CANTIDAD (unid.)]] -> 103.35505 | Q7: =TABLA_BASE[[#This Row],[ADV UNIT. (US$) ⚠️COSTO]]+TABLA_BASE[[#This Row],[IPM UNIT. (US$) ✅CF]]+TABLA_BASE[[#This Row],[IGV UNIT. (US$) ✅CF]] -> 0.068530987 | R7: =TABLA_BASE[[#This Row],[DEUDA ADUANERA UNIT.]]*TABLA_BASE[[#This Row],[CANTIDAD (unid.)]] -> 592.10773 | S7: =TABLA_BASE[[#This Row],[DEUDA ADUANERA UNIT.]]*'📋 Datos Generales'!$E$19 -> 0.25493527 | T7: =TABLA_BASE[[#This Row],[DEUDA ADUANERA TOTAL]]*'📋 Datos Generales'!$E$19 -> 2202.6408 | U7: =TABLA_BASE[[#This Row],[ADV UNIT. (US$) ⚠️COSTO]]*'📋 Datos Generales'!$E$19 -> 0.060991208 | V7: =TABLA_BASE[[#This Row],[ADV UNIT. (S/.)]]*TABLA_BASE[[#This Row],[CANTIDAD (unid.)]] -> 526.96404 | W7: =TABLA_BASE[[#This Row],[IPM UNIT. (US$) ✅CF]]*'📋 Datos Generales'!$E$19 -> 0.021541953 | X7: =TABLA_BASE[[#This Row],[IPM UNIT. (S/.)]]*TABLA_BASE[[#This Row],[CANTIDAD (unid.)]] -> 186.12247 | Y7: =TABLA_BASE[[#This Row],[IGV UNIT. (US$) ✅CF]]*'📋 Datos Generales'!$E$19 -> 0.17240211 | Z7: =TABLA_BASE[[#This Row],[IGV UNIT. (S/.)]]*TABLA_BASE[[#This Row],[CANTIDAD (unid.)]] -> 1489.5542 | AA7: =TABLA_BASE[[#This Row],[PERCEP. UNIT.(US$) ✅CF]]*'📋 Datos Generales'!$E$19 -> 0.04450009 | AB7: =TABLA_BASE[[#This Row],[PERCEP. UNIT.(S/.)]]*TABLA_BASE[[#This Row],[CANTIDAD (unid.)]] -> 384.48078 | AC7: =TABLA_BASE[[#This Row],[ADV UNIT. (US$) ⚠️COSTO]]+TABLA_BASE[[#This Row],[IPM UNIT. (US$) ✅CF]]+TABLA_BASE[[#This Row],[IGV UNIT. (US$) ✅CF]]+TABLA_BASE[[#This Row],[PERCEP. UNIT.(US$) ✅CF]] -> 0.080493377 | AD7: =TABLA_BASE[[#This Row],[TOTAL PAGO SUNAT UNIT.(US$)]]*TABLA_BASE[[#This Row],[CANTIDAD (unid.)]] -> 695.46278 | AE7: =TABLA_BASE[[#This Row],[TOTAL PAGO SUNAT UNIT.(US$)]]*'📋 Datos Generales'!$E$19 -> 0.29943536 | AF7: =TABLA_BASE[[#This Row],[TOTAL TRIB. UNIT.(S/.)]]*TABLA_BASE[[#This Row],[CANTIDAD (unid.)]] -> 2587.1215 | AG7: =IF('🧾 Factura Comercial'!G11=0,0,'📦 Gastos Importación'!$E$28*(IF('🧾 Tributos Aduana'!$F$6=0,0,'🧾 Factura Comercial'!I11/'🧾 Tributos Aduana'!$F$6))/'🧾 Factura Comercial'!G11) -> 0.29658606 | AH7: =TABLA_BASE[[#This Row],[GASTOS IMP. UNIT.(US$)]]*TABLA_BASE[[#This Row],[CANTIDAD (unid.)]] -> 2562.5036 | AI7: =TABLA_BASE[[#This Row],[GASTOS IMP. UNIT.(US$)]]*'📋 Datos Generales'!$E$19 -> 1.1033002 | AJ7: =TABLA_BASE[[#This Row],[GASTOS IMP. UNIT.(S/.)]]*TABLA_BASE[[#This Row],[CANTIDAD (unid.)]] -> 9532.5133 | AK7: ='🧮 Costos x Producto'!J11 -> 0.29658606 | AL7: ='🧮 Costos x Producto'!K11 -> 1.1033002 | AM7: =TABLA_BASE[[#This Row],[C/M UNIT. (S/.)]]*TABLA_BASE[[#This Row],[CANTIDAD (unid.)]] -> 9532.5133 | AN7: =IF('🧾 Factura Comercial'!G11=0,0,'🧾 Tributos Aduana'!$F$17*(IF('🧾 Tributos Aduana'!$F$6=0,0,'🧾 Factura Comercial'!I11/'🧾 Tributos Aduana'!$F$6))/'🧾 Factura Comercial'!G11) -> 0.016395486 | AO7: =IF('🧾 Factura Comercial'!G11=0,0,'🏦 Crédito Fiscal'!$C$16*(IF('🧾 Tributos Aduana'!$F$6=0,0,'🧾 Factura Comercial'!I11/'🧾 Tributos Aduana'!$F$6))/'🧾 Factura Comercial'!G11) -> 0.065311299 | AP7: =TABLA_BASE[[#This Row],[CF UNIT. ✅RECUP. (US$)]]*'📋 Datos Generales'!$E$19 -> 0.24295803 | AQ7: =TABLA_BASE[[#This Row],[CF UNIT. ✅RECUP.(S/.)]]*TABLA_BASE[[#This Row],[CANTIDAD (unid.)]] -> 2099.1574 | AR7: ='💰 Precio de Venta'!G12 -> 0.4 | AS7: ='💰 Precio de Venta'!H12 -> 1.8388336 | AT7: =TABLA_BASE[[#This Row],[VALOR VTA. UNIT.(S/.)]]*TABLA_BASE[[#This Row],[CANTIDAD (unid.)]] -> 15887.522 | AU7: ='💰 Precio de Venta'!I12 -> 2.1698236 | AV7: ='💰 Precio de Venta'!J12 -> 0.73553344 | AW7: =TABLA_BASE[[#This Row],[GANANCIA UNIT.(S/.)]]*TABLA_BASE[[#This Row],[CANTIDAD (unid.)]] -> 6355.0089 | AX7: ='💰 Precio de Venta'!K12 -> 1181 | AY7: =TABLA_BASE[[#This Row],[GANANCIA UNIT.(S/.)]]*'🧾 Factura Comercial'!G11 -> 6355.0089 | AZ7: =IF(TABLA_BASE[[#This Row],[PRECIO VTA. c/IGV(S/.)]]=0,0,TABLA_BASE[[#This Row],[GANANCIA UNIT.(S/.)]]/TABLA_BASE[[#This Row],[PRECIO VTA. c/IGV(S/.)]]) -> 0.33898305 | BA7: =IF(TABLA_BASE[[#This Row],[C/M UNIT. (S/.)]]=0,0,TABLA_BASE[[#This Row],[GANANCIA UNIT.(S/.)]]/TABLA_BASE[[#This Row],[C/M UNIT. (S/.)]]) -> 0.66666667 | BB7: =IF(TABLA_BASE[[#This Row],[MARGEN %]]>=0.5,"🟢 ALTO",IF(TABLA_BASE[[#This Row],[MARGEN %]]>=0.3,"🟡 MEDIO","🔴 BAJO")) -> 🟡 MEDIO
A8: ='🧾 Factura Comercial'!E12 -> Soporte Anillo Pop Socket Metálico | B8: ='🧾 Factura Comercial'!F12 -> Unid. | C8: ='🧾 Factura Comercial'!G12 -> 2160 | D8: ='🧾 Factura Comercial'!H12 -> 0.29 | E8: ='🧾 Factura Comercial'!I12 -> 626.4 | F8: =IF('🧾 Tributos Aduana'!$F$6=0,0,'🧾 Factura Comercial'!I12/'🧾 Tributos Aduana'!$F$6) -> 0.014353383 | G8: ='🧾 Factura Comercial'!H12*'📋 Datos Generales'!$E$19 -> 1.0788 | H8: =TABLA_BASE[[#This Row],[FOB UNIT. (S/.)]]*TABLA_BASE[[#This Row],[CANTIDAD (unid.)]] -> 2330.208 | I8: =IF('🧾 Tributos Aduana'!$F$6=0,0,'🧾 Tributos Aduana'!$F$17*('🧾 Factura Comercial'!H12/'🧾 Tributos Aduana'!$F$6)) -> 0.018287273 | J8: =TABLA_BASE[[#This Row],[ADV UNIT. (US$) ⚠️COSTO]]*TABLA_BASE[[#This Row],[CANTIDAD (unid.)]] -> 39.50051 | K8: =IF('🧾 Tributos Aduana'!$F$6=0,0,'🧾 Tributos Aduana'!$F$18*('🧾 Factura Comercial'!H12/'🧾 Tributos Aduana'!$F$6)) -> 0.0064590223 | L8: =TABLA_BASE[[#This Row],[IPM UNIT. (US$) ✅CF]]*TABLA_BASE[[#This Row],[CANTIDAD (unid.)]] -> 13.951488 | M8: =IF('🧾 Tributos Aduana'!$F$6=0,0,'🧾 Tributos Aduana'!$F$19*('🧾 Factura Comercial'!H12/'🧾 Tributos Aduana'!$F$6)) -> 0.051692114 | N8: =TABLA_BASE[[#This Row],[IGV UNIT. (US$) ✅CF]]*TABLA_BASE[[#This Row],[CANTIDAD (unid.)]] -> 111.65497 | O8: =IF('🧾 Tributos Aduana'!$F$6=0,0,'🧾 Tributos Aduana'!$F$23*('🧾 Factura Comercial'!H12/'🧾 Tributos Aduana'!$F$6)) -> 0.013342665 | P8: =TABLA_BASE[[#This Row],[PERCEP. UNIT.(US$) ✅CF]]*TABLA_BASE[[#This Row],[CANTIDAD (unid.)]] -> 28.820157 | Q8: =TABLA_BASE[[#This Row],[ADV UNIT. (US$) ⚠️COSTO]]+TABLA_BASE[[#This Row],[IPM UNIT. (US$) ✅CF]]+TABLA_BASE[[#This Row],[IGV UNIT. (US$) ✅CF]] -> 0.076438409 | R8: =TABLA_BASE[[#This Row],[DEUDA ADUANERA UNIT.]]*TABLA_BASE[[#This Row],[CANTIDAD (unid.)]] -> 165.10696 | S8: =TABLA_BASE[[#This Row],[DEUDA ADUANERA UNIT.]]*'📋 Datos Generales'!$E$19 -> 0.28435088 | T8: =TABLA_BASE[[#This Row],[DEUDA ADUANERA TOTAL]]*'📋 Datos Generales'!$E$19 -> 614.1979 | U8: =TABLA_BASE[[#This Row],[ADV UNIT. (US$) ⚠️COSTO]]*'📋 Datos Generales'!$E$19 -> 0.068028655 | V8: =TABLA_BASE[[#This Row],[ADV UNIT. (S/.)]]*TABLA_BASE[[#This Row],[CANTIDAD (unid.)]] -> 146.9419 | W8: =TABLA_BASE[[#This Row],[IPM UNIT. (US$) ✅CF]]*'📋 Datos Generales'!$E$19 -> 0.024027563 | X8: =TABLA_BASE[[#This Row],[IPM UNIT. (S/.)]]*TABLA_BASE[[#This Row],[CANTIDAD (unid.)]] -> 51.899536 | Y8: =TABLA_BASE[[#This Row],[IGV UNIT. (US$) ✅CF]]*'📋 Datos Generales'!$E$19 -> 0.19229466 | Z8: =TABLA_BASE[[#This Row],[IGV UNIT. (S/.)]]*TABLA_BASE[[#This Row],[CANTIDAD (unid.)]] -> 415.35647 | AA8: =TABLA_BASE[[#This Row],[PERCEP. UNIT.(US$) ✅CF]]*'📋 Datos Generales'!$E$19 -> 0.049634716 | AB8: =TABLA_BASE[[#This Row],[PERCEP. UNIT.(S/.)]]*TABLA_BASE[[#This Row],[CANTIDAD (unid.)]] -> 107.21099 | AC8: =TABLA_BASE[[#This Row],[ADV UNIT. (US$) ⚠️COSTO]]+TABLA_BASE[[#This Row],[IPM UNIT. (US$) ✅CF]]+TABLA_BASE[[#This Row],[IGV UNIT. (US$) ✅CF]]+TABLA_BASE[[#This Row],[PERCEP. UNIT.(US$) ✅CF]] -> 0.089781074 | AD8: =TABLA_BASE[[#This Row],[TOTAL PAGO SUNAT UNIT.(US$)]]*TABLA_BASE[[#This Row],[CANTIDAD (unid.)]] -> 193.92712 | AE8: =TABLA_BASE[[#This Row],[TOTAL PAGO SUNAT UNIT.(US$)]]*'📋 Datos Generales'!$E$19 -> 0.3339856 | AF8: =TABLA_BASE[[#This Row],[TOTAL TRIB. UNIT.(S/.)]]*TABLA_BASE[[#This Row],[CANTIDAD (unid.)]] -> 721.40889 | AG8: =IF('🧾 Factura Comercial'!G12=0,0,'📦 Gastos Importación'!$E$28*(IF('🧾 Tributos Aduana'!$F$6=0,0,'🧾 Factura Comercial'!I12/'🧾 Tributos Aduana'!$F$6))/'🧾 Factura Comercial'!G12) -> 0.33080753 | AH8: =TABLA_BASE[[#This Row],[GASTOS IMP. UNIT.(US$)]]*TABLA_BASE[[#This Row],[CANTIDAD (unid.)]] -> 714.54427 | AI8: =TABLA_BASE[[#This Row],[GASTOS IMP. UNIT.(US$)]]*'📋 Datos Generales'!$E$19 -> 1.230604 | AJ8: =TABLA_BASE[[#This Row],[GASTOS IMP. UNIT.(S/.)]]*TABLA_BASE[[#This Row],[CANTIDAD (unid.)]] -> 2658.1047 | AK8: ='🧮 Costos x Producto'!J12 -> 0.33080753 | AL8: ='🧮 Costos x Producto'!K12 -> 1.230604 | AM8: =TABLA_BASE[[#This Row],[C/M UNIT. (S/.)]]*TABLA_BASE[[#This Row],[CANTIDAD (unid.)]] -> 2658.1047 | AN8: =IF('🧾 Factura Comercial'!G12=0,0,'🧾 Tributos Aduana'!$F$17*(IF('🧾 Tributos Aduana'!$F$6=0,0,'🧾 Factura Comercial'!I12/'🧾 Tributos Aduana'!$F$6))/'🧾 Factura Comercial'!G12) -> 0.018287273 | AO8: =IF('🧾 Factura Comercial'!G12=0,0,'🏦 Crédito Fiscal'!$C$16*(IF('🧾 Tributos Aduana'!$F$6=0,0,'🧾 Factura Comercial'!I12/'🧾 Tributos Aduana'!$F$6))/'🧾 Factura Comercial'!G12) -> 0.072847218 | AP8: =TABLA_BASE[[#This Row],[CF UNIT. ✅RECUP. (US$)]]*'📋 Datos Generales'!$E$19 -> 0.27099165 | AQ8: =TABLA_BASE[[#This Row],[CF UNIT. ✅RECUP.(S/.)]]*TABLA_BASE[[#This Row],[CANTIDAD (unid.)]] -> 585.34196 | AR8: ='💰 Precio de Venta'!G13 -> 0.4 | AS8: ='💰 Precio de Venta'!H13 -> 2.0510067 | AT8: =TABLA_BASE[[#This Row],[VALOR VTA. UNIT.(S/.)]]*TABLA_BASE[[#This Row],[CANTIDAD (unid.)]] -> 4430.1745 | AU8: ='💰 Precio de Venta'!I13 -> 2.4201879 | AV8: ='💰 Precio de Venta'!J13 -> 0.82040268 | AW8: =TABLA_BASE[[#This Row],[GANANCIA UNIT.(S/.)]]*TABLA_BASE[[#This Row],[CANTIDAD (unid.)]] -> 1772.0698 | AX8: ='💰 Precio de Venta'!K13 -> 296 | AY8: =TABLA_BASE[[#This Row],[GANANCIA UNIT.(S/.)]]*'🧾 Factura Comercial'!G12 -> 1772.0698 | AZ8: =IF(TABLA_BASE[[#This Row],[PRECIO VTA. c/IGV(S/.)]]=0,0,TABLA_BASE[[#This Row],[GANANCIA UNIT.(S/.)]]/TABLA_BASE[[#This Row],[PRECIO VTA. c/IGV(S/.)]]) -> 0.33898305 | BA8: =IF(TABLA_BASE[[#This Row],[C/M UNIT. (S/.)]]=0,0,TABLA_BASE[[#This Row],[GANANCIA UNIT.(S/.)]]/TABLA_BASE[[#This Row],[C/M UNIT. (S/.)]]) -> 0.66666667 | BB8: =IF(TABLA_BASE[[#This Row],[MARGEN %]]>=0.5,"🟢 ALTO",IF(TABLA_BASE[[#This Row],[MARGEN %]]>=0.3,"🟡 MEDIO","🔴 BAJO")) -> 🟡 MEDIO
A9: ='🧾 Factura Comercial'!E13 -> Cargador Inalámbrico 15W Qi | B9: ='🧾 Factura Comercial'!F13 -> Unid. | C9: ='🧾 Factura Comercial'!G13 -> 240 | D9: ='🧾 Factura Comercial'!H13 -> 5.71 | E9: ='🧾 Factura Comercial'!I13 -> 1370.4 | F9: =IF('🧾 Tributos Aduana'!$F$6=0,0,'🧾 Factura Comercial'!I13/'🧾 Tributos Aduana'!$F$6) -> 0.031401462 | G9: ='🧾 Factura Comercial'!H13*'📋 Datos Generales'!$E$19 -> 21.2412 | H9: =TABLA_BASE[[#This Row],[FOB UNIT. (S/.)]]*TABLA_BASE[[#This Row],[CANTIDAD (unid.)]] -> 5097.888 | I9: =IF('🧾 Tributos Aduana'!$F$6=0,0,'🧾 Tributos Aduana'!$F$17*('🧾 Factura Comercial'!H13/'🧾 Tributos Aduana'!$F$6)) -> 0.3600701 | J9: =TABLA_BASE[[#This Row],[ADV UNIT. (US$) ⚠️COSTO]]*TABLA_BASE[[#This Row],[CANTIDAD (unid.)]] -> 86.416824 | K9: =IF('🧾 Tributos Aduana'!$F$6=0,0,'🧾 Tributos Aduana'!$F$18*('🧾 Factura Comercial'!H13/'🧾 Tributos Aduana'!$F$6)) -> 0.12717592 | L9: =TABLA_BASE[[#This Row],[IPM UNIT. (US$) ✅CF]]*TABLA_BASE[[#This Row],[CANTIDAD (unid.)]] -> 30.522221 | M9: =IF('🧾 Tributos Aduana'!$F$6=0,0,'🧾 Tributos Aduana'!$F$19*('🧾 Factura Comercial'!H13/'🧾 Tributos Aduana'!$F$6)) -> 1.0177999 | N9: =TABLA_BASE[[#This Row],[IGV UNIT. (US$) ✅CF]]*TABLA_BASE[[#This Row],[CANTIDAD (unid.)]] -> 244.27197 | O9: =IF('🧾 Tributos Aduana'!$F$6=0,0,'🧾 Tributos Aduana'!$F$23*('🧾 Factura Comercial'!H13/'🧾 Tributos Aduana'!$F$6)) -> 0.26271248 | P9: =TABLA_BASE[[#This Row],[PERCEP. UNIT.(US$) ✅CF]]*TABLA_BASE[[#This Row],[CANTIDAD (unid.)]] -> 63.050996 | Q9: =TABLA_BASE[[#This Row],[ADV UNIT. (US$) ⚠️COSTO]]+TABLA_BASE[[#This Row],[IPM UNIT. (US$) ✅CF]]+TABLA_BASE[[#This Row],[IGV UNIT. (US$) ✅CF]] -> 1.5050459 | R9: =TABLA_BASE[[#This Row],[DEUDA ADUANERA UNIT.]]*TABLA_BASE[[#This Row],[CANTIDAD (unid.)]] -> 361.21102 | S9: =TABLA_BASE[[#This Row],[DEUDA ADUANERA UNIT.]]*'📋 Datos Generales'!$E$19 -> 5.5987708 | T9: =TABLA_BASE[[#This Row],[DEUDA ADUANERA TOTAL]]*'📋 Datos Generales'!$E$19 -> 1343.705 | U9: =TABLA_BASE[[#This Row],[ADV UNIT. (US$) ⚠️COSTO]]*'📋 Datos Generales'!$E$19 -> 1.3394608 | V9: =TABLA_BASE[[#This Row],[ADV UNIT. (S/.)]]*TABLA_BASE[[#This Row],[CANTIDAD (unid.)]] -> 321.47058 | W9: =TABLA_BASE[[#This Row],[IPM UNIT. (US$) ✅CF]]*'📋 Datos Generales'!$E$19 -> 0.47309443 | X9: =TABLA_BASE[[#This Row],[IPM UNIT. (S/.)]]*TABLA_BASE[[#This Row],[CANTIDAD (unid.)]] -> 113.54266 | Y9: =TABLA_BASE[[#This Row],[IGV UNIT. (US$) ✅CF]]*'📋 Datos Generales'!$E$19 -> 3.7862156 | Z9: =TABLA_BASE[[#This Row],[IGV UNIT. (S/.)]]*TABLA_BASE[[#This Row],[CANTIDAD (unid.)]] -> 908.69174 | AA9: =TABLA_BASE[[#This Row],[PERCEP. UNIT.(US$) ✅CF]]*'📋 Datos Generales'!$E$19 -> 0.97729043 | AB9: =TABLA_BASE[[#This Row],[PERCEP. UNIT.(S/.)]]*TABLA_BASE[[#This Row],[CANTIDAD (unid.)]] -> 234.5497 | AC9: =TABLA_BASE[[#This Row],[ADV UNIT. (US$) ⚠️COSTO]]+TABLA_BASE[[#This Row],[IPM UNIT. (US$) ✅CF]]+TABLA_BASE[[#This Row],[IGV UNIT. (US$) ✅CF]]+TABLA_BASE[[#This Row],[PERCEP. UNIT.(US$) ✅CF]] -> 1.7677584 | AD9: =TABLA_BASE[[#This Row],[TOTAL PAGO SUNAT UNIT.(US$)]]*TABLA_BASE[[#This Row],[CANTIDAD (unid.)]] -> 424.26201 | AE9: =TABLA_BASE[[#This Row],[TOTAL PAGO SUNAT UNIT.(US$)]]*'📋 Datos Generales'!$E$19 -> 6.5760612 | AF9: =TABLA_BASE[[#This Row],[TOTAL TRIB. UNIT.(S/.)]]*TABLA_BASE[[#This Row],[CANTIDAD (unid.)]] -> 1578.2547 | AG9: =IF('🧾 Factura Comercial'!G13=0,0,'📦 Gastos Importación'!$E$28*(IF('🧾 Tributos Aduana'!$F$6=0,0,'🧾 Factura Comercial'!I13/'🧾 Tributos Aduana'!$F$6))/'🧾 Factura Comercial'!G13) -> 6.5134862 | AH9: =TABLA_BASE[[#This Row],[GASTOS IMP. UNIT.(US$)]]*TABLA_BASE[[#This Row],[CANTIDAD (unid.)]] -> 1563.2367 | AI9: =TABLA_BASE[[#This Row],[GASTOS IMP. UNIT.(US$)]]*'📋 Datos Generales'!$E$19 -> 24.230169 | AJ9: =TABLA_BASE[[#This Row],[GASTOS IMP. UNIT.(S/.)]]*TABLA_BASE[[#This Row],[CANTIDAD (unid.)]] -> 5815.2405 | AK9: ='🧮 Costos x Producto'!J13 -> 6.5134862 | AL9: ='🧮 Costos x Producto'!K13 -> 24.230169 | AM9: =TABLA_BASE[[#This Row],[C/M UNIT. (S/.)]]*TABLA_BASE[[#This Row],[CANTIDAD (unid.)]] -> 5815.2405 | AN9: =IF('🧾 Factura Comercial'!G13=0,0,'🧾 Tributos Aduana'!$F$17*(IF('🧾 Tributos Aduana'!$F$6=0,0,'🧾 Factura Comercial'!I13/'🧾 Tributos Aduana'!$F$6))/'🧾 Factura Comercial'!G13) -> 0.3600701 | AO9: =IF('🧾 Factura Comercial'!G13=0,0,'🏦 Crédito Fiscal'!$C$16*(IF('🧾 Tributos Aduana'!$F$6=0,0,'🧾 Factura Comercial'!I13/'🧾 Tributos Aduana'!$F$6))/'🧾 Factura Comercial'!G13) -> 1.4343366 | AP9: =TABLA_BASE[[#This Row],[CF UNIT. ✅RECUP. (US$)]]*'📋 Datos Generales'!$E$19 -> 5.3357321 | AQ9: =TABLA_BASE[[#This Row],[CF UNIT. ✅RECUP.(S/.)]]*TABLA_BASE[[#This Row],[CANTIDAD (unid.)]] -> 1280.5757 | AR9: ='💰 Precio de Venta'!G14 -> 0.4 | AS9: ='💰 Precio de Venta'!H14 -> 40.383615 | AT9: =TABLA_BASE[[#This Row],[VALOR VTA. UNIT.(S/.)]]*TABLA_BASE[[#This Row],[CANTIDAD (unid.)]] -> 9692.0675 | AU9: ='💰 Precio de Venta'!I14 -> 47.652665 | AV9: ='💰 Precio de Venta'!J14 -> 16.153446 | AW9: =TABLA_BASE[[#This Row],[GANANCIA UNIT.(S/.)]]*TABLA_BASE[[#This Row],[CANTIDAD (unid.)]] -> 3876.827 | AX9: ='💰 Precio de Venta'!K14 -> 33 | AY9: =TABLA_BASE[[#This Row],[GANANCIA UNIT.(S/.)]]*'🧾 Factura Comercial'!G13 -> 3876.827 | AZ9: =IF(TABLA_BASE[[#This Row],[PRECIO VTA. c/IGV(S/.)]]=0,0,TABLA_BASE[[#This Row],[GANANCIA UNIT.(S/.)]]/TABLA_BASE[[#This Row],[PRECIO VTA. c/IGV(S/.)]]) -> 0.33898305 | BA9: =IF(TABLA_BASE[[#This Row],[C/M UNIT. (S/.)]]=0,0,TABLA_BASE[[#This Row],[GANANCIA UNIT.(S/.)]]/TABLA_BASE[[#This Row],[C/M UNIT. (S/.)]]) -> 0.66666667 | BB9: =IF(TABLA_BASE[[#This Row],[MARGEN %]]>=0.5,"🟢 ALTO",IF(TABLA_BASE[[#This Row],[MARGEN %]]>=0.3,"🟡 MEDIO","🔴 BAJO")) -> 🟡 MEDIO
A10: ='🧾 Factura Comercial'!E14 -> Case Wallet Cuero PU Samsung S24 | B10: ='🧾 Factura Comercial'!F14 -> Unid. | C10: ='🧾 Factura Comercial'!G14 -> 1920 | D10: ='🧾 Factura Comercial'!H14 -> 0.76 | E10: ='🧾 Factura Comercial'!I14 -> 1459.2 | F10: =IF('🧾 Tributos Aduana'!$F$6=0,0,'🧾 Factura Comercial'!I14/'🧾 Tributos Aduana'!$F$6) -> 0.033436233 | G10: ='🧾 Factura Comercial'!H14*'📋 Datos Generales'!$E$19 -> 2.8272 | H10: =TABLA_BASE[[#This Row],[FOB UNIT. (S/.)]]*TABLA_BASE[[#This Row],[CANTIDAD (unid.)]] -> 5428.224 | I10: =IF('🧾 Tributos Aduana'!$F$6=0,0,'🧾 Tributos Aduana'!$F$17*('🧾 Factura Comercial'!H14/'🧾 Tributos Aduana'!$F$6)) -> 0.047925267 | J10: =TABLA_BASE[[#This Row],[ADV UNIT. (US$) ⚠️COSTO]]*TABLA_BASE[[#This Row],[CANTIDAD (unid.)]] -> 92.016513 | K10: =IF('🧾 Tributos Aduana'!$F$6=0,0,'🧾 Tributos Aduana'!$F$18*('🧾 Factura Comercial'!H14/'🧾 Tributos Aduana'!$F$6)) -> 0.016927093 | L10: =TABLA_BASE[[#This Row],[IPM UNIT. (US$) ✅CF]]*TABLA_BASE[[#This Row],[CANTIDAD (unid.)]] -> 32.500018 | M10: =IF('🧾 Tributos Aduana'!$F$6=0,0,'🧾 Tributos Aduana'!$F$19*('🧾 Factura Comercial'!H14/'🧾 Tributos Aduana'!$F$6)) -> 0.13546899 | N10: =TABLA_BASE[[#This Row],[IGV UNIT. (US$) ✅CF]]*TABLA_BASE[[#This Row],[CANTIDAD (unid.)]] -> 260.10046 | O10: =IF('🧾 Tributos Aduana'!$F$6=0,0,'🧾 Tributos Aduana'!$F$23*('🧾 Factura Comercial'!H14/'🧾 Tributos Aduana'!$F$6)) -> 0.034966985 | P10: =TABLA_BASE[[#This Row],[PERCEP. UNIT.(US$) ✅CF]]*TABLA_BASE[[#This Row],[CANTIDAD (unid.)]] -> 67.136612 | Q10: =TABLA_BASE[[#This Row],[ADV UNIT. (US$) ⚠️COSTO]]+TABLA_BASE[[#This Row],[IPM UNIT. (US$) ✅CF]]+TABLA_BASE[[#This Row],[IGV UNIT. (US$) ✅CF]] -> 0.20032135 | R10: =TABLA_BASE[[#This Row],[DEUDA ADUANERA UNIT.]]*TABLA_BASE[[#This Row],[CANTIDAD (unid.)]] -> 384.61699 | S10: =TABLA_BASE[[#This Row],[DEUDA ADUANERA UNIT.]]*'📋 Datos Generales'!$E$19 -> 0.74519541 | T10: =TABLA_BASE[[#This Row],[DEUDA ADUANERA TOTAL]]*'📋 Datos Generales'!$E$19 -> 1430.7752 | U10: =TABLA_BASE[[#This Row],[ADV UNIT. (US$) ⚠️COSTO]]*'📋 Datos Generales'!$E$19 -> 0.17828199 | V10: =TABLA_BASE[[#This Row],[ADV UNIT. (S/.)]]*TABLA_BASE[[#This Row],[CANTIDAD (unid.)]] -> 342.30143 | W10: =TABLA_BASE[[#This Row],[IPM UNIT. (US$) ✅CF]]*'📋 Datos Generales'!$E$19 -> 0.062968786 | X10: =TABLA_BASE[[#This Row],[IPM UNIT. (S/.)]]*TABLA_BASE[[#This Row],[CANTIDAD (unid.)]] -> 120.90007 | Y10: =TABLA_BASE[[#This Row],[IGV UNIT. (US$) ✅CF]]*'📋 Datos Generales'!$E$19 -> 0.50394463 | Z10: =TABLA_BASE[[#This Row],[IGV UNIT. (S/.)]]*TABLA_BASE[[#This Row],[CANTIDAD (unid.)]] -> 967.57369 | AA10: =TABLA_BASE[[#This Row],[PERCEP. UNIT.(US$) ✅CF]]*'📋 Datos Generales'!$E$19 -> 0.13007719 | AB10: =TABLA_BASE[[#This Row],[PERCEP. UNIT.(S/.)]]*TABLA_BASE[[#This Row],[CANTIDAD (unid.)]] -> 249.7482 | AC10: =TABLA_BASE[[#This Row],[ADV UNIT. (US$) ⚠️COSTO]]+TABLA_BASE[[#This Row],[IPM UNIT. (US$) ✅CF]]+TABLA_BASE[[#This Row],[IGV UNIT. (US$) ✅CF]]+TABLA_BASE[[#This Row],[PERCEP. UNIT.(US$) ✅CF]] -> 0.23528833 | AD10: =TABLA_BASE[[#This Row],[TOTAL PAGO SUNAT UNIT.(US$)]]*TABLA_BASE[[#This Row],[CANTIDAD (unid.)]] -> 451.7536 | AE10: =TABLA_BASE[[#This Row],[TOTAL PAGO SUNAT UNIT.(US$)]]*'📋 Datos Generales'!$E$19 -> 0.8752726 | AF10: =TABLA_BASE[[#This Row],[TOTAL TRIB. UNIT.(S/.)]]*TABLA_BASE[[#This Row],[CANTIDAD (unid.)]] -> 1680.5234 | AG10: =IF('🧾 Factura Comercial'!G14=0,0,'📦 Gastos Importación'!$E$28*(IF('🧾 Tributos Aduana'!$F$6=0,0,'🧾 Factura Comercial'!I14/'🧾 Tributos Aduana'!$F$6))/'🧾 Factura Comercial'!G14) -> 0.86694388 | AH10: =TABLA_BASE[[#This Row],[GASTOS IMP. UNIT.(US$)]]*TABLA_BASE[[#This Row],[CANTIDAD (unid.)]] -> 1664.5322 | AI10: =TABLA_BASE[[#This Row],[GASTOS IMP. UNIT.(US$)]]*'📋 Datos Generales'!$E$19 -> 3.2250312 | AJ10: =TABLA_BASE[[#This Row],[GASTOS IMP. UNIT.(S/.)]]*TABLA_BASE[[#This Row],[CANTIDAD (unid.)]] -> 6192.0599 | AK10: ='🧮 Costos x Producto'!J14 -> 0.86694388 | AL10: ='🧮 Costos x Producto'!K14 -> 3.2250312 | AM10: =TABLA_BASE[[#This Row],[C/M UNIT. (S/.)]]*TABLA_BASE[[#This Row],[CANTIDAD (unid.)]] -> 6192.0599 | AN10: =IF('🧾 Factura Comercial'!G14=0,0,'🧾 Tributos Aduana'!$F$17*(IF('🧾 Tributos Aduana'!$F$6=0,0,'🧾 Factura Comercial'!I14/'🧾 Tributos Aduana'!$F$6))/'🧾 Factura Comercial'!G14) -> 0.047925267 | AO10: =IF('🧾 Factura Comercial'!G14=0,0,'🏦 Crédito Fiscal'!$C$16*(IF('🧾 Tributos Aduana'!$F$6=0,0,'🧾 Factura Comercial'!I14/'🧾 Tributos Aduana'!$F$6))/'🧾 Factura Comercial'!G14) -> 0.19090995 | AP10: =TABLA_BASE[[#This Row],[CF UNIT. ✅RECUP. (US$)]]*'📋 Datos Generales'!$E$19 -> 0.71018501 | AQ10: =TABLA_BASE[[#This Row],[CF UNIT. ✅RECUP.(S/.)]]*TABLA_BASE[[#This Row],[CANTIDAD (unid.)]] -> 1363.5552 | AR10: ='💰 Precio de Venta'!G15 -> 0.4 | AS10: ='💰 Precio de Venta'!H15 -> 5.375052 | AT10: =TABLA_BASE[[#This Row],[VALOR VTA. UNIT.(S/.)]]*TABLA_BASE[[#This Row],[CANTIDAD (unid.)]] -> 10320.1 | AU10: ='💰 Precio de Venta'!I15 -> 6.3425614 | AV10: ='💰 Precio de Venta'!J15 -> 2.1500208 | AW10: =TABLA_BASE[[#This Row],[GANANCIA UNIT.(S/.)]]*TABLA_BASE[[#This Row],[CANTIDAD (unid.)]] -> 4128.04 | AX10: ='💰 Precio de Venta'!K15 -> 263 | AY10: =TABLA_BASE[[#This Row],[GANANCIA UNIT.(S/.)]]*'🧾 Factura Comercial'!G14 -> 4128.04 | AZ10: =IF(TABLA_BASE[[#This Row],[PRECIO VTA. c/IGV(S/.)]]=0,0,TABLA_BASE[[#This Row],[GANANCIA UNIT.(S/.)]]/TABLA_BASE[[#This Row],[PRECIO VTA. c/IGV(S/.)]]) -> 0.33898305 | BA10: =IF(TABLA_BASE[[#This Row],[C/M UNIT. (S/.)]]=0,0,TABLA_BASE[[#This Row],[GANANCIA UNIT.(S/.)]]/TABLA_BASE[[#This Row],[C/M UNIT. (S/.)]]) -> 0.66666667 | BB10: =IF(TABLA_BASE[[#This Row],[MARGEN %]]>=0.5,"🟢 ALTO",IF(TABLA_BASE[[#This Row],[MARGEN %]]>=0.3,"🟡 MEDIO","🔴 BAJO")) -> 🟡 MEDIO
A11: ='🧾 Factura Comercial'!E15 -> Adaptador USB-C a Jack 3.5mm | B11: ='🧾 Factura Comercial'!F15 -> Unid. | C11: ='🧾 Factura Comercial'!G15 -> 4800 | D11: ='🧾 Factura Comercial'!H15 -> 0.28 | E11: ='🧾 Factura Comercial'!I15 -> 1344 | F11: =IF('🧾 Tributos Aduana'!$F$6=0,0,'🧾 Factura Comercial'!I15/'🧾 Tributos Aduana'!$F$6) -> 0.03079653 | G11: ='🧾 Factura Comercial'!H15*'📋 Datos Generales'!$E$19 -> 1.0416 | H11: =TABLA_BASE[[#This Row],[FOB UNIT. (S/.)]]*TABLA_BASE[[#This Row],[CANTIDAD (unid.)]] -> 4999.68 | I11: =IF('🧾 Tributos Aduana'!$F$6=0,0,'🧾 Tributos Aduana'!$F$17*('🧾 Factura Comercial'!H15/'🧾 Tributos Aduana'!$F$6)) -> 0.017656677 | J11: =TABLA_BASE[[#This Row],[ADV UNIT. (US$) ⚠️COSTO]]*TABLA_BASE[[#This Row],[CANTIDAD (unid.)]] -> 84.752051 | K11: =IF('🧾 Tributos Aduana'!$F$6=0,0,'🧾 Tributos Aduana'!$F$18*('🧾 Factura Comercial'!H15/'🧾 Tributos Aduana'!$F$6)) -> 0.0062362974 | L11: =TABLA_BASE[[#This Row],[IPM UNIT. (US$) ✅CF]]*TABLA_BASE[[#This Row],[CANTIDAD (unid.)]] -> 29.934227 | M11: =IF('🧾 Tributos Aduana'!$F$6=0,0,'🧾 Tributos Aduana'!$F$19*('🧾 Factura Comercial'!H15/'🧾 Tributos Aduana'!$F$6)) -> 0.049909627 | N11: =TABLA_BASE[[#This Row],[IGV UNIT. (US$) ✅CF]]*TABLA_BASE[[#This Row],[CANTIDAD (unid.)]] -> 239.56621 | O11: =IF('🧾 Tributos Aduana'!$F$6=0,0,'🧾 Tributos Aduana'!$F$23*('🧾 Factura Comercial'!H15/'🧾 Tributos Aduana'!$F$6)) -> 0.012882574 | P11: =TABLA_BASE[[#This Row],[PERCEP. UNIT.(US$) ✅CF]]*TABLA_BASE[[#This Row],[CANTIDAD (unid.)]] -> 61.836353 | Q11: =TABLA_BASE[[#This Row],[ADV UNIT. (US$) ⚠️COSTO]]+TABLA_BASE[[#This Row],[IPM UNIT. (US$) ✅CF]]+TABLA_BASE[[#This Row],[IGV UNIT. (US$) ✅CF]] -> 0.073802602 | R11: =TABLA_BASE[[#This Row],[DEUDA ADUANERA UNIT.]]*TABLA_BASE[[#This Row],[CANTIDAD (unid.)]] -> 354.25249 | S11: =TABLA_BASE[[#This Row],[DEUDA ADUANERA UNIT.]]*'📋 Datos Generales'!$E$19 -> 0.27454568 | T11: =TABLA_BASE[[#This Row],[DEUDA ADUANERA TOTAL]]*'📋 Datos Generales'!$E$19 -> 1317.8193 | U11: =TABLA_BASE[[#This Row],[ADV UNIT. (US$) ⚠️COSTO]]*'📋 Datos Generales'!$E$19 -> 0.06568284 | V11: =TABLA_BASE[[#This Row],[ADV UNIT. (S/.)]]*TABLA_BASE[[#This Row],[CANTIDAD (unid.)]] -> 315.27763 | W11: =TABLA_BASE[[#This Row],[IPM UNIT. (US$) ✅CF]]*'📋 Datos Generales'!$E$19 -> 0.023199026 | X11: =TABLA_BASE[[#This Row],[IPM UNIT. (S/.)]]*TABLA_BASE[[#This Row],[CANTIDAD (unid.)]] -> 111.35533 | Y11: =TABLA_BASE[[#This Row],[IGV UNIT. (US$) ✅CF]]*'📋 Datos Generales'!$E$19 -> 0.18566381 | Z11: =TABLA_BASE[[#This Row],[IGV UNIT. (S/.)]]*TABLA_BASE[[#This Row],[CANTIDAD (unid.)]] -> 891.1863 | AA11: =TABLA_BASE[[#This Row],[PERCEP. UNIT.(US$) ✅CF]]*'📋 Datos Generales'!$E$19 -> 0.047923174 | AB11: =TABLA_BASE[[#This Row],[PERCEP. UNIT.(S/.)]]*TABLA_BASE[[#This Row],[CANTIDAD (unid.)]] -> 230.03123 | AC11: =TABLA_BASE[[#This Row],[ADV UNIT. (US$) ⚠️COSTO]]+TABLA_BASE[[#This Row],[IPM UNIT. (US$) ✅CF]]+TABLA_BASE[[#This Row],[IGV UNIT. (US$) ✅CF]]+TABLA_BASE[[#This Row],[PERCEP. UNIT.(US$) ✅CF]] -> 0.086685175 | AD11: =TABLA_BASE[[#This Row],[TOTAL PAGO SUNAT UNIT.(US$)]]*TABLA_BASE[[#This Row],[CANTIDAD (unid.)]] -> 416.08884 | AE11: =TABLA_BASE[[#This Row],[TOTAL PAGO SUNAT UNIT.(US$)]]*'📋 Datos Generales'!$E$19 -> 0.32246885 | AF11: =TABLA_BASE[[#This Row],[TOTAL TRIB. UNIT.(S/.)]]*TABLA_BASE[[#This Row],[CANTIDAD (unid.)]] -> 1547.8505 | AG11: =IF('🧾 Factura Comercial'!G15=0,0,'📦 Gastos Importación'!$E$28*(IF('🧾 Tributos Aduana'!$F$6=0,0,'🧾 Factura Comercial'!I15/'🧾 Tributos Aduana'!$F$6))/'🧾 Factura Comercial'!G15) -> 0.31940038 | AH11: =TABLA_BASE[[#This Row],[GASTOS IMP. UNIT.(US$)]]*TABLA_BASE[[#This Row],[CANTIDAD (unid.)]] -> 1533.1218 | AI11: =TABLA_BASE[[#This Row],[GASTOS IMP. UNIT.(US$)]]*'📋 Datos Generales'!$E$19 -> 1.1881694 | AJ11: =TABLA_BASE[[#This Row],[GASTOS IMP. UNIT.(S/.)]]*TABLA_BASE[[#This Row],[CANTIDAD (unid.)]] -> 5703.2131 | AK11: ='🧮 Costos x Producto'!J15 -> 0.31940038 | AL11: ='🧮 Costos x Producto'!K15 -> 1.1881694 | AM11: =TABLA_BASE[[#This Row],[C/M UNIT. (S/.)]]*TABLA_BASE[[#This Row],[CANTIDAD (unid.)]] -> 5703.2131 | AN11: =IF('🧾 Factura Comercial'!G15=0,0,'🧾 Tributos Aduana'!$F$17*(IF('🧾 Tributos Aduana'!$F$6=0,0,'🧾 Factura Comercial'!I15/'🧾 Tributos Aduana'!$F$6))/'🧾 Factura Comercial'!G15) -> 0.017656677 | AO11: =IF('🧾 Factura Comercial'!G15=0,0,'🏦 Crédito Fiscal'!$C$16*(IF('🧾 Tributos Aduana'!$F$6=0,0,'🧾 Factura Comercial'!I15/'🧾 Tributos Aduana'!$F$6))/'🧾 Factura Comercial'!G15) -> 0.070335245 | AP11: =TABLA_BASE[[#This Row],[CF UNIT. ✅RECUP. (US$)]]*'📋 Datos Generales'!$E$19 -> 0.26164711 | AQ11: =TABLA_BASE[[#This Row],[CF UNIT. ✅RECUP.(S/.)]]*TABLA_BASE[[#This Row],[CANTIDAD (unid.)]] -> 1255.9061 | AR11: ='💰 Precio de Venta'!G16 -> 0.4 | AS11: ='💰 Precio de Venta'!H16 -> 1.9802823 | AT11: =TABLA_BASE[[#This Row],[VALOR VTA. UNIT.(S/.)]]*TABLA_BASE[[#This Row],[CANTIDAD (unid.)]] -> 9505.3552 | AU11: ='💰 Precio de Venta'!I16 -> 2.3367331 | AV11: ='💰 Precio de Venta'!J16 -> 0.79211293 | AW11: =TABLA_BASE[[#This Row],[GANANCIA UNIT.(S/.)]]*TABLA_BASE[[#This Row],[CANTIDAD (unid.)]] -> 3802.1421 | AX11: ='💰 Precio de Venta'!K16 -> 657 | AY11: =TABLA_BASE[[#This Row],[GANANCIA UNIT.(S/.)]]*'🧾 Factura Comercial'!G15 -> 3802.1421 | AZ11: =IF(TABLA_BASE[[#This Row],[PRECIO VTA. c/IGV(S/.)]]=0,0,TABLA_BASE[[#This Row],[GANANCIA UNIT.(S/.)]]/TABLA_BASE[[#This Row],[PRECIO VTA. c/IGV(S/.)]]) -> 0.33898305 | BA11: =IF(TABLA_BASE[[#This Row],[C/M UNIT. (S/.)]]=0,0,TABLA_BASE[[#This Row],[GANANCIA UNIT.(S/.)]]/TABLA_BASE[[#This Row],[C/M UNIT. (S/.)]]) -> 0.66666667 | BB11: =IF(TABLA_BASE[[#This Row],[MARGEN %]]>=0.5,"🟢 ALTO",IF(TABLA_BASE[[#This Row],[MARGEN %]]>=0.3,"🟡 MEDIO","🔴 BAJO")) -> 🟡 MEDIO
A12: ='🧾 Factura Comercial'!E16 -> Adaptador YYY 67 | B12: ='🧾 Factura Comercial'!F16 -> Unid. | C12: ='🧾 Factura Comercial'!G16 -> 2000 | D12: ='🧾 Factura Comercial'!H16 -> 0.5 | E12: ='🧾 Factura Comercial'!I16 -> 1000 | F12: =IF('🧾 Tributos Aduana'!$F$6=0,0,'🧾 Factura Comercial'!I16/'🧾 Tributos Aduana'!$F$6) -> 0.022914085 | G12: ='🧾 Factura Comercial'!H16*'📋 Datos Generales'!$E$19 -> 1.86 | H12: =TABLA_BASE[[#This Row],[FOB UNIT. (S/.)]]*TABLA_BASE[[#This Row],[CANTIDAD (unid.)]] -> 3720 | I12: =IF('🧾 Tributos Aduana'!$F$6=0,0,'🧾 Tributos Aduana'!$F$17*('🧾 Factura Comercial'!H16/'🧾 Tributos Aduana'!$F$6)) -> 0.031529781 | J12: =TABLA_BASE[[#This Row],[ADV UNIT. (US$) ⚠️COSTO]]*TABLA_BASE[[#This Row],[CANTIDAD (unid.)]] -> 63.059562 | K12: =IF('🧾 Tributos Aduana'!$F$6=0,0,'🧾 Tributos Aduana'!$F$18*('🧾 Factura Comercial'!H16/'🧾 Tributos Aduana'!$F$6)) -> 0.011136245 | L12: =TABLA_BASE[[#This Row],[IPM UNIT. (US$) ✅CF]]*TABLA_BASE[[#This Row],[CANTIDAD (unid.)]] -> 22.272491 | M12: =IF('🧾 Tributos Aduana'!$F$6=0,0,'🧾 Tributos Aduana'!$F$19*('🧾 Factura Comercial'!H16/'🧾 Tributos Aduana'!$F$6)) -> 0.089124334 | N12: =TABLA_BASE[[#This Row],[IGV UNIT. (US$) ✅CF]]*TABLA_BASE[[#This Row],[CANTIDAD (unid.)]] -> 178.24867 | O12: =IF('🧾 Tributos Aduana'!$F$6=0,0,'🧾 Tributos Aduana'!$F$23*('🧾 Factura Comercial'!H16/'🧾 Tributos Aduana'!$F$6)) -> 0.023004596 | P12: =TABLA_BASE[[#This Row],[PERCEP. UNIT.(US$) ✅CF]]*TABLA_BASE[[#This Row],[CANTIDAD (unid.)]] -> 46.009191 | Q12: =TABLA_BASE[[#This Row],[ADV UNIT. (US$) ⚠️COSTO]]+TABLA_BASE[[#This Row],[IPM UNIT. (US$) ✅CF]]+TABLA_BASE[[#This Row],[IGV UNIT. (US$) ✅CF]] -> 0.13179036 | R12: =TABLA_BASE[[#This Row],[DEUDA ADUANERA UNIT.]]*TABLA_BASE[[#This Row],[CANTIDAD (unid.)]] -> 263.58072 | S12: =TABLA_BASE[[#This Row],[DEUDA ADUANERA UNIT.]]*'📋 Datos Generales'!$E$19 -> 0.49026014 | T12: =TABLA_BASE[[#This Row],[DEUDA ADUANERA TOTAL]]*'📋 Datos Generales'!$E$19 -> 980.52028 | U12: =TABLA_BASE[[#This Row],[ADV UNIT. (US$) ⚠️COSTO]]*'📋 Datos Generales'!$E$19 -> 0.11729079 | V12: =TABLA_BASE[[#This Row],[ADV UNIT. (S/.)]]*TABLA_BASE[[#This Row],[CANTIDAD (unid.)]] -> 234.58157 | W12: =TABLA_BASE[[#This Row],[IPM UNIT. (US$) ✅CF]]*'📋 Datos Generales'!$E$19 -> 0.041426833 | X12: =TABLA_BASE[[#This Row],[IPM UNIT. (S/.)]]*TABLA_BASE[[#This Row],[CANTIDAD (unid.)]] -> 82.853665 | Y12: =TABLA_BASE[[#This Row],[IGV UNIT. (US$) ✅CF]]*'📋 Datos Generales'!$E$19 -> 0.33154252 | Z12: =TABLA_BASE[[#This Row],[IGV UNIT. (S/.)]]*TABLA_BASE[[#This Row],[CANTIDAD (unid.)]] -> 663.08504 | AA12: =TABLA_BASE[[#This Row],[PERCEP. UNIT.(US$) ✅CF]]*'📋 Datos Generales'!$E$19 -> 0.085577096 | AB12: =TABLA_BASE[[#This Row],[PERCEP. UNIT.(S/.)]]*TABLA_BASE[[#This Row],[CANTIDAD (unid.)]] -> 171.15419 | AC12: =TABLA_BASE[[#This Row],[ADV UNIT. (US$) ⚠️COSTO]]+TABLA_BASE[[#This Row],[IPM UNIT. (US$) ✅CF]]+TABLA_BASE[[#This Row],[IGV UNIT. (US$) ✅CF]]+TABLA_BASE[[#This Row],[PERCEP. UNIT.(US$) ✅CF]] -> 0.15479496 | AD12: =TABLA_BASE[[#This Row],[TOTAL PAGO SUNAT UNIT.(US$)]]*TABLA_BASE[[#This Row],[CANTIDAD (unid.)]] -> 309.58991 | AE12: =TABLA_BASE[[#This Row],[TOTAL PAGO SUNAT UNIT.(US$)]]*'📋 Datos Generales'!$E$19 -> 0.57583723 | AF12: =TABLA_BASE[[#This Row],[TOTAL TRIB. UNIT.(S/.)]]*TABLA_BASE[[#This Row],[CANTIDAD (unid.)]] -> 1151.6745 | AG12: =IF('🧾 Factura Comercial'!G16=0,0,'📦 Gastos Importación'!$E$28*(IF('🧾 Tributos Aduana'!$F$6=0,0,'🧾 Factura Comercial'!I16/'🧾 Tributos Aduana'!$F$6))/'🧾 Factura Comercial'!G16) -> 0.57035781 | AH12: =TABLA_BASE[[#This Row],[GASTOS IMP. UNIT.(US$)]]*TABLA_BASE[[#This Row],[CANTIDAD (unid.)]] -> 1140.7156 | AI12: =TABLA_BASE[[#This Row],[GASTOS IMP. UNIT.(US$)]]*'📋 Datos Generales'!$E$19 -> 2.1217311 | AJ12: =TABLA_BASE[[#This Row],[GASTOS IMP. UNIT.(S/.)]]*TABLA_BASE[[#This Row],[CANTIDAD (unid.)]] -> 4243.4621 | AK12: ='🧮 Costos x Producto'!J16 -> 0.57035781 | AL12: ='🧮 Costos x Producto'!K16 -> 2.1217311 | AM12: =TABLA_BASE[[#This Row],[C/M UNIT. (S/.)]]*TABLA_BASE[[#This Row],[CANTIDAD (unid.)]] -> 4243.4621 | AN12: =IF('🧾 Factura Comercial'!G16=0,0,'🧾 Tributos Aduana'!$F$17*(IF('🧾 Tributos Aduana'!$F$6=0,0,'🧾 Factura Comercial'!I16/'🧾 Tributos Aduana'!$F$6))/'🧾 Factura Comercial'!G16) -> 0.031529781 | AO12: =IF('🧾 Factura Comercial'!G16=0,0,'🏦 Crédito Fiscal'!$C$16*(IF('🧾 Tributos Aduana'!$F$6=0,0,'🧾 Factura Comercial'!I16/'🧾 Tributos Aduana'!$F$6))/'🧾 Factura Comercial'!G16) -> 0.12559865 | AP12: =TABLA_BASE[[#This Row],[CF UNIT. ✅RECUP. (US$)]]*'📋 Datos Generales'!$E$19 -> 0.46722698 | AQ12: =TABLA_BASE[[#This Row],[CF UNIT. ✅RECUP.(S/.)]]*TABLA_BASE[[#This Row],[CANTIDAD (unid.)]] -> 934.45396 | AR12: ='💰 Precio de Venta'!G17 -> 0.4 | AS12: ='💰 Precio de Venta'!H17 -> 3.5362184 | AT12: =TABLA_BASE[[#This Row],[VALOR VTA. UNIT.(S/.)]]*TABLA_BASE[[#This Row],[CANTIDAD (unid.)]] -> 7072.4369 | AU12: ='💰 Precio de Venta'!I17 -> 4.1727378 | AV12: ='💰 Precio de Venta'!J17 -> 1.4144874 | AW12: =TABLA_BASE[[#This Row],[GANANCIA UNIT.(S/.)]]*TABLA_BASE[[#This Row],[CANTIDAD (unid.)]] -> 2828.9748 | AX12: ='💰 Precio de Venta'!K17 -> 274 | AY12: =TABLA_BASE[[#This Row],[GANANCIA UNIT.(S/.)]]*'🧾 Factura Comercial'!G16 -> 2828.9748 | AZ12: =IF(TABLA_BASE[[#This Row],[PRECIO VTA. c/IGV(S/.)]]=0,0,TABLA_BASE[[#This Row],[GANANCIA UNIT.(S/.)]]/TABLA_BASE[[#This Row],[PRECIO VTA. c/IGV(S/.)]]) -> 0.33898305 | BA12: =IF(TABLA_BASE[[#This Row],[C/M UNIT. (S/.)]]=0,0,TABLA_BASE[[#This Row],[GANANCIA UNIT.(S/.)]]/TABLA_BASE[[#This Row],[C/M UNIT. (S/.)]]) -> 0.66666667 | BB12: =IF(TABLA_BASE[[#This Row],[MARGEN %]]>=0.5,"🟢 ALTO",IF(TABLA_BASE[[#This Row],[MARGEN %]]>=0.3,"🟡 MEDIO","🔴 BAJO")) -> 🟡 MEDIO
A13: ='🧾 Factura Comercial'!E17 -> Case Transparente TPU iPhone 15 | B13: ='🧾 Factura Comercial'!F17 -> Unid. | C13: ='🧾 Factura Comercial'!G17 -> 480 | D13: ='🧾 Factura Comercial'!H17 -> 1.21 | E13: ='🧾 Factura Comercial'!I17 -> 580.8 | F13: =IF('🧾 Tributos Aduana'!$F$6=0,0,'🧾 Factura Comercial'!I17/'🧾 Tributos Aduana'!$F$6) -> 0.013308501 | G13: ='🧾 Factura Comercial'!H17*'📋 Datos Generales'!$E$19 -> 4.5012 | H13: =TABLA_BASE[[#This Row],[FOB UNIT. (S/.)]]*TABLA_BASE[[#This Row],[CANTIDAD (unid.)]] -> 2160.576 | I13: =IF('🧾 Tributos Aduana'!$F$6=0,0,'🧾 Tributos Aduana'!$F$17*('🧾 Factura Comercial'!H17/'🧾 Tributos Aduana'!$F$6)) -> 0.07630207 | J13: =TABLA_BASE[[#This Row],[ADV UNIT. (US$) ⚠️COSTO]]*TABLA_BASE[[#This Row],[CANTIDAD (unid.)]] -> 36.624994 | K13: =IF('🧾 Tributos Aduana'!$F$6=0,0,'🧾 Tributos Aduana'!$F$18*('🧾 Factura Comercial'!H17/'🧾 Tributos Aduana'!$F$6)) -> 0.026949714 | L13: =TABLA_BASE[[#This Row],[IPM UNIT. (US$) ✅CF]]*TABLA_BASE[[#This Row],[CANTIDAD (unid.)]] -> 12.935863 | M13: =IF('🧾 Tributos Aduana'!$F$6=0,0,'🧾 Tributos Aduana'!$F$19*('🧾 Factura Comercial'!H17/'🧾 Tributos Aduana'!$F$6)) -> 0.21568089 | N13: =TABLA_BASE[[#This Row],[IGV UNIT. (US$) ✅CF]]*TABLA_BASE[[#This Row],[CANTIDAD (unid.)]] -> 103.52683 | O13: =IF('🧾 Tributos Aduana'!$F$6=0,0,'🧾 Tributos Aduana'!$F$23*('🧾 Factura Comercial'!H17/'🧾 Tributos Aduana'!$F$6)) -> 0.055671121 | P13: =TABLA_BASE[[#This Row],[PERCEP. UNIT.(US$) ✅CF]]*TABLA_BASE[[#This Row],[CANTIDAD (unid.)]] -> 26.722138 | Q13: =TABLA_BASE[[#This Row],[ADV UNIT. (US$) ⚠️COSTO]]+TABLA_BASE[[#This Row],[IPM UNIT. (US$) ✅CF]]+TABLA_BASE[[#This Row],[IGV UNIT. (US$) ✅CF]] -> 0.31893267 | R13: =TABLA_BASE[[#This Row],[DEUDA ADUANERA UNIT.]]*TABLA_BASE[[#This Row],[CANTIDAD (unid.)]] -> 153.08768 | S13: =TABLA_BASE[[#This Row],[DEUDA ADUANERA UNIT.]]*'📋 Datos Generales'!$E$19 -> 1.1864295 | T13: =TABLA_BASE[[#This Row],[DEUDA ADUANERA TOTAL]]*'📋 Datos Generales'!$E$19 -> 569.48618 | U13: =TABLA_BASE[[#This Row],[ADV UNIT. (US$) ⚠️COSTO]]*'📋 Datos Generales'!$E$19 -> 0.2838437 | V13: =TABLA_BASE[[#This Row],[ADV UNIT. (S/.)]]*TABLA_BASE[[#This Row],[CANTIDAD (unid.)]] -> 136.24498 | W13: =TABLA_BASE[[#This Row],[IPM UNIT. (US$) ✅CF]]*'📋 Datos Generales'!$E$19 -> 0.10025293 | X13: =TABLA_BASE[[#This Row],[IPM UNIT. (S/.)]]*TABLA_BASE[[#This Row],[CANTIDAD (unid.)]] -> 48.121409 | Y13: =TABLA_BASE[[#This Row],[IGV UNIT. (US$) ✅CF]]*'📋 Datos Generales'!$E$19 -> 0.8023329 | Z13: =TABLA_BASE[[#This Row],[IGV UNIT. (S/.)]]*TABLA_BASE[[#This Row],[CANTIDAD (unid.)]] -> 385.11979 | AA13: =TABLA_BASE[[#This Row],[PERCEP. UNIT.(US$) ✅CF]]*'📋 Datos Generales'!$E$19 -> 0.20709657 | AB13: =TABLA_BASE[[#This Row],[PERCEP. UNIT.(S/.)]]*TABLA_BASE[[#This Row],[CANTIDAD (unid.)]] -> 99.406354 | AC13: =TABLA_BASE[[#This Row],[ADV UNIT. (US$) ⚠️COSTO]]+TABLA_BASE[[#This Row],[IPM UNIT. (US$) ✅CF]]+TABLA_BASE[[#This Row],[IGV UNIT. (US$) ✅CF]]+TABLA_BASE[[#This Row],[PERCEP. UNIT.(US$) ✅CF]] -> 0.37460379 | AD13: =TABLA_BASE[[#This Row],[TOTAL PAGO SUNAT UNIT.(US$)]]*TABLA_BASE[[#This Row],[CANTIDAD (unid.)]] -> 179.80982 | AE13: =TABLA_BASE[[#This Row],[TOTAL PAGO SUNAT UNIT.(US$)]]*'📋 Datos Generales'!$E$19 -> 1.3935261 | AF13: =TABLA_BASE[[#This Row],[TOTAL TRIB. UNIT.(S/.)]]*TABLA_BASE[[#This Row],[CANTIDAD (unid.)]] -> 668.89253 | AG13: =IF('🧾 Factura Comercial'!G17=0,0,'📦 Gastos Importación'!$E$28*(IF('🧾 Tributos Aduana'!$F$6=0,0,'🧾 Factura Comercial'!I17/'🧾 Tributos Aduana'!$F$6))/'🧾 Factura Comercial'!G17) -> 1.3802659 | AH13: =TABLA_BASE[[#This Row],[GASTOS IMP. UNIT.(US$)]]*TABLA_BASE[[#This Row],[CANTIDAD (unid.)]] -> 662.52764 | AI13: =TABLA_BASE[[#This Row],[GASTOS IMP. UNIT.(US$)]]*'📋 Datos Generales'!$E$19 -> 5.1345892 | AJ13: =TABLA_BASE[[#This Row],[GASTOS IMP. UNIT.(S/.)]]*TABLA_BASE[[#This Row],[CANTIDAD (unid.)]] -> 2464.6028 | AK13: ='🧮 Costos x Producto'!J17 -> 1.3802659 | AL13: ='🧮 Costos x Producto'!K17 -> 5.1345892 | AM13: =TABLA_BASE[[#This Row],[C/M UNIT. (S/.)]]*TABLA_BASE[[#This Row],[CANTIDAD (unid.)]] -> 2464.6028 | AN13: =IF('🧾 Factura Comercial'!G17=0,0,'🧾 Tributos Aduana'!$F$17*(IF('🧾 Tributos Aduana'!$F$6=0,0,'🧾 Factura Comercial'!I17/'🧾 Tributos Aduana'!$F$6))/'🧾 Factura Comercial'!G17) -> 0.07630207 | AO13: =IF('🧾 Factura Comercial'!G17=0,0,'🏦 Crédito Fiscal'!$C$16*(IF('🧾 Tributos Aduana'!$F$6=0,0,'🧾 Factura Comercial'!I17/'🧾 Tributos Aduana'!$F$6))/'🧾 Factura Comercial'!G17) -> 0.30394874 | AP13: =TABLA_BASE[[#This Row],[CF UNIT. ✅RECUP. (US$)]]*'📋 Datos Generales'!$E$19 -> 1.1306893 | AQ13: =TABLA_BASE[[#This Row],[CF UNIT. ✅RECUP.(S/.)]]*TABLA_BASE[[#This Row],[CANTIDAD (unid.)]] -> 542.73086 | AR13: ='💰 Precio de Venta'!G18 -> 0.4 | AS13: ='💰 Precio de Venta'!H18 -> 8.5576486 | AT13: =TABLA_BASE[[#This Row],[VALOR VTA. UNIT.(S/.)]]*TABLA_BASE[[#This Row],[CANTIDAD (unid.)]] -> 4107.6713 | AU13: ='💰 Precio de Venta'!I18 -> 10.098025 | AV13: ='💰 Precio de Venta'!J18 -> 3.4230594 | AW13: =TABLA_BASE[[#This Row],[GANANCIA UNIT.(S/.)]]*TABLA_BASE[[#This Row],[CANTIDAD (unid.)]] -> 1643.0685 | AX13: ='💰 Precio de Venta'!K18 -> 66 | AY13: =TABLA_BASE[[#This Row],[GANANCIA UNIT.(S/.)]]*'🧾 Factura Comercial'!G17 -> 1643.0685 | AZ13: =IF(TABLA_BASE[[#This Row],[PRECIO VTA. c/IGV(S/.)]]=0,0,TABLA_BASE[[#This Row],[GANANCIA UNIT.(S/.)]]/TABLA_BASE[[#This Row],[PRECIO VTA. c/IGV(S/.)]]) -> 0.33898305 | BA13: =IF(TABLA_BASE[[#This Row],[C/M UNIT. (S/.)]]=0,0,TABLA_BASE[[#This Row],[GANANCIA UNIT.(S/.)]]/TABLA_BASE[[#This Row],[C/M UNIT. (S/.)]]) -> 0.66666667 | BB13: =IF(TABLA_BASE[[#This Row],[MARGEN %]]>=0.5,"🟢 ALTO",IF(TABLA_BASE[[#This Row],[MARGEN %]]>=0.3,"🟡 MEDIO","🔴 BAJO")) -> 🟡 MEDIO
A14: ='🧾 Factura Comercial'!E18 -> Cable USB-C Trenzado 1m | B14: ='🧾 Factura Comercial'!F18 -> Unid. | C14: ='🧾 Factura Comercial'!G18 -> 2880 | D14: ='🧾 Factura Comercial'!H18 -> 0.68 | E14: ='🧾 Factura Comercial'!I18 -> 1958.4 | F14: =IF('🧾 Tributos Aduana'!$F$6=0,0,'🧾 Factura Comercial'!I18/'🧾 Tributos Aduana'!$F$6) -> 0.044874944 | G14: ='🧾 Factura Comercial'!H18*'📋 Datos Generales'!$E$19 -> 2.5296 | H14: =TABLA_BASE[[#This Row],[FOB UNIT. (S/.)]]*TABLA_BASE[[#This Row],[CANTIDAD (unid.)]] -> 7285.248 | I14: =IF('🧾 Tributos Aduana'!$F$6=0,0,'🧾 Tributos Aduana'!$F$17*('🧾 Factura Comercial'!H18/'🧾 Tributos Aduana'!$F$6)) -> 0.042880502 | J14: =TABLA_BASE[[#This Row],[ADV UNIT. (US$) ⚠️COSTO]]*TABLA_BASE[[#This Row],[CANTIDAD (unid.)]] -> 123.49585 | K14: =IF('🧾 Tributos Aduana'!$F$6=0,0,'🧾 Tributos Aduana'!$F$18*('🧾 Factura Comercial'!H18/'🧾 Tributos Aduana'!$F$6)) -> 0.015145294 | L14: =TABLA_BASE[[#This Row],[IPM UNIT. (US$) ✅CF]]*TABLA_BASE[[#This Row],[CANTIDAD (unid.)]] -> 43.618446 | M14: =IF('🧾 Tributos Aduana'!$F$6=0,0,'🧾 Tributos Aduana'!$F$19*('🧾 Factura Comercial'!H18/'🧾 Tributos Aduana'!$F$6)) -> 0.12120909 | N14: =TABLA_BASE[[#This Row],[IGV UNIT. (US$) ✅CF]]*TABLA_BASE[[#This Row],[CANTIDAD (unid.)]] -> 349.08219 | O14: =IF('🧾 Tributos Aduana'!$F$6=0,0,'🧾 Tributos Aduana'!$F$23*('🧾 Factura Comercial'!H18/'🧾 Tributos Aduana'!$F$6)) -> 0.03128625 | P14: =TABLA_BASE[[#This Row],[PERCEP. UNIT.(US$) ✅CF]]*TABLA_BASE[[#This Row],[CANTIDAD (unid.)]] -> 90.1044 | Q14: =TABLA_BASE[[#This Row],[ADV UNIT. (US$) ⚠️COSTO]]+TABLA_BASE[[#This Row],[IPM UNIT. (US$) ✅CF]]+TABLA_BASE[[#This Row],[IGV UNIT. (US$) ✅CF]] -> 0.17923489 | R14: =TABLA_BASE[[#This Row],[DEUDA ADUANERA UNIT.]]*TABLA_BASE[[#This Row],[CANTIDAD (unid.)]] -> 516.19648 | S14: =TABLA_BASE[[#This Row],[DEUDA ADUANERA UNIT.]]*'📋 Datos Generales'!$E$19 -> 0.66675379 | T14: =TABLA_BASE[[#This Row],[DEUDA ADUANERA TOTAL]]*'📋 Datos Generales'!$E$19 -> 1920.2509 | U14: =TABLA_BASE[[#This Row],[ADV UNIT. (US$) ⚠️COSTO]]*'📋 Datos Generales'!$E$19 -> 0.15951547 | V14: =TABLA_BASE[[#This Row],[ADV UNIT. (S/.)]]*TABLA_BASE[[#This Row],[CANTIDAD (unid.)]] -> 459.40455 | W14: =TABLA_BASE[[#This Row],[IPM UNIT. (US$) ✅CF]]*'📋 Datos Generales'!$E$19 -> 0.056340492 | X14: =TABLA_BASE[[#This Row],[IPM UNIT. (S/.)]]*TABLA_BASE[[#This Row],[CANTIDAD (unid.)]] -> 162.26062 | Y14: =TABLA_BASE[[#This Row],[IGV UNIT. (US$) ✅CF]]*'📋 Datos Generales'!$E$19 -> 0.45089783 | Z14: =TABLA_BASE[[#This Row],[IGV UNIT. (S/.)]]*TABLA_BASE[[#This Row],[CANTIDAD (unid.)]] -> 1298.5857 | AA14: =TABLA_BASE[[#This Row],[PERCEP. UNIT.(US$) ✅CF]]*'📋 Datos Generales'!$E$19 -> 0.11638485 | AB14: =TABLA_BASE[[#This Row],[PERCEP. UNIT.(S/.)]]*TABLA_BASE[[#This Row],[CANTIDAD (unid.)]] -> 335.18837 | AC14: =TABLA_BASE[[#This Row],[ADV UNIT. (US$) ⚠️COSTO]]+TABLA_BASE[[#This Row],[IPM UNIT. (US$) ✅CF]]+TABLA_BASE[[#This Row],[IGV UNIT. (US$) ✅CF]]+TABLA_BASE[[#This Row],[PERCEP. UNIT.(US$) ✅CF]] -> 0.21052114 | AD14: =TABLA_BASE[[#This Row],[TOTAL PAGO SUNAT UNIT.(US$)]]*TABLA_BASE[[#This Row],[CANTIDAD (unid.)]] -> 606.30088 | AE14: =TABLA_BASE[[#This Row],[TOTAL PAGO SUNAT UNIT.(US$)]]*'📋 Datos Generales'!$E$19 -> 0.78313864 | AF14: =TABLA_BASE[[#This Row],[TOTAL TRIB. UNIT.(S/.)]]*TABLA_BASE[[#This Row],[CANTIDAD (unid.)]] -> 2255.4393 | AG14: =IF('🧾 Factura Comercial'!G18=0,0,'📦 Gastos Importación'!$E$28*(IF('🧾 Tributos Aduana'!$F$6=0,0,'🧾 Factura Comercial'!I18/'🧾 Tributos Aduana'!$F$6))/'🧾 Factura Comercial'!G18) -> 0.77568663 | AH14: =TABLA_BASE[[#This Row],[GASTOS IMP. UNIT.(US$)]]*TABLA_BASE[[#This Row],[CANTIDAD (unid.)]] -> 2233.9775 | AI14: =TABLA_BASE[[#This Row],[GASTOS IMP. UNIT.(US$)]]*'📋 Datos Generales'!$E$19 -> 2.8855542 | AJ14: =TABLA_BASE[[#This Row],[GASTOS IMP. UNIT.(S/.)]]*TABLA_BASE[[#This Row],[CANTIDAD (unid.)]] -> 8310.3962 | AK14: ='🧮 Costos x Producto'!J18 -> 0.77568663 | AL14: ='🧮 Costos x Producto'!K18 -> 2.8855542 | AM14: =TABLA_BASE[[#This Row],[C/M UNIT. (S/.)]]*TABLA_BASE[[#This Row],[CANTIDAD (unid.)]] -> 8310.3962 | AN14: =IF('🧾 Factura Comercial'!G18=0,0,'🧾 Tributos Aduana'!$F$17*(IF('🧾 Tributos Aduana'!$F$6=0,0,'🧾 Factura Comercial'!I18/'🧾 Tributos Aduana'!$F$6))/'🧾 Factura Comercial'!G18) -> 0.042880502 | AO14: =IF('🧾 Factura Comercial'!G18=0,0,'🏦 Crédito Fiscal'!$C$16*(IF('🧾 Tributos Aduana'!$F$6=0,0,'🧾 Factura Comercial'!I18/'🧾 Tributos Aduana'!$F$6))/'🧾 Factura Comercial'!G18) -> 0.17081417 | AP14: =TABLA_BASE[[#This Row],[CF UNIT. ✅RECUP. (US$)]]*'📋 Datos Generales'!$E$19 -> 0.6354287 | AQ14: =TABLA_BASE[[#This Row],[CF UNIT. ✅RECUP.(S/.)]]*TABLA_BASE[[#This Row],[CANTIDAD (unid.)]] -> 1830.0346 | AR14: ='💰 Precio de Venta'!G19 -> 0.4 | AS14: ='💰 Precio de Venta'!H19 -> 4.8092571 | AT14: =TABLA_BASE[[#This Row],[VALOR VTA. UNIT.(S/.)]]*TABLA_BASE[[#This Row],[CANTIDAD (unid.)]] -> 13850.66 | AU14: ='💰 Precio de Venta'!I19 -> 5.6749233 | AV14: ='💰 Precio de Venta'!J19 -> 1.9237028 | AW14: =TABLA_BASE[[#This Row],[GANANCIA UNIT.(S/.)]]*TABLA_BASE[[#This Row],[CANTIDAD (unid.)]] -> 5540.2642 | AX14: ='💰 Precio de Venta'!K19 -> 394 | AY14: =TABLA_BASE[[#This Row],[GANANCIA UNIT.(S/.)]]*'🧾 Factura Comercial'!G18 -> 5540.2642 | AZ14: =IF(TABLA_BASE[[#This Row],[PRECIO VTA. c/IGV(S/.)]]=0,0,TABLA_BASE[[#This Row],[GANANCIA UNIT.(S/.)]]/TABLA_BASE[[#This Row],[PRECIO VTA. c/IGV(S/.)]]) -> 0.33898305 | BA14: =IF(TABLA_BASE[[#This Row],[C/M UNIT. (S/.)]]=0,0,TABLA_BASE[[#This Row],[GANANCIA UNIT.(S/.)]]/TABLA_BASE[[#This Row],[C/M UNIT. (S/.)]]) -> 0.66666667 | BB14: =IF(TABLA_BASE[[#This Row],[MARGEN %]]>=0.5,"🟢 ALTO",IF(TABLA_BASE[[#This Row],[MARGEN %]]>=0.3,"🟡 MEDIO","🔴 BAJO")) -> 🟡 MEDIO
... A502: ='🧾 Factura Comercial'!E506 -> 0 | B502: ='🧾 Factura Comercial'!F506 -> Unid. | C502: ='🧾 Factura Comercial'!G506 -> 0 | D502: ='🧾 Factura Comercial'!H506 -> 0 | E502: ='🧾 Factura Comercial'!I506 -> 0 | F502: =IF('🧾 Tributos Aduana'!$F$6=0,0,'🧾 Factura Comercial'!I506/'🧾 Tributos Aduana'!$F$6) -> 0 | G502: ='🧾 Factura Comercial'!H506*'📋 Datos Generales'!$E$19 -> 0 | H502: =TABLA_BASE[[#This Row],[FOB UNIT. (S/.)]]*TABLA_BASE[[#This Row],[CANTIDAD (unid.)]] -> 0 | I502: =IF('🧾 Tributos Aduana'!$F$6=0,0,'🧾 Tributos Aduana'!$F$17*('🧾 Factura Comercial'!H506/'🧾 Tributos Aduana'!$F$6)) -> 0 | J502: =TABLA_BASE[[#This Row],[ADV UNIT. (US$) ⚠️COSTO]]*TABLA_BASE[[#This Row],[CANTIDAD (unid.)]] -> 0 | K502: =IF('🧾 Tributos Aduana'!$F$6=0,0,'🧾 Tributos Aduana'!$F$18*('🧾 Factura Comercial'!H506/'🧾 Tributos Aduana'!$F$6)) -> 0 | L502: =TABLA_BASE[[#This Row],[IPM UNIT. (US$) ✅CF]]*TABLA_BASE[[#This Row],[CANTIDAD (unid.)]] -> 0 | M502: =IF('🧾 Tributos Aduana'!$F$6=0,0,'🧾 Tributos Aduana'!$F$19*('🧾 Factura Comercial'!H506/'🧾 Tributos Aduana'!$F$6)) -> 0 | N502: =TABLA_BASE[[#This Row],[IGV UNIT. (US$) ✅CF]]*TABLA_BASE[[#This Row],[CANTIDAD (unid.)]] -> 0 | O502: =IF('🧾 Tributos Aduana'!$F$6=0,0,'🧾 Tributos Aduana'!$F$23*('🧾 Factura Comercial'!H506/'🧾 Tributos Aduana'!$F$6)) -> 0 | P502: =TABLA_BASE[[#This Row],[PERCEP. UNIT.(US$) ✅CF]]*TABLA_BASE[[#This Row],[CANTIDAD (unid.)]] -> 0 | Q502: =TABLA_BASE[[#This Row],[ADV UNIT. (US$) ⚠️COSTO]]+TABLA_BASE[[#This Row],[IPM UNIT. (US$) ✅CF]]+TABLA_BASE[[#This Row],[IGV UNIT. (US$) ✅CF]] -> 0 | R502: =TABLA_BASE[[#This Row],[DEUDA ADUANERA UNIT.]]*TABLA_BASE[[#This Row],[CANTIDAD (unid.)]] -> 0 | S502: =TABLA_BASE[[#This Row],[DEUDA ADUANERA UNIT.]]*'📋 Datos Generales'!$E$19 -> 0 | T502: =TABLA_BASE[[#This Row],[DEUDA ADUANERA TOTAL]]*'📋 Datos Generales'!$E$19 -> 0 | U502: =TABLA_BASE[[#This Row],[ADV UNIT. (US$) ⚠️COSTO]]*'📋 Datos Generales'!$E$19 -> 0 | V502: =TABLA_BASE[[#This Row],[ADV UNIT. (S/.)]]*TABLA_BASE[[#This Row],[CANTIDAD (unid.)]] -> 0 | W502: =TABLA_BASE[[#This Row],[IPM UNIT. (US$) ✅CF]]*'📋 Datos Generales'!$E$19 -> 0 | X502: =TABLA_BASE[[#This Row],[IPM UNIT. (S/.)]]*TABLA_BASE[[#This Row],[CANTIDAD (unid.)]] -> 0 | Y502: =TABLA_BASE[[#This Row],[IGV UNIT. (US$) ✅CF]]*'📋 Datos Generales'!$E$19 -> 0 | Z502: =TABLA_BASE[[#This Row],[IGV UNIT. (S/.)]]*TABLA_BASE[[#This Row],[CANTIDAD (unid.)]] -> 0 | AA502: =TABLA_BASE[[#This Row],[PERCEP. UNIT.(US$) ✅CF]]*'📋 Datos Generales'!$E$19 -> 0 | AB502: =TABLA_BASE[[#This Row],[PERCEP. UNIT.(S/.)]]*TABLA_BASE[[#This Row],[CANTIDAD (unid.)]] -> 0 | AC502: =TABLA_BASE[[#This Row],[ADV UNIT. (US$) ⚠️COSTO]]+TABLA_BASE[[#This Row],[IPM UNIT. (US$) ✅CF]]+TABLA_BASE[[#This Row],[IGV UNIT. (US$) ✅CF]]+TABLA_BASE[[#This Row],[PERCEP. UNIT.(US$) ✅CF]] -> 0 | AD502: =TABLA_BASE[[#This Row],[TOTAL PAGO SUNAT UNIT.(US$)]]*TABLA_BASE[[#This Row],[CANTIDAD (unid.)]] -> 0 | AE502: =TABLA_BASE[[#This Row],[TOTAL PAGO SUNAT UNIT.(US$)]]*'📋 Datos Generales'!$E$19 -> 0 | AF502: =TABLA_BASE[[#This Row],[TOTAL TRIB. UNIT.(S/.)]]*TABLA_BASE[[#This Row],[CANTIDAD (unid.)]] -> 0 | AG502: =IF('🧾 Factura Comercial'!G506=0,0,'📦 Gastos Importación'!$E$28*(IF('🧾 Tributos Aduana'!$F$6=0,0,'🧾 Factura Comercial'!I506/'🧾 Tributos Aduana'!$F$6))/'🧾 Factura Comercial'!G506) -> 0 | AH502: =TABLA_BASE[[#This Row],[GASTOS IMP. UNIT.(US$)]]*TABLA_BASE[[#This Row],[CANTIDAD (unid.)]] -> 0 | AI502: =TABLA_BASE[[#This Row],[GASTOS IMP. UNIT.(US$)]]*'📋 Datos Generales'!$E$19 -> 0 | AJ502: =TABLA_BASE[[#This Row],[GASTOS IMP. UNIT.(S/.)]]*TABLA_BASE[[#This Row],[CANTIDAD (unid.)]] -> 0 | AK502: ='🧮 Costos x Producto'!J506 -> 0 | AL502: ='🧮 Costos x Producto'!K506 -> 0 | AM502: =TABLA_BASE[[#This Row],[C/M UNIT. (S/.)]]*TABLA_BASE[[#This Row],[CANTIDAD (unid.)]] -> 0 | AN502: =IF('🧾 Factura Comercial'!G506=0,0,'🧾 Tributos Aduana'!$F$17*(IF('🧾 Tributos Aduana'!$F$6=0,0,'🧾 Factura Comercial'!I506/'🧾 Tributos Aduana'!$F$6))/'🧾 Factura Comercial'!G506) -> 0 | AO502: =IF('🧾 Factura Comercial'!G506=0,0,'🏦 Crédito Fiscal'!$C$16*(IF('🧾 Tributos Aduana'!$F$6=0,0,'🧾 Factura Comercial'!I506/'🧾 Tributos Aduana'!$F$6))/'🧾 Factura Comercial'!G506) -> 0 | AP502: =TABLA_BASE[[#This Row],[CF UNIT. ✅RECUP. (US$)]]*'📋 Datos Generales'!$E$19 -> 0 | AQ502: =TABLA_BASE[[#This Row],[CF UNIT. ✅RECUP.(S/.)]]*TABLA_BASE[[#This Row],[CANTIDAD (unid.)]] -> 0 | AR502: ='💰 Precio de Venta'!G507 -> 0.4 | AS502: ='💰 Precio de Venta'!H507 -> 0 | AT502: =TABLA_BASE[[#This Row],[VALOR VTA. UNIT.(S/.)]]*TABLA_BASE[[#This Row],[CANTIDAD (unid.)]] -> 0 | AU502: ='💰 Precio de Venta'!I507 -> 0 | AV502: ='💰 Precio de Venta'!J507 -> 0 | AW502: =TABLA_BASE[[#This Row],[GANANCIA UNIT.(S/.)]]*TABLA_BASE[[#This Row],[CANTIDAD (unid.)]] -> 0 | AX502: ='💰 Precio de Venta'!K507 -> 0 | AY502: =TABLA_BASE[[#This Row],[GANANCIA UNIT.(S/.)]]*'🧾 Factura Comercial'!G506 -> 0 | AZ502: =IF(TABLA_BASE[[#This Row],[PRECIO VTA. c/IGV(S/.)]]=0,0,TABLA_BASE[[#This Row],[GANANCIA UNIT.(S/.)]]/TABLA_BASE[[#This Row],[PRECIO VTA. c/IGV(S/.)]]) -> 0 | BA502: =IF(TABLA_BASE[[#This Row],[C/M UNIT. (S/.)]]=0,0,TABLA_BASE[[#This Row],[GANANCIA UNIT.(S/.)]]/TABLA_BASE[[#This Row],[C/M UNIT. (S/.)]]) -> 0 | BB502: =IF(TABLA_BASE[[#This Row],[MARGEN %]]>=0.5,"🟢 ALTO",IF(TABLA_BASE[[#This Row],[MARGEN %]]>=0.3,"🟡 MEDIO","🔴 BAJO")) -> 🟡 MEDIO
C503: =SUM(TABLA_BASE[CANTIDAD (unid.)]) -> 104672 | D503: =SUM(TABLA_BASE[FOB UNIT. (US$)]) -> 30.29 | E503: =SUM(TABLA_BASE[FOB TOTAL (US$)]) -> 43641.28 | G503: =SUM(TABLA_BASE[FOB UNIT. (S/.)]) -> 112.6788 | H503: =SUM(TABLA_BASE[FOB TOTAL (S/.)]) -> 162345.56 | I503: =SUM(TABLA_BASE[ADV UNIT. (US$) ⚠️COSTO]) -> 1.9100741 | J503: =SUM(TABLA_BASE[ADV TOTAL (US$) ⚠️COSTO]) -> 2752 | K503: =SUM(TABLA_BASE[IPM UNIT. (US$) ✅CF]) -> 0.67463374 | L503: =SUM(TABLA_BASE[IPM TOTAL (US$) ✅CF]) -> 972 | M503: =SUM(TABLA_BASE[IGV UNIT. (US$) ✅CF]) -> 5.3991521 | N503: =SUM(TABLA_BASE[IGV TOTAL (US$) ✅CF]) -> 7779 | O503: =SUM(TABLA_BASE[PERCEP. UNIT.(US$) ✅CF]) -> 1.3936184 | P503: =SUM(TABLA_BASE[PERCEP. TOTAL.(US$) ✅CF]) -> 2007.9 | Q503: =SUM(TABLA_BASE[DEUDA ADUANERA UNIT.]) -> 7.98386 | R503: =SUM(TABLA_BASE[DEUDA ADUANERA TOTAL]) -> 11503 | S503: =SUM(TABLA_BASE[DEUDA ADUANERA UNIT. /S/.)]) -> 29.699959 | T503: =SUM(TABLA_BASE[DEUDA ADUANERA TOTAL (s/.)2]) -> 42791.16 | U503: =SUM(TABLA_BASE[ADV UNIT. (S/.)]) -> 7.1054758 | V503: =SUM(TABLA_BASE[ADV TOTAL. (S/.)]) -> 10237.44 | W503: =SUM(TABLA_BASE[IPM UNIT. (S/.)]) -> 2.5096375 | X503: =SUM(TABLA_BASE[IPM TOTAL (S/.)2]) -> 3615.84 | Y503: =SUM(TABLA_BASE[IGV UNIT. (S/.)]) -> 20.084846 | Z503: =SUM(TABLA_BASE[IGV TOTAL (S/.)2]) -> 28937.88 | AA503: =SUM(TABLA_BASE[PERCEP. UNIT.(S/.)]) -> 5.1842605 | AB503: =SUM(TABLA_BASE[PERCEP. TOTAL.(S/.)2]) -> 7469.388 | AC503: =SUM(TABLA_BASE[TOTAL PAGO SUNAT UNIT.(US$)]) -> 9.3774784 | AD503: =SUM(TABLA_BASE[TOTAL PAGO SUNAT TOTAL(US$)]) -> 13510.9 | AE503: =SUM(TABLA_BASE[TOTAL TRIB. UNIT.(S/.)]) -> 34.88422 | AF503: =SUM(TABLA_BASE[TOTAL TRIB. TOTAL .(S/.)]) -> 50260.548 | AG503: =SUM(TABLA_BASE[GASTOS IMP. UNIT.(US$)]) -> 34.552276 | AH503: =SUM(TABLA_BASE[GASTOS IMP. TOTAL.(US$)2]) -> 49782.29 | AI503: =SUM(TABLA_BASE[GASTOS IMP. UNIT.(S/.)]) -> 128.53447 | AJ503: =SUM(TABLA_BASE[GASTOS IMP. TOTAL.(S/.)2]) -> 185190.12 | AK503: =SUM(TABLA_BASE[C/M UNIT. (US$)]) -> 34.552276 | AL503: =SUM(TABLA_BASE[C/M UNIT. (S/.)]) -> 128.53447 | AM503: =SUM(TABLA_BASE[C/M TOTAL (S/.)2]) -> 185190.12 | AN503: =SUM(TABLA_BASE[ADV UNIT. ⚠️COSTO (US$)]) -> 1.9100741 | AO503: =SUM(TABLA_BASE[CF UNIT. ✅RECUP. (US$)]) -> 7.6087663 | AP503: =SUM(TABLA_BASE[CF UNIT. ✅RECUP.(S/.)]) -> 28.304611 | AQ503: =SUM(TABLA_BASE[TOTAL CREDITO FISCAL POR PRODUCTO]) -> 40780.767 | AR503: =SUM(TABLA_BASE[MARGEN %]) -> 200 | AT503: =SUM(TABLA_BASE[VALOR VTA. TOTAL (S/.)]) -> 308650.2 | AW503: =SUM(TABLA_BASE[GANANCIA TOTAL.(S/.)]) -> 123460.08 | AY503: =SUM(TABLA_BASE[GANANCIA TOTAL(S/.)]) -> 123460.08 | BA503: =SUM(TABLA_BASE[ROI UNIT.]) -> 18.666667 | BB503: =SUM(TABLA_BASE[CLASIF. MARGEN]) -> 0

Sheet 📊 Dashboard
E1: 📊 CALCULADORA DE COSTOS DE IMPORTACIÓN — DASHBOARD EJECUTIVO
E2: ='📋 Datos Generales'!E6&" | DUA: "&'📋 Datos Generales'!E5&" | País: "&'📋 Datos Generales'!E9&" | Proveedor: "&'📋 Datos Generales'!E10&" | Incoterm: "&'📋 Datos Generales'!E11&" | TC: S/."&TEXT('📋 Datos Generales'!E19,"0.000") -> EMPRESA IMPORTADORA S.A.C. | DUA: DAM-2025-000001 | País: China | Proveedor: HWPI Co. Ltd. | Incoterm: FOB | TC: S/.3.720
E4: 💰 COSTO TOTAL IMPORTACIÓN (S/.) | F4: 📦 VALOR CIF (US$) | G4: ⚖️ ADV ARANCEL (US$) | H4: 📋 DEUDA ADUANERA (US$) | I4: 💹 INGRESOS EST. TOTALES (S/.) | J4: 🏦 CRÉDITO FISCAL (US$) | K4: 📈 MARGEN GLOBAL (%) | L4: 🎯 PERCEPCIÓN IGV (US$)
E5: ='🧮 Costos x Producto'!I4 -> 185190.12 | F5: ='🧾 Tributos Aduana'!F14 -> 45865.55 | G5: ='🧾 Tributos Aduana'!F17 -> 2752 | H5: ='🧾 Tributos Aduana'!F20 -> 11503 | I5: =SUMPRODUCT('🧾 Factura Comercial'!G7:G36,'💰 Precio de Venta'!H8:H37) -> 308650.2 | J5: ='🏦 Crédito Fiscal'!C16 -> 10962.572 | K5: =IF(SUMPRODUCT('🧾 Factura Comercial'!G7:G36,'💰 Precio de Venta'!H8:H37)=0,0,(SUMPRODUCT('🧾 Factura Comercial'!G7:G36,'💰 Precio de Venta'!H8:H37)-'🧮 Costos x Producto'!I4)/SUMPRODUCT('🧾 Factura Comercial'!G7:G36,'💰 Precio de Venta'!H8:H37)) -> 0.4 | L5: ='🧾 Tributos Aduana'!F23 -> 2007.9
E8: PERCEPCIÓN IGV (US$) | F8: TIPO DE CAMBIO (PEN) | G8: AD VALOREM (%) | H8: PERCEPCIÓN (%) | I8: CIF = VALOR EN ADUANAS (US$)
E9: ='🧾 Tributos Aduana'!F23 -> 2007.9 | F9: ='📋 Datos Generales'!E19 -> 3.72 | G9: ='📋 Datos Generales'!E20 -> 0.06 | H9: ='📋 Datos Generales'!E23 -> 0.035 | I9: ='🧾 Tributos Aduana'!F14 -> 45865.55
E12: 📊 DESGLOSE DE COSTOS DE IMPORTACIÓN
E13: CONCEPTO | F13: MONTO (US$) | G13: MONTO (S/.) | H13: % DEL TOTAL
E14: Valor FOB Total | F14: ='🧾 Tributos Aduana'!F6 -> 43641.28 | G14: =F14*'📋 Datos Generales'!E19 -> 162345.56 | H14: =IF('🧮 Costos x Producto'!G4=0,0,F14/'🧮 Costos x Producto'!G4) -> 0.87664268
E15: Flete Internacional | F15: ='🧾 Tributos Aduana'!F7 -> 2090 | G15: =F15*'📋 Datos Generales'!E19 -> 7774.8 | H15: =IF('🧮 Costos x Producto'!G4=0,0,F15/'🧮 Costos x Producto'!G4) -> 0.041982802
E16: Seguro (Prima Neta) | F16: ='🧾 Tributos Aduana'!F10 -> 134.27 | G16: =F16*'📋 Datos Generales'!E19 -> 499.4844 | H16: =IF('🧮 Costos x Producto'!G4=0,0,F16/'🧮 Costos x Producto'!G4) -> 0.0026971439
E17: Aranceles (ADV) | F17: ='🧾 Tributos Aduana'!F17 -> 2752 | G17: =F17*'📋 Datos Generales'!E19 -> 10237.44 | H17: =IF('🧮 Costos x Producto'!G4=0,0,F17/'🧮 Costos x Producto'!G4) -> 0.055280703
E18: IGV + IPM Aduanas | F18: ='🧾 Tributos Aduana'!F19+'🧾 Tributos Aduana'!F18 -> 8751 | G18: =F18*'📋 Datos Generales'!E19 -> 32553.72 | H18: =IF('🧮 Costos x Producto'!G4=0,0,F18/'🧮 Costos x Producto'!G4) -> 0.1757854
E19: Percepción IGV | F19: ='🧾 Tributos Aduana'!F23 -> 2007.9 | G19: =F19*'📋 Datos Generales'!E19 -> 7469.388 | H19: =IF('🧮 Costos x Producto'!G4=0,0,F19/'🧮 Costos x Producto'!G4) -> 0.040333621
E20: Gastos de Importación | F20: ='📦 Gastos Importación'!E28 -> 49782.29 | G20: =F20*'📋 Datos Generales'!E19 -> 185190.12 | H20: =IF('🧮 Costos x Producto'!G4=0,0,F20/'🧮 Costos x Producto'!G4) -> 1
E22: 💹 RESUMEN DE RENTABILIDAD
E23: Costo Total Importación (S/.) | F23: ='🧮 Costos x Producto'!I4 -> 185190.12 | G23: Ingresos Totales si se vende todo (S/.) | H23: =SUMPRODUCT('🧾 Factura Comercial'!G7:G36,'💰 Precio de Venta'!H8:H37) -> 308650.2
E24: Utilidad Bruta Total (S/.) | F24: =H23-F23 -> 123460.08 | G24: Margen Global Real (%) | H24: =IF(H23=0,0,(H23-F23)/H23) -> 0.4 | I24: =IF(H23=0,0,(H23-F23)/H23) -> 0.4
E25: Crédito Fiscal a Favor (US$) | F25: ='🏦 Crédito Fiscal'!C16 -> 10962.572 | G25: Crédito Fiscal a Favor (S/.) | H25: ='🏦 Crédito Fiscal'!C17 -> 40780.767
E26: 💹 ANÁLISIS DE RENTABILIDAD Y PRECIOS POR PRODUCTO
E27: 🏷️ TOTAL INGRESOS (S/.) | F27: 📦 COSTO TOTAL (S/.) | G27: 💵 UTILIDAD BRUTA (S/.) | H27: 📊 MARGEN NETO (%) | I27: 🏦 CF a FAVOR (US$) | J27: 🏦 CF a FAVOR (S/.) | K27: 📦 PRODS. IMPORTADOS | L27: 💲 FOB PROMEDIO (US$)
E28: =SUMPRODUCT('🧾 Factura Comercial'!G7:G36,'💰 Precio de Venta'!H8:H37) -> 308650.2 | F28: ='🧮 Costos x Producto'!I4 -> 185190.12 | G28: =E28-F28 -> 123460.08 | H28: =IF(E28=0,0,G28/E28) -> 0.4 | I28: ='🏦 Crédito Fiscal'!C16 -> 10962.572 | J28: ='🏦 Crédito Fiscal'!C17 -> 40780.767 | K28: =COUNTIF('🧾 Factura Comercial'!E7:E36,"?*") -> 28 | L28: =IF(K28=0,0,'🧾 Factura Comercial'!I507/K28) -> 1558.6171
E48: 🏦 DETALLE CRÉDITO FISCAL vs COSTOS REALES
E49: CONCEPTO | F49: MONTO (US$) | G49: MONTO (S/.) | H49: TIPO
E50: Ad Valorem (COSTO REAL) | F50: ='🧾 Tributos Aduana'!F17 -> 2752 | G50: =F50*'📋 Datos Generales'!E19 -> 10237.44 | H50: 💸 COSTO
E51: IPM (Crédito Fiscal) | F51: ='🧾 Tributos Aduana'!F18 -> 972 | G51: =F51*'📋 Datos Generales'!E19 -> 3615.84 | H51: ✅ CF
E52: IGV Aduanas (Crédito Fiscal) | F52: ='🧾 Tributos Aduana'!F19 -> 7779 | G52: =F52*'📋 Datos Generales'!E19 -> 28937.88 | H52: ✅ CF
E53: Percepción (Crédito Fiscal) | F53: ='🧾 Tributos Aduana'!F23 -> 2007.9 | G53: =F53*'📋 Datos Generales'!E19 -> 7469.388 | H53: ✅ CF
E54: IGV Seguro (Crédito Fiscal) | F54: ='🧾 Tributos Aduana'!F12 -> 24.1686 | G54: =F54*'📋 Datos Generales'!E19 -> 89.907192 | H54: ✅ CF
E55: IGV Gastos Afectos (CF) | F55: ='📦 Gastos Importación'!F26 -> 179.5032 | G55: =F55*'📋 Datos Generales'!E19 -> 667.7519 | H55: ✅ CF
E56: TOTAL CRÉDITO FISCAL (US$) | F56: ='🏦 Crédito Fiscal'!C16 -> 10962.572 | G56: ='🏦 Crédito Fiscal'!C17 -> 40780.767 | H56: COSTO REAL: ='🧾 Tributos Aduana'!C16&" US$"
N60: Componente | O60: US$ | P60: S/.
N61: FOB Mercadería | O61: ='🧾 Tributos Aduana'!F6 -> 43641.28 | P61: =O61*'📋 Datos Generales'!E19 -> 162345.56
N62: Flete | O62: ='🧾 Tributos Aduana'!F7 -> 2090 | P62: =O62*'📋 Datos Generales'!E19 -> 7774.8
N63: Seguro | O63: ='🧾 Tributos Aduana'!F10 -> 134.27 | P63: =O63*'📋 Datos Generales'!E19 -> 499.4844
N64: Aranceles (ADV) | O64: ='🧾 Tributos Aduana'!F17 -> 2752 | P64: =O64*'📋 Datos Generales'!E19 -> 10237.44
N65: Gastos Operativos | O65: ='📦 Gastos Importación'!E26 -> 997.24 | P65: =O65*'📋 Datos Generales'!E19 -> 3709.7328
N66: Gastos Admin/Fin. | O66: ='📦 Gastos Importación'!E27 -> 167.5 | P66: =O66*'📋 Datos Generales'!E19 -> 623.1
N70: Tributo | O70: Monto US$
N71: Ad Valorem | O71: ='🧾 Tributos Aduana'!F17 -> 2752
N72: IPM | O72: ='🧾 Tributos Aduana'!F18 -> 972
N73: IGV Aduanas | O73: ='🧾 Tributos Aduana'!F19 -> 7779
N74: Percepción | O74: ='🧾 Tributos Aduana'!F23 -> 2007.9
N75: IGV Seguro | O75: ='🧾 Tributos Aduana'!F12 -> 24.1686
N80: Producto | O80: FOB Total US$ | P80: C/M Unit PEN | Q80: PV Unit PEN | R80: Ganancia Unit PEN
N81: ='🧾 Factura Comercial'!E7 -> Case Transparente TPU iPhone 15 | O81: ='🧾 Factura Comercial'!I7 -> 580.8 | P81: ='🧮 Costos x Producto'!K7 -> 5.1345892 | Q81: ='💰 Precio de Venta'!H8 -> 8.5576486 | R81: ='💰 Precio de Venta'!J8 -> 3.4230594
N82: ='🧾 Factura Comercial'!E8 -> Cable USB-C Trenzado 1m | O82: ='🧾 Factura Comercial'!I8 -> 1958.4 | P82: ='🧮 Costos x Producto'!K8 -> 2.8855542 | Q82: ='💰 Precio de Venta'!H9 -> 4.8092571 | R82: ='💰 Precio de Venta'!J9 -> 1.9237028
N83: ='🧾 Factura Comercial'!E9 -> Protector Pantalla Vidrio Templado | O83: ='🧾 Factura Comercial'!I9 -> 1152 | P83: ='🧮 Costos x Producto'!K9 -> 1.6973849 | Q83: ='💰 Precio de Venta'!H10 -> 2.8289748 | R83: ='💰 Precio de Venta'!J10 -> 1.1315899
N84: ='🧾 Factura Comercial'!E10 -> Audífonos In-Ear con Micrófono | O84: ='🧾 Factura Comercial'!I10 -> 3476.16 | P84: ='🧮 Costos x Producto'!K10 -> 1.4427771 | Q84: ='💰 Precio de Venta'!H11 -> 2.4046285 | R84: ='💰 Precio de Venta'!J11 -> 0.96185142
N85: ='🧾 Factura Comercial'!E11 -> Cable Micro USB 2m Nylon | O85: ='🧾 Factura Comercial'!I11 -> 2246.4 | P85: ='🧮 Costos x Producto'!K11 -> 1.1033002 | Q85: ='💰 Precio de Venta'!H12 -> 1.8388336 | R85: ='💰 Precio de Venta'!J12 -> 0.73553344
N86: ='🧾 Factura Comercial'!E12 -> Soporte Anillo Pop Socket Metálico | O86: ='🧾 Factura Comercial'!I12 -> 626.4 | P86: ='🧮 Costos x Producto'!K12 -> 1.230604 | Q86: ='💰 Precio de Venta'!H13 -> 2.0510067 | R86: ='💰 Precio de Venta'!J13 -> 0.82040268
N87: ='🧾 Factura Comercial'!E13 -> Cargador Inalámbrico 15W Qi | O87: ='🧾 Factura Comercial'!I13 -> 1370.4 | P87: ='🧮 Costos x Producto'!K13 -> 24.230169 | Q87: ='💰 Precio de Venta'!H14 -> 40.383615 | R87: ='💰 Precio de Venta'!J14 -> 16.153446
N88: ='🧾 Factura Comercial'!E14 -> Case Wallet Cuero PU Samsung S24 | O88: ='🧾 Factura Comercial'!I14 -> 1459.2 | P88: ='🧮 Costos x Producto'!K14 -> 3.2250312 | Q88: ='💰 Precio de Venta'!H15 -> 5.375052 | R88: ='💰 Precio de Venta'!J15 -> 2.1500208
N89: ='🧾 Factura Comercial'!E15 -> Adaptador USB-C a Jack 3.5mm | O89: ='🧾 Factura Comercial'!I15 -> 1344 | P89: ='🧮 Costos x Producto'!K15 -> 1.1881694 | Q89: ='💰 Precio de Venta'!H16 -> 1.9802823 | R89: ='💰 Precio de Venta'!J16 -> 0.79211293
N90: Concepto | O90: Monto US$ | P90: Tipo
N91: Ad Valorem | O91: ='🧾 Tributos Aduana'!F17 -> 2752
N92: IPM | O92: ='🧾 Tributos Aduana'!F18 -> 972
N93: IGV Aduanas | O93: ='🧾 Tributos Aduana'!F19 -> 7779
N94: Percepción | O94: ='🧾 Tributos Aduana'!F23 -> 2007.9
N95: IGV Seguro | O95: ='🧾 Tributos Aduana'!F12 -> 24.1686
N96: IGV Gastos | O96: ='📦 Gastos Importación'!F26 -> 179.5032
N100: Concepto | O100: US$
N101: Costo Real (ADV) | O101: ='🧾 Tributos Aduana'!F17 -> 2752
N102: Crédito Fiscal | O102: ='🏦 Crédito Fiscal'!C16 -> 10962.572

Sheet 📊 Dashboard General
C13: ='📋 Datos Generales'!E6&" | DUA: "&'📋 Datos Generales'!E5&" | País: "&'📋 Datos Generales'!E9&" | Proveedor: "&'📋 Datos Generales'!E10&" | Incoterm: "&'📋 Datos Generales'!E11&" | TC: S/."&TEXT('📋 Datos Generales'!E19,"0.000") -> EMPRESA IMPORTADORA S.A.C. | DUA: DAM-2025-000001 | País: China | Proveedor: HWPI Co. Ltd. | Incoterm: FOB | TC: S/.3.720
AK20: ¿

Sheet 🏦Detallado por Producto
B2: 🔍 ANÁLISIS DETALLADO POR PRODUCTO — TODOS LOS COSTOS, TRIBUTOS Y MÁRGENES
B4: 📦 FOB TOTAL (US$): | C4: ='[1]🧾 Tributos Aduana'!C5 -> 14213.76 | E4: 🚢 CIF (US$): | F4: ='[1]🧾 Tributos Aduana'!C13 -> 14687.558 | H4: ⚖️ FACTOR PRORRATEO: | I4: ='[1]🧮 Costos x Producto'!D4 -> 0 | K4: 💱 TIPO DE CAMBIO: | L4: ='[1]📋 Datos Generales'!C19 -> 3.72 | N4: 📊 COSTO TOTAL (US$): | O4: ='[1]🧮 Costos x Producto'!D3 -> 0 | Q4: 🏦 CRÉDITO FISCAL (US$): | R4: ='[1]🏦 Crédito Fiscal'!C10 -> 6341.0973
B6: 📦 SECCIÓN 1: IDENTIFICACIÓN DEL PRODUCTO Y VALOR FOB
B7: # | C7: DESCRIPCIÓN DEL PRODUCTO | D7: UNIDAD | E7: CANTIDAD (unid.) | F7: FOB UNIT. (US$) | G7: FOB TOTAL (US$) | H7: % PART. FOB | I7: FOB UNIT. (S/.) | J7: FOB TOTAL (S/.)
B8: =1 -> 1 | C8: ='🧾 Factura Comercial'!E5:E34 | D8: ='[1]🧾 Factura Comercial'!D4 -> Unid. | E8: ='[1]🧾 Factura Comercial'!E4 -> 480 | F8: ='[1]🧾 Factura Comercial'!F4 -> 1.21 | G8: ='[1]🧾 Factura Comercial'!G4 -> 580.8 | H8: =IF('[1]🧾 Tributos Aduana'!C5=0,0,'[1]🧾 Factura Comercial'!G4/'[1]🧾 Tributos Aduana'!C5) -> 0.040861813 | I8: ='[1]🧾 Factura Comercial'!F4*'[1]📋 Datos Generales'!C19 -> 4.5012 | J8: ='[1]🧾 Factura Comercial'!G4*'[1]📋 Datos Generales'!C19 -> 2160.576
B9: =2 -> 2 | C9: ='[1]🧾 Factura Comercial'!C5 -> Friction Cars OPP Bag 23cm | D9: ='[1]🧾 Factura Comercial'!D5 -> Unid. | E9: ='[1]🧾 Factura Comercial'!E5 -> 2880 | F9: ='[1]🧾 Factura Comercial'!F5 -> 0.68 | G9: ='[1]🧾 Factura Comercial'!G5 -> 1958.4 | H9: =IF('[1]🧾 Tributos Aduana'!C5=0,0,'[1]🧾 Factura Comercial'!G5/'[1]🧾 Tributos Aduana'!C5) -> 0.13778198 | I9: ='[1]🧾 Factura Comercial'!F5*'[1]📋 Datos Generales'!C19 -> 2.5296 | J9: ='[1]🧾 Factura Comercial'!G5*'[1]📋 Datos Generales'!C19 -> 7285.248 | L9: Free Wheel Motor OPP Bag 21cm
B10: =3 -> 3 | C10: ='[1]🧾 Factura Comercial'!C6 -> Free Wheel Motor OPP Bag 21cm | D10: ='[1]🧾 Factura Comercial'!D6 -> Unid. | E10: ='[1]🧾 Factura Comercial'!E6 -> 2880 | F10: ='[1]🧾 Factura Comercial'!F6 -> 0.4 | G10: ='[1]🧾 Factura Comercial'!G6 -> 1152 | H10: =IF('[1]🧾 Tributos Aduana'!C5=0,0,'[1]🧾 Factura Comercial'!G6/'[1]🧾 Tributos Aduana'!C5) -> 0.081048224 | I10: ='[1]🧾 Factura Comercial'!F6*'[1]📋 Datos Generales'!C19 -> 1.488 | J10: ='[1]🧾 Factura Comercial'!G6*'[1]📋 Datos Generales'!C19 -> 4285.44
B11: =4 -> 4 | C11: ='[1]🧾 Factura Comercial'!C7 -> Friction Cars OPP Bag 22cm | D11: ='[1]🧾 Factura Comercial'!D7 -> Unid. | E11: ='[1]🧾 Factura Comercial'!E7 -> 10224 | F11: ='[1]🧾 Factura Comercial'!F7 -> 0.34 | G11: ='[1]🧾 Factura Comercial'!G7 -> 3476.16 | H11: =IF('[1]🧾 Tributos Aduana'!C5=0,0,'[1]🧾 Factura Comercial'!G7/'[1]🧾 Tributos Aduana'!C5) -> 0.24456301 | I11: ='[1]🧾 Factura Comercial'!F7*'[1]📋 Datos Generales'!C19 -> 1.2648 | J11: ='[1]🧾 Factura Comercial'!G7*'[1]📋 Datos Generales'!C19 -> 12931.315
B12: =5 -> 5 | C12: ='[1]🧾 Factura Comercial'!C8 -> Pull Line Friction Car OPP Bag | D12: ='[1]🧾 Factura Comercial'!D8 -> Unid. | E12: ='[1]🧾 Factura Comercial'!E8 -> 8640 | F12: ='[1]🧾 Factura Comercial'!F8 -> 0.26 | G12: ='[1]🧾 Factura Comercial'!G8 -> 2246.4 | H12: =IF('[1]🧾 Tributos Aduana'!C5=0,0,'[1]🧾 Factura Comercial'!G8/'[1]🧾 Tributos Aduana'!C5) -> 0.15804404 | I12: ='[1]🧾 Factura Comercial'!F8*'[1]📋 Datos Generales'!C19 -> 0.9672 | J12: ='[1]🧾 Factura Comercial'!G8*'[1]📋 Datos Generales'!C19 -> 8356.608
B13: =6 -> 6 | C13: ='[1]🧾 Factura Comercial'!C9 -> Friction Car OPP Bag | D13: ='[1]🧾 Factura Comercial'!D9 -> Unid. | E13: ='[1]🧾 Factura Comercial'!E9 -> 2160 | F13: ='[1]🧾 Factura Comercial'!F9 -> 0.29 | G13: ='[1]🧾 Factura Comercial'!G9 -> 626.4 | H13: =IF('[1]🧾 Tributos Aduana'!C5=0,0,'[1]🧾 Factura Comercial'!G9/'[1]🧾 Tributos Aduana'!C5) -> 0.044069972 | I13: ='[1]🧾 Factura Comercial'!F9*'[1]📋 Datos Generales'!C19 -> 1.0788 | J13: ='[1]🧾 Factura Comercial'!G9*'[1]📋 Datos Generales'!C19 -> 2330.208
B14: =7 -> 7 | C14: ='[1]🧾 Factura Comercial'!C10 -> Free Wheel Ride on Digger Handle | D14: ='[1]🧾 Factura Comercial'!D10 -> Unid. | E14: ='[1]🧾 Factura Comercial'!E10 -> 240 | F14: ='[1]🧾 Factura Comercial'!F10 -> 5.71 | G14: ='[1]🧾 Factura Comercial'!G10 -> 1370.4 | H14: =IF('[1]🧾 Tributos Aduana'!C5=0,0,'[1]🧾 Factura Comercial'!G10/'[1]🧾 Tributos Aduana'!C5) -> 0.096413616 | I14: ='[1]🧾 Factura Comercial'!F10*'[1]📋 Datos Generales'!C19 -> 21.2412 | J14: ='[1]🧾 Factura Comercial'!G10*'[1]📋 Datos Generales'!C19 -> 5097.888
B15: =8 -> 8 | C15: ='[1]🧾 Factura Comercial'!C11 -> Friction Car with Music and Light | D15: ='[1]🧾 Factura Comercial'!D11 -> Unid. | E15: ='[1]🧾 Factura Comercial'!E11 -> 1920 | F15: ='[1]🧾 Factura Comercial'!F11 -> 0.76 | G15: ='[1]🧾 Factura Comercial'!G11 -> 1459.2 | H15: =IF('[1]🧾 Tributos Aduana'!C5=0,0,'[1]🧾 Factura Comercial'!G11/'[1]🧾 Tributos Aduana'!C5) -> 0.10266108 | I15: ='[1]🧾 Factura Comercial'!F11*'[1]📋 Datos Generales'!C19 -> 2.8272 | J15: ='[1]🧾 Factura Comercial'!G11*'[1]📋 Datos Generales'!C19 -> 5428.224
B16: =9 -> 9 | C16: ='[1]🧾 Factura Comercial'!C12 -> Pull Line Function Car OPP Bag | D16: ='[1]🧾 Factura Comercial'!D12 -> Unid. | E16: ='[1]🧾 Factura Comercial'!E12 -> 4800 | F16: ='[1]🧾 Factura Comercial'!F12 -> 0.28 | G16: ='[1]🧾 Factura Comercial'!G12 -> 1344 | H16: =IF('[1]🧾 Tributos Aduana'!C5=0,0,'[1]🧾 Factura Comercial'!G12/'[1]🧾 Tributos Aduana'!C5) -> 0.094556261 | I16: ='[1]🧾 Factura Comercial'!F12*'[1]📋 Datos Generales'!C19 -> 1.0416 | J16: ='[1]🧾 Factura Comercial'!G12*'[1]📋 Datos Generales'!C19 -> 4999.68
C17: ✦ TOTALES | E17: =SUM('[1]🧾 Factura Comercial'!E4:E12) -> 34224 | G17: ='[1]🧾 Tributos Aduana'!C5 -> 14213.76 | H17: =1 -> 1 | J17: ='[1]🧾 Tributos Aduana'!C5*'[1]📋 Datos Generales'!C19 -> 52875.187
B19: ⚖️ SECCIÓN 2: TRIBUTOS ADUANEROS POR PRODUCTO (prorrateo por FOB)
B20: # | C20: PRODUCTO | D20: FACTOR PRORRATEO | E20: ADV UNIT. (US$) ⚠️COSTO | F20: IPM UNIT. (US$) ✅CF | G20: IGV UNIT. (US$) ✅CF | H20: PERCEP. UNIT.(US$) ✅CF | I20: DEUDA ADUANERA UNIT. | J20: ADV UNIT. (S/.) | K20: IPM UNIT. (S/.) | L20: IGV UNIT. (S/.) | M20: PERCEP. UNIT.(S/.) | N20: TOTAL TRIB. UNIT.(US$) | O20: TOTAL TRIB. UNIT.(S/.)
B21: =1 -> 1 | C21: ='[1]🧾 Factura Comercial'!C4 -> Friction Car Platform Cover | D21: ='[1]🧮 Costos x Producto'!F6 -> 580.8 | E21: =IF('[1]🧾 Tributos Aduana'!C5=0,0,'[1]🧾 Tributos Aduana'!C16*('[1]🧾 Factura Comercial'!F4/'[1]🧾 Tributos Aduana'!C5)) -> 0.074998452 | F21: =IF('[1]🧾 Tributos Aduana'!C5=0,0,'[1]🧾 Tributos Aduana'!C17*('[1]🧾 Factura Comercial'!F4/'[1]🧾 Tributos Aduana'!C5)) -> 0.02647505 | G21: =IF('[1]🧾 Tributos Aduana'!C5=0,0,'[1]🧾 Tributos Aduana'!C18*('[1]🧾 Factura Comercial'!F4/'[1]🧾 Tributos Aduana'!C5)) -> 0.21205578 | H21: =IF('[1]🧾 Tributos Aduana'!C5=0,0,'[1]🧾 Tributos Aduana'!C22*('[1]🧾 Factura Comercial'!F4/'[1]🧾 Tributos Aduana'!C5)) -> 0.05473525 | I21: =D21+E21+F21+G21 -> 581.11353 | J21: =D21*'[1]📋 Datos Generales'!C19 -> 2160.576 | K21: =E21*'[1]📋 Datos Generales'!C19 -> 0.27899424 | L21: =F21*'[1]📋 Datos Generales'!C19 -> 0.098487184 | M21: =G21*'[1]📋 Datos Generales'!C19 -> 0.78884751 | N21: =D21+E21+F21+G21 -> 581.11353 | O21: =N21*'[1]📋 Datos Generales'!C19 -> 2161.7423
B22: =2 -> 2 | C22: ='[1]🧾 Factura Comercial'!C5 -> Friction Cars OPP Bag 23cm | D22: ='[1]🧮 Costos x Producto'!F7 -> 1958.4 | E22: =IF('[1]🧾 Tributos Aduana'!C5=0,0,'[1]🧾 Tributos Aduana'!C16*('[1]🧾 Factura Comercial'!F5/'[1]🧾 Tributos Aduana'!C5)) -> 0.04214789 | F22: =IF('[1]🧾 Tributos Aduana'!C5=0,0,'[1]🧾 Tributos Aduana'!C17*('[1]🧾 Factura Comercial'!F5/'[1]🧾 Tributos Aduana'!C5)) -> 0.01487854 | G22: =IF('[1]🧾 Tributos Aduana'!C5=0,0,'[1]🧾 Tributos Aduana'!C18*('[1]🧾 Factura Comercial'!F5/'[1]🧾 Tributos Aduana'!C5)) -> 0.11917184 | H22: =IF('[1]🧾 Tributos Aduana'!C5=0,0,'[1]🧾 Tributos Aduana'!C22*('[1]🧾 Factura Comercial'!F5/'[1]🧾 Tributos Aduana'!C5)) -> 0.030760306 | I22: =D22+E22+F22+G22 -> 1958.5762 | J22: =D22*'[1]📋 Datos Generales'!C19 -> 7285.248 | K22: =E22*'[1]📋 Datos Generales'!C19 -> 0.15679015 | L22: =F22*'[1]📋 Datos Generales'!C19 -> 0.05534817 | M22: =G22*'[1]📋 Datos Generales'!C19 -> 0.44331926 | N22: =D22+E22+F22+G22 -> 1958.5762 | O22: =N22*'[1]📋 Datos Generales'!C19 -> 7285.9035
B23: =3 -> 3 | C23: ='[1]🧾 Factura Comercial'!C6 -> Free Wheel Motor OPP Bag 21cm | D23: ='[1]🧮 Costos x Producto'!F8 -> 1152 | E23: =IF('[1]🧾 Tributos Aduana'!C5=0,0,'[1]🧾 Tributos Aduana'!C16*('[1]🧾 Factura Comercial'!F6/'[1]🧾 Tributos Aduana'!C5)) -> 0.024792877 | F23: =IF('[1]🧾 Tributos Aduana'!C5=0,0,'[1]🧾 Tributos Aduana'!C17*('[1]🧾 Factura Comercial'!F6/'[1]🧾 Tributos Aduana'!C5)) -> 0.0087520825 | G23: =IF('[1]🧾 Tributos Aduana'!C5=0,0,'[1]🧾 Tributos Aduana'!C18*('[1]🧾 Factura Comercial'!F6/'[1]🧾 Tributos Aduana'!C5)) -> 0.070101085 | H23: =IF('[1]🧾 Tributos Aduana'!C5=0,0,'[1]🧾 Tributos Aduana'!C22*('[1]🧾 Factura Comercial'!F6/'[1]🧾 Tributos Aduana'!C5)) -> 0.018094297 | I23: =D23+E23+F23+G23 -> 1152.1036 | J23: =D23*'[1]📋 Datos Generales'!C19 -> 4285.44 | K23: =E23*'[1]📋 Datos Generales'!C19 -> 0.092229502 | L23: =F23*'[1]📋 Datos Generales'!C19 -> 0.032557747 | M23: =G23*'[1]📋 Datos Generales'!C19 -> 0.26077604 | N23: =D23+E23+F23+G23 -> 1152.1036 | O23: =N23*'[1]📋 Datos Generales'!C19 -> 4285.8256
B24: =4 -> 4 | C24: ='[1]🧾 Factura Comercial'!C7 -> Friction Cars OPP Bag 22cm | D24: ='[1]🧮 Costos x Producto'!F9 -> 3476.16 | E24: =IF('[1]🧾 Tributos Aduana'!C5=0,0,'[1]🧾 Tributos Aduana'!C16*('[1]🧾 Factura Comercial'!F7/'[1]🧾 Tributos Aduana'!C5)) -> 0.021073945 | F24: =IF('[1]🧾 Tributos Aduana'!C5=0,0,'[1]🧾 Tributos Aduana'!C17*('[1]🧾 Factura Comercial'!F7/'[1]🧾 Tributos Aduana'!C5)) -> 0.0074392701 | G24: =IF('[1]🧾 Tributos Aduana'!C5=0,0,'[1]🧾 Tributos Aduana'!C18*('[1]🧾 Factura Comercial'!F7/'[1]🧾 Tributos Aduana'!C5)) -> 0.059585922 | H24: =IF('[1]🧾 Tributos Aduana'!C5=0,0,'[1]🧾 Tributos Aduana'!C22*('[1]🧾 Factura Comercial'!F7/'[1]🧾 Tributos Aduana'!C5)) -> 0.015380153 | I24: =D24+E24+F24+G24 -> 3476.2481 | J24: =D24*'[1]📋 Datos Generales'!C19 -> 12931.315 | K24: =E24*'[1]📋 Datos Generales'!C19 -> 0.078395076 | L24: =F24*'[1]📋 Datos Generales'!C19 -> 0.027674085 | M24: =G24*'[1]📋 Datos Generales'!C19 -> 0.22165963 | N24: =D24+E24+F24+G24 -> 3476.2481 | O24: =N24*'[1]📋 Datos Generales'!C19 -> 12931.643
B25: =5 -> 5 | C25: ='[1]🧾 Factura Comercial'!C8 -> Pull Line Friction Car OPP Bag | D25: ='[1]🧮 Costos x Producto'!F10 -> 2246.4 | E25: =IF('[1]🧾 Tributos Aduana'!C5=0,0,'[1]🧾 Tributos Aduana'!C16*('[1]🧾 Factura Comercial'!F8/'[1]🧾 Tributos Aduana'!C5)) -> 0.01611537 | F25: =IF('[1]🧾 Tributos Aduana'!C5=0,0,'[1]🧾 Tributos Aduana'!C17*('[1]🧾 Factura Comercial'!F8/'[1]🧾 Tributos Aduana'!C5)) -> 0.0056888536 | G25: =IF('[1]🧾 Tributos Aduana'!C5=0,0,'[1]🧾 Tributos Aduana'!C18*('[1]🧾 Factura Comercial'!F8/'[1]🧾 Tributos Aduana'!C5)) -> 0.045565705 | H25: =IF('[1]🧾 Tributos Aduana'!C5=0,0,'[1]🧾 Tributos Aduana'!C22*('[1]🧾 Factura Comercial'!F8/'[1]🧾 Tributos Aduana'!C5)) -> 0.011761293 | I25: =D25+E25+F25+G25 -> 2246.4674 | J25: =D25*'[1]📋 Datos Generales'!C19 -> 8356.608 | K25: =E25*'[1]📋 Datos Generales'!C19 -> 0.059949176 | L25: =F25*'[1]📋 Datos Generales'!C19 -> 0.021162535 | M25: =G25*'[1]📋 Datos Generales'!C19 -> 0.16950442 | N25: =D25+E25+F25+G25 -> 2246.4674 | O25: =N25*'[1]📋 Datos Generales'!C19 -> 8356.8586
B26: =6 -> 6 | C26: ='[1]🧾 Factura Comercial'!C9 -> Friction Car OPP Bag | D26: ='[1]🧮 Costos x Producto'!F11 -> 626.4 | E26: =IF('[1]🧾 Tributos Aduana'!C5=0,0,'[1]🧾 Tributos Aduana'!C16*('[1]🧾 Factura Comercial'!F9/'[1]🧾 Tributos Aduana'!C5)) -> 0.017974836 | F26: =IF('[1]🧾 Tributos Aduana'!C5=0,0,'[1]🧾 Tributos Aduana'!C17*('[1]🧾 Factura Comercial'!F9/'[1]🧾 Tributos Aduana'!C5)) -> 0.0063452598 | G26: =IF('[1]🧾 Tributos Aduana'!C5=0,0,'[1]🧾 Tributos Aduana'!C18*('[1]🧾 Factura Comercial'!F9/'[1]🧾 Tributos Aduana'!C5)) -> 0.050823287 | H26: =IF('[1]🧾 Tributos Aduana'!C5=0,0,'[1]🧾 Tributos Aduana'!C22*('[1]🧾 Factura Comercial'!F9/'[1]🧾 Tributos Aduana'!C5)) -> 0.013118366 | I26: =D26+E26+F26+G26 -> 626.47514 | J26: =D26*'[1]📋 Datos Generales'!C19 -> 2330.208 | K26: =E26*'[1]📋 Datos Generales'!C19 -> 0.066866389 | L26: =F26*'[1]📋 Datos Generales'!C19 -> 0.023604366 | M26: =G26*'[1]📋 Datos Generales'!C19 -> 0.18906263 | N26: =D26+E26+F26+G26 -> 626.47514 | O26: =N26*'[1]📋 Datos Generales'!C19 -> 2330.4875
B27: =7 -> 7 | C27: ='[1]🧾 Factura Comercial'!C10 -> Free Wheel Ride on Digger Handle | D27: ='[1]🧮 Costos x Producto'!F12 -> 1370.4 | E27: =IF('[1]🧾 Tributos Aduana'!C5=0,0,'[1]🧾 Tributos Aduana'!C16*('[1]🧾 Factura Comercial'!F10/'[1]🧾 Tributos Aduana'!C5)) -> 0.35391832 | F27: =IF('[1]🧾 Tributos Aduana'!C5=0,0,'[1]🧾 Tributos Aduana'!C17*('[1]🧾 Factura Comercial'!F10/'[1]🧾 Tributos Aduana'!C5)) -> 0.12493598 | G27: =IF('[1]🧾 Tributos Aduana'!C5=0,0,'[1]🧾 Tributos Aduana'!C18*('[1]🧾 Factura Comercial'!F10/'[1]🧾 Tributos Aduana'!C5)) -> 1.000693 | H27: =IF('[1]🧾 Tributos Aduana'!C5=0,0,'[1]🧾 Tributos Aduana'!C22*('[1]🧾 Factura Comercial'!F10/'[1]🧾 Tributos Aduana'!C5)) -> 0.25829609 | I27: =D27+E27+F27+G27 -> 1371.8795 | J27: =D27*'[1]📋 Datos Generales'!C19 -> 5097.888 | K27: =E27*'[1]📋 Datos Generales'!C19 -> 1.3165761 | L27: =F27*'[1]📋 Datos Generales'!C19 -> 0.46476184 | M27: =G27*'[1]📋 Datos Generales'!C19 -> 3.7225779 | N27: =D27+E27+F27+G27 -> 1371.8795 | O27: =N27*'[1]📋 Datos Generales'!C19 -> 5103.3919
B28: =8 -> 8 | C28: ='[1]🧾 Factura Comercial'!C11 -> Friction Car with Music and Light | D28: ='[1]🧮 Costos x Producto'!F13 -> 1459.2 | E28: =IF('[1]🧾 Tributos Aduana'!C5=0,0,'[1]🧾 Tributos Aduana'!C16*('[1]🧾 Factura Comercial'!F11/'[1]🧾 Tributos Aduana'!C5)) -> 0.047106466 | F28: =IF('[1]🧾 Tributos Aduana'!C5=0,0,'[1]🧾 Tributos Aduana'!C17*('[1]🧾 Factura Comercial'!F11/'[1]🧾 Tributos Aduana'!C5)) -> 0.016628957 | G28: =IF('[1]🧾 Tributos Aduana'!C5=0,0,'[1]🧾 Tributos Aduana'!C18*('[1]🧾 Factura Comercial'!F11/'[1]🧾 Tributos Aduana'!C5)) -> 0.13319206 | H28: =IF('[1]🧾 Tributos Aduana'!C5=0,0,'[1]🧾 Tributos Aduana'!C22*('[1]🧾 Factura Comercial'!F11/'[1]🧾 Tributos Aduana'!C5)) -> 0.034379165 | I28: =D28+E28+F28+G28 -> 1459.3969 | J28: =D28*'[1]📋 Datos Generales'!C19 -> 5428.224 | K28: =E28*'[1]📋 Datos Generales'!C19 -> 0.17523605 | L28: =F28*'[1]📋 Datos Generales'!C19 -> 0.061859719 | M28: =G28*'[1]📋 Datos Generales'!C19 -> 0.49547447 | N28: =D28+E28+F28+G28 -> 1459.3969 | O28: =N28*'[1]📋 Datos Generales'!C19 -> 5428.9566
B29: =9 -> 9 | C29: ='[1]🧾 Factura Comercial'!C12 -> Pull Line Function Car OPP Bag | D29: ='[1]🧮 Costos x Producto'!F14 -> 1344 | E29: =IF('[1]🧾 Tributos Aduana'!C5=0,0,'[1]🧾 Tributos Aduana'!C16*('[1]🧾 Factura Comercial'!F12/'[1]🧾 Tributos Aduana'!C5)) -> 0.017355014 | F29: =IF('[1]🧾 Tributos Aduana'!C5=0,0,'[1]🧾 Tributos Aduana'!C17*('[1]🧾 Factura Comercial'!F12/'[1]🧾 Tributos Aduana'!C5)) -> 0.0061264577 | G29: =IF('[1]🧾 Tributos Aduana'!C5=0,0,'[1]🧾 Tributos Aduana'!C18*('[1]🧾 Factura Comercial'!F12/'[1]🧾 Tributos Aduana'!C5)) -> 0.04907076 | H29: =IF('[1]🧾 Tributos Aduana'!C5=0,0,'[1]🧾 Tributos Aduana'!C22*('[1]🧾 Factura Comercial'!F12/'[1]🧾 Tributos Aduana'!C5)) -> 0.012666008 | I29: =D29+E29+F29+G29 -> 1344.0726 | J29: =D29*'[1]📋 Datos Generales'!C19 -> 4999.68 | K29: =E29*'[1]📋 Datos Generales'!C19 -> 0.064560651 | L29: =F29*'[1]📋 Datos Generales'!C19 -> 0.022790423 | M29: =G29*'[1]📋 Datos Generales'!C19 -> 0.18254323 | N29: =D29+E29+F29+G29 -> 1344.0726 | O29: =N29*'[1]📋 Datos Generales'!C19 -> 4999.9499
C30: ✦ TOTALES | E30: ='[1]🧾 Tributos Aduana'!C16 -> 881 | F30: ='[1]🧾 Tributos Aduana'!C17 -> 311 | G30: ='[1]🧾 Tributos Aduana'!C18 -> 2491 | H30: ='[1]🧾 Tributos Aduana'!C22 -> 642.97 | I30: ='[1]🧾 Tributos Aduana'!C19+'[1]🧾 Tributos Aduana'!C22 -> 4325.97 | N30: ='[1]🧾 Tributos Aduana'!C19 -> 3683 | O30: ='[1]🧾 Tributos Aduana'!C19*'[1]📋 Datos Generales'!C19 -> 13700.76
B32: 🧮 SECCIÓN 3: COSTO DE IMPORTACIÓN · CRÉDITO FISCAL · PRECIO DE VENTA · MARGEN
B33: # | C33: PRODUCTO | D33: GASTOS IMP. UNIT.(US$) | E33: GASTOS IMP. UNIT.(S/.) | F33: C/M UNIT. (US$) | G33: C/M UNIT. (S/.) | H33: ADV UNIT. ⚠️COSTO(US$) | I33: CF UNIT. ✅RECUP.(US$) | J33: CF UNIT. ✅RECUP.(S/.) | K33: MARGEN % | L33: VALOR VTA. UNIT.(S/.) | M33: PRECIO VTA. c/IGV(S/.) | N33: GANANCIA UNIT.(S/.) | O33: PUNTO EQUILIBRIO | P33: GANANCIA TOTAL(S/.) | Q33: % UTILIDAD S/PRECIO | R33: ROI UNIT. | S33: CLASIF. MARGEN
B34: =1 -> 1 | C34: ='[1]🧾 Factura Comercial'!C4 -> Friction Car Platform Cover | D34: =IF('[1]🧾 Factura Comercial'!E4=0,0,'[1]📦 Gastos Importación'!C27*(IF('[1]🧾 Tributos Aduana'!C5=0,0,'[1]🧾 Factura Comercial'!F4/'[1]🧾 Tributos Aduana'!C5))/'[1]🧾 Factura Comercial'!E4) -> 0.0028601925 | E34: =D34*'[1]📋 Datos Generales'!C19 -> 0.010639916 | F34: ='[1]🧮 Costos x Producto'!H6 -> 2.6982247 | G34: ='[1]🧮 Costos x Producto'!I6 -> 10.037396 | H34: =IF('[1]🧾 Factura Comercial'!E4=0,0,'[1]🧾 Tributos Aduana'!C16*(IF('[1]🧾 Tributos Aduana'!C5=0,0,'[1]🧾 Factura Comercial'!F4/'[1]🧾 Tributos Aduana'!C5))/'[1]🧾 Factura Comercial'!E4) -> 0.00015624678 | I34: =IF('[1]🧾 Factura Comercial'!E4=0,0,'[1]🏦 Crédito Fiscal'!C10*(IF('[1]🧾 Tributos Aduana'!C5=0,0,'[1]🧾 Factura Comercial'!F4/'[1]🧾 Tributos Aduana'!C5))/'[1]🧾 Factura Comercial'!E4) -> 0.0011246039 | J34: =I34*'[1]📋 Datos Generales'!C19 -> 0.0041835264 | K34: ='[1]💰 Precio de Venta'!E5 -> 0.4 | L34: ='[1]💰 Precio de Venta'!F5 -> 16.728993 | M34: ='[1]💰 Precio de Venta'!G5 -> 19.740212 | N34: ='[1]💰 Precio de Venta'!H5 -> 6.6915973 | O34: ='[1]💰 Precio de Venta'!I5 -> 66 | P34: =N34*'[1]🧾 Factura Comercial'!E4 -> 3211.9667 | Q34: =IF(M34=0,0,N34/M34) -> 0.33898305 | R34: =IF(G34=0,0,N34/G34) -> 0.66666667 | S34: =IF(K34>=0.5,"🟢 ALTO",IF(K34>=0.3,"🟡 MEDIO","🔴 BAJO")) -> 🟡 MEDIO
B35: =2 -> 2 | C35: ='[1]🧾 Factura Comercial'!C5 -> Friction Cars OPP Bag 23cm | D35: =IF('[1]🧾 Factura Comercial'!E5=0,0,'[1]📦 Gastos Importación'!C27*(IF('[1]🧾 Tributos Aduana'!C5=0,0,'[1]🧾 Factura Comercial'!F5/'[1]🧾 Tributos Aduana'!C5))/'[1]🧾 Factura Comercial'!E5) -> 0.00026789682 | E35: =D35*'[1]📋 Datos Generales'!C19 -> 0.00099657616 | F35: ='[1]🧮 Costos x Producto'!H7 -> 1.5163577 | G35: ='[1]🧮 Costos x Producto'!I7 -> 5.6408506 | H35: =IF('[1]🧾 Factura Comercial'!E5=0,0,'[1]🧾 Tributos Aduana'!C16*(IF('[1]🧾 Tributos Aduana'!C5=0,0,'[1]🧾 Factura Comercial'!F5/'[1]🧾 Tributos Aduana'!C5))/'[1]🧾 Factura Comercial'!E5) -> 1.4634684e-05 | I35: =IF('[1]🧾 Factura Comercial'!E5=0,0,'[1]🏦 Crédito Fiscal'!C10*(IF('[1]🧾 Tributos Aduana'!C5=0,0,'[1]🧾 Factura Comercial'!F5/'[1]🧾 Tributos Aduana'!C5))/'[1]🧾 Factura Comercial'!E5) -> 0.0001053348 | J35: =I35*'[1]📋 Datos Generales'!C19 -> 0.00039184545 | K35: ='[1]💰 Precio de Venta'!E6 -> 0.4 | L35: ='[1]💰 Precio de Venta'!F6 -> 9.4014176 | M35: ='[1]💰 Precio de Venta'!G6 -> 11.093673 | N35: ='[1]💰 Precio de Venta'!H6 -> 3.7605671 | O35: ='[1]💰 Precio de Venta'!I6 -> 394 | P35: =N35*'[1]🧾 Factura Comercial'!E5 -> 10830.433 | Q35: =IF(M35=0,0,N35/M35) -> 0.33898305 | R35: =IF(G35=0,0,N35/G35) -> 0.66666667 | S35: =IF(K35>=0.5,"🟢 ALTO",IF(K35>=0.3,"🟡 MEDIO","🔴 BAJO")) -> 🟡 MEDIO
B36: =3 -> 3 | C36: ='[1]🧾 Factura Comercial'!C6 -> Free Wheel Motor OPP Bag 21cm | D36: =IF('[1]🧾 Factura Comercial'!E6=0,0,'[1]📦 Gastos Importación'!C27*(IF('[1]🧾 Tributos Aduana'!C5=0,0,'[1]🧾 Factura Comercial'!F6/'[1]🧾 Tributos Aduana'!C5))/'[1]🧾 Factura Comercial'!E6) -> 0.00015758636 | E36: =D36*'[1]📋 Datos Generales'!C19 -> 0.00058622127 | F36: ='[1]🧮 Costos x Producto'!H8 -> 0.89197511 | G36: ='[1]🧮 Costos x Producto'!I8 -> 3.3181474 | H36: =IF('[1]🧾 Factura Comercial'!E6=0,0,'[1]🧾 Tributos Aduana'!C16*(IF('[1]🧾 Tributos Aduana'!C5=0,0,'[1]🧾 Factura Comercial'!F6/'[1]🧾 Tributos Aduana'!C5))/'[1]🧾 Factura Comercial'!E6) -> 8.6086378e-06 | I36: =IF('[1]🧾 Factura Comercial'!E6=0,0,'[1]🏦 Crédito Fiscal'!C10*(IF('[1]🧾 Tributos Aduana'!C5=0,0,'[1]🧾 Factura Comercial'!F6/'[1]🧾 Tributos Aduana'!C5))/'[1]🧾 Factura Comercial'!E6) -> 6.1961645e-05 | J36: =I36*'[1]📋 Datos Generales'!C19 -> 0.00023049732 | K36: ='[1]💰 Precio de Venta'!E7 -> 0.4 | L36: ='[1]💰 Precio de Venta'!F7 -> 5.5302457 | M36: ='[1]💰 Precio de Venta'!G7 -> 6.5256899 | N36: ='[1]💰 Precio de Venta'!H7 -> 2.2120983 | O36: ='[1]💰 Precio de Venta'!I7 -> 394 | P36: =N36*'[1]🧾 Factura Comercial'!E6 -> 6370.843 | Q36: =IF(M36=0,0,N36/M36) -> 0.33898305 | R36: =IF(G36=0,0,N36/G36) -> 0.66666667 | S36: =IF(K36>=0.5,"🟢 ALTO",IF(K36>=0.3,"🟡 MEDIO","🔴 BAJO")) -> 🟡 MEDIO
B37: =4 -> 4 | C37: ='[1]🧾 Factura Comercial'!C7 -> Friction Cars OPP Bag 22cm | D37: =IF('[1]🧾 Factura Comercial'!E7=0,0,'[1]📦 Gastos Importación'!C27*(IF('[1]🧾 Tributos Aduana'!C5=0,0,'[1]🧾 Factura Comercial'!F7/'[1]🧾 Tributos Aduana'!C5))/'[1]🧾 Factura Comercial'!E7) -> 3.7731946e-05 | E37: =D37*'[1]📋 Datos Generales'!C19 -> 0.00014036284 | F37: ='[1]🧮 Costos x Producto'!H9 -> 0.75817884 | G37: ='[1]🧮 Costos x Producto'!I9 -> 2.8204253 | H37: =IF('[1]🧾 Factura Comercial'!E7=0,0,'[1]🧾 Tributos Aduana'!C16*(IF('[1]🧾 Tributos Aduana'!C5=0,0,'[1]🧾 Factura Comercial'!F7/'[1]🧾 Tributos Aduana'!C5))/'[1]🧾 Factura Comercial'!E7) -> 2.0612231e-06 | I37: =IF('[1]🧾 Factura Comercial'!E7=0,0,'[1]🏦 Crédito Fiscal'!C10*(IF('[1]🧾 Tributos Aduana'!C5=0,0,'[1]🧾 Factura Comercial'!F7/'[1]🧾 Tributos Aduana'!C5))/'[1]🧾 Factura Comercial'!E7) -> 1.4835887e-05 | J37: =I37*'[1]📋 Datos Generales'!C19 -> 5.5189499e-05 | K37: ='[1]💰 Precio de Venta'!E8 -> 0.4 | L37: ='[1]💰 Precio de Venta'!F8 -> 4.7007088 | M37: ='[1]💰 Precio de Venta'!G8 -> 5.5468364 | N37: ='[1]💰 Precio de Venta'!H8 -> 1.8802835 | O37: ='[1]💰 Precio de Venta'!I8 -> 1398 | P37: =N37*'[1]🧾 Factura Comercial'!E7 -> 19224.019 | Q37: =IF(M37=0,0,N37/M37) -> 0.33898305 | R37: =IF(G37=0,0,N37/G37) -> 0.66666667 | S37: =IF(K37>=0.5,"🟢 ALTO",IF(K37>=0.3,"🟡 MEDIO","🔴 BAJO")) -> 🟡 MEDIO
B38: =5 -> 5 | C38: ='[1]🧾 Factura Comercial'!C8 -> Pull Line Friction Car OPP Bag | D38: =IF('[1]🧾 Factura Comercial'!E8=0,0,'[1]📦 Gastos Importación'!C27*(IF('[1]🧾 Tributos Aduana'!C5=0,0,'[1]🧾 Factura Comercial'!F8/'[1]🧾 Tributos Aduana'!C5))/'[1]🧾 Factura Comercial'!E8) -> 3.4143712e-05 | E38: =D38*'[1]📋 Datos Generales'!C19 -> 0.00012701461 | F38: ='[1]🧮 Costos x Producto'!H10 -> 0.57978382 | G38: ='[1]🧮 Costos x Producto'!I10 -> 2.1567958 | H38: =IF('[1]🧾 Factura Comercial'!E8=0,0,'[1]🧾 Tributos Aduana'!C16*(IF('[1]🧾 Tributos Aduana'!C5=0,0,'[1]🧾 Factura Comercial'!F8/'[1]🧾 Tributos Aduana'!C5))/'[1]🧾 Factura Comercial'!E8) -> 1.8652048e-06 | I38: =IF('[1]🧾 Factura Comercial'!E8=0,0,'[1]🏦 Crédito Fiscal'!C10*(IF('[1]🧾 Tributos Aduana'!C5=0,0,'[1]🧾 Factura Comercial'!F8/'[1]🧾 Tributos Aduana'!C5))/'[1]🧾 Factura Comercial'!E8) -> 1.3425023e-05 | J38: =I38*'[1]📋 Datos Generales'!C19 -> 4.9941086e-05 | K38: ='[1]💰 Precio de Venta'!E9 -> 0.4 | L38: ='[1]💰 Precio de Venta'!F9 -> 3.5946597 | M38: ='[1]💰 Precio de Venta'!G9 -> 4.2416984 | N38: ='[1]💰 Precio de Venta'!H9 -> 1.4378639 | O38: ='[1]💰 Precio de Venta'!I9 -> 1181 | P38: =N38*'[1]🧾 Factura Comercial'!E8 -> 12423.144 | Q38: =IF(M38=0,0,N38/M38) -> 0.33898305 | R38: =IF(G38=0,0,N38/G38) -> 0.66666667 | S38: =IF(K38>=0.5,"🟢 ALTO",IF(K38>=0.3,"🟡 MEDIO","🔴 BAJO")) -> 🟡 MEDIO
B39: =6 -> 6 | C39: ='[1]🧾 Factura Comercial'!C9 -> Friction Car OPP Bag | D39: =IF('[1]🧾 Factura Comercial'!E9=0,0,'[1]📦 Gastos Importación'!C27*(IF('[1]🧾 Tributos Aduana'!C5=0,0,'[1]🧾 Factura Comercial'!F9/'[1]🧾 Tributos Aduana'!C5))/'[1]🧾 Factura Comercial'!E9) -> 0.00015233348 | E39: =D39*'[1]📋 Datos Generales'!C19 -> 0.00056668056 | F39: ='[1]🧮 Costos x Producto'!H11 -> 0.64668195 | G39: ='[1]🧮 Costos x Producto'!I11 -> 2.4056569 | H39: =IF('[1]🧾 Factura Comercial'!E9=0,0,'[1]🧾 Tributos Aduana'!C16*(IF('[1]🧾 Tributos Aduana'!C5=0,0,'[1]🧾 Factura Comercial'!F9/'[1]🧾 Tributos Aduana'!C5))/'[1]🧾 Factura Comercial'!E9) -> 8.3216832e-06 | I39: =IF('[1]🧾 Factura Comercial'!E9=0,0,'[1]🏦 Crédito Fiscal'!C10*(IF('[1]🧾 Tributos Aduana'!C5=0,0,'[1]🧾 Factura Comercial'!F9/'[1]🧾 Tributos Aduana'!C5))/'[1]🧾 Factura Comercial'!E9) -> 5.9896257e-05 | J39: =I39*'[1]📋 Datos Generales'!C19 -> 0.00022281408 | K39: ='[1]💰 Precio de Venta'!E10 -> 0.4 | L39: ='[1]💰 Precio de Venta'!F10 -> 4.0094281 | M39: ='[1]💰 Precio de Venta'!G10 -> 4.7311252 | N39: ='[1]💰 Precio de Venta'!H10 -> 1.6037712 | O39: ='[1]💰 Precio de Venta'!I10 -> 296 | P39: =N39*'[1]🧾 Factura Comercial'!E9 -> 3464.1459 | Q39: =IF(M39=0,0,N39/M39) -> 0.33898305 | R39: =IF(G39=0,0,N39/G39) -> 0.66666667 | S39: =IF(K39>=0.5,"🟢 ALTO",IF(K39>=0.3,"🟡 MEDIO","🔴 BAJO")) -> 🟡 MEDIO
B40: =7 -> 7 | C40: ='[1]🧾 Factura Comercial'!C10 -> Free Wheel Ride on Digger Handle | D40: =IF('[1]🧾 Factura Comercial'!E10=0,0,'[1]📦 Gastos Importación'!C27*(IF('[1]🧾 Tributos Aduana'!C5=0,0,'[1]🧾 Factura Comercial'!F10/'[1]🧾 Tributos Aduana'!C5))/'[1]🧾 Factura Comercial'!E10) -> 0.026994544 | E40: =D40*'[1]📋 Datos Generales'!C19 -> 0.1004197 | F40: ='[1]🧮 Costos x Producto'!H12 -> 12.732945 | G40: ='[1]🧮 Costos x Producto'!I12 -> 47.366554 | H40: =IF('[1]🧾 Factura Comercial'!E10=0,0,'[1]🧾 Tributos Aduana'!C16*(IF('[1]🧾 Tributos Aduana'!C5=0,0,'[1]🧾 Factura Comercial'!F10/'[1]🧾 Tributos Aduana'!C5))/'[1]🧾 Factura Comercial'!E10) -> 0.0014746596 | I40: =IF('[1]🧾 Factura Comercial'!E10=0,0,'[1]🏦 Crédito Fiscal'!C10*(IF('[1]🧾 Tributos Aduana'!C5=0,0,'[1]🧾 Factura Comercial'!F10/'[1]🧾 Tributos Aduana'!C5))/'[1]🧾 Factura Comercial'!E10) -> 0.01061403 | J40: =I40*'[1]📋 Datos Generales'!C19 -> 0.039484191 | K40: ='[1]💰 Precio de Venta'!E11 -> 0.4 | L40: ='[1]💰 Precio de Venta'!F11 -> 78.944257 | M40: ='[1]💰 Precio de Venta'!G11 -> 93.154223 | N40: ='[1]💰 Precio de Venta'!H11 -> 31.577703 | O40: ='[1]💰 Precio de Venta'!I11 -> 33 | P40: =N40*'[1]🧾 Factura Comercial'!E10 -> 7578.6487 | Q40: =IF(M40=0,0,N40/M40) -> 0.33898305 | R40: =IF(G40=0,0,N40/G40) -> 0.66666667 | S40: =IF(K40>=0.5,"🟢 ALTO",IF(K40>=0.3,"🟡 MEDIO","🔴 BAJO")) -> 🟡 MEDIO
B41: =8 -> 8 | C41: ='[1]🧾 Factura Comercial'!C11 -> Friction Car with Music and Light | D41: =IF('[1]🧾 Factura Comercial'!E11=0,0,'[1]📦 Gastos Importación'!C27*(IF('[1]🧾 Tributos Aduana'!C5=0,0,'[1]🧾 Factura Comercial'!F11/'[1]🧾 Tributos Aduana'!C5))/'[1]🧾 Factura Comercial'!E11) -> 0.00044912113 | E41: =D41*'[1]📋 Datos Generales'!C19 -> 0.0016707306 | F41: ='[1]🧮 Costos x Producto'!H13 -> 1.6947527 | G41: ='[1]🧮 Costos x Producto'!I13 -> 6.3044801 | H41: =IF('[1]🧾 Factura Comercial'!E11=0,0,'[1]🧾 Tributos Aduana'!C16*(IF('[1]🧾 Tributos Aduana'!C5=0,0,'[1]🧾 Factura Comercial'!F11/'[1]🧾 Tributos Aduana'!C5))/'[1]🧾 Factura Comercial'!E11) -> 2.4534618e-05 | I41: =IF('[1]🧾 Factura Comercial'!E11=0,0,'[1]🏦 Crédito Fiscal'!C10*(IF('[1]🧾 Tributos Aduana'!C5=0,0,'[1]🧾 Factura Comercial'!F11/'[1]🧾 Tributos Aduana'!C5))/'[1]🧾 Factura Comercial'!E11) -> 0.00017659069 | J41: =I41*'[1]📋 Datos Generales'!C19 -> 0.00065691736 | K41: ='[1]💰 Precio de Venta'!E12 -> 0.4 | L41: ='[1]💰 Precio de Venta'!F12 -> 10.507467 | M41: ='[1]💰 Precio de Venta'!G12 -> 12.398811 | N41: ='[1]💰 Precio de Venta'!H12 -> 4.2029867 | O41: ='[1]💰 Precio de Venta'!I12 -> 263 | P41: =N41*'[1]🧾 Factura Comercial'!E11 -> 8069.7345 | Q41: =IF(M41=0,0,N41/M41) -> 0.33898305 | R41: =IF(G41=0,0,N41/G41) -> 0.66666667 | S41: =IF(K41>=0.5,"🟢 ALTO",IF(K41>=0.3,"🟡 MEDIO","🔴 BAJO")) -> 🟡 MEDIO
B42: =9 -> 9 | C42: ='[1]🧾 Factura Comercial'!C12 -> Pull Line Function Car OPP Bag | D42: =IF('[1]🧾 Factura Comercial'!E12=0,0,'[1]📦 Gastos Importación'!C27*(IF('[1]🧾 Tributos Aduana'!C5=0,0,'[1]🧾 Factura Comercial'!F12/'[1]🧾 Tributos Aduana'!C5))/'[1]🧾 Factura Comercial'!E12) -> 6.6186272e-05 | E42: =D42*'[1]📋 Datos Generales'!C19 -> 0.00024621293 | F42: ='[1]🧮 Costos x Producto'!H14 -> 0.62438258 | G42: ='[1]🧮 Costos x Producto'!I14 -> 2.3227032 | H42: =IF('[1]🧾 Factura Comercial'!E12=0,0,'[1]🧾 Tributos Aduana'!C16*(IF('[1]🧾 Tributos Aduana'!C5=0,0,'[1]🧾 Factura Comercial'!F12/'[1]🧾 Tributos Aduana'!C5))/'[1]🧾 Factura Comercial'!E12) -> 3.6156279e-06 | I42: =IF('[1]🧾 Factura Comercial'!E12=0,0,'[1]🏦 Crédito Fiscal'!C10*(IF('[1]🧾 Tributos Aduana'!C5=0,0,'[1]🧾 Factura Comercial'!F12/'[1]🧾 Tributos Aduana'!C5))/'[1]🧾 Factura Comercial'!E12) -> 2.6023891e-05 | J42: =I42*'[1]📋 Datos Generales'!C19 -> 9.6808875e-05 | K42: ='[1]💰 Precio de Venta'!E13 -> 0.4 | L42: ='[1]💰 Precio de Venta'!F13 -> 3.871172 | M42: ='[1]💰 Precio de Venta'!G13 -> 4.5679829 | N42: ='[1]💰 Precio de Venta'!H13 -> 1.5484688 | O42: ='[1]💰 Precio de Venta'!I13 -> 657 | P42: =N42*'[1]🧾 Factura Comercial'!E12 -> 7432.6502 | Q42: =IF(M42=0,0,N42/M42) -> 0.33898305 | R42: =IF(G42=0,0,N42/G42) -> 0.66666667 | S42: =IF(K42>=0.5,"🟢 ALTO",IF(K42>=0.3,"🟡 MEDIO","🔴 BAJO")) -> 🟡 MEDIO
C43: ✦ TOTALES Y PROMEDIOS | F43: ='[1]🧮 Costos x Producto'!D3 -> 0 | G43: ='[1]🧮 Costos x Producto'!F3 -> 0 | H43: ='[1]🧾 Tributos Aduana'!C16 -> 881 | I43: ='[1]🏦 Crédito Fiscal'!C10 -> 6341.0973 | J43: ='[1]🏦 Crédito Fiscal'!C11 -> 23588.882 | K43: =AVERAGE('[1]💰 Precio de Venta'!E5:E13) -> 0.4 | N43: =SUM(N34:N42) -> 54.91534 | P43: =SUM(P34:P42) -> 78605.585 | Q43: =AVERAGE(Q34:Q42) -> 0.33898305 | R43: =AVERAGE(R34:R42) -> 0.66666667
B45: 📊 SECCIÓN 4: RESUMEN VISUAL — TOP PRODUCTOS
B46: P1 | D46: P2 | F46: P3 | H46: P4 | J46: P5 | L46: P6 | N46: P7 | P46: P8 | R46: P9
B47: ='[1]🧾 Factura Comercial'!C4 -> Friction Car Platform Cover | D47: ='[1]🧾 Factura Comercial'!C5 -> Friction Cars OPP Bag 23cm | F47: ='[1]🧾 Factura Comercial'!C6 -> Free Wheel Motor OPP Bag 21cm | H47: ='[1]🧾 Factura Comercial'!C7 -> Friction Cars OPP Bag 22cm | J47: ='[1]🧾 Factura Comercial'!C8 -> Pull Line Friction Car OPP Bag | L47: ='[1]🧾 Factura Comercial'!C9 -> Friction Car OPP Bag | N47: ='[1]🧾 Factura Comercial'!C10 -> Free Wheel Ride on Digger Handle | P47: ='[1]🧾 Factura Comercial'!C11 -> Friction Car with Music and Light | R47: ='[1]🧾 Factura Comercial'!C12 -> Pull Line Function Car OPP Bag
B48: C/M | C48: ='[1]🧮 Costos x Producto'!I6 -> 10.037396 | D48: C/M | E48: ='[1]🧮 Costos x Producto'!I7 -> 5.6408506 | F48: C/M | G48: ='[1]🧮 Costos x Producto'!I8 -> 3.3181474 | H48: C/M | I48: ='[1]🧮 Costos x Producto'!I9 -> 2.8204253 | J48: C/M | K48: ='[1]🧮 Costos x Producto'!I10 -> 2.1567958 | L48: C/M | M48: ='[1]🧮 Costos x Producto'!I11 -> 2.4056569 | N48: C/M | O48: ='[1]🧮 Costos x Producto'!I12 -> 47.366554 | P48: C/M | Q48: ='[1]🧮 Costos x Producto'!I13 -> 6.3044801 | R48: C/M | S48: ='[1]🧮 Costos x Producto'!I14 -> 2.3227032
B49: PV | C49: ='[1]💰 Precio de Venta'!G5 -> 19.740212 | D49: PV | E49: ='[1]💰 Precio de Venta'!G6 -> 11.093673 | F49: PV | G49: ='[1]💰 Precio de Venta'!G7 -> 6.5256899 | H49: PV | I49: ='[1]💰 Precio de Venta'!G8 -> 5.5468364 | J49: PV | K49: ='[1]💰 Precio de Venta'!G9 -> 4.2416984 | L49: PV | M49: ='[1]💰 Precio de Venta'!G10 -> 4.7311252 | N49: PV | O49: ='[1]💰 Precio de Venta'!G11 -> 93.154223 | P49: PV | Q49: ='[1]💰 Precio de Venta'!G12 -> 12.398811 | R49: PV | S49: ='[1]💰 Precio de Venta'!G13 -> 4.5679829
B50: GAN. | C50: ='[1]💰 Precio de Venta'!H5 -> 6.6915973 | D50: GAN. | E50: ='[1]💰 Precio de Venta'!H6 -> 3.7605671 | F50: GAN. | G50: ='[1]💰 Precio de Venta'!H7 -> 2.2120983 | H50: GAN. | I50: ='[1]💰 Precio de Venta'!H8 -> 1.8802835 | J50: GAN. | K50: ='[1]💰 Precio de Venta'!H9 -> 1.4378639 | L50: GAN. | M50: ='[1]💰 Precio de Venta'!H10 -> 1.6037712 | N50: GAN. | O50: ='[1]💰 Precio de Venta'!H11 -> 31.577703 | P50: GAN. | Q50: ='[1]💰 Precio de Venta'!H12 -> 4.2029867 | R50: GAN. | S50: ='[1]💰 Precio de Venta'!H13 -> 1.5484688
B51: MARG. | C51: ='[1]💰 Precio de Venta'!E5 -> 0.4 | D51: MARG. | E51: ='[1]💰 Precio de Venta'!E6 -> 0.4 | F51: MARG. | G51: ='[1]💰 Precio de Venta'!E7 -> 0.4 | H51: MARG. | I51: ='[1]💰 Precio de Venta'!E8 -> 0.4 | J51: MARG. | K51: ='[1]💰 Precio de Venta'!E9 -> 0.4 | L51: MARG. | M51: ='[1]💰 Precio de Venta'!E10 -> 0.4 | N51: MARG. | O51: ='[1]💰 Precio de Venta'!E11 -> 0.4 | P51: MARG. | Q51: ='[1]💰 Precio de Venta'!E12 -> 0.4 | R51: MARG. | S51: ='[1]💰 Precio de Venta'!E13 -> 0.4
B52: ROI | C52: =IF('[1]🧮 Costos x Producto'!I6=0,0,'[1]💰 Precio de Venta'!H5/'[1]🧮 Costos x Producto'!I6) -> 0.66666667 | D52: ROI | E52: =IF('[1]🧮 Costos x Producto'!I7=0,0,'[1]💰 Precio de Venta'!H6/'[1]🧮 Costos x Producto'!I7) -> 0.66666667 | F52: ROI | G52: =IF('[1]🧮 Costos x Producto'!I8=0,0,'[1]💰 Precio de Venta'!H7/'[1]🧮 Costos x Producto'!I8) -> 0.66666667 | H52: ROI | I52: =IF('[1]🧮 Costos x Producto'!I9=0,0,'[1]💰 Precio de Venta'!H8/'[1]🧮 Costos x Producto'!I9) -> 0.66666667 | J52: ROI | K52: =IF('[1]🧮 Costos x Producto'!I10=0,0,'[1]💰 Precio de Venta'!H9/'[1]🧮 Costos x Producto'!I10) -> 0.66666667 | L52: ROI | M52: =IF('[1]🧮 Costos x Producto'!I11=0,0,'[1]💰 Precio de Venta'!H10/'[1]🧮 Costos x Producto'!I11) -> 0.66666667 | N52: ROI | O52: =IF('[1]🧮 Costos x Producto'!I12=0,0,'[1]💰 Precio de Venta'!H11/'[1]🧮 Costos x Producto'!I12) -> 0.66666667 | P52: ROI | Q52: =IF('[1]🧮 Costos x Producto'!I13=0,0,'[1]💰 Precio de Venta'!H12/'[1]🧮 Costos x Producto'!I13) -> 0.66666667 | R52: ROI | S52: =IF('[1]🧮 Costos x Producto'!I14=0,0,'[1]💰 Precio de Venta'!H13/'[1]🧮 Costos x Producto'!I14) -> 0.66666667
B72: 🔍 DETALLE POR PRODUCTO — Todos los valores se calculan automáticamente desde las hojas fuente · © 2026
B200: Producto | C200: Ganancia Total S/. | D200: C/M Unit S/. | E200: PV Unit S/.
B201: ='[1]🧾 Factura Comercial'!C4 -> Friction Car Platform Cover | C201: =P34 -> 3211.9667 | D201: ='[1]🧮 Costos x Producto'!I6 -> 10.037396 | E201: ='[1]💰 Precio de Venta'!G5 -> 19.740212
B202: ='[1]🧾 Factura Comercial'!C5 -> Friction Cars OPP Bag 23cm | C202: =P35 -> 10830.433 | D202: ='[1]🧮 Costos x Producto'!I7 -> 5.6408506 | E202: ='[1]💰 Precio de Venta'!G6 -> 11.093673
B203: ='[1]🧾 Factura Comercial'!C6 -> Free Wheel Motor OPP Bag 21cm | C203: =P36 -> 6370.843 | D203: ='[1]🧮 Costos x Producto'!I8 -> 3.3181474 | E203: ='[1]💰 Precio de Venta'!G7 -> 6.5256899
B204: ='[1]🧾 Factura Comercial'!C7 -> Friction Cars OPP Bag 22cm | C204: =P37 -> 19224.019 | D204: ='[1]🧮 Costos x Producto'!I9 -> 2.8204253 | E204: ='[1]💰 Precio de Venta'!G8 -> 5.5468364
B205: ='[1]🧾 Factura Comercial'!C8 -> Pull Line Friction Car OPP Bag | C205: =P38 -> 12423.144 | D205: ='[1]🧮 Costos x Producto'!I10 -> 2.1567958 | E205: ='[1]💰 Precio de Venta'!G9 -> 4.2416984
B206: ='[1]🧾 Factura Comercial'!C9 -> Friction Car OPP Bag | C206: =P39 -> 3464.1459 | D206: ='[1]🧮 Costos x Producto'!I11 -> 2.4056569 | E206: ='[1]💰 Precio de Venta'!G10 -> 4.7311252
B207: ='[1]🧾 Factura Comercial'!C10 -> Free Wheel Ride on Digger Handle | C207: =P40 -> 7578.6487 | D207: ='[1]🧮 Costos x Producto'!I12 -> 47.366554 | E207: ='[1]💰 Precio de Venta'!G11 -> 93.154223
B208: ='[1]🧾 Factura Comercial'!C11 -> Friction Car with Music and Light | C208: =P41 -> 8069.7345 | D208: ='[1]🧮 Costos x Producto'!I13 -> 6.3044801 | E208: ='[1]💰 Precio de Venta'!G12 -> 12.398811
B209: ='[1]🧾 Factura Comercial'!C12 -> Pull Line Function Car OPP Bag | C209: =P42 -> 7432.6502 | D209: ='[1]🧮 Costos x Producto'!I14 -> 2.3227032 | E209: ='[1]💰 Precio de Venta'!G13 -> 4.5679829

Sheet 📊 KPI x Producto
B13: ='📋 Datos Generales'!E6&" | DUA: "&'📋 Datos Generales'!E5&" | País: "&'📋 Datos Generales'!E9&" | Proveedor: "&'📋 Datos Generales'!E10&" | Incoterm: "&'📋 Datos Generales'!E11&" | TC: S/."&TEXT('📋 Datos Generales'!E19,"0.000") -> EMPRESA IMPORTADORA S.A.C. | DUA: DAM-2025-000001 | País: China | Proveedor: HWPI Co. Ltd. | Incoterm: FOB | TC: S/.3.720 | AH13: LISTA DE PRODUCTOS
AH14: Case Transparente TPU iPhone 15
X21: =VLOOKUP($AH$14,TABLA_BASE[#All],6,FALSE) -> 0.013308501
H22: =VLOOKUP($AH$14,TABLA_BASE[#All],3,FALSE) -> 480 | K22: =VLOOKUP($AH$14,TABLA_BASE[#All],4,FALSE) -> 1.21 | N22: =VLOOKUP($AH$14,TABLA_BASE[#All],7,FALSE) -> 4.5012 | T22: =VLOOKUP($AH$14,TABLA_BASE[#All],8,FALSE) -> 2160.576 | AR22: =VLOOKUP($AH$14,TABLA_BASE[#All],50,FALSE) -> 66
T23: =VLOOKUP($AH$14,TABLA_BASE[#All],5,FALSE) -> 580.8 | AB23: =VLOOKUP($AH$14,TABLA_BASE[#All],44,FALSE) -> 0.4 | AD23: ='Detallado por producto'!AS3 -> 8.5576486 | AR23: =VLOOKUP($AH$14,TABLA_BASE[#All],41,FALSE) -> 0.30394874
AD25: =VLOOKUP($AH$14,TABLA_BASE[#All],45,FALSE) -> 8.5576486 | AF25: =VLOOKUP($AH$14,TABLA_BASE[#All],46,FALSE) -> 4107.6713
AD27: =VLOOKUP($AH$14,TABLA_BASE[#All],44,FALSE) -> 0.4
AD30: ='Detallado por producto'!AY3 -> 1643.0685
AD32: =VLOOKUP($AH$14,TABLA_BASE[#All],48,FALSE) -> 3.4230594 | AF32: =VLOOKUP($AH$14,TABLA_BASE[#All],49,FALSE) -> 1643.0685
AD33: =VLOOKUP($AH$14,TABLA_BASE[#All],38,FALSE) -> 5.1345892 | AF33: =VLOOKUP($AH$14,TABLA_BASE[#All],39,FALSE) -> 2464.6028
AD34: =VLOOKUP($AH$14,TABLA_BASE[#All],45,FALSE) -> 8.5576486
AD35: =VLOOKUP($AH$14,TABLA_BASE[#All],42,FALSE) -> 1.1306893 | AF35: =VLOOKUP($AH$14,TABLA_BASE[#All],43,FALSE) -> 542.73086
AD36: =VLOOKUP($AH$14,TABLA_BASE[#All],42,FALSE) -> 1.1306893
I62: =VLOOKUP($AH$14,TABLA_BASE[#All],21,FALSE) -> 0.2838437 | K62: =VLOOKUP($AH$14,TABLA_BASE[#All],22,FALSE) -> 136.24498 | M62: =VLOOKUP($AH$14,TABLA_BASE[#All],23,FALSE) -> 0.10025293 | O62: =VLOOKUP($AH$14,TABLA_BASE[#All],24,FALSE) -> 48.121409 | Q62: =VLOOKUP($AH$14,TABLA_BASE[#All],25,FALSE) -> 0.8023329 | S62: =VLOOKUP($AH$14,TABLA_BASE[#All],26,FALSE) -> 385.11979 | T62: =VLOOKUP($AH$14,TABLA_BASE[#All],27,FALSE) -> 0.20709657 | V62: =VLOOKUP($AH$14,TABLA_BASE[#All],28,FALSE) -> 99.406354 | X62: =VLOOKUP($AH$14,TABLA_BASE[#All],19,FALSE) -> 1.1864295
I65: =VLOOKUP($AH$14,TABLA_BASE[#All],20,FALSE) -> 569.48618
